Workbook
Name CeldadeinicioDxCcaptaCP36: 'PVP Subv - Optima Pyme'!$BE$18
Name CeldadeinicioDxCportaCP36: 'PVP Subv - Optima Pyme'!$BK$1
Name CeldaInicioDxCCapta: 'PVP Subv - Optima Pyme'!$U$1
Name CeldaInicioDxCCapta9MAS: 'PVP Subv - Sol Pers Pyme'!$U$1
Name CeldaInicioDxCCapta9MASAAPP: 'PVP Subv - Sol Pers Pyme AAPP'!$I$1
Name CeldaInicioDxCCaptaAAPP: 'PVP Subv - Optima Pyme AAPP'!$I$1
Name CeldaInicioDxCIEW: 'PVP Subv IEW - Pyme'!$N$1
Name CeldaInicioDxCIEWAAPP: 'PVP Subv IEW - Pyme AAPP'!$N$1
Name CeldaInicioDxCPorta: 'PVP Subv - Optima Pyme'!$AA$1
Name CeldaInicioDxCPorta_36: 'PVP Subv - Optima Pyme 36'!$O$1
Name CeldaInicioDxCPorta36: 'PVP Subv - Optima Pyme 36'!$O$18
Name CeldaInicioDxCPorta9MAS: 'PVP Subv - Sol Pers Pyme'!$AA$1
Name CeldaInicioDxCPorta9MASAAPP: 'PVP Subv - Sol Pers Pyme AAPP'!$O$1
Name CeldaInicioDxCPortaAAPP: 'PVP Subv - Optima Pyme AAPP'!$O$1
Name CeldaInicioDxCVAP: 'PVP VaP - Pyme'!$Z$1
Name CeldaInicioDxCVAPIEW: 'PVP VaP IEW Pro - Pyme'!$AA$1
Name CeldaInicioPrecioCesión: 'PVP Subv - Sol Pers Pyme'!$D$1
Name CeldaInicioPrecioCesión: 'PVP Subv - Optima Pyme'!$D$1
Name CeldaInicioPrecioCesiónIEW: 'PVP Subv IEW - Pyme'!$D$1
Name CeldaInicioPVPRCapta: 'PVP Subv - Sol Pers Pyme'!$I$1
Name CeldaInicioPVPRCapta: 'PVP Subv - Optima Pyme'!$I$1
Name CeldaInicioPVPRIEW: 'PVP Subv IEW - Pyme'!$I$1
Name CeldaInicioPVPRPorta: 'PVP Subv - Sol Pers Pyme'!$O$1
Name CeldaInicioPVPRPorta: 'PVP Subv - Optima Pyme'!$O$1
Name CeldaInicioPVPRVAP: 'PVP VaP - Pyme'!$J$1
Name CeldaInicioPVPRVAPIEW: 'PVP VaP IEW Pro - Pyme'!$M$1
Name cualquiera: MR!$W$5
Name k: Tabla3[]
Name MinoraciónPROMOS: #REF!
Name no_aplica: MR!$W$4
Name SIoNO: MR!$X$4:$X$5
Name ValoresPaqueteVozDatos: MR!$U$4:$U$11
Name ValoresSVA: MR!$V$4:$V$5
Name valoresTarifa: MR!$S$4:$S$15
Name valoresTerminal: 'PVP Subv - Sol Pers Pyme'!$C$26:$C$244
Name valoresTerminal: 'PVP Subv - Optima Pyme'!$C$26:$C$238
Name valoresTerminalIEW: 'PVP Subv IEW - Pyme'!$C$25:$C$48
Name valoresTipoAlta: MR!$T$4:$T$5

Sheet LEEME
B3: CONFIGURADOR DE MARGENES | I3: Mes: | L3: ENERO | O3: 01/01 al 31/01
I4: Versión: | L4: Tarifas nuevas v0 _SD
B7: Acerca del Configurador
B9: 1.- Este configurador es una herramienta de apoyo para el análisis y viabilidad de las operaciones
B10: 2.- La información que se obtenga de esta herramienta es meramente orientativa
B11: 3.- Los datos obtenidos de la utilización de esta herramienta en ningún caso tendrán carácter vinculante
B14: Condicionantes del Configurador. El configurador contempla la estructura de Marco Retributivo y de Oferta Táctica con las siguientes excepciones / supuestos:
B16: 1.- El configurador contempla tanto la oferta VAP como la oferta subvencionada para tarifas multilínea, independientemente del tamaño y tipo de cliente, y para tarifas iew pro e internet 4G en clientes CIF 10+ y NIF 10+
B17: 2.- El configurador sólo contempla comisiones de alta para captación y portabilidad. No contempla comisión de alta para migraciones
B18: 3.- La subvención para ampliaciones de clientes con antigüedad igual o superior a 4 meses en VAP es igual a la subvención para portabilidades
B19: 4.- El configurador no contempla la oferta de bundles ni segundos dispositivos
B20: 5.- SOLO LAS CELDAS MARCADAS EN AMARILLO SON MODIFICABLES PARA CONFIGURAR LA OFERTA
B21: 6.- ASEGURATE DE VOLVER CAMBIAR EL TIPO DE TERMINAL CUANDO CAMBIES ENTRE TARIFAS DE VOZ Y DATOS Y TARIFAS DE IEW
B22: 7.- POR FAVOR, COMUNICA A TU SUPERVISOR CUALQUIER POSIBLE ANOMALIA O ERROR DETECTADO

Sheet Configurador Operaciones
A1: RENTABILIDAD DE LA OPERACIÓN MÓVIL | D1: ¿ Es Administración Pública ? | F1: NO | G1: Tipo DHO | H1: TIPO1 | J1: RENTABILIDAD DE LA OPERACIÓN FIJO
B2: IMPORTE TOTAL (24 meses) | C2: IMPORTE TOTAL (36 meses) | D2: RESUMEN DE LA OPERACIÓN | J2: MARGEN FIJO | K2: =B111 -> 6
A3: COMISIONES | B3: =SUMIFS($B$12:$B$101,$A$12:$A$101,A3) -> 0 | C3: =B3+H19+H29+H39+H49+H59+H69+H79+H89+H99+F17+F27+F37+F47+F57+F67+F77+F87+F97 -> 0 | D3: PARQUE ESPERADO DEL CLIENTE A FINAL DE MES | G3: Cliente > 40 líneas | H3: =G5+G6+K4 -> 0 | J3: BIG PYME | K3: =P119+P126+P133+P140 -> 0 | L3: =IF(AND(K3>0,K4>1),1,0) -> 0
A4: SUBVENCIÓN TERMINAL | B4: =SUMIFS($B$12:$B$101,$A$12:$A$101,A4) -> 0 | C4: =$E$17+$B$4+$E$27+$E$37+$E$47+$E$57+$E$67+$E$77+$E$87+$E$97 -> 0 | D4: Nº TOTAL DE LÍNEAS VOZ | G4: =SUMIFS(B1:B101,A1:A101,"PERFIL DE ALTA") -> 0 | J4: Puestos BIG PYME | K4: =L119+L126+L133+L140 -> 0
A5: PVPR TERMINAL (sin IVA) | B5: =SUMIFS($B$12:$B$101,$A$12:$A$101,A5) -> 0 | D5: voz sin datos | G5: =SUMIFS(B1:B101,A1:A101,"PERFIL DE ALTA",D1:D101,"multilínea",F1:F101,"sin datos") -> 0 | J5: BIG PYME acceso Móvil | K5: =O119+O126+O133+O140 -> 0 | L5: =IF(K5>0,1,0) -> 0
A6: PRECIO CESIÓN TERMINAL | B6: =SUMIFS($B$12:$B$101,$A$12:$A$101,A6) -> 0 | C6: =B6 -> 0 | D6: voz con datos | G6: =SUMIFS(B1:B101,A1:A101,"PERFIL DE ALTA",D1:D101,"multilínea")-G5 -> 0 | J6: CONECTA PYMES | K6: =M119+M126+M133+M140 -> 0 | L6: =IF(K6>1,K6,0) -> 0
A7: MARGEN | B7: =SUMIFS($B$12:$B$101,$A$12:$A$101,A7) -> 0 | C7: =C3+C4+C6 -> 0 | D7: IEW Pro | G7: =G4-G5-G6 -> 0 | J7: NETWORKPLUS | K7: =N119+N126+N133+N140 -> 0 | L7: =IF(K7>0,1,0) -> 0
H8: =(G4+IF(K4>1,K4,0)-G7) -> 0 | I8: PUNTOS | J8: CONECTA EMPRESAS | K8: =Q119+Q126+Q133+Q140 -> 0 | L8: =IF(K8>0,1,0) -> 0
A9: CLIENTE EN CARTERA | C9: NO | D9: OPERACIÓN ESTRATEGICA | F9: =IF(AND(M13="SI",H8>99),"NO",IF(C9="NO",IF(H9>19,"SI",IF(L10>0.5,"SI","NO")),IF(H9>2,"SI",IF(K6+L7+L8+L5+L3+L9+L10>0,"SI","NO")))) -> NO | G9: LINEAS ESTRATEGIA | H9: =IF(M13="SI",IF(H8>99,99,H8),H8) -> 0 | I9: =($I$15*$B$13+$I$25*$B$23+$I$35*$B$33+$I$45*$B$43+$I$55*$B$53+$I$65*$B$63+$I$75*$B$73+$I$85*$B$83+$I$95*$B$93+$B$110)/MR!$I$13 -> 0 | J9: O365 / OTROS SVAS | K9: =S119+S126+S133+S140 -> 0 | L9: =IF(K9>1,1,0) -> 0
A10: MARGEN TOTAL DE LA OPERACIÓN F+M | B10: =B7+K2+I10 -> 6 | C10: =C7+K2+I10 -> 6 | E10: con tope de 6.000 € de estrategia | G10: TOTAL ESTRATEGIA | H10: =IF(AND(M13="SI",H8>99),0,IF(F9="NO",0,J15+J25+J35+J45+J55+J65+J75+J85+J95+B110)) -> 0 | I10: =IF(H10>6000,6000-H10,0) -> 0 | J10: SOLUCIONES DIGITALES | K10: =$T$120+$T$127+$T$134+$T$141 -> 0 | L10: =SUM(L3:L9)+K10 -> 0
B12: Nº ALTAS CON ESTE PERFIL | C12: TARIFA | D12: TIPO DE TARIFA | E12: TIPO DE ALTA | F12: PAQUETE DE VOZ Y DATOS | G12: CV USUARIO | H12: MFO CON FIJO PORTADO | I12: VENTA A PLAZOS | J12: TERMINAL | K12: GAMA | L12: MÓDULO OT | M12: ÓPTIMA | N12: O2O | O12: 36 m | P12: ESTRAT
A13: PERFIL DE ALTA | B13: 0 | D13: =IFERROR(INDEX(MR!Q:Q,MATCH(C13,MR!P:P,0)),"") | I13: NO | K13: =IF(J13="","SIN TERMINAL",IF(D13="IEW",INDEX('PVP Subv IEW - Pyme'!F:F,MATCH(J13,'PVP Subv IEW - Pyme'!C:C,0)),INDEX('PVP Subv - Optima Pyme'!F:F,MATCH(J13,'PVP Subv - Optima Pyme'!C:C,0)))) -> SIN TERMINAL | L13: =IFERROR(IF(D13="IEW",INDEX('MODULOS OT IEW'!D:D,MATCH(C13,'MODULOS OT IEW'!A:A,0)),INDEX('MODULOS OT MULTILINEA'!F:F,MATCH(E13&F13&K13,'MODULOS OT MULTILINEA'!A:A,0))),"") | M13: =+IF(C13="","",IF(OR(C13="Óptima Plus Empresas",C13="Óptima Plus Empresas BIG"),"SI","NO")) | N13: =+IF(C13="","",IF($C$9="SI","NO",IF(OR(C13="Óptima Plus Empresas",C13="Óptima Plus Empresas BIG"),"SI","NO"))) | O13: =+IF(N13="NO","NO",IF(AND(E13="portabilidad",L13<>"ENTRADA PRO"),"SI","NO")) -> NO | P13: =IF(AND(E13="capta",F13="EMPRESAS VOZ"),0,1) -> 1
B14: IMPORTE TOTAL | C14: IMPORTE UNITARIO | D14: PAQUETE DE VOZ Y DATOS | E14: ACTIVACION | F14: ACTIVACION CP 24 POR TERMINAL | G14: SVAs | H14: O2O | I14: ESTRATEGICA | N14: =IF(N13="SI",1,0) -> 0
A15: COMISIONES | B15: =C15*B13 -> 0 | C15: =D15+E15+F15+G15-H16*N14+I15 -> 0 | D15: =IFERROR(IF(AND(M13="SI",$G$3="Cliente 1-19 líneas"),SUMIFS(MR!$B$5:$B$13,MR!$A$5:$A$13,F13),IF(AND(M13="SI",$G$3="Cliente 20-39 líneas"),SUMIFS(MR!$C$5:$C$13,MR!$A$5:$A$13,F13),IF(AND(M13="SI",$G$3="Cliente > 40 líneas"),SUMIFS(MR!$D$5:$D$13,MR!$A$5:$A$13,F13),IF(AND(M13="NO",$G$3="Cliente 1-19 líneas"),SUMIFS(MR!$B$17:$B$25,MR!$A$17:$A$25,F13),IF(AND(M13="NO",$G$3="Cliente 20-39 líneas"),SUMIFS(MR!$C$17:$C$25,MR!$A$17:$A$25,F13),IF(AND(M13="NO",$G$3="Cliente > 40 líneas"),SUMIFS(MR!$D$17:$D$25,MR!$A$17:$A$25,F13),0)))))),)+IFERROR(IF(AND(M13="SI",$G$3="Cliente 1-19 líneas"),SUMIFS(MR!$B$30:$B$37,MR!$A$30:$A$37,F13),IF(AND(M13="SI",$G$3="Cliente 20-39 líneas"),SUMIFS(MR!$C$30:$C$37,MR!$A$30:$A$37,F13),IF(AND(M13="SI",$G$3="Cliente > 40 líneas"),SUMIFS(MR!$D$30:$D$37,MR!$A$30:$A$37,F13),IF(AND(M13="NO",$G$3="Cliente 1-19 líneas"),SUMIFS(MR!$B$41:$B$48,MR!$A$41:$A$48,F13),IF(AND(M13="NO",$G$3="Cliente 20-39 líneas"),SUMIFS(MR!$C$41:$C$48,MR!$A$41:$A$48,F13),IF(AND(M13="NO",$G$3="Cliente > 40 líneas"),SUMIFS(MR!$D$41:$D$48,MR!$A$41:$A$48,F13),0)))))),) -> 0 | E15: =IFERROR(IF(AND(M13="SI",E13="capta",D13="multilínea"),SUMIFS(MR!$E$5:$E$13,MR!$A$5:$A$13,F13),IF(AND(M13="SI",E13="portabilidad",D13="multilínea"),SUMIFS(MR!$F$5:$F$13,MR!$A$5:$A$13,F13),IF(AND(M13="NO",E13="capta",D13="multilínea"),SUMIFS(MR!$E$17:$E$25,MR!$A$17:$A$25,F13),IF(AND(M13="NO",E13="portabilidad",D13="multilínea"),SUMIFS(MR!$F$17:$F$25,MR!$A$17:$A$25,F13),IF(AND(M13="NO",E13="capta",D13="IEW"),SUMIFS(MR!$B$53:$B$61,MR!$A$53:$A$61,C13),IF(AND(M13="NO",E13="portabilidad",D13="IEW"),SUMIFS(MR!$B$53:$B$61,MR!$A$53:$A$61,C13),0)))))),)+IFERROR(IF(AND(M13="SI",E13="capta",D13="multilínea"),SUMIFS(MR!$E$30:$E$37,MR!$A$30:$A$37,F13),IF(AND(M13="SI",E13="portabilidad",D13="multilínea"),SUMIFS(MR!$F$30:$F$37,MR!$A$30:$A$37,F13),IF(AND(M13="NO",E13="capta",D13="multilínea"),SUMIFS(MR!$E$48:$E$398,MR!$A$41:$A$48,F13),IF(AND(M13="NO",E13="portabilidad",D13="multilínea"),SUMIFS(MR!$F$41:$F$48,MR!$A$41:$A$48,F13),0)))),) -> 0 | F15: =(IFERROR(IF(K13="SIN TERMINAL",0,IF(I13="SI",10,SUMIFS(MR!$G$6:$G$11,MR!$A$6:$A$11,F13))),0))*K15 -> 0 | G15: =IFERROR(IF(D13="multilínea",IF(G13="SI",MR!$N$4,0)+IF(H13="SI",MR!$N$5,0),0),0) -> 0 | I15: =(IF(D13="multilínea",IF($F$9="SI",IF($M13="SI",SUMIFS(MR!$I$6:$I$11,MR!$A$6:$A$11,F13),SUMIFS(MR!$I$18:$I$23,MR!$A$18:$A$23,F13))),SUMIFS(MR!$D$54:$D$61,MR!$A$54:$A$61,C13)))*P13 -> 0 | J15: =IF(M13="SI",IF(B13>99,99*I15,I15*B13),I15*B13) -> 0 | K15: =IF(IFERROR(SEARCH("CESIÓN",$J13,1),0)>0,0,1) -> 1
A16: SUBVENCIÓN TERMINAL | B16: =IFERROR(C16*B13,"SIN OFERTA") -> SIN OFERTA | C16: =IFERROR(IFERROR(IF($F$1="NO", IF(I13="SI",IF(E13="portabilidad", IF(D13="multilínea",IF(AND(C13<>"Soluciones Personalizadas RPV",C13<>"Soluciones Personalizadas Centrex"), OFFSET(CeldaInicioDxCVAP,MATCH(J13,'PVP VaP - Pyme'!C:C,0)-1,MATCH(L13,'PVP VaP - Pyme'!$Z$22:$AL$22,0)-1) +OFFSET(CeldaInicioDxCVAP,MATCH(J13,'PVP VaP - Pyme'!C:C,0)-1,MATCH(L13,'PVP VaP - Pyme'!$Z$22:$AL$22,0)))), IF(D13="IEW", OFFSET(CeldaInicioDxCVAPIEW,MATCH(J13,'PVP VaP IEW Pro - Pyme'!C:C,0)-1,MATCH(L13,'PVP VaP IEW Pro - Pyme'!$AA$22:$AH$22,0)-1) +OFFSET(CeldaInicioDxCVAPIEW,MATCH(J13,'PVP VaP IEW Pro - Pyme'!C:C,0)-1,MATCH(L13,'PVP VaP IEW Pro - Pyme'!$AA$22:$AH$22,0)), )), IF(M13="","SIN OFERTA",IF(M13="SI",IF(B17="SIN OFERTA",B17,IF(D13="IEW",OFFSET(CeldaInicioDxCIEW,MATCH(J13,'PVP Subv IEW - Pyme'!C:C,0)-1,MATCH(L13,'PVP Subv IEW - Pyme'!$I$4:$L$4,0)-1),OFFSET(IF(E13="portabilidad",CeldaInicioDxCPorta,CeldaInicioDxCCapta),MATCH(J13,'PVP Subv - Optima Pyme'!$C:$C,0)-1,MATCH(L13,'PVP Subv - Optima Pyme'!$I$4:$M$4,0)-1))), IF(B17="SIN OFERTA",B17,IF(D13="IEW",OFFSET(CeldaInicioDxCIEW,MATCH(J13,'PVP Subv IEW - Pyme'!C:C,0)-1,MATCH(L13,'PVP Subv IEW - Pyme'!$I$4:$L$4,0)-1),OFFSET(IF(E13="portabilidad",CeldaInicioDxCPorta9MAS,CeldaInicioDxCCapta9MAS),MATCH(J13,'PVP Subv - Sol Pers Pyme'!$C:$C,0)-1,MATCH(L13,'PVP Subv - Sol Pers Pyme'!$I$4:$M$4,0)-1))))))) +IF($F$1="SI", IF(I13="SI",IF(E13="portabilidad", IF(D13="multilínea",IF(AND(C13<>"Soluciones Personalizadas RPV",C13<>"Soluciones Personalizadas Centrex"), OFFSET(CeldaInicioDxCVAP,MATCH(J13,'PVP VaP - Pyme'!C:C,0)-1,MATCH(L13,'PVP VaP - Pyme'!$Z$22:$AL$22,0)-1) +OFFSET(CeldaInicioDxCVAP,MATCH(J13,'PVP VaP - Pyme'!C:C,0)-1,MATCH(L13,'PVP VaP - Pyme'!$Z$22:$AL$22,0)))), IF(D13="IEW", OFFSET(CeldaInicioDxCVAPIEW,MATCH(J13,'PVP VaP IEW Pro - Pyme'!C:C,0)-1,MATCH(L13,'PVP VaP IEW Pro - Pyme'!$AA$22:$AH$22,0)-1) +OFFSET(CeldaInicioDxCVAPIEW,MATCH(J13,'PVP VaP IEW Pro - Pyme'!C:C,0)-1,MATCH(L13,'PVP VaP IEW Pro - Pyme'!$AA$22:$AH$22,0)), )), IF(M13="","SIN OFERTA",IF(M13="SI",IF(B17="SIN OFERTA",B17,IF(D13="IEW",OFFSET(CeldaInicioDxCIEWAAPP,MATCH(J13,'PVP Subv IEW - Pyme AAPP'!C:C,0)-1,MATCH(L13,'PVP Subv IEW - Pyme AAPP'!$I$4:$L$4,0)-1),OFFSET(IF(E13="portabilidad",CeldaInicioDxCPortaAAPP,CeldaInicioDxCCaptaAAPP),MATCH(J13,'PVP Subv - Optima Pyme AAPP'!$C:$C,0)-1,MATCH(L13,'PVP Subv - Optima Pyme AAPP'!$I$4:$M$4,0)-1))), IF(B17="SIN OFERTA",B17,IF(D13="IEW",OFFSET(CeldaInicioDxCIEWAAPP,MATCH(J13,'PVP Subv IEW - Pyme AAPP'!C:C,0)-1,MATCH(L13,'PVP Subv IEW - Pyme AAPP'!$I$4:$L$4,0)-1),OFFSET(IF(E13="portabilidad",CeldaInicioDxCPorta9MASAAPP,CeldaInicioDxCCapta9MASAAPP),MATCH(J13,'PVP Subv - Sol Pers Pyme AAPP'!$C:$C,0)-1,MATCH(L13,'PVP Subv - Sol Pers Pyme AAPP'!$I$4:$M$4,0)-1))))))),"SIN OFERTA")+D16,"SIN OFERTA") -> SIN OFERTA | E16: =IFERROR(F16*B13,"SIN OFERTA") -> SIN OFERTA | F16: =IF(O13="SI",OFFSET(CeldadeinicioDxCportaCP36,MATCH(J13,'PVP Subv - Optima Pyme'!$C:$C,0)-1,MATCH(L13,'PVP Subv - Optima Pyme'!$BK$23:$BO$23,0)-1),"-") -> - | H16: =IFERROR(IF(N13="NO",0,SUMIFS(MR!$N$17:$N$21,MR!$M$17:$M$21,H15)),0) -> 0
A17: PVPR TERMINAL (sin IVA) | B17: =IFERROR(C17*B13,"SIN OFERTA") -> 0 | D17: Dif. CP 24 m | E17: =IF(E16="SIN OFERTA",0,(E16-B16)) -> 0 | F17: =IF(B16="SIN OFERTA",0,5*B13) -> 0 | G17: Válida en módulos: | H17: =IFERROR(INDEX(Tabla32[APLICA],MATCH(H15,Tabla32[PROMO],0)),"")
A18: PRECIO CESIÓN TERMINAL | B18: =IFERROR(C18*B13,"SIN OFERTA") -> SIN OFERTA | C18: =IF(M13="SI",IFERROR(-IF(D13="IEW",OFFSET(CeldaInicioPrecioCesiónIEW,MATCH(J13,'PVP Subv IEW - Pyme'!C:C,0)-1,0),OFFSET(CeldaInicioPrecioCesión,MATCH(J13,'PVP Subv - Optima Pyme'!$C:$C,0)-1,0)),"SIN OFERTA"), IFERROR(-IF(D13="IEW",OFFSET(CeldaInicioPrecioCesiónIEW,MATCH(J13,'PVP Subv IEW - Pyme'!C:C,0)-1,0),OFFSET(CeldaInicioPrecioCesión,MATCH(J13,'PVP Subv - Sol Pers Pyme'!$C:$C,0)-1,0)),"SIN OFERTA")) -> SIN OFERTA | H18: =IF(H16=12,H16+MR!$L$24,IF(H16=18,H16+MR!$L$23,IF(H16=48,H16+MR!$L$22,0))) -> 0
A19: MARGEN | B19: =IFERROR(B13*C19,"SIN OFERTA") -> 0 | C19: =IFERROR(C15+IF(NOT(ISNUMBER(C16)),0,C16)+IF(NOT(ISNUMBER(C17)),0,C17)+IF(NOT(ISNUMBER(C18)),0,C18),"SIN OFERTA") -> 0 | D19: MARGEN 36 | E19: =IFERROR(B13*F19,"SIN OFERTA") -> 0 | F19: =IFERROR(C19+(E17/B13),0) -> 0 | H19: =(H16-H18)*B13 -> 0 | I19: dif. Cp 24
A22: SUBVENCIÓN TERMINAL | B22: Nº ALTAS CON ESTE PERFIL | C22: TARIFA | D22: TIPO DE TARIFA | E22: TIPO DE ALTA | F22: PAQUETE DE VOZ Y DATOS | G22: CV USUARIO | H22: MFO CON FIJO PORTADO | I22: VENTA A PLAZOS | J22: TERMINAL | K22: GAMA | L22: MÓDULO OT | M22: ÓPTIMA | N22: O2O | O22: 36 m | P22: ESTRAT
A23: PERFIL DE ALTA | D23: =IFERROR(INDEX(MR!Q:Q,MATCH(C23,MR!P:P,0)),"") | I23: NO | K23: =IF(J23="","SIN TERMINAL",IF(D23="IEW",INDEX('PVP Subv IEW - Pyme'!F:F,MATCH(J23,'PVP Subv IEW - Pyme'!C:C,0)),INDEX('PVP Subv - Optima Pyme'!F:F,MATCH(J23,'PVP Subv - Optima Pyme'!C:C,0)))) -> SIN TERMINAL | L23: =IFERROR(IF(D23="IEW",INDEX('MODULOS OT IEW'!D:D,MATCH(C23,'MODULOS OT IEW'!A:A,0)),INDEX('MODULOS OT MULTILINEA'!F:F,MATCH(E23&F23&K23,'MODULOS OT MULTILINEA'!A:A,0))),"") | M23: =+IF(C23="","",IF(OR(C23="Óptima Plus Empresas",C23="Óptima Plus Empresas BIG"),"SI","NO")) | N23: =+IF(C23="","",IF($C$9="SI","NO",IF(OR(C23="Óptima Plus Empresas",C23="Óptima Plus Empresas BIG"),"SI","NO"))) | O23: =+IF(N23="NO","NO",IF(AND(E23="portabilidad",L23<>"ENTRADA PRO"),"SI","NO")) -> NO | P23: =IF(AND(E23="capta",F23="EMPRESAS VOZ"),0,1) -> 1
B24: IMPORTE TOTAL | C24: IMPORTE UNITARIO | D24: PAQUETE DE VOZ Y DATOS | E24: ACTIVACION | F24: ACTIVACION CP 24 POR TERMINAL | G24: SVAs | H24: O2O | I24: ESTRATEGICA | N24: =IF(N23="SI",1,0) -> 0
A25: COMISIONES | B25: =C25*B23 -> 0 | C25: =D25+E25+F25+G25-H26*N24+I25 -> 0 | D25: =IFERROR(IF(AND(M23="SI",$G$3="Cliente 1-19 líneas"),SUMIFS(MR!$B$5:$B$13,MR!$A$5:$A$13,F23),IF(AND(M23="SI",$G$3="Cliente 20-39 líneas"),SUMIFS(MR!$C$5:$C$13,MR!$A$5:$A$13,F23),IF(AND(M23="SI",$G$3="Cliente > 40 líneas"),SUMIFS(MR!$D$5:$D$13,MR!$A$5:$A$13,F23),IF(AND(M23="NO",$G$3="Cliente 1-19 líneas"),SUMIFS(MR!$B$17:$B$25,MR!$A$17:$A$25,F23),IF(AND(M23="NO",$G$3="Cliente 20-39 líneas"),SUMIFS(MR!$C$17:$C$25,MR!$A$17:$A$25,F23),IF(AND(M23="NO",$G$3="Cliente > 40 líneas"),SUMIFS(MR!$D$17:$D$25,MR!$A$17:$A$25,F23),0)))))),)+IFERROR(IF(AND(M23="SI",$G$3="Cliente 1-19 líneas"),SUMIFS(MR!$B$30:$B$37,MR!$A$30:$A$37,F23),IF(AND(M23="SI",$G$3="Cliente 20-39 líneas"),SUMIFS(MR!$C$30:$C$37,MR!$A$30:$A$37,F23),IF(AND(M23="SI",$G$3="Cliente > 40 líneas"),SUMIFS(MR!$D$30:$D$37,MR!$A$30:$A$37,F23),IF(AND(M23="NO",$G$3="Cliente 1-19 líneas"),SUMIFS(MR!$B$41:$B$48,MR!$A$41:$A$48,F23),IF(AND(M23="NO",$G$3="Cliente 20-39 líneas"),SUMIFS(MR!$C$41:$C$48,MR!$A$41:$A$48,F23),IF(AND(M23="NO",$G$3="Cliente > 40 líneas"),SUMIFS(MR!$D$41:$D$48,MR!$A$41:$A$48,F23),0)))))),) -> 0 | E25: =IFERROR(IF(AND(M23="SI",E23="capta",D23="multilínea"),SUMIFS(MR!$E$5:$E$13,MR!$A$5:$A$13,F23),IF(AND(M23="SI",E23="portabilidad",D23="multilínea"),SUMIFS(MR!$F$5:$F$13,MR!$A$5:$A$13,F23),IF(AND(M23="NO",E23="capta",D23="multilínea"),SUMIFS(MR!$E$17:$E$25,MR!$A$17:$A$25,F23),IF(AND(M23="NO",E23="portabilidad",D23="multilínea"),SUMIFS(MR!$F$17:$F$25,MR!$A$17:$A$25,F23),IF(AND(M23="NO",E23="capta",D23="IEW"),SUMIFS(MR!$B$53:$B$61,MR!$A$53:$A$61,C23),IF(AND(M23="NO",E23="portabilidad",D23="IEW"),SUMIFS(MR!$B$53:$B$61,MR!$A$53:$A$61,C23),0)))))),)+IFERROR(IF(AND(M23="SI",E23="capta",D23="multilínea"),SUMIFS(MR!$E$30:$E$37,MR!$A$30:$A$37,F23),IF(AND(M23="SI",E23="portabilidad",D23="multilínea"),SUMIFS(MR!$F$30:$F$37,MR!$A$30:$A$37,F23),IF(AND(M23="NO",E23="capta",D23="multilínea"),SUMIFS(MR!$E$48:$E$398,MR!$A$41:$A$48,F23),IF(AND(M23="NO",E23="portabilidad",D23="multilínea"),SUMIFS(MR!$F$41:$F$48,MR!$A$41:$A$48,F23),0)))),) -> 0 | F25: =(IFERROR(IF(K23="SIN TERMINAL",0,IF(I23="SI",10,SUMIFS(MR!$G$6:$G$11,MR!$A$6:$A$11,F23))),0))*K25 -> 0 | G25: =IFERROR(IF(D23="multilínea",IF(G23="SI",MR!$N$4,0)+IF(H23="SI",MR!$N$5,0),0),0) -> 0 | I25: =(IF(D23="multilínea",IF($F$9="SI",IF($M23="SI",SUMIFS(MR!$I$6:$I$11,MR!$A$6:$A$11,F23),SUMIFS(MR!$I$18:$I$23,MR!$A$18:$A$23,F23))),SUMIFS(MR!$D$54:$D$61,MR!$A$54:$A$61,C23)))*P23 -> 0 | J25: =IF(M23="SI",IF($B$13+$B$23>99,(99-$B$13)*I25,B23*I25),B23*I25) -> 0 | K25: =IF(IFERROR(SEARCH("CESIÓN",$J23,1),0)>0,0,1) -> 1
A26: SUBVENCIÓN TERMINAL | B26: =IFERROR(C26*B23,"SIN OFERTA") -> SIN OFERTA | C26: =IFERROR(IFERROR(IF($F$1="NO", IF(I23="SI",IF(E23="portabilidad", IF(D23="multilínea",IF(AND(C23<>"Soluciones Personalizadas RPV",C23<>"Soluciones Personalizadas Centrex"), OFFSET(CeldaInicioDxCVAP,MATCH(J23,'PVP VaP - Pyme'!C:C,0)-1,MATCH(L23,'PVP VaP - Pyme'!$Z$22:$AL$22,0)-1) +OFFSET(CeldaInicioDxCVAP,MATCH(J23,'PVP VaP - Pyme'!C:C,0)-1,MATCH(L23,'PVP VaP - Pyme'!$Z$22:$AL$22,0)))), IF(D23="IEW", OFFSET(CeldaInicioDxCVAPIEW,MATCH(J23,'PVP VaP IEW Pro - Pyme'!C:C,0)-1,MATCH(L23,'PVP VaP IEW Pro - Pyme'!$AA$22:$AH$22,0)-1) +OFFSET(CeldaInicioDxCVAPIEW,MATCH(J23,'PVP VaP IEW Pro - Pyme'!C:C,0)-1,MATCH(L23,'PVP VaP IEW Pro - Pyme'!$AA$22:$AH$22,0)), )), IF(M23="","SIN OFERTA",IF(M23="SI",IF(B27="SIN OFERTA",B27,IF(D23="IEW",OFFSET(CeldaInicioDxCIEW,MATCH(J23,'PVP Subv IEW - Pyme'!C:C,0)-1,MATCH(L23,'PVP Subv IEW - Pyme'!$I$4:$L$4,0)-1),OFFSET(IF(E23="portabilidad",CeldaInicioDxCPorta,CeldaInicioDxCCapta),MATCH(J23,'PVP Subv - Optima Pyme'!$C:$C,0)-1,MATCH(L23,'PVP Subv - Optima Pyme'!$I$4:$M$4,0)-1))), IF(B27="SIN OFERTA",B27,IF(D23="IEW",OFFSET(CeldaInicioDxCIEW,MATCH(J23,'PVP Subv IEW - Pyme'!C:C,0)-1,MATCH(L23,'PVP Subv IEW - Pyme'!$I$4:$L$4,0)-1),OFFSET(IF(E23="portabilidad",CeldaInicioDxCPorta9MAS,CeldaInicioDxCCapta9MAS),MATCH(J23,'PVP Subv - Sol Pers Pyme'!$C:$C,0)-1,MATCH(L23,'PVP Subv - Sol Pers Pyme'!$I$4:$M$4,0)-1))))))) +IF($F$1="SI", IF(I23="SI",IF(E23="portabilidad", IF(D23="multilínea",IF(AND(C23<>"Soluciones Personalizadas RPV",C23<>"Soluciones Personalizadas Centrex"), OFFSET(CeldaInicioDxCVAP,MATCH(J23,'PVP VaP - Pyme'!C:C,0)-1,MATCH(L23,'PVP VaP - Pyme'!$Z$22:$AL$22,0)-1) +OFFSET(CeldaInicioDxCVAP,MATCH(J23,'PVP VaP - Pyme'!C:C,0)-1,MATCH(L23,'PVP VaP - Pyme'!$Z$22:$AL$22,0)))), IF(D23="IEW", OFFSET(CeldaInicioDxCVAPIEW,MATCH(J23,'PVP VaP IEW Pro - Pyme'!C:C,0)-1,MATCH(L23,'PVP VaP IEW Pro - Pyme'!$AA$22:$AH$22,0)-1) +OFFSET(CeldaInicioDxCVAPIEW,MATCH(J23,'PVP VaP IEW Pro - Pyme'!C:C,0)-1,MATCH(L23,'PVP VaP IEW Pro - Pyme'!$AA$22:$AH$22,0)), )), IF(M23="","SIN OFERTA",IF(M23="SI",IF(B27="SIN OFERTA",B27,IF(D23="IEW",OFFSET(CeldaInicioDxCIEWAAPP,MATCH(J23,'PVP Subv IEW - Pyme AAPP'!C:C,0)-1,MATCH(L23,'PVP Subv IEW - Pyme AAPP'!$I$4:$L$4,0)-1),OFFSET(IF(E23="portabilidad",CeldaInicioDxCPortaAAPP,CeldaInicioDxCCaptaAAPP),MATCH(J23,'PVP Subv - Optima Pyme AAPP'!$C:$C,0)-1,MATCH(L23,'PVP Subv - Optima Pyme AAPP'!$I$4:$M$4,0)-1))), IF(B27="SIN OFERTA",B27,IF(D23="IEW",OFFSET(CeldaInicioDxCIEWAAPP,MATCH(J23,'PVP Subv IEW - Pyme AAPP'!C:C,0)-1,MATCH(L23,'PVP Subv IEW - Pyme AAPP'!$I$4:$L$4,0)-1),OFFSET(IF(E23="portabilidad",CeldaInicioDxCPorta9MASAAPP,CeldaInicioDxCCapta9MASAAPP),MATCH(J23,'PVP Subv - Sol Pers Pyme AAPP'!$C:$C,0)-1,MATCH(L23,'PVP Subv - Sol Pers Pyme AAPP'!$I$4:$M$4,0)-1))))))),"SIN OFERTA")+D26,"SIN OFERTA") -> SIN OFERTA | E26: =IFERROR(F26*B23,"SIN OFERTA") -> SIN OFERTA | F26: =IF(O23="SI",OFFSET(CeldadeinicioDxCportaCP36,MATCH(J23,'PVP Subv - Optima Pyme'!$C:$C,0)-1,MATCH(L23,'PVP Subv - Optima Pyme'!$BK$23:$BO$23,0)-1),"-") -> - | H26: =IFERROR(IF(N23="NO",0,SUMIFS(MR!$N$17:$N$21,MR!$M$17:$M$21,H25)),0) -> 0
A27: PVPR TERMINAL (sin IVA) | B27: =IFERROR(C27*B23,"SIN OFERTA") -> 0 | D27: Dif. CP 24 m | E27: =IF(E26="SIN OFERTA",0,(E26-B26)) -> 0 | F27: =IF(B26="SIN OFERTA",0,5*B23) -> 0 | G27: Válida en módulos: | H27: =IFERROR(INDEX(Tabla32[APLICA],MATCH(H25,Tabla32[PROMO],0)),"")
A28: PRECIO CESIÓN TERMINAL | B28: =IFERROR(C28*B23,"SIN OFERTA") -> SIN OFERTA | C28: =IF(M23="SI",IFERROR(-IF(D23="IEW",OFFSET(CeldaInicioPrecioCesiónIEW,MATCH(J23,'PVP Subv IEW - Pyme'!C:C,0)-1,0),OFFSET(CeldaInicioPrecioCesión,MATCH(J23,'PVP Subv - Optima Pyme'!$C:$C,0)-1,0)),"SIN OFERTA"), IFERROR(-IF(D23="IEW",OFFSET(CeldaInicioPrecioCesiónIEW,MATCH(J23,'PVP Subv IEW - Pyme'!C:C,0)-1,0),OFFSET(CeldaInicioPrecioCesión,MATCH(J23,'PVP Subv - Sol Pers Pyme'!$C:$C,0)-1,0)),"SIN OFERTA")) -> SIN OFERTA | H28: =IF(H26=12,H26+MR!$L$24,IF(H26=18,H26+MR!$L$23,IF(H26=48,H26+MR!$L$22,0))) -> 0
A29: MARGEN | B29: =IFERROR(B23*C29,"SIN OFERTA") -> 0 | C29: =IFERROR(C25+IF(NOT(ISNUMBER(C26)),0,C26)+IF(NOT(ISNUMBER(C27)),0,C27)+IF(NOT(ISNUMBER(C28)),0,C28),"SIN OFERTA") -> 0 | D29: MARGEN 36 | E29: =IFERROR(B23*F29,"SIN OFERTA") -> 0 | F29: =IFERROR(C29+(E27/B23),0) -> 0 | H29: =(H26-H28)*B23 -> 0 | I29: dif. Cp 24
B32: Nº ALTAS CON ESTE PERFIL | C32: TARIFA | D32: TIPO DE TARIFA | E32: TIPO DE ALTA | F32: PAQUETE DE VOZ Y DATOS | G32: CV USUARIO | H32: MFO CON FIJO PORTADO | I32: VENTA A PLAZOS | J32: TERMINAL | K32: GAMA | L32: MÓDULO OT | M32: ÓPTIMA | N32: O2O | O32: 36 m | P32: ESTRAT
A33: PERFIL DE ALTA | D33: =IFERROR(INDEX(MR!Q:Q,MATCH(C33,MR!P:P,0)),"") | I33: NO | K33: =IF(J33="","SIN TERMINAL",IF(D33="IEW",INDEX('PVP Subv IEW - Pyme'!F:F,MATCH(J33,'PVP Subv IEW - Pyme'!C:C,0)),INDEX('PVP Subv - Optima Pyme'!F:F,MATCH(J33,'PVP Subv - Optima Pyme'!C:C,0)))) -> SIN TERMINAL | L33: =IFERROR(IF(D33="IEW",INDEX('MODULOS OT IEW'!D:D,MATCH(C33,'MODULOS OT IEW'!A:A,0)),INDEX('MODULOS OT MULTILINEA'!F:F,MATCH(E33&F33&K33,'MODULOS OT MULTILINEA'!A:A,0))),"") | M33: =+IF(C33="","",IF(OR(C33="Óptima Plus Empresas",C33="Óptima Plus Empresas BIG"),"SI","NO")) | N33: =+IF(C33="","",IF($C$9="SI","NO",IF(OR(C33="Óptima Plus Empresas",C33="Óptima Plus Empresas BIG"),"SI","NO"))) | O33: =+IF(N33="NO","NO",IF(AND(E33="portabilidad",L33<>"ENTRADA PRO"),"SI","NO")) -> NO | P33: =IF(AND(E33="capta",F33="EMPRESAS VOZ"),0,1) -> 1
C34: IMPORTE UNITARIO | D34: PAQUETE DE VOZ Y DATOS | E34: ACTIVACION | F34: ACTIVACION CP 24 POR TERMINAL | G34: SVAs | H34: O2O | I34: ESTRATEGICA | N34: =IF(N33="SI",1,0) -> 0
A35: COMISIONES | B35: =C35*B33 -> 0 | C35: =D35+E35+F35+G35-H36*N34+I35 -> 0 | D35: =IFERROR(IF(AND(M33="SI",$G$3="Cliente 1-19 líneas"),SUMIFS(MR!$B$5:$B$13,MR!$A$5:$A$13,F33),IF(AND(M33="SI",$G$3="Cliente 20-39 líneas"),SUMIFS(MR!$C$5:$C$13,MR!$A$5:$A$13,F33),IF(AND(M33="SI",$G$3="Cliente > 40 líneas"),SUMIFS(MR!$D$5:$D$13,MR!$A$5:$A$13,F33),IF(AND(M33="NO",$G$3="Cliente 1-19 líneas"),SUMIFS(MR!$B$17:$B$25,MR!$A$17:$A$25,F33),IF(AND(M33="NO",$G$3="Cliente 20-39 líneas"),SUMIFS(MR!$C$17:$C$25,MR!$A$17:$A$25,F33),IF(AND(M33="NO",$G$3="Cliente > 40 líneas"),SUMIFS(MR!$D$17:$D$25,MR!$A$17:$A$25,F33),0)))))),)+IFERROR(IF(AND(M33="SI",$G$3="Cliente 1-19 líneas"),SUMIFS(MR!$B$30:$B$37,MR!$A$30:$A$37,F33),IF(AND(M33="SI",$G$3="Cliente 20-39 líneas"),SUMIFS(MR!$C$30:$C$37,MR!$A$30:$A$37,F33),IF(AND(M33="SI",$G$3="Cliente > 40 líneas"),SUMIFS(MR!$D$30:$D$37,MR!$A$30:$A$37,F33),IF(AND(M33="NO",$G$3="Cliente 1-19 líneas"),SUMIFS(MR!$B$41:$B$48,MR!$A$41:$A$48,F33),IF(AND(M33="NO",$G$3="Cliente 20-39 líneas"),SUMIFS(MR!$C$41:$C$48,MR!$A$41:$A$48,F33),IF(AND(M33="NO",$G$3="Cliente > 40 líneas"),SUMIFS(MR!$D$41:$D$48,MR!$A$41:$A$48,F33),0)))))),) -> 0 | E35: =IFERROR(IF(AND(M33="SI",E33="capta",D33="multilínea"),SUMIFS(MR!$E$5:$E$13,MR!$A$5:$A$13,F33),IF(AND(M33="SI",E33="portabilidad",D33="multilínea"),SUMIFS(MR!$F$5:$F$13,MR!$A$5:$A$13,F33),IF(AND(M33="NO",E33="capta",D33="multilínea"),SUMIFS(MR!$E$17:$E$25,MR!$A$17:$A$25,F33),IF(AND(M33="NO",E33="portabilidad",D33="multilínea"),SUMIFS(MR!$F$17:$F$25,MR!$A$17:$A$25,F33),IF(AND(M33="NO",E33="capta",D33="IEW"),SUMIFS(MR!$B$53:$B$61,MR!$A$53:$A$61,C33),IF(AND(M33="NO",E33="portabilidad",D33="IEW"),SUMIFS(MR!$B$53:$B$61,MR!$A$53:$A$61,C33),0)))))),)+IFERROR(IF(AND(M33="SI",E33="capta",D33="multilínea"),SUMIFS(MR!$E$30:$E$37,MR!$A$30:$A$37,F33),IF(AND(M33="SI",E33="portabilidad",D33="multilínea"),SUMIFS(MR!$F$30:$F$37,MR!$A$30:$A$37,F33),IF(AND(M33="NO",E33="capta",D33="multilínea"),SUMIFS(MR!$E$48:$E$398,MR!$A$41:$A$48,F33),IF(AND(M33="NO",E33="portabilidad",D33="multilínea"),SUMIFS(MR!$F$41:$F$48,MR!$A$41:$A$48,F33),0)))),) -> 0 | F35: =(IFERROR(IF(K33="SIN TERMINAL",0,IF(I33="SI",10,SUMIFS(MR!$G$6:$G$11,MR!$A$6:$A$11,F33))),0))*K35 -> 0 | G35: =IFERROR(IF(D33="multilínea",IF(G33="SI",MR!$N$4,0)+IF(H33="SI",MR!$N$5,0),0),0) -> 0 | I35: =(IF(D33="multilínea",IF($F$9="SI",IF($M33="SI",SUMIFS(MR!$I$6:$I$11,MR!$A$6:$A$11,F33),SUMIFS(MR!$I$18:$I$23,MR!$A$18:$A$23,F33))),SUMIFS(MR!$D$54:$D$61,MR!$A$54:$A$61,C33)))*P33 -> 0 | J35: =IF(M33="SI",IF($B$13+$B$23+$B$33>99,(99-$B$13-$B$23)*I35,B33*I35),B33*I35) -> 0 | K35: =IF(IFERROR(SEARCH("CESIÓN",$J33,1),0)>0,0,1) -> 1
A36: SUBVENCIÓN TERMINAL | B36: =IFERROR(C36*B33,"SIN OFERTA") -> SIN OFERTA | C36: =IFERROR(IFERROR(IF($F$1="NO", IF(I33="SI",IF(E33="portabilidad", IF(D33="multilínea",IF(AND(C33<>"Soluciones Personalizadas RPV",C33<>"Soluciones Personalizadas Centrex"), OFFSET(CeldaInicioDxCVAP,MATCH(J33,'PVP VaP - Pyme'!C:C,0)-1,MATCH(L33,'PVP VaP - Pyme'!$Z$22:$AL$22,0)-1) +OFFSET(CeldaInicioDxCVAP,MATCH(J33,'PVP VaP - Pyme'!C:C,0)-1,MATCH(L33,'PVP VaP - Pyme'!$Z$22:$AL$22,0)))), IF(D33="IEW", OFFSET(CeldaInicioDxCVAPIEW,MATCH(J33,'PVP VaP IEW Pro - Pyme'!C:C,0)-1,MATCH(L33,'PVP VaP IEW Pro - Pyme'!$AA$22:$AH$22,0)-1) +OFFSET(CeldaInicioDxCVAPIEW,MATCH(J33,'PVP VaP IEW Pro - Pyme'!C:C,0)-1,MATCH(L33,'PVP VaP IEW Pro - Pyme'!$AA$22:$AH$22,0)), )), IF(M33="","SIN OFERTA",IF(M33="SI",IF(B37="SIN OFERTA",B37,IF(D33="IEW",OFFSET(CeldaInicioDxCIEW,MATCH(J33,'PVP Subv IEW - Pyme'!C:C,0)-1,MATCH(L33,'PVP Subv IEW - Pyme'!$I$4:$L$4,0)-1),OFFSET(IF(E33="portabilidad",CeldaInicioDxCPorta,CeldaInicioDxCCapta),MATCH(J33,'PVP Subv - Optima Pyme'!$C:$C,0)-1,MATCH(L33,'PVP Subv - Optima Pyme'!$I$4:$M$4,0)-1))), IF(B37="SIN OFERTA",B37,IF(D33="IEW",OFFSET(CeldaInicioDxCIEW,MATCH(J33,'PVP Subv IEW - Pyme'!C:C,0)-1,MATCH(L33,'PVP Subv IEW - Pyme'!$I$4:$L$4,0)-1),OFFSET(IF(E33="portabilidad",CeldaInicioDxCPorta9MAS,CeldaInicioDxCCapta9MAS),MATCH(J33,'PVP Subv - Sol Pers Pyme'!$C:$C,0)-1,MATCH(L33,'PVP Subv - Sol Pers Pyme'!$I$4:$M$4,0)-1))))))) +IF($F$1="SI", IF(I33="SI",IF(E33="portabilidad", IF(D33="multilínea",IF(AND(C33<>"Soluciones Personalizadas RPV",C33<>"Soluciones Personalizadas Centrex"), OFFSET(CeldaInicioDxCVAP,MATCH(J33,'PVP VaP - Pyme'!C:C,0)-1,MATCH(L33,'PVP VaP - Pyme'!$Z$22:$AL$22,0)-1) +OFFSET(CeldaInicioDxCVAP,MATCH(J33,'PVP VaP - Pyme'!C:C,0)-1,MATCH(L33,'PVP VaP - Pyme'!$Z$22:$AL$22,0)))), IF(D33="IEW", OFFSET(CeldaInicioDxCVAPIEW,MATCH(J33,'PVP VaP IEW Pro - Pyme'!C:C,0)-1,MATCH(L33,'PVP VaP IEW Pro - Pyme'!$AA$22:$AH$22,0)-1) +OFFSET(CeldaInicioDxCVAPIEW,MATCH(J33,'PVP VaP IEW Pro - Pyme'!C:C,0)-1,MATCH(L33,'PVP VaP IEW Pro - Pyme'!$AA$22:$AH$22,0)), )), IF(M33="","SIN OFERTA",IF(M33="SI",IF(B37="SIN OFERTA",B37,IF(D33="IEW",OFFSET(CeldaInicioDxCIEWAAPP,MATCH(J33,'PVP Subv IEW - Pyme AAPP'!C:C,0)-1,MATCH(L33,'PVP Subv IEW - Pyme AAPP'!$I$4:$L$4,0)-1),OFFSET(IF(E33="portabilidad",CeldaInicioDxCPortaAAPP,CeldaInicioDxCCaptaAAPP),MATCH(J33,'PVP Subv - Optima Pyme AAPP'!$C:$C,0)-1,MATCH(L33,'PVP Subv - Optima Pyme AAPP'!$I$4:$M$4,0)-1))), IF(B37="SIN OFERTA",B37,IF(D33="IEW",OFFSET(CeldaInicioDxCIEWAAPP,MATCH(J33,'PVP Subv IEW - Pyme AAPP'!C:C,0)-1,MATCH(L33,'PVP Subv IEW - Pyme AAPP'!$I$4:$L$4,0)-1),OFFSET(IF(E33="portabilidad",CeldaInicioDxCPorta9MASAAPP,CeldaInicioDxCCapta9MASAAPP),MATCH(J33,'PVP Subv - Sol Pers Pyme AAPP'!$C:$C,0)-1,MATCH(L33,'PVP Subv - Sol Pers Pyme AAPP'!$I$4:$M$4,0)-1))))))),"SIN OFERTA")+D36,"SIN OFERTA") -> SIN OFERTA | E36: =IFERROR(F36*B33,"SIN OFERTA") -> SIN OFERTA | F36: =IF(O33="SI",OFFSET(CeldadeinicioDxCportaCP36,MATCH(J33,'PVP Subv - Optima Pyme'!$C:$C,0)-1,MATCH(L33,'PVP Subv - Optima Pyme'!$BK$23:$BO$23,0)-1),"-") -> - | H36: =IFERROR(IF(N33="NO",0,SUMIFS(MR!$N$17:$N$21,MR!$M$17:$M$21,H35)),0) -> 0
A37: PVPR TERMINAL (sin IVA) | B37: =IFERROR(C37*B33,"SIN OFERTA") -> 0 | D37: Dif. CP 24 m | E37: =IF(E36="SIN OFERTA",0,(E36-B36)) -> 0 | F37: =IF(B36="SIN OFERTA",0,5*B33) -> 0 | G37: Válida en módulos: | H37: =IFERROR(INDEX(Tabla32[APLICA],MATCH(H35,Tabla32[PROMO],0)),"")
A38: PRECIO CESIÓN TERMINAL | B38: =IFERROR(C38*B33,"SIN OFERTA") -> SIN OFERTA | C38: =IF(M33="SI",IFERROR(-IF(D33="IEW",OFFSET(CeldaInicioPrecioCesiónIEW,MATCH(J33,'PVP Subv IEW - Pyme'!C:C,0)-1,0),OFFSET(CeldaInicioPrecioCesión,MATCH(J33,'PVP Subv - Optima Pyme'!$C:$C,0)-1,0)),"SIN OFERTA"), IFERROR(-IF(D33="IEW",OFFSET(CeldaInicioPrecioCesiónIEW,MATCH(J33,'PVP Subv IEW - Pyme'!C:C,0)-1,0),OFFSET(CeldaInicioPrecioCesión,MATCH(J33,'PVP Subv - Sol Pers Pyme'!$C:$C,0)-1,0)),"SIN OFERTA")) -> SIN OFERTA | H38: =IF(H36=12,H36+MR!$L$24,IF(H36=18,H36+MR!$L$23,IF(H36=48,H36+MR!$L$22,0))) -> 0
A39: MARGEN | B39: =IFERROR(B33*C39,"SIN OFERTA") -> 0 | C39: =IFERROR(C35+IF(NOT(ISNUMBER(C36)),0,C36)+IF(NOT(ISNUMBER(C37)),0,C37)+IF(NOT(ISNUMBER(C38)),0,C38),"SIN OFERTA") -> 0 | D39: MARGEN 36 | E39: =IFERROR(B33*F39,"SIN OFERTA") -> 0 | F39: =IFERROR(C39+(E37/B33),0) -> 0 | H39: =(H36-H38)*B33 -> 0 | I39: dif. Cp 24
B42: Nº ALTAS CON ESTE PERFIL | C42: TARIFA | D42: TIPO DE TARIFA | E42: TIPO DE ALTA | F42: PAQUETE DE VOZ Y DATOS | G42: CV USUARIO | H42: MFO CON FIJO PORTADO | I42: VENTA A PLAZOS | J42: TERMINAL | K42: GAMA | L42: MÓDULO OT | M42: ÓPTIMA | N42: O2O | O42: 36 m | P42: ESTRAT
A43: PERFIL DE ALTA | D43: =IFERROR(INDEX(MR!Q:Q,MATCH(C43,MR!P:P,0)),"") | K43: =IF(J43="","SIN TERMINAL",IF(D43="IEW",INDEX('PVP Subv IEW - Pyme'!F:F,MATCH(J43,'PVP Subv IEW - Pyme'!C:C,0)),INDEX('PVP Subv - Optima Pyme'!F:F,MATCH(J43,'PVP Subv - Optima Pyme'!C:C,0)))) -> SIN TERMINAL | L43: =IFERROR(IF(D43="IEW",INDEX('MODULOS OT IEW'!D:D,MATCH(C43,'MODULOS OT IEW'!A:A,0)),INDEX('MODULOS OT MULTILINEA'!F:F,MATCH(E43&F43&K43,'MODULOS OT MULTILINEA'!A:A,0))),"") | M43: =+IF(C43="","",IF(OR(C43="Óptima Plus Empresas",C43="Óptima Plus Empresas BIG"),"SI","NO")) | N43: =+IF(C43="","",IF($C$9="SI","NO",IF(OR(C43="Óptima Plus Empresas",C43="Óptima Plus Empresas BIG"),"SI","NO"))) | O43: =+IF(N43="NO","NO",IF(AND(E43="portabilidad",L43<>"ENTRADA PRO"),"SI","NO")) -> NO | P43: =IF(AND(E43="capta",F43="EMPRESAS VOZ"),0,1) -> 1
B44: IMPORTE TOTAL | C44: IMPORTE UNITARIO | D44: PAQUETE DE VOZ Y DATOS | E44: ACTIVACION | F44: ACTIVACION CP 24 POR TERMINAL | G44: SVAs | H44: O2O | I44: ESTRATEGICA | N44: =IF(N43="SI",1,0) -> 0
A45: COMISIONES | B45: =C45*B43 -> 0 | C45: =D45+E45+F45+G45-H46*N44+I45 -> 0 | D45: =IFERROR(IF(AND(M43="SI",$G$3="Cliente 1-19 líneas"),SUMIFS(MR!$B$5:$B$13,MR!$A$5:$A$13,F43),IF(AND(M43="SI",$G$3="Cliente 20-39 líneas"),SUMIFS(MR!$C$5:$C$13,MR!$A$5:$A$13,F43),IF(AND(M43="SI",$G$3="Cliente > 40 líneas"),SUMIFS(MR!$D$5:$D$13,MR!$A$5:$A$13,F43),IF(AND(M43="NO",$G$3="Cliente 1-19 líneas"),SUMIFS(MR!$B$17:$B$25,MR!$A$17:$A$25,F43),IF(AND(M43="NO",$G$3="Cliente 20-39 líneas"),SUMIFS(MR!$C$17:$C$25,MR!$A$17:$A$25,F43),IF(AND(M43="NO",$G$3="Cliente > 40 líneas"),SUMIFS(MR!$D$17:$D$25,MR!$A$17:$A$25,F43),0)))))),)+IFERROR(IF(AND(M43="SI",$G$3="Cliente 1-19 líneas"),SUMIFS(MR!$B$30:$B$37,MR!$A$30:$A$37,F43),IF(AND(M43="SI",$G$3="Cliente 20-39 líneas"),SUMIFS(MR!$C$30:$C$37,MR!$A$30:$A$37,F43),IF(AND(M43="SI",$G$3="Cliente > 40 líneas"),SUMIFS(MR!$D$30:$D$37,MR!$A$30:$A$37,F43),IF(AND(M43="NO",$G$3="Cliente 1-19 líneas"),SUMIFS(MR!$B$41:$B$48,MR!$A$41:$A$48,F43),IF(AND(M43="NO",$G$3="Cliente 20-39 líneas"),SUMIFS(MR!$C$41:$C$48,MR!$A$41:$A$48,F43),IF(AND(M43="NO",$G$3="Cliente > 40 líneas"),SUMIFS(MR!$D$41:$D$48,MR!$A$41:$A$48,F43),0)))))),) -> 0 | E45: =IFERROR(IF(AND(M43="SI",E43="capta",D43="multilínea"),SUMIFS(MR!$E$5:$E$13,MR!$A$5:$A$13,F43),IF(AND(M43="SI",E43="portabilidad",D43="multilínea"),SUMIFS(MR!$F$5:$F$13,MR!$A$5:$A$13,F43),IF(AND(M43="NO",E43="capta",D43="multilínea"),SUMIFS(MR!$E$17:$E$25,MR!$A$17:$A$25,F43),IF(AND(M43="NO",E43="portabilidad",D43="multilínea"),SUMIFS(MR!$F$17:$F$25,MR!$A$17:$A$25,F43),IF(AND(M43="NO",E43="capta",D43="IEW"),SUMIFS(MR!$B$53:$B$61,MR!$A$53:$A$61,C43),IF(AND(M43="NO",E43="portabilidad",D43="IEW"),SUMIFS(MR!$B$53:$B$61,MR!$A$53:$A$61,C43),0)))))),)+IFERROR(IF(AND(M43="SI",E43="capta",D43="multilínea"),SUMIFS(MR!$E$30:$E$37,MR!$A$30:$A$37,F43),IF(AND(M43="SI",E43="portabilidad",D43="multilínea"),SUMIFS(MR!$F$30:$F$37,MR!$A$30:$A$37,F43),IF(AND(M43="NO",E43="capta",D43="multilínea"),SUMIFS(MR!$E$48:$E$398,MR!$A$41:$A$48,F43),IF(AND(M43="NO",E43="portabilidad",D43="multilínea"),SUMIFS(MR!$F$41:$F$48,MR!$A$41:$A$48,F43),0)))),) -> 0 | F45: =(IFERROR(IF(K43="SIN TERMINAL",0,IF(I43="SI",10,SUMIFS(MR!$G$6:$G$11,MR!$A$6:$A$11,F43))),0))*K45 -> 0 | G45: =IFERROR(IF(D43="multilínea",IF(G43="SI",MR!$N$4,0)+IF(H43="SI",MR!$N$5,0),0),0) -> 0 | I45: =(IF(D43="multilínea",IF($F$9="SI",IF($M43="SI",SUMIFS(MR!$I$6:$I$11,MR!$A$6:$A$11,F43),SUMIFS(MR!$I$18:$I$23,MR!$A$18:$A$23,F43))),SUMIFS(MR!$D$54:$D$61,MR!$A$54:$A$61,C43)))*P43 -> 0 | J45: =IF(M43="SI",IF($B$13+$B$23+$B$33+$B$43>99,(99-$B$13-$B$23-$B$33)*I45,B43*I45),B43*I45) -> 0 | K45: =IF(IFERROR(SEARCH("CESIÓN",$J43,1),0)>0,0,1) -> 1
A46: SUBVENCIÓN TERMINAL | B46: =IFERROR(C46*B43,"SIN OFERTA") -> SIN OFERTA | C46: =IFERROR(IFERROR(IF($F$1="NO", IF(I43="SI",IF(E43="portabilidad", IF(D43="multilínea",IF(AND(C43<>"Soluciones Personalizadas RPV",C43<>"Soluciones Personalizadas Centrex"), OFFSET(CeldaInicioDxCVAP,MATCH(J43,'PVP VaP - Pyme'!C:C,0)-1,MATCH(L43,'PVP VaP - Pyme'!$Z$22:$AL$22,0)-1) +OFFSET(CeldaInicioDxCVAP,MATCH(J43,'PVP VaP - Pyme'!C:C,0)-1,MATCH(L43,'PVP VaP - Pyme'!$Z$22:$AL$22,0)))), IF(D43="IEW", OFFSET(CeldaInicioDxCVAPIEW,MATCH(J43,'PVP VaP IEW Pro - Pyme'!C:C,0)-1,MATCH(L43,'PVP VaP IEW Pro - Pyme'!$AA$22:$AH$22,0)-1) +OFFSET(CeldaInicioDxCVAPIEW,MATCH(J43,'PVP VaP IEW Pro - Pyme'!C:C,0)-1,MATCH(L43,'PVP VaP IEW Pro - Pyme'!$AA$22:$AH$22,0)), )), IF(M43="","SIN OFERTA",IF(M43="SI",IF(B47="SIN OFERTA",B47,IF(D43="IEW",OFFSET(CeldaInicioDxCIEW,MATCH(J43,'PVP Subv IEW - Pyme'!C:C,0)-1,MATCH(L43,'PVP Subv IEW - Pyme'!$I$4:$L$4,0)-1),OFFSET(IF(E43="portabilidad",CeldaInicioDxCPorta,CeldaInicioDxCCapta),MATCH(J43,'PVP Subv - Optima Pyme'!$C:$C,0)-1,MATCH(L43,'PVP Subv - Optima Pyme'!$I$4:$M$4,0)-1))), IF(B47="SIN OFERTA",B47,IF(D43="IEW",OFFSET(CeldaInicioDxCIEW,MATCH(J43,'PVP Subv IEW - Pyme'!C:C,0)-1,MATCH(L43,'PVP Subv IEW - Pyme'!$I$4:$L$4,0)-1),OFFSET(IF(E43="portabilidad",CeldaInicioDxCPorta9MAS,CeldaInicioDxCCapta9MAS),MATCH(J43,'PVP Subv - Sol Pers Pyme'!$C:$C,0)-1,MATCH(L43,'PVP Subv - Sol Pers Pyme'!$I$4:$M$4,0)-1))))))) +IF($F$1="SI", IF(I43="SI",IF(E43="portabilidad", IF(D43="multilínea",IF(AND(C43<>"Soluciones Personalizadas RPV",C43<>"Soluciones Personalizadas Centrex"), OFFSET(CeldaInicioDxCVAP,MATCH(J43,'PVP VaP - Pyme'!C:C,0)-1,MATCH(L43,'PVP VaP - Pyme'!$Z$22:$AL$22,0)-1) +OFFSET(CeldaInicioDxCVAP,MATCH(J43,'PVP VaP - Pyme'!C:C,0)-1,MATCH(L43,'PVP VaP - Pyme'!$Z$22:$AL$22,0)))), IF(D43="IEW", OFFSET(CeldaInicioDxCVAPIEW,MATCH(J43,'PVP VaP IEW Pro - Pyme'!C:C,0)-1,MATCH(L43,'PVP VaP IEW Pro - Pyme'!$AA$22:$AH$22,0)-1) +OFFSET(CeldaInicioDxCVAPIEW,MATCH(J43,'PVP VaP IEW Pro - Pyme'!C:C,0)-1,MATCH(L43,'PVP VaP IEW Pro - Pyme'!$AA$22:$AH$22,0)), )), IF(M43="","SIN OFERTA",IF(M43="SI",IF(B47="SIN OFERTA",B47,IF(D43="IEW",OFFSET(CeldaInicioDxCIEWAAPP,MATCH(J43,'PVP Subv IEW - Pyme AAPP'!C:C,0)-1,MATCH(L43,'PVP Subv IEW - Pyme AAPP'!$I$4:$L$4,0)-1),OFFSET(IF(E43="portabilidad",CeldaInicioDxCPortaAAPP,CeldaInicioDxCCaptaAAPP),MATCH(J43,'PVP Subv - Optima Pyme AAPP'!$C:$C,0)-1,MATCH(L43,'PVP Subv - Optima Pyme AAPP'!$I$4:$M$4,0)-1))), IF(B47="SIN OFERTA",B47,IF(D43="IEW",OFFSET(CeldaInicioDxCIEWAAPP,MATCH(J43,'PVP Subv IEW - Pyme AAPP'!C:C,0)-1,MATCH(L43,'PVP Subv IEW - Pyme AAPP'!$I$4:$L$4,0)-1),OFFSET(IF(E43="portabilidad",CeldaInicioDxCPorta9MASAAPP,CeldaInicioDxCCapta9MASAAPP),MATCH(J43,'PVP Subv - Sol Pers Pyme AAPP'!$C:$C,0)-1,MATCH(L43,'PVP Subv - Sol Pers Pyme AAPP'!$I$4:$M$4,0)-1))))))),"SIN OFERTA")+D46,"SIN OFERTA") -> SIN OFERTA | E46: =IFERROR(F46*B43,"SIN OFERTA") -> SIN OFERTA | F46: =IF(O43="SI",OFFSET(CeldadeinicioDxCportaCP36,MATCH(J43,'PVP Subv - Optima Pyme'!$C:$C,0)-1,MATCH(L43,'PVP Subv - Optima Pyme'!$BK$23:$BO$23,0)-1),"-") -> - | H46: =IFERROR(IF(N43="NO",0,SUMIFS(MR!$N$17:$N$21,MR!$M$17:$M$21,H45)),0) -> 0
A47: PVPR TERMINAL (sin IVA) | B47: =IFERROR(C47*B43,"SIN OFERTA") -> 0 | D47: Dif. CP 24 m | E47: =IF(E46="SIN OFERTA",0,(E46-B46)) -> 0 | F47: =IF(B46="SIN OFERTA",0,5*B43) -> 0 | G47: Válida en módulos: | H47: =IFERROR(INDEX(Tabla32[APLICA],MATCH(H45,Tabla32[PROMO],0)),"")
A48: PRECIO CESIÓN TERMINAL | B48: =IFERROR(C48*B43,"SIN OFERTA") -> SIN OFERTA | C48: =IF(M43="SI",IFERROR(-IF(D43="IEW",OFFSET(CeldaInicioPrecioCesiónIEW,MATCH(J43,'PVP Subv IEW - Pyme'!C:C,0)-1,0),OFFSET(CeldaInicioPrecioCesión,MATCH(J43,'PVP Subv - Optima Pyme'!$C:$C,0)-1,0)),"SIN OFERTA"), IFERROR(-IF(D43="IEW",OFFSET(CeldaInicioPrecioCesiónIEW,MATCH(J43,'PVP Subv IEW - Pyme'!C:C,0)-1,0),OFFSET(CeldaInicioPrecioCesión,MATCH(J43,'PVP Subv - Sol Pers Pyme'!$C:$C,0)-1,0)),"SIN OFERTA")) -> SIN OFERTA | H48: =IF(H46=12,H46+MR!$L$24,IF(H46=18,H46+MR!$L$23,IF(H46=48,H46+MR!$L$22,0))) -> 0
A49: MARGEN | B49: =IFERROR(B43*C49,"SIN OFERTA") -> 0 | C49: =IFERROR(C45+IF(NOT(ISNUMBER(C46)),0,C46)+IF(NOT(ISNUMBER(C47)),0,C47)+IF(NOT(ISNUMBER(C48)),0,C48),"SIN OFERTA") -> 0 | D49: MARGEN 36 | E49: =IFERROR(B43*F49,"SIN OFERTA") -> 0 | F49: =IFERROR(C49+(E47/B43),0) -> 0 | H49: =(H46-H48)*B43 -> 0 | I49: dif. Cp 24
B52: Nº ALTAS CON ESTE PERFIL | C52: TARIFA | D52: TIPO DE TARIFA | E52: TIPO DE ALTA | F52: PAQUETE DE VOZ Y DATOS | G52: CV USUARIO | H52: MFO CON FIJO PORTADO | I52: VENTA A PLAZOS | J52: TERMINAL | K52: GAMA | L52: MÓDULO OT | M52: ÓPTIMA | N52: O2O | O52: 36 m | P52: ESTRAT
A53: PERFIL DE ALTA | D53: =IFERROR(INDEX(MR!Q:Q,MATCH(C53,MR!P:P,0)),"") | K53: =IF(J53="","SIN TERMINAL",IF(D53="IEW",INDEX('PVP Subv IEW - Pyme'!F:F,MATCH(J53,'PVP Subv IEW - Pyme'!C:C,0)),INDEX('PVP Subv - Optima Pyme'!F:F,MATCH(J53,'PVP Subv - Optima Pyme'!C:C,0)))) -> SIN TERMINAL | L53: =IFERROR(IF(D53="IEW",INDEX('MODULOS OT IEW'!D:D,MATCH(C53,'MODULOS OT IEW'!A:A,0)),INDEX('MODULOS OT MULTILINEA'!F:F,MATCH(E53&F53&K53,'MODULOS OT MULTILINEA'!A:A,0))),"") | M53: =+IF(C53="","",IF(OR(C53="Óptima Plus Empresas",C53="Óptima Plus Empresas BIG"),"SI","NO")) | N53: =+IF(C53="","",IF($C$9="SI","NO",IF(OR(C53="Óptima Plus Empresas",C53="Óptima Plus Empresas BIG"),"SI","NO"))) | O53: =+IF(N53="NO","NO",IF(AND(E53="portabilidad",L53<>"ENTRADA PRO"),"SI","NO")) -> NO | P53: =IF(AND(E53="capta",F53="EMPRESAS VOZ"),0,1) -> 1
B54: IMPORTE TOTAL | C54: IMPORTE UNITARIO | D54: PAQUETE DE VOZ Y DATOS | E54: ACTIVACION | F54: ACTIVACION CP 24 POR TERMINAL | G54: SVAs | H54: O2O | I54: ESTRATEGICA | N54: =IF(N53="SI",1,0) -> 0
A55: COMISIONES | B55: =C55*B53 -> 0 | C55: =D55+E55+F55+G55-H56*N54+I55 -> 0 | D55: =IFERROR(IF(AND(M53="SI",$G$3="Cliente 1-19 líneas"),SUMIFS(MR!$B$5:$B$13,MR!$A$5:$A$13,F53),IF(AND(M53="SI",$G$3="Cliente 20-39 líneas"),SUMIFS(MR!$C$5:$C$13,MR!$A$5:$A$13,F53),IF(AND(M53="SI",$G$3="Cliente > 40 líneas"),SUMIFS(MR!$D$5:$D$13,MR!$A$5:$A$13,F53),IF(AND(M53="NO",$G$3="Cliente 1-19 líneas"),SUMIFS(MR!$B$17:$B$25,MR!$A$17:$A$25,F53),IF(AND(M53="NO",$G$3="Cliente 20-39 líneas"),SUMIFS(MR!$C$17:$C$25,MR!$A$17:$A$25,F53),IF(AND(M53="NO",$G$3="Cliente > 40 líneas"),SUMIFS(MR!$D$17:$D$25,MR!$A$17:$A$25,F53),0)))))),) -> 0 | E55: =IFERROR(IF(AND(M53="SI",E53="capta",D53="multilínea"),SUMIFS(MR!$E$5:$E$13,MR!$A$5:$A$13,F53),IF(AND(M53="SI",E53="portabilidad",D53="multilínea"),SUMIFS(MR!$F$5:$F$13,MR!$A$5:$A$13,F53),IF(AND(M53="NO",E53="capta",D53="multilínea"),SUMIFS(MR!$E$17:$E$25,MR!$A$17:$A$25,F53),IF(AND(M53="NO",E53="portabilidad",D53="multilínea"),SUMIFS(MR!$F$17:$F$25,MR!$A$17:$A$25,F53),IF(AND(M53="NO",E53="capta",D53="IEW"),SUMIFS(MR!$B$53:$B$61,MR!$A$53:$A$61,C53),IF(AND(M53="NO",E53="portabilidad",D53="IEW"),SUMIFS(MR!$B$53:$B$61,MR!$A$53:$A$61,C53),0)))))),) -> 0 | F55: =(IFERROR(IF(K53="SIN TERMINAL",0,IF(I53="SI",10,SUMIFS(MR!$G$6:$G$11,MR!$A$6:$A$11,F53))),0))*K55 -> 0 | G55: =IFERROR(IF(D53="multilínea",IF(G53="SI",MR!$N$4,0)+IF(H53="SI",MR!$N$5,0),0),0) -> 0 | I55: =(IF(D53="multilínea",IF($F$9="SI",IF($M53="SI",SUMIFS(MR!$I$6:$I$11,MR!$A$6:$A$11,F53),SUMIFS(MR!$I$18:$I$23,MR!$A$18:$A$23,F53))),SUMIFS(MR!$D$54:$D$61,MR!$A$54:$A$61,C53)))*P53 -> 0 | J55: =IF(M53="SI",IF($B$13+$B$23+$B$33+$B$43+$B$53>99,(99-$B$13-$B$23-$B$33-$B$43)*I55,B53*I55),B53*I55) -> 0 | K55: =IF(IFERROR(SEARCH("CESIÓN",$J53,1),0)>0,0,1) -> 1
A56: SUBVENCIÓN TERMINAL | B56: =IFERROR(C56*B53,"SIN OFERTA") -> SIN OFERTA | C56: =IFERROR(IFERROR(IF($F$1="NO", IF(I53="SI",IF(E53="portabilidad", IF(D53="multilínea",IF(AND(C53<>"Soluciones Personalizadas RPV",C53<>"Soluciones Personalizadas Centrex"), OFFSET(CeldaInicioDxCVAP,MATCH(J53,'PVP VaP - Pyme'!C:C,0)-1,MATCH(L53,'PVP VaP - Pyme'!$Z$22:$AL$22,0)-1) +OFFSET(CeldaInicioDxCVAP,MATCH(J53,'PVP VaP - Pyme'!C:C,0)-1,MATCH(L53,'PVP VaP - Pyme'!$Z$22:$AL$22,0)))), IF(D53="IEW", OFFSET(CeldaInicioDxCVAPIEW,MATCH(J53,'PVP VaP IEW Pro - Pyme'!C:C,0)-1,MATCH(L53,'PVP VaP IEW Pro - Pyme'!$AA$22:$AH$22,0)-1) +OFFSET(CeldaInicioDxCVAPIEW,MATCH(J53,'PVP VaP IEW Pro - Pyme'!C:C,0)-1,MATCH(L53,'PVP VaP IEW Pro - Pyme'!$AA$22:$AH$22,0)), )), IF(M53="","SIN OFERTA",IF(M53="SI",IF(B57="SIN OFERTA",B57,IF(D53="IEW",OFFSET(CeldaInicioDxCIEW,MATCH(J53,'PVP Subv IEW - Pyme'!C:C,0)-1,MATCH(L53,'PVP Subv IEW - Pyme'!$I$4:$L$4,0)-1),OFFSET(IF(E53="portabilidad",CeldaInicioDxCPorta,CeldaInicioDxCCapta),MATCH(J53,'PVP Subv - Optima Pyme'!$C:$C,0)-1,MATCH(L53,'PVP Subv - Optima Pyme'!$I$4:$M$4,0)-1))), IF(B57="SIN OFERTA",B57,IF(D53="IEW",OFFSET(CeldaInicioDxCIEW,MATCH(J53,'PVP Subv IEW - Pyme'!C:C,0)-1,MATCH(L53,'PVP Subv IEW - Pyme'!$I$4:$L$4,0)-1),OFFSET(IF(E53="portabilidad",CeldaInicioDxCPorta9MAS,CeldaInicioDxCCapta9MAS),MATCH(J53,'PVP Subv - Sol Pers Pyme'!$C:$C,0)-1,MATCH(L53,'PVP Subv - Sol Pers Pyme'!$I$4:$M$4,0)-1))))))) +IF($F$1="SI", IF(I53="SI",IF(E53="portabilidad", IF(D53="multilínea",IF(AND(C53<>"Soluciones Personalizadas RPV",C53<>"Soluciones Personalizadas Centrex"), OFFSET(CeldaInicioDxCVAP,MATCH(J53,'PVP VaP - Pyme'!C:C,0)-1,MATCH(L53,'PVP VaP - Pyme'!$Z$22:$AL$22,0)-1) +OFFSET(CeldaInicioDxCVAP,MATCH(J53,'PVP VaP - Pyme'!C:C,0)-1,MATCH(L53,'PVP VaP - Pyme'!$Z$22:$AL$22,0)))), IF(D53="IEW", OFFSET(CeldaInicioDxCVAPIEW,MATCH(J53,'PVP VaP IEW Pro - Pyme'!C:C,0)-1,MATCH(L53,'PVP VaP IEW Pro - Pyme'!$AA$22:$AH$22,0)-1) +OFFSET(CeldaInicioDxCVAPIEW,MATCH(J53,'PVP VaP IEW Pro - Pyme'!C:C,0)-1,MATCH(L53,'PVP VaP IEW Pro - Pyme'!$AA$22:$AH$22,0)), )), IF(M53="","SIN OFERTA",IF(M53="SI",IF(B57="SIN OFERTA",B57,IF(D53="IEW",OFFSET(CeldaInicioDxCIEWAAPP,MATCH(J53,'PVP Subv IEW - Pyme AAPP'!C:C,0)-1,MATCH(L53,'PVP Subv IEW - Pyme AAPP'!$I$4:$L$4,0)-1),OFFSET(IF(E53="portabilidad",CeldaInicioDxCPortaAAPP,CeldaInicioDxCCaptaAAPP),MATCH(J53,'PVP Subv - Optima Pyme AAPP'!$C:$C,0)-1,MATCH(L53,'PVP Subv - Optima Pyme AAPP'!$I$4:$M$4,0)-1))), IF(B57="SIN OFERTA",B57,IF(D53="IEW",OFFSET(CeldaInicioDxCIEWAAPP,MATCH(J53,'PVP Subv IEW - Pyme AAPP'!C:C,0)-1,MATCH(L53,'PVP Subv IEW - Pyme AAPP'!$I$4:$L$4,0)-1),OFFSET(IF(E53="portabilidad",CeldaInicioDxCPorta9MASAAPP,CeldaInicioDxCCapta9MASAAPP),MATCH(J53,'PVP Subv - Sol Pers Pyme AAPP'!$C:$C,0)-1,MATCH(L53,'PVP Subv - Sol Pers Pyme AAPP'!$I$4:$M$4,0)-1))))))),"SIN OFERTA")+D56,"SIN OFERTA") -> SIN OFERTA | E56: =IFERROR(F56*B53,"SIN OFERTA") -> SIN OFERTA | F56: =IF(O53="SI",OFFSET(CeldadeinicioDxCportaCP36,MATCH(J53,'PVP Subv - Optima Pyme'!$C:$C,0)-1,MATCH(L53,'PVP Subv - Optima Pyme'!$BK$23:$BO$23,0)-1),"-") -> - | H56: =IFERROR(IF(N53="NO",0,SUMIFS(MR!$N$17:$N$21,MR!$M$17:$M$21,H55)),0) -> 0
A57: PVPR TERMINAL (sin IVA) | B57: =IFERROR(C57*B53,"SIN OFERTA") -> 0 | D57: Dif. CP 24 m | E57: =IF(E56="SIN OFERTA",0,(E56-B56)) -> 0 | F57: =IF(B56="SIN OFERTA",0,5*B53) -> 0 | G57: Válida en módulos: | H57: =IFERROR(INDEX(Tabla32[APLICA],MATCH(H55,Tabla32[PROMO],0)),"")
A58: PRECIO CESIÓN TERMINAL | B58: =IFERROR(C58*B53,"SIN OFERTA") -> SIN OFERTA | C58: =IF(M53="SI",IFERROR(-IF(D53="IEW",OFFSET(CeldaInicioPrecioCesiónIEW,MATCH(J53,'PVP Subv IEW - Pyme'!C:C,0)-1,0),OFFSET(CeldaInicioPrecioCesión,MATCH(J53,'PVP Subv - Optima Pyme'!$C:$C,0)-1,0)),"SIN OFERTA"), IFERROR(-IF(D53="IEW",OFFSET(CeldaInicioPrecioCesiónIEW,MATCH(J53,'PVP Subv IEW - Pyme'!C:C,0)-1,0),OFFSET(CeldaInicioPrecioCesión,MATCH(J53,'PVP Subv - Sol Pers Pyme'!$C:$C,0)-1,0)),"SIN OFERTA")) -> SIN OFERTA | H58: =IF(H56=12,H56+MR!$L$24,IF(H56=18,H56+MR!$L$23,IF(H56=48,H56+MR!$L$22,0))) -> 0
A59: MARGEN | B59: =IFERROR(B53*C59,"SIN OFERTA") -> 0 | C59: =IFERROR(C55+IF(NOT(ISNUMBER(C56)),0,C56)+IF(NOT(ISNUMBER(C57)),0,C57)+IF(NOT(ISNUMBER(C58)),0,C58),"SIN OFERTA") -> 0 | D59: MARGEN 36 | E59: =IFERROR(B53*F59,"SIN OFERTA") -> 0 | F59: =IFERROR(C59+(E57/B53),0) -> 0 | H59: =(H56-H58)*B53 -> 0 | I59: dif. Cp 24
B62: Nº ALTAS CON ESTE PERFIL | C62: TARIFA | D62: TIPO DE TARIFA | E62: TIPO DE ALTA | F62: PAQUETE DE VOZ Y DATOS | G62: CV USUARIO | H62: MFO CON FIJO PORTADO | I62: VENTA A PLAZOS | J62: TERMINAL | K62: GAMA | L62: MÓDULO OT | M62: ÓPTIMA | N62: O2O | O62: 36 m | P62: ESTRAT
A63: PERFIL DE ALTA | D63: =IFERROR(INDEX(MR!Q:Q,MATCH(C63,MR!P:P,0)),"") | K63: =IF(J63="","SIN TERMINAL",IF(D63="IEW",INDEX('PVP Subv IEW - Pyme'!F:F,MATCH(J63,'PVP Subv IEW - Pyme'!C:C,0)),INDEX('PVP Subv - Optima Pyme'!F:F,MATCH(J63,'PVP Subv - Optima Pyme'!C:C,0)))) -> SIN TERMINAL | L63: =IFERROR(IF(D63="IEW",INDEX('MODULOS OT IEW'!D:D,MATCH(C63,'MODULOS OT IEW'!A:A,0)),INDEX('MODULOS OT MULTILINEA'!F:F,MATCH(E63&F63&K63,'MODULOS OT MULTILINEA'!A:A,0))),"") | M63: =+IF(C63="","",IF(OR(C63="Óptima Plus Empresas",C63="Óptima Plus Empresas BIG"),"SI","NO")) | N63: =+IF(C63="","",IF($C$9="SI","NO",IF(OR(C63="Óptima Plus Empresas",C63="Óptima Plus Empresas BIG"),"SI","NO"))) | O63: =+IF(N63="NO","NO",IF(AND(E63="portabilidad",L63<>"ENTRADA PRO"),"SI","NO")) -> NO | P63: =IF(AND(E63="capta",F63="EMPRESAS VOZ"),0,1) -> 1
B64: IMPORTE TOTAL | C64: IMPORTE UNITARIO | D64: PAQUETE DE VOZ Y DATOS | E64: ACTIVACION | F64: ACTIVACION CP 24 POR TERMINAL | G64: SVAs | H64: O2O | I64: ESTRATEGICA | N64: =IF(N63="SI",1,0) -> 0
A65: COMISIONES | B65: =C65*B63 -> 0 | C65: =D65+E65+F65+G65-H66*N64+I65 -> 0 | D65: =IFERROR(IF(AND(M63="SI",$G$3="Cliente 1-19 líneas"),SUMIFS(MR!$B$5:$B$13,MR!$A$5:$A$13,F63),IF(AND(M63="SI",$G$3="Cliente 20-39 líneas"),SUMIFS(MR!$C$5:$C$13,MR!$A$5:$A$13,F63),IF(AND(M63="SI",$G$3="Cliente > 40 líneas"),SUMIFS(MR!$D$5:$D$13,MR!$A$5:$A$13,F63),IF(AND(M63="NO",$G$3="Cliente 1-19 líneas"),SUMIFS(MR!$B$17:$B$25,MR!$A$17:$A$25,F63),IF(AND(M63="NO",$G$3="Cliente 20-39 líneas"),SUMIFS(MR!$C$17:$C$25,MR!$A$17:$A$25,F63),IF(AND(M63="NO",$G$3="Cliente > 40 líneas"),SUMIFS(MR!$D$17:$D$25,MR!$A$17:$A$25,F63),0)))))),)+IFERROR(IF(AND(M63="SI",$G$3="Cliente 1-19 líneas"),SUMIFS(MR!$B$30:$B$37,MR!$A$30:$A$37,F63),IF(AND(M63="SI",$G$3="Cliente 20-39 líneas"),SUMIFS(MR!$C$30:$C$37,MR!$A$30:$A$37,F63),IF(AND(M63="SI",$G$3="Cliente > 40 líneas"),SUMIFS(MR!$D$30:$D$37,MR!$A$30:$A$37,F63),IF(AND(M63="NO",$G$3="Cliente 1-19 líneas"),SUMIFS(MR!$B$41:$B$48,MR!$A$41:$A$48,F63),IF(AND(M63="NO",$G$3="Cliente 20-39 líneas"),SUMIFS(MR!$C$41:$C$48,MR!$A$41:$A$48,F63),IF(AND(M63="NO",$G$3="Cliente > 40 líneas"),SUMIFS(MR!$D$41:$D$48,MR!$A$41:$A$48,F63),0)))))),) -> 0 | E65: =IFERROR(IF(AND(M63="SI",E63="capta",D63="multilínea"),SUMIFS(MR!$E$5:$E$13,MR!$A$5:$A$13,F63),IF(AND(M63="SI",E63="portabilidad",D63="multilínea"),SUMIFS(MR!$F$5:$F$13,MR!$A$5:$A$13,F63),IF(AND(M63="NO",E63="capta",D63="multilínea"),SUMIFS(MR!$E$17:$E$25,MR!$A$17:$A$25,F63),IF(AND(M63="NO",E63="portabilidad",D63="multilínea"),SUMIFS(MR!$F$17:$F$25,MR!$A$17:$A$25,F63),IF(AND(M63="NO",E63="capta",D63="IEW"),SUMIFS(MR!$B$53:$B$61,MR!$A$53:$A$61,C63),IF(AND(M63="NO",E63="portabilidad",D63="IEW"),SUMIFS(MR!$B$53:$B$61,MR!$A$53:$A$61,C63),0)))))),)+IFERROR(IF(AND(M63="SI",E63="capta",D63="multilínea"),SUMIFS(MR!$E$30:$E$37,MR!$A$30:$A$37,F63),IF(AND(M63="SI",E63="portabilidad",D63="multilínea"),SUMIFS(MR!$F$30:$F$37,MR!$A$30:$A$37,F63),IF(AND(M63="NO",E63="capta",D63="multilínea"),SUMIFS(MR!$E$48:$E$398,MR!$A$41:$A$48,F63),IF(AND(M63="NO",E63="portabilidad",D63="multilínea"),SUMIFS(MR!$F$41:$F$48,MR!$A$41:$A$48,F63),0)))),) -> 0 | F65: =(IFERROR(IF(K63="SIN TERMINAL",0,IF(I63="SI",10,SUMIFS(MR!$G$6:$G$11,MR!$A$6:$A$11,F63))),0))*K65 -> 0 | G65: =IFERROR(IF(D63="multilínea",IF(G63="SI",MR!$N$4,0)+IF(H63="SI",MR!$N$5,0),0),0) -> 0 | I65: =(IF(D63="multilínea",IF($F$9="SI",IF($M63="SI",SUMIFS(MR!$I$6:$I$11,MR!$A$6:$A$11,F63),SUMIFS(MR!$I$18:$I$23,MR!$A$18:$A$23,F63))),SUMIFS(MR!$D$54:$D$61,MR!$A$54:$A$61,C63)))*P63 -> 0 | J65: =IF(M63="SI",IF($B$13+$B$23+$B$33+$B$43+$B$53+$B$63>99,(99-$B$13-$B$23-$B$33-$B$43-B$53)*I65,B63*I65),B63*I65) -> 0 | K65: =IF(IFERROR(SEARCH("CESIÓN",$J63,1),0)>0,0,1) -> 1
A66: SUBVENCIÓN TERMINAL | B66: =IFERROR(C66*B63,"SIN OFERTA") -> SIN OFERTA | C66: =IFERROR(IFERROR(IF($F$1="NO", IF(I63="SI",IF(E63="portabilidad", IF(D63="multilínea",IF(AND(C63<>"Soluciones Personalizadas RPV",C63<>"Soluciones Personalizadas Centrex"), OFFSET(CeldaInicioDxCVAP,MATCH(J63,'PVP VaP - Pyme'!C:C,0)-1,MATCH(L63,'PVP VaP - Pyme'!$Z$22:$AL$22,0)-1) +OFFSET(CeldaInicioDxCVAP,MATCH(J63,'PVP VaP - Pyme'!C:C,0)-1,MATCH(L63,'PVP VaP - Pyme'!$Z$22:$AL$22,0)))), IF(D63="IEW", OFFSET(CeldaInicioDxCVAPIEW,MATCH(J63,'PVP VaP IEW Pro - Pyme'!C:C,0)-1,MATCH(L63,'PVP VaP IEW Pro - Pyme'!$AA$22:$AH$22,0)-1) +OFFSET(CeldaInicioDxCVAPIEW,MATCH(J63,'PVP VaP IEW Pro - Pyme'!C:C,0)-1,MATCH(L63,'PVP VaP IEW Pro - Pyme'!$AA$22:$AH$22,0)), )), IF(M63="","SIN OFERTA",IF(M63="SI",IF(B67="SIN OFERTA",B67,IF(D63="IEW",OFFSET(CeldaInicioDxCIEW,MATCH(J63,'PVP Subv IEW - Pyme'!C:C,0)-1,MATCH(L63,'PVP Subv IEW - Pyme'!$I$4:$L$4,0)-1),OFFSET(IF(E63="portabilidad",CeldaInicioDxCPorta,CeldaInicioDxCCapta),MATCH(J63,'PVP Subv - Optima Pyme'!$C:$C,0)-1,MATCH(L63,'PVP Subv - Optima Pyme'!$I$4:$M$4,0)-1))), IF(B67="SIN OFERTA",B67,IF(D63="IEW",OFFSET(CeldaInicioDxCIEW,MATCH(J63,'PVP Subv IEW - Pyme'!C:C,0)-1,MATCH(L63,'PVP Subv IEW - Pyme'!$I$4:$L$4,0)-1),OFFSET(IF(E63="portabilidad",CeldaInicioDxCPorta9MAS,CeldaInicioDxCCapta9MAS),MATCH(J63,'PVP Subv - Sol Pers Pyme'!$C:$C,0)-1,MATCH(L63,'PVP Subv - Sol Pers Pyme'!$I$4:$M$4,0)-1))))))) +IF($F$1="SI", IF(I63="SI",IF(E63="portabilidad", IF(D63="multilínea",IF(AND(C63<>"Soluciones Personalizadas RPV",C63<>"Soluciones Personalizadas Centrex"), OFFSET(CeldaInicioDxCVAP,MATCH(J63,'PVP VaP - Pyme'!C:C,0)-1,MATCH(L63,'PVP VaP - Pyme'!$Z$22:$AL$22,0)-1) +OFFSET(CeldaInicioDxCVAP,MATCH(J63,'PVP VaP - Pyme'!C:C,0)-1,MATCH(L63,'PVP VaP - Pyme'!$Z$22:$AL$22,0)))), IF(D63="IEW", OFFSET(CeldaInicioDxCVAPIEW,MATCH(J63,'PVP VaP IEW Pro - Pyme'!C:C,0)-1,MATCH(L63,'PVP VaP IEW Pro - Pyme'!$AA$22:$AH$22,0)-1) +OFFSET(CeldaInicioDxCVAPIEW,MATCH(J63,'PVP VaP IEW Pro - Pyme'!C:C,0)-1,MATCH(L63,'PVP VaP IEW Pro - Pyme'!$AA$22:$AH$22,0)), )), IF(M63="","SIN OFERTA",IF(M63="SI",IF(B67="SIN OFERTA",B67,IF(D63="IEW",OFFSET(CeldaInicioDxCIEWAAPP,MATCH(J63,'PVP Subv IEW - Pyme AAPP'!C:C,0)-1,MATCH(L63,'PVP Subv IEW - Pyme AAPP'!$I$4:$L$4,0)-1),OFFSET(IF(E63="portabilidad",CeldaInicioDxCPortaAAPP,CeldaInicioDxCCaptaAAPP),MATCH(J63,'PVP Subv - Optima Pyme AAPP'!$C:$C,0)-1,MATCH(L63,'PVP Subv - Optima Pyme AAPP'!$I$4:$M$4,0)-1))), IF(B67="SIN OFERTA",B67,IF(D63="IEW",OFFSET(CeldaInicioDxCIEWAAPP,MATCH(J63,'PVP Subv IEW - Pyme AAPP'!C:C,0)-1,MATCH(L63,'PVP Subv IEW - Pyme AAPP'!$I$4:$L$4,0)-1),OFFSET(IF(E63="portabilidad",CeldaInicioDxCPorta9MASAAPP,CeldaInicioDxCCapta9MASAAPP),MATCH(J63,'PVP Subv - Sol Pers Pyme AAPP'!$C:$C,0)-1,MATCH(L63,'PVP Subv - Sol Pers Pyme AAPP'!$I$4:$M$4,0)-1))))))),"SIN OFERTA")+D66,"SIN OFERTA") -> SIN OFERTA | E66: =IFERROR(F66*B63,"SIN OFERTA") -> SIN OFERTA | F66: =IF(O63="SI",OFFSET(CeldadeinicioDxCportaCP36,MATCH(J63,'PVP Subv - Optima Pyme'!$C:$C,0)-1,MATCH(L63,'PVP Subv - Optima Pyme'!$BK$23:$BO$23,0)-1),"-") -> - | H66: =IFERROR(IF(N63="NO",0,SUMIFS(MR!$N$17:$N$21,MR!$M$17:$M$21,H65)),0) -> 0
A67: PVPR TERMINAL (sin IVA) | B67: =IFERROR(C67*B63,"SIN OFERTA") -> 0 | D67: Dif. CP 24 m | E67: =IF(E66="SIN OFERTA",0,(E66-B66)) -> 0 | F67: =IF(B66="SIN OFERTA",0,5*B63) -> 0 | G67: Válida en módulos: | H67: =IFERROR(INDEX(Tabla32[APLICA],MATCH(H65,Tabla32[PROMO],0)),"")
A68: PRECIO CESIÓN TERMINAL | B68: =IFERROR(C68*B63,"SIN OFERTA") -> SIN OFERTA | C68: =IF(M63="SI",IFERROR(-IF(D63="IEW",OFFSET(CeldaInicioPrecioCesiónIEW,MATCH(J63,'PVP Subv IEW - Pyme'!C:C,0)-1,0),OFFSET(CeldaInicioPrecioCesión,MATCH(J63,'PVP Subv - Optima Pyme'!$C:$C,0)-1,0)),"SIN OFERTA"), IFERROR(-IF(D63="IEW",OFFSET(CeldaInicioPrecioCesiónIEW,MATCH(J63,'PVP Subv IEW - Pyme'!C:C,0)-1,0),OFFSET(CeldaInicioPrecioCesión,MATCH(J63,'PVP Subv - Sol Pers Pyme'!$C:$C,0)-1,0)),"SIN OFERTA")) -> SIN OFERTA | H68: =IF(H66=12,H66+MR!$L$24,IF(H66=18,H66+MR!$L$23,IF(H66=48,H66+MR!$L$22,0))) -> 0
A69: MARGEN | B69: =IFERROR(B63*C69,"SIN OFERTA") -> 0 | C69: =IFERROR(C65+IF(NOT(ISNUMBER(C66)),0,C66)+IF(NOT(ISNUMBER(C67)),0,C67)+IF(NOT(ISNUMBER(C68)),0,C68),"SIN OFERTA") -> 0 | D69: MARGEN 36 | E69: =IFERROR(B63*F69,"SIN OFERTA") -> 0 | F69: =IFERROR(C69+(E67/B63),0) -> 0 | H69: =(H66-H68)*B63 -> 0 | I69: dif. Cp 24
B72: Nº ALTAS CON ESTE PERFIL | C72: TARIFA | D72: TIPO DE TARIFA | E72: TIPO DE ALTA | F72: PAQUETE DE VOZ Y DATOS | G72: CV USUARIO | H72: MFO CON FIJO PORTADO | I72: VENTA A PLAZOS | J72: TERMINAL | K72: GAMA | L72: MÓDULO OT | M72: ÓPTIMA | N72: O2O | O72: 36 m | P72: ESTRAT
A73: PERFIL DE ALTA | D73: =IFERROR(INDEX(MR!Q:Q,MATCH(C73,MR!P:P,0)),"") | K73: =IF(J73="","SIN TERMINAL",IF(D73="IEW",INDEX('PVP Subv IEW - Pyme'!F:F,MATCH(J73,'PVP Subv IEW - Pyme'!C:C,0)),INDEX('PVP Subv - Optima Pyme'!F:F,MATCH(J73,'PVP Subv - Optima Pyme'!C:C,0)))) -> SIN TERMINAL | L73: =IFERROR(IF(D73="IEW",INDEX('MODULOS OT IEW'!D:D,MATCH(C73,'MODULOS OT IEW'!A:A,0)),INDEX('MODULOS OT MULTILINEA'!F:F,MATCH(E73&F73&K73,'MODULOS OT MULTILINEA'!A:A,0))),"") | M73: =+IF(C73="","",IF(OR(C73="Óptima Plus Empresas",C73="Óptima Plus Empresas BIG"),"SI","NO")) | N73: =+IF(C73="","",IF($C$9="SI","NO",IF(OR(C73="Óptima Plus Empresas",C73="Óptima Plus Empresas BIG"),"SI","NO"))) | O73: =+IF(N73="NO","NO",IF(AND(E73="portabilidad",L73<>"ENTRADA PRO"),"SI","NO")) -> NO | P73: =IF(AND(E73="capta",F73="EMPRESAS VOZ"),0,1) -> 1
B74: IMPORTE TOTAL | C74: IMPORTE UNITARIO | D74: PAQUETE DE VOZ Y DATOS | E74: ACTIVACION | F74: ACTIVACION CP 24 POR TERMINAL | G74: SVAs | H74: O2O | I74: ESTRATEGICA | N74: =IF(N73="SI",1,0) -> 0
A75: COMISIONES | B75: =C75*B73 -> 0 | C75: =D75+E75+F75+G75-H76*N74+I75 -> 0 | D75: =IFERROR(IF(AND(M73="SI",$G$3="Cliente 1-19 líneas"),SUMIFS(MR!$B$5:$B$13,MR!$A$5:$A$13,F73),IF(AND(M73="SI",$G$3="Cliente 20-39 líneas"),SUMIFS(MR!$C$5:$C$13,MR!$A$5:$A$13,F73),IF(AND(M73="SI",$G$3="Cliente > 40 líneas"),SUMIFS(MR!$D$5:$D$13,MR!$A$5:$A$13,F73),IF(AND(M73="NO",$G$3="Cliente 1-19 líneas"),SUMIFS(MR!$B$17:$B$25,MR!$A$17:$A$25,F73),IF(AND(M73="NO",$G$3="Cliente 20-39 líneas"),SUMIFS(MR!$C$17:$C$25,MR!$A$17:$A$25,F73),IF(AND(M73="NO",$G$3="Cliente > 40 líneas"),SUMIFS(MR!$D$17:$D$25,MR!$A$17:$A$25,F73),0)))))),)+IFERROR(IF(AND(M73="SI",$G$3="Cliente 1-19 líneas"),SUMIFS(MR!$B$30:$B$37,MR!$A$30:$A$37,F73),IF(AND(M73="SI",$G$3="Cliente 20-39 líneas"),SUMIFS(MR!$C$30:$C$37,MR!$A$30:$A$37,F73),IF(AND(M73="SI",$G$3="Cliente > 40 líneas"),SUMIFS(MR!$D$30:$D$37,MR!$A$30:$A$37,F73),IF(AND(M73="NO",$G$3="Cliente 1-19 líneas"),SUMIFS(MR!$B$41:$B$48,MR!$A$41:$A$48,F73),IF(AND(M73="NO",$G$3="Cliente 20-39 líneas"),SUMIFS(MR!$C$41:$C$48,MR!$A$41:$A$48,F73),IF(AND(M73="NO",$G$3="Cliente > 40 líneas"),SUMIFS(MR!$D$41:$D$48,MR!$A$41:$A$48,F73),0)))))),) -> 0 | E75: =IFERROR(IF(AND(M73="SI",E73="capta",D73="multilínea"),SUMIFS(MR!$E$5:$E$13,MR!$A$5:$A$13,F73),IF(AND(M73="SI",E73="portabilidad",D73="multilínea"),SUMIFS(MR!$F$5:$F$13,MR!$A$5:$A$13,F73),IF(AND(M73="NO",E73="capta",D73="multilínea"),SUMIFS(MR!$E$17:$E$25,MR!$A$17:$A$25,F73),IF(AND(M73="NO",E73="portabilidad",D73="multilínea"),SUMIFS(MR!$F$17:$F$25,MR!$A$17:$A$25,F73),IF(AND(M73="NO",E73="capta",D73="IEW"),SUMIFS(MR!$B$53:$B$61,MR!$A$53:$A$61,C73),IF(AND(M73="NO",E73="portabilidad",D73="IEW"),SUMIFS(MR!$B$53:$B$61,MR!$A$53:$A$61,C73),0)))))),)+IFERROR(IF(AND(M73="SI",E73="capta",D73="multilínea"),SUMIFS(MR!$E$30:$E$37,MR!$A$30:$A$37,F73),IF(AND(M73="SI",E73="portabilidad",D73="multilínea"),SUMIFS(MR!$F$30:$F$37,MR!$A$30:$A$37,F73),IF(AND(M73="NO",E73="capta",D73="multilínea"),SUMIFS(MR!$E$48:$E$398,MR!$A$41:$A$48,F73),IF(AND(M73="NO",E73="portabilidad",D73="multilínea"),SUMIFS(MR!$F$41:$F$48,MR!$A$41:$A$48,F73),0)))),) -> 0 | F75: =(IFERROR(IF(K73="SIN TERMINAL",0,IF(I73="SI",10,SUMIFS(MR!$G$6:$G$11,MR!$A$6:$A$11,F73))),0))*K75 -> 0 | G75: =IFERROR(IF(D73="multilínea",IF(G73="SI",MR!$N$4,0)+IF(H73="SI",MR!$N$5,0),0),0) -> 0 | I75: =(IF(D73="multilínea",IF($F$9="SI",IF($M73="SI",SUMIFS(MR!$I$6:$I$11,MR!$A$6:$A$11,F73),SUMIFS(MR!$I$18:$I$23,MR!$A$18:$A$23,F73))),SUMIFS(MR!$D$54:$D$61,MR!$A$54:$A$61,C73)))*P73 -> 0 | J75: =IF(M73="SI",IF($B$13+$B$23+$B$33+$B$43+$B$53+$B$63+$B$73>99,(99-$B$13-$B$23-$B$33-$B$43-B$53-$B$63)*I75,B73*I75),B73*I75) -> 0 | K75: =IF(IFERROR(SEARCH("CESIÓN",$J73,1),0)>0,0,1) -> 1
A76: SUBVENCIÓN TERMINAL | B76: =IFERROR(C76*B73,"SIN OFERTA") -> SIN OFERTA | C76: =IFERROR(IFERROR(IF($F$1="NO", IF(I73="SI",IF(E73="portabilidad", IF(D73="multilínea",IF(AND(C73<>"Soluciones Personalizadas RPV",C73<>"Soluciones Personalizadas Centrex"), OFFSET(CeldaInicioDxCVAP,MATCH(J73,'PVP VaP - Pyme'!C:C,0)-1,MATCH(L73,'PVP VaP - Pyme'!$Z$22:$AL$22,0)-1) +OFFSET(CeldaInicioDxCVAP,MATCH(J73,'PVP VaP - Pyme'!C:C,0)-1,MATCH(L73,'PVP VaP - Pyme'!$Z$22:$AL$22,0)))), IF(D73="IEW", OFFSET(CeldaInicioDxCVAPIEW,MATCH(J73,'PVP VaP IEW Pro - Pyme'!C:C,0)-1,MATCH(L73,'PVP VaP IEW Pro - Pyme'!$AA$22:$AH$22,0)-1) +OFFSET(CeldaInicioDxCVAPIEW,MATCH(J73,'PVP VaP IEW Pro - Pyme'!C:C,0)-1,MATCH(L73,'PVP VaP IEW Pro - Pyme'!$AA$22:$AH$22,0)), )), IF(M73="","SIN OFERTA",IF(M73="SI",IF(B77="SIN OFERTA",B77,IF(D73="IEW",OFFSET(CeldaInicioDxCIEW,MATCH(J73,'PVP Subv IEW - Pyme'!C:C,0)-1,MATCH(L73,'PVP Subv IEW - Pyme'!$I$4:$L$4,0)-1),OFFSET(IF(E73="portabilidad",CeldaInicioDxCPorta,CeldaInicioDxCCapta),MATCH(J73,'PVP Subv - Optima Pyme'!$C:$C,0)-1,MATCH(L73,'PVP Subv - Optima Pyme'!$I$4:$M$4,0)-1))), IF(B77="SIN OFERTA",B77,IF(D73="IEW",OFFSET(CeldaInicioDxCIEW,MATCH(J73,'PVP Subv IEW - Pyme'!C:C,0)-1,MATCH(L73,'PVP Subv IEW - Pyme'!$I$4:$L$4,0)-1),OFFSET(IF(E73="portabilidad",CeldaInicioDxCPorta9MAS,CeldaInicioDxCCapta9MAS),MATCH(J73,'PVP Subv - Sol Pers Pyme'!$C:$C,0)-1,MATCH(L73,'PVP Subv - Sol Pers Pyme'!$I$4:$M$4,0)-1))))))) +IF($F$1="SI", IF(I73="SI",IF(E73="portabilidad", IF(D73="multilínea",IF(AND(C73<>"Soluciones Personalizadas RPV",C73<>"Soluciones Personalizadas Centrex"), OFFSET(CeldaInicioDxCVAP,MATCH(J73,'PVP VaP - Pyme'!C:C,0)-1,MATCH(L73,'PVP VaP - Pyme'!$Z$22:$AL$22,0)-1) +OFFSET(CeldaInicioDxCVAP,MATCH(J73,'PVP VaP - Pyme'!C:C,0)-1,MATCH(L73,'PVP VaP - Pyme'!$Z$22:$AL$22,0)))), IF(D73="IEW", OFFSET(CeldaInicioDxCVAPIEW,MATCH(J73,'PVP VaP IEW Pro - Pyme'!C:C,0)-1,MATCH(L73,'PVP VaP IEW Pro - Pyme'!$AA$22:$AH$22,0)-1) +OFFSET(CeldaInicioDxCVAPIEW,MATCH(J73,'PVP VaP IEW Pro - Pyme'!C:C,0)-1,MATCH(L73,'PVP VaP IEW Pro - Pyme'!$AA$22:$AH$22,0)), )), IF(M73="","SIN OFERTA",IF(M73="SI",IF(B77="SIN OFERTA",B77,IF(D73="IEW",OFFSET(CeldaInicioDxCIEWAAPP,MATCH(J73,'PVP Subv IEW - Pyme AAPP'!C:C,0)-1,MATCH(L73,'PVP Subv IEW - Pyme AAPP'!$I$4:$L$4,0)-1),OFFSET(IF(E73="portabilidad",CeldaInicioDxCPortaAAPP,CeldaInicioDxCCaptaAAPP),MATCH(J73,'PVP Subv - Optima Pyme AAPP'!$C:$C,0)-1,MATCH(L73,'PVP Subv - Optima Pyme AAPP'!$I$4:$M$4,0)-1))), IF(B77="SIN OFERTA",B77,IF(D73="IEW",OFFSET(CeldaInicioDxCIEWAAPP,MATCH(J73,'PVP Subv IEW - Pyme AAPP'!C:C,0)-1,MATCH(L73,'PVP Subv IEW - Pyme AAPP'!$I$4:$L$4,0)-1),OFFSET(IF(E73="portabilidad",CeldaInicioDxCPorta9MASAAPP,CeldaInicioDxCCapta9MASAAPP),MATCH(J73,'PVP Subv - Sol Pers Pyme AAPP'!$C:$C,0)-1,MATCH(L73,'PVP Subv - Sol Pers Pyme AAPP'!$I$4:$M$4,0)-1))))))),"SIN OFERTA")+D76,"SIN OFERTA") -> SIN OFERTA | E76: =IFERROR(F76*B73,"SIN OFERTA") -> SIN OFERTA | F76: =IF(O73="SI",OFFSET(CeldadeinicioDxCportaCP36,MATCH(J73,'PVP Subv - Optima Pyme'!$C:$C,0)-1,MATCH(L73,'PVP Subv - Optima Pyme'!$BK$23:$BO$23,0)-1),"-") -> - | H76: =IFERROR(IF(N73="NO",0,SUMIFS(MR!$N$17:$N$21,MR!$M$17:$M$21,H75)),0) -> 0
A77: PVPR TERMINAL (sin IVA) | B77: =IFERROR(C77*B73,"SIN OFERTA") -> 0 | D77: Dif. CP 24 m | E77: =IF(E76="SIN OFERTA",0,(E76-B76)) -> 0 | F77: =IF(B76="SIN OFERTA",0,5*B73) -> 0 | G77: Válida en módulos: | H77: =IFERROR(INDEX(Tabla32[APLICA],MATCH(H75,Tabla32[PROMO],0)),"")
A78: PRECIO CESIÓN TERMINAL | B78: =IFERROR(C78*B73,"SIN OFERTA") -> SIN OFERTA | C78: =IF(M73="SI",IFERROR(-IF(D73="IEW",OFFSET(CeldaInicioPrecioCesiónIEW,MATCH(J73,'PVP Subv IEW - Pyme'!C:C,0)-1,0),OFFSET(CeldaInicioPrecioCesión,MATCH(J73,'PVP Subv - Optima Pyme'!$C:$C,0)-1,0)),"SIN OFERTA"), IFERROR(-IF(D73="IEW",OFFSET(CeldaInicioPrecioCesiónIEW,MATCH(J73,'PVP Subv IEW - Pyme'!C:C,0)-1,0),OFFSET(CeldaInicioPrecioCesión,MATCH(J73,'PVP Subv - Sol Pers Pyme'!$C:$C,0)-1,0)),"SIN OFERTA")) -> SIN OFERTA | H78: =IF(H76=12,H76+MR!$L$24,IF(H76=18,H76+MR!$L$23,IF(H76=48,H76+MR!$L$22,0))) -> 0
A79: MARGEN | B79: =IFERROR(B73*C79,"SIN OFERTA") -> 0 | C79: =IFERROR(C75+IF(NOT(ISNUMBER(C76)),0,C76)+IF(NOT(ISNUMBER(C77)),0,C77)+IF(NOT(ISNUMBER(C78)),0,C78),"SIN OFERTA") -> 0 | D79: MARGEN 36 | E79: =IFERROR(B73*F79,"SIN OFERTA") -> 0 | F79: =IFERROR(C79+(E77/B73),0) -> 0 | H79: =(H76-H78)*B73 -> 0 | I79: dif. Cp 24
B82: Nº ALTAS CON ESTE PERFIL | C82: TARIFA | D82: TIPO DE TARIFA | E82: TIPO DE ALTA | F82: PAQUETE DE VOZ Y DATOS | G82: CV USUARIO | H82: MFO CON FIJO PORTADO | I82: VENTA A PLAZOS | J82: TERMINAL | K82: GAMA | L82: MÓDULO OT | M82: ÓPTIMA | N82: O2O | O82: 36 m | P82: ESTRAT
A83: PERFIL DE ALTA | D83: =IFERROR(INDEX(MR!Q:Q,MATCH(C83,MR!P:P,0)),"") | K83: =IF(J83="","SIN TERMINAL",IF(D83="IEW",INDEX('PVP Subv IEW - Pyme'!F:F,MATCH(J83,'PVP Subv IEW - Pyme'!C:C,0)),INDEX('PVP Subv - Optima Pyme'!F:F,MATCH(J83,'PVP Subv - Optima Pyme'!C:C,0)))) -> SIN TERMINAL | L83: =IFERROR(IF(D83="IEW",INDEX('MODULOS OT IEW'!D:D,MATCH(C83,'MODULOS OT IEW'!A:A,0)),INDEX('MODULOS OT MULTILINEA'!F:F,MATCH(E83&F83&K83,'MODULOS OT MULTILINEA'!A:A,0))),"") | M83: =+IF(C83="","",IF(OR(C83="Óptima Plus Empresas",C83="Óptima Plus Empresas BIG"),"SI","NO")) | N83: =+IF(C83="","",IF($C$9="SI","NO",IF(OR(C83="Óptima Plus Empresas",C83="Óptima Plus Empresas BIG"),"SI","NO"))) | O83: =+IF(N83="NO","NO",IF(AND(E83="portabilidad",L83<>"ENTRADA PRO"),"SI","NO")) -> NO | P83: =IF(AND(E83="capta",F83="EMPRESAS VOZ"),0,1) -> 1
B84: IMPORTE TOTAL | C84: IMPORTE UNITARIO | D84: PAQUETE DE VOZ Y DATOS | E84: ACTIVACION | F84: ACTIVACION CP 24 POR TERMINAL | G84: SVAs | H84: O2O | I84: ESTRATEGICA | N84: =IF(N83="SI",1,0) -> 0
A85: COMISIONES | B85: =C85*B83 -> 0 | C85: =D85+E85+F85+G85-H86*N84+I85 -> 0 | D85: =IFERROR(IF(AND(M83="SI",$G$3="Cliente 1-19 líneas"),SUMIFS(MR!$B$5:$B$13,MR!$A$5:$A$13,F83),IF(AND(M83="SI",$G$3="Cliente 20-39 líneas"),SUMIFS(MR!$C$5:$C$13,MR!$A$5:$A$13,F83),IF(AND(M83="SI",$G$3="Cliente > 40 líneas"),SUMIFS(MR!$D$5:$D$13,MR!$A$5:$A$13,F83),IF(AND(M83="NO",$G$3="Cliente 1-19 líneas"),SUMIFS(MR!$B$17:$B$25,MR!$A$17:$A$25,F83),IF(AND(M83="NO",$G$3="Cliente 20-39 líneas"),SUMIFS(MR!$C$17:$C$25,MR!$A$17:$A$25,F83),IF(AND(M83="NO",$G$3="Cliente > 40 líneas"),SUMIFS(MR!$D$17:$D$25,MR!$A$17:$A$25,F83),0)))))),)+IFERROR(IF(AND(M83="SI",$G$3="Cliente 1-19 líneas"),SUMIFS(MR!$B$30:$B$37,MR!$A$30:$A$37,F83),IF(AND(M83="SI",$G$3="Cliente 20-39 líneas"),SUMIFS(MR!$C$30:$C$37,MR!$A$30:$A$37,F83),IF(AND(M83="SI",$G$3="Cliente > 40 líneas"),SUMIFS(MR!$D$30:$D$37,MR!$A$30:$A$37,F83),IF(AND(M83="NO",$G$3="Cliente 1-19 líneas"),SUMIFS(MR!$B$41:$B$48,MR!$A$41:$A$48,F83),IF(AND(M83="NO",$G$3="Cliente 20-39 líneas"),SUMIFS(MR!$C$41:$C$48,MR!$A$41:$A$48,F83),IF(AND(M83="NO",$G$3="Cliente > 40 líneas"),SUMIFS(MR!$D$41:$D$48,MR!$A$41:$A$48,F83),0)))))),) -> 0 | E85: =IFERROR(IF(AND(M83="SI",E83="capta",D83="multilínea"),SUMIFS(MR!$E$5:$E$13,MR!$A$5:$A$13,F83),IF(AND(M83="SI",E83="portabilidad",D83="multilínea"),SUMIFS(MR!$F$5:$F$13,MR!$A$5:$A$13,F83),IF(AND(M83="NO",E83="capta",D83="multilínea"),SUMIFS(MR!$E$17:$E$25,MR!$A$17:$A$25,F83),IF(AND(M83="NO",E83="portabilidad",D83="multilínea"),SUMIFS(MR!$F$17:$F$25,MR!$A$17:$A$25,F83),IF(AND(M83="NO",E83="capta",D83="IEW"),SUMIFS(MR!$B$53:$B$61,MR!$A$53:$A$61,C83),IF(AND(M83="NO",E83="portabilidad",D83="IEW"),SUMIFS(MR!$B$53:$B$61,MR!$A$53:$A$61,C83),0)))))),)+IFERROR(IF(AND(M83="SI",E83="capta",D83="multilínea"),SUMIFS(MR!$E$30:$E$37,MR!$A$30:$A$37,F83),IF(AND(M83="SI",E83="portabilidad",D83="multilínea"),SUMIFS(MR!$F$30:$F$37,MR!$A$30:$A$37,F83),IF(AND(M83="NO",E83="capta",D83="multilínea"),SUMIFS(MR!$E$48:$E$398,MR!$A$41:$A$48,F83),IF(AND(M83="NO",E83="portabilidad",D83="multilínea"),SUMIFS(MR!$F$41:$F$48,MR!$A$41:$A$48,F83),0)))),) -> 0 | F85: =(IFERROR(IF(K83="SIN TERMINAL",0,IF(I83="SI",10,SUMIFS(MR!$G$6:$G$11,MR!$A$6:$A$11,F83))),0))*K85 -> 0 | G85: =IFERROR(IF(D83="multilínea",IF(G83="SI",MR!$N$4,0)+IF(H83="SI",MR!$N$5,0),0),0) -> 0 | I85: =(IF(D83="multilínea",IF($F$9="SI",IF($M83="SI",SUMIFS(MR!$I$6:$I$11,MR!$A$6:$A$11,F83),SUMIFS(MR!$I$18:$I$23,MR!$A$18:$A$23,F83))),SUMIFS(MR!$D$54:$D$61,MR!$A$54:$A$61,C83)))*P83 -> 0 | J85: =IF(M83="SI",IF($B$13+$B$23+$B$33+$B$43+$B$53+$B$63+$B$73+$B$83>99,(99-$B$13-$B$23-$B$33-$B$43-B$53-$B$63-$B$73)*I85,B83*I85),B83*I85) -> 0 | K85: =IF(IFERROR(SEARCH("CESIÓN",$J83,1),0)>0,0,1) -> 1
A86: SUBVENCIÓN TERMINAL | B86: =IFERROR(C86*B83,"SIN OFERTA") -> SIN OFERTA | C86: =IFERROR(IFERROR(IF($F$1="NO", IF(I83="SI",IF(E83="portabilidad", IF(D83="multilínea",IF(AND(C83<>"Soluciones Personalizadas RPV",C83<>"Soluciones Personalizadas Centrex"), OFFSET(CeldaInicioDxCVAP,MATCH(J83,'PVP VaP - Pyme'!C:C,0)-1,MATCH(L83,'PVP VaP - Pyme'!$Z$22:$AL$22,0)-1) +OFFSET(CeldaInicioDxCVAP,MATCH(J83,'PVP VaP - Pyme'!C:C,0)-1,MATCH(L83,'PVP VaP - Pyme'!$Z$22:$AL$22,0)))), IF(D83="IEW", OFFSET(CeldaInicioDxCVAPIEW,MATCH(J83,'PVP VaP IEW Pro - Pyme'!C:C,0)-1,MATCH(L83,'PVP VaP IEW Pro - Pyme'!$AA$22:$AH$22,0)-1) +OFFSET(CeldaInicioDxCVAPIEW,MATCH(J83,'PVP VaP IEW Pro - Pyme'!C:C,0)-1,MATCH(L83,'PVP VaP IEW Pro - Pyme'!$AA$22:$AH$22,0)), )), IF(M83="","SIN OFERTA",IF(M83="SI",IF(B87="SIN OFERTA",B87,IF(D83="IEW",OFFSET(CeldaInicioDxCIEW,MATCH(J83,'PVP Subv IEW - Pyme'!C:C,0)-1,MATCH(L83,'PVP Subv IEW - Pyme'!$I$4:$L$4,0)-1),OFFSET(IF(E83="portabilidad",CeldaInicioDxCPorta,CeldaInicioDxCCapta),MATCH(J83,'PVP Subv - Optima Pyme'!$C:$C,0)-1,MATCH(L83,'PVP Subv - Optima Pyme'!$I$4:$M$4,0)-1))), IF(B87="SIN OFERTA",B87,IF(D83="IEW",OFFSET(CeldaInicioDxCIEW,MATCH(J83,'PVP Subv IEW - Pyme'!C:C,0)-1,MATCH(L83,'PVP Subv IEW - Pyme'!$I$4:$L$4,0)-1),OFFSET(IF(E83="portabilidad",CeldaInicioDxCPorta9MAS,CeldaInicioDxCCapta9MAS),MATCH(J83,'PVP Subv - Sol Pers Pyme'!$C:$C,0)-1,MATCH(L83,'PVP Subv - Sol Pers Pyme'!$I$4:$M$4,0)-1))))))) +IF($F$1="SI", IF(I83="SI",IF(E83="portabilidad", IF(D83="multilínea",IF(AND(C83<>"Soluciones Personalizadas RPV",C83<>"Soluciones Personalizadas Centrex"), OFFSET(CeldaInicioDxCVAP,MATCH(J83,'PVP VaP - Pyme'!C:C,0)-1,MATCH(L83,'PVP VaP - Pyme'!$Z$22:$AL$22,0)-1) +OFFSET(CeldaInicioDxCVAP,MATCH(J83,'PVP VaP - Pyme'!C:C,0)-1,MATCH(L83,'PVP VaP - Pyme'!$Z$22:$AL$22,0)))), IF(D83="IEW", OFFSET(CeldaInicioDxCVAPIEW,MATCH(J83,'PVP VaP IEW Pro - Pyme'!C:C,0)-1,MATCH(L83,'PVP VaP IEW Pro - Pyme'!$AA$22:$AH$22,0)-1) +OFFSET(CeldaInicioDxCVAPIEW,MATCH(J83,'PVP VaP IEW Pro - Pyme'!C:C,0)-1,MATCH(L83,'PVP VaP IEW Pro - Pyme'!$AA$22:$AH$22,0)), )), IF(M83="","SIN OFERTA",IF(M83="SI",IF(B87="SIN OFERTA",B87,IF(D83="IEW",OFFSET(CeldaInicioDxCIEWAAPP,MATCH(J83,'PVP Subv IEW - Pyme AAPP'!C:C,0)-1,MATCH(L83,'PVP Subv IEW - Pyme AAPP'!$I$4:$L$4,0)-1),OFFSET(IF(E83="portabilidad",CeldaInicioDxCPortaAAPP,CeldaInicioDxCCaptaAAPP),MATCH(J83,'PVP Subv - Optima Pyme AAPP'!$C:$C,0)-1,MATCH(L83,'PVP Subv - Optima Pyme AAPP'!$I$4:$M$4,0)-1))), IF(B87="SIN OFERTA",B87,IF(D83="IEW",OFFSET(CeldaInicioDxCIEWAAPP,MATCH(J83,'PVP Subv IEW - Pyme AAPP'!C:C,0)-1,MATCH(L83,'PVP Subv IEW - Pyme AAPP'!$I$4:$L$4,0)-1),OFFSET(IF(E83="portabilidad",CeldaInicioDxCPorta9MASAAPP,CeldaInicioDxCCapta9MASAAPP),MATCH(J83,'PVP Subv - Sol Pers Pyme AAPP'!$C:$C,0)-1,MATCH(L83,'PVP Subv - Sol Pers Pyme AAPP'!$I$4:$M$4,0)-1))))))),"SIN OFERTA")+D86,"SIN OFERTA") -> SIN OFERTA | E86: =IFERROR(F86*B83,"SIN OFERTA") -> SIN OFERTA | F86: =IF(O83="SI",OFFSET(CeldadeinicioDxCportaCP36,MATCH(J83,'PVP Subv - Optima Pyme'!$C:$C,0)-1,MATCH(L83,'PVP Subv - Optima Pyme'!$BK$23:$BO$23,0)-1),"-") -> - | H86: =IFERROR(IF(N83="NO",0,SUMIFS(MR!$N$17:$N$21,MR!$M$17:$M$21,H85)),0) -> 0
A87: PVPR TERMINAL (sin IVA) | B87: =IFERROR(C87*B83,"SIN OFERTA") -> 0 | D87: Dif. CP 24 m | E87: =IF(E86="SIN OFERTA",0,(E86-B86)) -> 0 | F87: =IF(B86="SIN OFERTA",0,5*B83) -> 0 | G87: Válida en módulos: | H87: =IFERROR(INDEX(Tabla32[APLICA],MATCH(H85,Tabla32[PROMO],0)),"")
A88: PRECIO CESIÓN TERMINAL | B88: =IFERROR(C88*B83,"SIN OFERTA") -> SIN OFERTA | C88: =IF(M83="SI",IFERROR(-IF(D83="IEW",OFFSET(CeldaInicioPrecioCesiónIEW,MATCH(J83,'PVP Subv IEW - Pyme'!C:C,0)-1,0),OFFSET(CeldaInicioPrecioCesión,MATCH(J83,'PVP Subv - Optima Pyme'!$C:$C,0)-1,0)),"SIN OFERTA"), IFERROR(-IF(D83="IEW",OFFSET(CeldaInicioPrecioCesiónIEW,MATCH(J83,'PVP Subv IEW - Pyme'!C:C,0)-1,0),OFFSET(CeldaInicioPrecioCesión,MATCH(J83,'PVP Subv - Sol Pers Pyme'!$C:$C,0)-1,0)),"SIN OFERTA")) -> SIN OFERTA | H88: =IF(H86=12,H86+MR!$L$24,IF(H86=18,H86+MR!$L$23,IF(H86=48,H86+MR!$L$22,0))) -> 0
A89: MARGEN | B89: =IFERROR(B83*C89,"SIN OFERTA") -> 0 | C89: =IFERROR(C85+IF(NOT(ISNUMBER(C86)),0,C86)+IF(NOT(ISNUMBER(C87)),0,C87)+IF(NOT(ISNUMBER(C88)),0,C88),"SIN OFERTA") -> 0 | D89: MARGEN 36 | E89: =IFERROR(B83*F89,"SIN OFERTA") -> 0 | F89: =IFERROR(C89+(E87/B83),0) -> 0 | H89: =(H86-H88)*B83 -> 0 | I89: dif. Cp 24
B92: Nº ALTAS CON ESTE PERFIL | C92: TARIFA | D92: TIPO DE TARIFA | E92: TIPO DE ALTA | F92: PAQUETE DE VOZ Y DATOS | G92: CV USUARIO | H92: MFO CON FIJO PORTADO | I92: VENTA A PLAZOS | J92: TERMINAL | K92: GAMA | L92: MÓDULO OT | M92: ÓPTIMA | N92: O2O | O92: 36 m | P92: ESTRAT
A93: PERFIL DE ALTA | B93: 0 | D93: =IFERROR(INDEX(MR!Q:Q,MATCH(C93,MR!P:P,0)),"") | K93: =IF(J93="","SIN TERMINAL",IF(D93="IEW",INDEX('PVP Subv IEW - Pyme'!F:F,MATCH(J93,'PVP Subv IEW - Pyme'!C:C,0)),INDEX('PVP Subv - Optima Pyme'!F:F,MATCH(J93,'PVP Subv - Optima Pyme'!C:C,0)))) -> SIN TERMINAL | L93: =IFERROR(IF(D93="IEW",INDEX('MODULOS OT IEW'!D:D,MATCH(C93,'MODULOS OT IEW'!A:A,0)),INDEX('MODULOS OT MULTILINEA'!F:F,MATCH(E93&F93&K93,'MODULOS OT MULTILINEA'!A:A,0))),"") | M93: =+IF(C93="","",IF(OR(C93="Óptima Plus Empresas",C93="Óptima Plus Empresas BIG"),"SI","NO")) | N93: =+IF(C93="","",IF($C$9="SI","NO",IF(OR(C93="Óptima Plus Empresas",C93="Óptima Plus Empresas BIG"),"SI","NO"))) | O93: =+IF(N93="NO","NO",IF(AND(E93="portabilidad",L93<>"ENTRADA PRO"),"SI","NO")) -> NO | P93: =IF(AND(E93="capta",F93="EMPRESAS VOZ"),0,1) -> 1
B94: IMPORTE TOTAL | C94: IMPORTE UNITARIO | D94: PAQUETE DE VOZ Y DATOS | E94: ACTIVACION | F94: ACTIVACION CP 24 POR TERMINAL | G94: SVAs | H94: O2O | I94: ESTRATEGICA | N94: =IF(N93="SI",1,0) -> 0
A95: COMISIONES | B95: =C95*B93 -> 0 | C95: =D95+E95+F95+G95-H96*N94+I95 -> 0 | D95: =IFERROR(IF(AND(M93="SI",$G$3="Cliente 1-19 líneas"),SUMIFS(MR!$B$5:$B$13,MR!$A$5:$A$13,F93),IF(AND(M93="SI",$G$3="Cliente 20-39 líneas"),SUMIFS(MR!$C$5:$C$13,MR!$A$5:$A$13,F93),IF(AND(M93="SI",$G$3="Cliente > 40 líneas"),SUMIFS(MR!$D$5:$D$13,MR!$A$5:$A$13,F93),IF(AND(M93="NO",$G$3="Cliente 1-19 líneas"),SUMIFS(MR!$B$17:$B$25,MR!$A$17:$A$25,F93),IF(AND(M93="NO",$G$3="Cliente 20-39 líneas"),SUMIFS(MR!$C$17:$C$25,MR!$A$17:$A$25,F93),IF(AND(M93="NO",$G$3="Cliente > 40 líneas"),SUMIFS(MR!$D$17:$D$25,MR!$A$17:$A$25,F93),0)))))),)+IFERROR(IF(AND(M93="SI",$G$3="Cliente 1-19 líneas"),SUMIFS(MR!$B$30:$B$37,MR!$A$30:$A$37,F93),IF(AND(M93="SI",$G$3="Cliente 20-39 líneas"),SUMIFS(MR!$C$30:$C$37,MR!$A$30:$A$37,F93),IF(AND(M93="SI",$G$3="Cliente > 40 líneas"),SUMIFS(MR!$D$30:$D$37,MR!$A$30:$A$37,F93),IF(AND(M93="NO",$G$3="Cliente 1-19 líneas"),SUMIFS(MR!$B$41:$B$48,MR!$A$41:$A$48,F93),IF(AND(M93="NO",$G$3="Cliente 20-39 líneas"),SUMIFS(MR!$C$41:$C$48,MR!$A$41:$A$48,F93),IF(AND(M93="NO",$G$3="Cliente > 40 líneas"),SUMIFS(MR!$D$41:$D$48,MR!$A$41:$A$48,F93),0)))))),) -> 0 | E95: =IFERROR(IF(AND(M93="SI",E93="capta",D93="multilínea"),SUMIFS(MR!$E$5:$E$13,MR!$A$5:$A$13,F93),IF(AND(M93="SI",E93="portabilidad",D93="multilínea"),SUMIFS(MR!$F$5:$F$13,MR!$A$5:$A$13,F93),IF(AND(M93="NO",E93="capta",D93="multilínea"),SUMIFS(MR!$E$17:$E$25,MR!$A$17:$A$25,F93),IF(AND(M93="NO",E93="portabilidad",D93="multilínea"),SUMIFS(MR!$F$17:$F$25,MR!$A$17:$A$25,F93),IF(AND(M93="NO",E93="capta",D93="IEW"),SUMIFS(MR!$B$53:$B$61,MR!$A$53:$A$61,C93),IF(AND(M93="NO",E93="portabilidad",D93="IEW"),SUMIFS(MR!$B$53:$B$61,MR!$A$53:$A$61,C93),0)))))),)+IFERROR(IF(AND(M93="SI",E93="capta",D93="multilínea"),SUMIFS(MR!$E$30:$E$37,MR!$A$30:$A$37,F93),IF(AND(M93="SI",E93="portabilidad",D93="multilínea"),SUMIFS(MR!$F$30:$F$37,MR!$A$30:$A$37,F93),IF(AND(M93="NO",E93="capta",D93="multilínea"),SUMIFS(MR!$E$48:$E$398,MR!$A$41:$A$48,F93),IF(AND(M93="NO",E93="portabilidad",D93="multilínea"),SUMIFS(MR!$F$41:$F$48,MR!$A$41:$A$48,F93),0)))),) -> 0 | F95: =(IFERROR(IF(K93="SIN TERMINAL",0,IF(I93="SI",10,SUMIFS(MR!$G$6:$G$11,MR!$A$6:$A$11,F93))),0))*K95 -> 0 | G95: =IFERROR(IF(D93="multilínea",IF(G93="SI",MR!$N$4,0)+IF(H93="SI",MR!$N$5,0),0),0) -> 0 | I95: =(IF(D93="multilínea",IF($F$9="SI",IF($M93="SI",SUMIFS(MR!$I$6:$I$11,MR!$A$6:$A$11,F93),SUMIFS(MR!$I$18:$I$23,MR!$A$18:$A$23,F93))),SUMIFS(MR!$D$54:$D$61,MR!$A$54:$A$61,C93)))*P93 -> 0 | J95: =IF(M93="SI",IF($B$13+$B$23+$B$33+$B$43+$B$53+$B$63+$B$73+$B$83+$B$93>99,(99-$B$13-$B$23-$B$33-$B$43-B$53-$B$63-$B$73-$B$83)*I95,B93*I95),B93*I95) -> 0 | K95: =IF(IFERROR(SEARCH("CESIÓN",$J93,1),0)>0,0,1) -> 1
A96: SUBVENCIÓN TERMINAL | B96: =IFERROR(C96*B93,"SIN OFERTA") -> SIN OFERTA | C96: =IFERROR(IFERROR(IF($F$1="NO", IF(I93="SI",IF(E93="portabilidad", IF(D93="multilínea",IF(AND(C93<>"Soluciones Personalizadas RPV",C93<>"Soluciones Personalizadas Centrex"), OFFSET(CeldaInicioDxCVAP,MATCH(J93,'PVP VaP - Pyme'!C:C,0)-1,MATCH(L93,'PVP VaP - Pyme'!$Z$22:$AL$22,0)-1) +OFFSET(CeldaInicioDxCVAP,MATCH(J93,'PVP VaP - Pyme'!C:C,0)-1,MATCH(L93,'PVP VaP - Pyme'!$Z$22:$AL$22,0)))), IF(D93="IEW", OFFSET(CeldaInicioDxCVAPIEW,MATCH(J93,'PVP VaP IEW Pro - Pyme'!C:C,0)-1,MATCH(L93,'PVP VaP IEW Pro - Pyme'!$AA$22:$AH$22,0)-1) +OFFSET(CeldaInicioDxCVAPIEW,MATCH(J93,'PVP VaP IEW Pro - Pyme'!C:C,0)-1,MATCH(L93,'PVP VaP IEW Pro - Pyme'!$AA$22:$AH$22,0)), )), IF(M93="","SIN OFERTA",IF(M93="SI",IF(B97="SIN OFERTA",B97,IF(D93="IEW",OFFSET(CeldaInicioDxCIEW,MATCH(J93,'PVP Subv IEW - Pyme'!C:C,0)-1,MATCH(L93,'PVP Subv IEW - Pyme'!$I$4:$L$4,0)-1),OFFSET(IF(E93="portabilidad",CeldaInicioDxCPorta,CeldaInicioDxCCapta),MATCH(J93,'PVP Subv - Optima Pyme'!$C:$C,0)-1,MATCH(L93,'PVP Subv - Optima Pyme'!$I$4:$M$4,0)-1))), IF(B97="SIN OFERTA",B97,IF(D93="IEW",OFFSET(CeldaInicioDxCIEW,MATCH(J93,'PVP Subv IEW - Pyme'!C:C,0)-1,MATCH(L93,'PVP Subv IEW - Pyme'!$I$4:$L$4,0)-1),OFFSET(IF(E93="portabilidad",CeldaInicioDxCPorta9MAS,CeldaInicioDxCCapta9MAS),MATCH(J93,'PVP Subv - Sol Pers Pyme'!$C:$C,0)-1,MATCH(L93,'PVP Subv - Sol Pers Pyme'!$I$4:$M$4,0)-1))))))) +IF($F$1="SI", IF(I93="SI",IF(E93="portabilidad", IF(D93="multilínea",IF(AND(C93<>"Soluciones Personalizadas RPV",C93<>"Soluciones Personalizadas Centrex"), OFFSET(CeldaInicioDxCVAP,MATCH(J93,'PVP VaP - Pyme'!C:C,0)-1,MATCH(L93,'PVP VaP - Pyme'!$Z$22:$AL$22,0)-1) +OFFSET(CeldaInicioDxCVAP,MATCH(J93,'PVP VaP - Pyme'!C:C,0)-1,MATCH(L93,'PVP VaP - Pyme'!$Z$22:$AL$22,0)))), IF(D93="IEW", OFFSET(CeldaInicioDxCVAPIEW,MATCH(J93,'PVP VaP IEW Pro - Pyme'!C:C,0)-1,MATCH(L93,'PVP VaP IEW Pro - Pyme'!$AA$22:$AH$22,0)-1) +OFFSET(CeldaInicioDxCVAPIEW,MATCH(J93,'PVP VaP IEW Pro - Pyme'!C:C,0)-1,MATCH(L93,'PVP VaP IEW Pro - Pyme'!$AA$22:$AH$22,0)), )), IF(M93="","SIN OFERTA",IF(M93="SI",IF(B97="SIN OFERTA",B97,IF(D93="IEW",OFFSET(CeldaInicioDxCIEWAAPP,MATCH(J93,'PVP Subv IEW - Pyme AAPP'!C:C,0)-1,MATCH(L93,'PVP Subv IEW - Pyme AAPP'!$I$4:$L$4,0)-1),OFFSET(IF(E93="portabilidad",CeldaInicioDxCPortaAAPP,CeldaInicioDxCCaptaAAPP),MATCH(J93,'PVP Subv - Optima Pyme AAPP'!$C:$C,0)-1,MATCH(L93,'PVP Subv - Optima Pyme AAPP'!$I$4:$M$4,0)-1))), IF(B97="SIN OFERTA",B97,IF(D93="IEW",OFFSET(CeldaInicioDxCIEWAAPP,MATCH(J93,'PVP Subv IEW - Pyme AAPP'!C:C,0)-1,MATCH(L93,'PVP Subv IEW - Pyme AAPP'!$I$4:$L$4,0)-1),OFFSET(IF(E93="portabilidad",CeldaInicioDxCPorta9MASAAPP,CeldaInicioDxCCapta9MASAAPP),MATCH(J93,'PVP Subv - Sol Pers Pyme AAPP'!$C:$C,0)-1,MATCH(L93,'PVP Subv - Sol Pers Pyme AAPP'!$I$4:$M$4,0)-1))))))),"SIN OFERTA")+D96,"SIN OFERTA") -> SIN OFERTA | E96: =IFERROR(F96*B93,"SIN OFERTA") -> SIN OFERTA | F96: =IF(O93="SI",OFFSET(CeldadeinicioDxCportaCP36,MATCH(J93,'PVP Subv - Optima Pyme'!$C:$C,0)-1,MATCH(L93,'PVP Subv - Optima Pyme'!$BK$23:$BO$23,0)-1),"-") -> - | H96: =IFERROR(IF(N93="NO",0,SUMIFS(MR!$N$17:$N$21,MR!$M$17:$M$21,H95)),0) -> 0
A97: PVPR TERMINAL (sin IVA) | B97: =IFERROR(C97*B93,"SIN OFERTA") -> 0 | D97: Dif. CP 24 m | E97: =IF(E96="SIN OFERTA",0,(E96-B96)) -> 0 | F97: =IF(B96="SIN OFERTA",0,5*B93) -> 0 | G97: Válida en módulos: | H97: =IFERROR(INDEX(Tabla32[APLICA],MATCH(H95,Tabla32[PROMO],0)),"")
A98: PRECIO CESIÓN TERMINAL | B98: =IFERROR(C98*B93,"SIN OFERTA") -> SIN OFERTA | C98: =IF(M93="SI",IFERROR(-IF(D93="IEW",OFFSET(CeldaInicioPrecioCesiónIEW,MATCH(J93,'PVP Subv IEW - Pyme'!C:C,0)-1,0),OFFSET(CeldaInicioPrecioCesión,MATCH(J93,'PVP Subv - Optima Pyme'!$C:$C,0)-1,0)),"SIN OFERTA"), IFERROR(-IF(D93="IEW",OFFSET(CeldaInicioPrecioCesiónIEW,MATCH(J93,'PVP Subv IEW - Pyme'!C:C,0)-1,0),OFFSET(CeldaInicioPrecioCesión,MATCH(J93,'PVP Subv - Sol Pers Pyme'!$C:$C,0)-1,0)),"SIN OFERTA")) -> SIN OFERTA | H98: =IF(H96=12,H96+MR!$L$24,IF(H96=18,H96+MR!$L$23,IF(H96=48,H96+MR!$L$22,0))) -> 0
A99: MARGEN | B99: =IFERROR(B93*C99,"SIN OFERTA") -> 0 | C99: =IFERROR(C95+IF(NOT(ISNUMBER(C96)),0,C96)+IF(NOT(ISNUMBER(C97)),0,C97)+IF(NOT(ISNUMBER(C98)),0,C98),"SIN OFERTA") -> 0 | D99: MARGEN 36 | E99: =IFERROR(B93*F99,"SIN OFERTA") -> 0 | F99: =IFERROR(C99+(E97/B93),0) -> 0 | H99: =(H96-H98)*B93 -> 0 | I99: dif. Cp 24
A105: PRODUCTOS DE FIJO PYME / SOLUCIONES DIGITALES / CIBERPROTECCIÓN
A107: RENTABILIDAD DE LA OPERACIÓN
B108: IMPORTE TOTAL | D108: RESUMEN DE LA OPERACIÓN
A109: COMISIONES | B109: =SUMIFS($B$115:$B$145,$A$115:$A$145,A109) -> 6 | D109: Nº TOTAL DE FIJO | G109: =SUMIFS(B107:B145,A107:A145,"PERFIL DE ALTA FIJO") -> 1
A110: ESTRATEGICA | B110: =$B$122+$B$129+$B$136+$B$143 -> 0
B111: =B109+B110 -> 6
A113: Puntos Fijo | B113: =B110/MR!$I$13 -> 0
B117: Nº ALTAS CON ESTE PERFIL | C117: Producto de Fijo | D117: TIPO DE FIJO | E117: Puestos fijos tipo 1 | F117: Puestos móviles comunicator o GCU | G117: Puestos fijos tipo 2 | H117: Puestos móviles comunicator o GCU | I117: SVAs N+ | J117: SVAs office 365 / otros SVAs SME / Soluciones Digitales /Ciberprotección | K117: SVAs Conecta Empresas | T117: SOLUCIONES DIGITALES | AA117: CIBERPROTECCIÓN RED FIJA | AC117: CIBERPROTECCIÓN RED MÓVIL | AE117: CIBERSEGURIDAD
A118: PERFIL DE ALTA FIJO | B118: 0 | D118: =IFERROR(INDEX(MR!$Q$15:$Q$42,MATCH(C118,MR!$P$15:$P$42,0)),"") | L118: Total Puestos BIG | M118: Total Cpymes | N118: Total Network Plus | O118: BIG MOVIL | P118: TOTAL BIG | Q118: Total Cempresas | R118: Total SVAs Cempresas | S118: Total O365 | T118: Web Essentials | U118: Web Empresas | V118: E-commerce | W118: Posicionamiento Web | X118: Gestión facturas | Y118: Presencia Digital | Z118: Redes Sociales | AA118: Seguridad en tu Sede Estandar | AB118: Seguridad en tu Sede Avanzada | AC118: =MR!$A$135 -> Ciberprotección Red Móvil | AD118: =MR!$A$136 -> Ciberprotección Red Móvil + App | AE118: =MR!$A$140 -> Seguridad en Tu Móvil | AF118: =MR!$A$141 -> Seguridad en Tu Correo | AG118: =MR!$A$142 -> Seguridad en Tu Dispositivo
D119: Nº Puestos | E119: 0 | F119: 0 | G119: 0 | H119: 0 | I119: 0 | L119: =IF($D118="BIG PYME",SUM($E119:$H119)-$F119-$H119,0) -> 0 | M119: =IF($D118="CONECTA PYMES",$B118,0) -> 0 | N119: =$I119 -> 0 | O119: =IF($C118="Acceso Móvil",$B118,0) -> 0 | P119: =IF($D118="BIG PYME",$B118,0) -> 0 | Q119: =IF($D118="CONECTA EMPRESAS",$B118,0) -> 0 | R119: =IF($D118="CONECTA EMPRESAS",$K119,0) -> 0 | S119: =IF($J118="Microsoft 365 Básico Anual",$J119/2,0)+IF($J118="Microsoft 365 Estandar Anual",$J119,0)+IF($J118="Nueva Localización",$J119,0)+IF($J118="Localización",$J119,0)+IF($J118="Control Horario",$J119/2,0)+IF($J118="Soporte IT",$J119,0)+IF($J118="Wifi Clientes",$J119,0) -> 0 | T119: =IF($J118="Web Essentials",$J119,0) -> 0 | U119: =IF($J118="Web Empresas",$J119,0) -> 0 | V119: =IF($J118="E-commerce",$J119,0) -> 0 | W119: =IF($J118="Posicionamiento Web",$J119,0) -> 0 | X119: =IF($J118="Gestión de facturas y clientes 2",$J119,0)/2 -> 0 | Y119: =IF($J118="Presencia Digital",$J119,0) -> 0 | Z119: =IF($J118="Redes Sociales",$J119,0)/2 -> 0 | AA119: =IF($K118="Seguridad en tu Sede Estandar",$K119,0) -> 0 | AB119: =IF($K118="Seguridad en tu Sede Avanzada",$K119,0) -> 0 | AC119: =IF($J118="Ciberprotección Red Móvil",$J119,0) -> 0 | AD119: =IF($J118="Ciberprotección App",$J119,0) -> 0 | AE119: =IF($J118="Seguridad en Tu Móvil",$J119,0) -> 0 | AF119: =IF($J118="Seguridad en Tu Correo",$J119,0) -> 0 | AG119: =IF($J118="Seguridad en Tu Dispositivo",$J119,0) -> 0
B120: IMPORTE TOTAL | C120: IMPORTE UNITARIO | E120: IMPORTE UNITARIO | F120: IMPORTE UNITARIO | G120: IMPORTE UNITARIO | H120: IMPORTE UNITARIO | I120: IMPORTE UNITARIO | J120: IMPORTE UNITARIO | K120: IMPORTE UNITARIO | T120: =SUM($T119:$Z119) -> 0
A121: COMISIONES | B121: =B118*C121+SUMPRODUCT(E119:K119,E121:K121) -> 0 | C121: =IF(D118="CONECTA PYMES",SUMIFS(MR!$B$68:$B$78,MR!$A$68:$A$78,C118),IF(D118="CONECTA EMPRESAS",SUMIFS(MR!$B$108:$B$111,MR!$A$108:$A$111,C118),SUMIFS(MR!$B$81:$B$87,MR!$A$81:$A$87,C118))) -> 0 | E121: =IF(OR(D118="CONECTA PYMES",D118="CONECTA EMPRESAS"),0,SUMIFS(MR!$B$88:$B$94,MR!$A$88:$A$94,E118)) -> 0 | F121: =IF(OR(D118="CONECTA PYMES",D118="CONECTA EMPRESAS"),0,SUMIFS(MR!$D$88:$D$94,MR!$A$88:$A$94,F118)) -> 0 | G121: =IF(OR(D118="CONECTA PYMES",D118="CONECTA EMPRESAS"),0,SUMIFS(MR!$B$88:$B$94,MR!$A$88:$A$94,G118)) -> 0 | H121: =IF(OR(D118="CONECTA PYMES",D118="CONECTA EMPRESAS"),0,SUMIFS(MR!$B$88:$B$94,MR!$A$88:$A$94,H118)) -> 0 | I121: =IF(D118="BIG PYME",0,SUMIFS(MR!$B$100:$B$101,MR!$A$100:$A$101,I118)) -> 0 | J121: =SUMIFS(MR!$B$122:$B$143,MR!$A$122:$A$143,J118) -> 0 | K121: =SUMIFS(MR!$B$112:$B$116,MR!$A$112:$A$116,K118) -> 0
A122: ESTRATEGICA | B122: =B118*C122+SUMPRODUCT(E119:K119,E122:K122) -> 0 | C122: =SUMIFS(MR!$D$68:$D$119,MR!$A$68:$A$119,C118) -> 0 | E122: =IF(OR(D118="CONECTA PYMES",D118="CONECTA EMPRESAS"),0,SUMIFS(MR!$D$88:$D$94,MR!$A$88:$A$94,E118)) -> 0 | F122: =IF(OR(D118="CONECTA PYMES",D118="CONECTA EMPRESAS"),0,SUMIFS(MR!$B$88:$B$94,MR!$A$88:$A$94,F118)) -> 0 | G122: =IF(OR(D118="CONECTA PYMES",D118="CONECTA EMPRESAS"),0,SUMIFS(MR!$D$88:$D$94,MR!$A$88:$A$94,G118)) -> 0 | H122: =IF(OR(D118="CONECTA PYMES",D118="CONECTA EMPRESAS"),0,SUMIFS(MR!$D$88:$D$94,MR!$A$88:$A$94,H118)) -> 0 | I122: =IF(D118="BIG PYME",0,SUMIFS(MR!$D$100:$D$101,MR!$A$100:$A$101,I118)) -> 0 | J122: =SUMIFS(MR!$D$122:$D$143,MR!$A$122:$A$143,J118) -> 0 | K122: =SUMIFS(MR!$D$112:$D$116,MR!$A$112:$A$116,K118) -> 0
B124: Nº ALTAS CON ESTE PERFIL | C124: Producto de Fijo | D124: TIPO DE FIJO | E124: Puestos fijos tipo 1 | F124: Puestos móviles comunicator o GCU | G124: Puestos fijos tipo 2 | H124: Puestos móviles comunicator o GCU | I124: SVAs N+ | J124: SVAs office 365 / otros SVAs SME / Soluciones Digitales | K124: SVAs Conecta Empresas | T124: SOLUCIONES DIGITALES | AA124: CIBERPROTECCIÓN RED FIJA | AC124: CIBERPROTECCIÓN RED MÓVIL | AE124: CIBERSEGURIDAD
A125: PERFIL DE ALTA FIJO | B125: 1 | D125: =IFERROR(INDEX(MR!$Q$15:$Q$42,MATCH(C125,MR!$P$15:$P$42,0)),"") | L125: Total Puestos BIG | M125: Total Cpymes | N125: Total Network Plus | O125: BIG MOVIL | P125: TOTAL BIG | Q125: Total Cempresas | R125: Total SVAs Cempresas | S125: Total O365 | T125: Web Essentials | U125: Web Empresas | V125: E-commerce | W125: Posicionamiento Web | X125: Gestión facturas | Y125: Presencia Digital | Z125: Redes Sociales | AA125: Seguridad en tu Sede Estandar | AB125: Seguridad en tu Sede Avanzada | AC125: =MR!$A$135 -> Ciberprotección Red Móvil | AD125: =MR!$A$136 -> Ciberprotección Red Móvil + App | AE125: =MR!$A$140 -> Seguridad en Tu Móvil | AF125: =MR!$A$141 -> Seguridad en Tu Correo | AG125: =MR!$A$142 -> Seguridad en Tu Dispositivo
D126: Nº Puestos | E126: 0 | F126: 0 | G126: 0 | H126: 0 | I126: 0 | K126: 0 | L126: =IF($D125="BIG PYME",SUM($E126:$H126)-$F126-$H126,0) -> 0 | M126: =IF($D125="CONECTA PYMES",$B125,0) -> 0 | N126: =$I126 -> 0 | O126: =IF($C125="Acceso Móvil",$B125,0) -> 0 | P126: =IF($D125="BIG PYME",$B125,0) -> 0 | Q126: =IF($D125="CONECTA EMPRESAS",$B125,0) -> 0 | R126: =IF($D125="CONECTA EMPRESAS",$K126,0) -> 0 | S126: =IF($J125="Microsoft 365 Básico Anual",$J126/2,0)+IF($J125="Microsoft 365 Estandar Anual",$J126,0)+IF($J125="Nueva Localización",$J126,0)+IF($J125="Localización",$J126,0)+IF($J125="Control Horario",$J126/2,0)+IF($J125="Soporte IT",$J126,0)+IF($J125="Wifi Clientes",$J126,0) -> 0 | T126: =IF($J125="Web Essentials",$J126,0) -> 0 | U126: =IF($J125="Web Empresas",$J126,0) -> 0 | V126: =IF($J125="E-commerce",$J126,0) -> 0 | W126: =IF($J125="Posicionamiento Web",$J126,0) -> 0 | X126: =IF($J125="Gestión de facturas y clientes 2",$J126,0)/2 -> 0 | Y126: =IF($J125="Presencia Digital",$J126,0)/2 -> 0 | Z126: =IF($J125="Redes Sociales",$J126,0)/2 -> 0 | AA126: =IF($K125="Seguridad en tu Sede Estandar",$K126,0) -> 0 | AB126: =IF($K125="Seguridad en tu Sede Avanzada",$K126,0) -> 0 | AC126: =IF($J125="Ciberprotección Red Móvil",$J126,0) -> 0 | AD126: =IF($J125="Ciberprotección App",$J126,0) -> 0 | AE126: =IF($J125="Seguridad en Tu Móvil",$J126,0) -> 0 | AF126: =IF($J125="Seguridad en Tu Correo",$J126,0) -> 0 | AG126: =IF($J125="Seguridad en Tu Dispositivo",$J126,0) -> 0
B127: IMPORTE TOTAL | C127: IMPORTE UNITARIO | E127: IMPORTE UNITARIO | F127: IMPORTE UNITARIO | G127: IMPORTE UNITARIO | H127: IMPORTE UNITARIO | I127: IMPORTE UNITARIO | J127: IMPORTE UNITARIO | K127: IMPORTE UNITARIO | T127: =SUM($T126:$Z126) -> 0
A128: COMISIONES | B128: =B125*C128+SUMPRODUCT(E126:K126,E128:K128) -> 0 | C128: =IF(D125="CONECTA PYMES",SUMIFS(MR!$B$68:$B$76,MR!$A$68:$A$76,C125),IF(D125="CONECTA EMPRESAS",SUMIFS(MR!$B$108:$B$111,MR!$A$108:$A$111,C125),SUMIFS(MR!$B$81:$B$87,MR!$A$81:$A$87,C125))) -> 0 | E128: =IF(OR(D125="CONECTA PYMES",D125="CONECTA EMPRESAS"),0,SUMIFS(MR!$B$88:$B$94,MR!$A$88:$A$94,E125)) -> 0 | F128: =IF(OR(D125="CONECTA PYMES",D125="CONECTA EMPRESAS"),0,SUMIFS(MR!$D$88:$D$94,MR!$A$88:$A$94,F125)) -> 0 | G128: =IF(OR(D125="CONECTA PYMES",D125="CONECTA EMPRESAS"),0,SUMIFS(MR!$B$88:$B$94,MR!$A$88:$A$94,G125)) -> 0 | H128: =IF(OR(D125="CONECTA PYMES",D125="CONECTA EMPRESAS"),0,SUMIFS(MR!$B$88:$B$94,MR!$A$88:$A$94,H125)) -> 0 | I128: =IF(D125="BIG PYME",0,SUMIFS(MR!$B$100:$B$101,MR!$A$100:$A$101,I125)) -> 0 | J128: =SUMIFS(MR!$B$122:$B$143,MR!$A$122:$A$143,J125) -> 0 | K128: =SUMIFS(MR!$B$112:$B$116,MR!$A$112:$A$116,K125) -> 0
...

Sheet PVP VaP - Pyme
B2: OFERTA TÁCTICA EMPRESAS | H2: Pago Único | J2: CAPTA | M2: PORTABILIDAD
B4: 45658 | C4: 01/01 al 31/01 | J4: - | M4: ENTRADA PRO | O4: NORMAL PRO | Q4: VALOR PRO | S4: PREMIUM PRO | U4: TOP PRO
B5: 1. CONDICIONES DE LA OFERTA VENTA A PLAZOS (según tarifa y situación del cliente) | D5: Tarifas | H5: Todas Tarifas | J5: - | M5: T. Optima Plus Empresas T. Optima Plus Empresas Big + Empresas Voz y Empresas 1 | O5: T. Optima Plus Empresas T. Optima Plus Empresas Big + Empresas 5 y Empresas Intranet | Q5: T. Optima Plus Empresas T. Optima Plus Empresas Big + Empresas 20 | S5: T. Optima Plus Empresas T. Optima Plus Empresas Big + Empresas Infinita | U5: T. Optima Plus Empresas T. Optima Plus Empresas Big + Empresas Internacional
D13: Ampliaciones (meses antigüedad) | H13: Todos | J13: cliente -4 M, solo accede a Pago Único | M13: + 4 M | O13: + 4 M | Q13: + 4 M | S13: + 4 M | U13: + 4 M
D14: Origen (Portabilidad / Migración) | H14: Pos | J14: Capta de cliente nuevo, solo accede a Pago Único | M14: Pospago | O14: Pospago | Q14: Pospago | S14: Pospago | U14: Pospago
D15: CP Tarifa Voz | H15: 12 M | J15: - | M15: 24 M | O15: 24 M | Q15: 24 M | S15: 24 M | U15: 24 M
D16: CP Tarifa Datos | H16: - | J16: - | M16: 24 M | O16: 24 M Plus | Q16: 24 M Plus | S16: 24 M Plus | U16: 24 M Plus | AN16: DIFERENCIAS Vs MES ANTERIOR
AN17: 6 | AO17: 7 | AP17: 8 | AQ17: 9 | AR17: 10 | AS17: 11 | AT17: 12 | AU17: 13 | AV17: 14 | AW17: 15 | AX17: 16 | AY17: 17 | AZ17: 18 | BA17: 19 | BB17: 20
B18: 2. PRECIO DEL TERMINAL POR GRUPO DE TARIFAS | H18: Pago Único | J18: PVPR CAPTA (tarifas móvil y convergentes) | M18: PVPR PORTABILIDAD | X18: DxC Pago Único | Z18: DxC CAPTA (tarifas móvil y convergentes) | AC18: DxC PORTABILIDAD | AN18: Pago Único | AP18: PVPR CAPTA (tarifas móvil y convergentes) | AS18: PVPR PORTABILIDAD
M20: GRUPOS DE TARIFAS MÓVIL | AC20: GRUPOS DE TARIFAS MÓVIL | AS20: GRUPOS DE TARIFAS MÓVIL
J22: - | M22: ENTRADA PRO | O22: NORMAL PRO | Q22: VALOR PRO | S22: PREMIUM PRO | U22: TOP PRO | Z22: - | AC22: ENTRADA PRO | AE22: NORMAL PRO | AG22: VALOR PRO | AI22: PREMIUM PRO | AK22: TOP PRO | AP22: ENTRADA PRO | AS22: ENTRADA PRO | AU22: NORMAL PRO | AW22: VALOR PRO | AY22: PREMIUM PRO | BA22: TOP PRO
B24: MARCA | C24: Modelo (Novedades) | D24: Precio Cesión | E24: Canon Digital | F24: Gama | G24: Meses Cuota | H24: Pago Unico (sin IVA) | J24: Pago Inicial (sin IVA) | K24: Cuota Mes (sin IVA) | M24: Pago Inicial (sin IVA) | N24: Cuota Mes (sin IVA) | O24: Pago Inicial (sin IVA) | P24: Cuota Mes (sin IVA) | Q24: Pago Inicial (sin IVA) | R24: Cuota Mes (sin IVA) | S24: Pago Inicial (sin IVA) | T24: Cuota Mes (sin IVA) | U24: Pago Inicial (sin IVA) | V24: Cuota Mes (sin IVA) | X24: DxC Pago Unico | Z24: DxC Precio | AA24: DxC VaP | AC24: DxC Precio | AD24: DxC VaP | AE24: DxC Precio | AF24: DxC VaP | AG24: DxC Precio | AH24: DxC VaP | AI24: DxC Precio | AJ24: DxC VaP | AK24: DxC Precio | AL24: DxC VaP | AN24: Pago Unico (sin IVA) | AP24: Pago Inicial (sin IVA) | AQ24: Cuota Mes (sin IVA) | AS24: Pago Inicial (sin IVA) | AT24: Cuota Mes (sin IVA) | AU24: Pago Inicial (sin IVA) | AV24: Cuota Mes (sin IVA) | AW24: Pago Inicial (sin IVA) | AX24: Cuota Mes (sin IVA) | AY24: Pago Inicial (sin IVA) | AZ24: Cuota Mes (sin IVA) | BA24: Pago Inicial (sin IVA) | BB24: Cuota Mes (sin IVA)
B25: ORANGE | C25: AD HOC H3 CESIÓN | D25: 0 | E25: 1.1 | F25: FIXED STYLE | G25: - | H25: - | J25: - | K25: - | M25: - | N25: - | O25: - | P25: - | Q25: - | R25: - | S25: - | T25: - | U25: - | V25: - | X25: 0 | Z25: 0 | AA25: 0 | AC25: 0 | AD25: 0 | AE25: 0 | AF25: 0 | AG25: 0 | AH25: 0 | AI25: 0 | AJ25: 0 | AK25: 0 | AL25: 0 | AN25: 0 | AP25: 0 | AQ25: 0 | AS25: 0 | AT25: 0 | AU25: 0 | AV25: 0 | AW25: 0 | AX25: 0 | AY25: 0 | AZ25: 0 | BA25: 0 | BB25: 0
B26: ORANGE | C26: ADOC D30 | D26: 239 | E26: 3.75 | F26: FIXED STYLE | G26: 24 | H26: 280 | J26: - | K26: - | M26: 0 | N26: 7.3 | O26: 0 | P26: 5.9 | Q26: 0 | R26: 2.5 | S26: 0 | T26: 0 | U26: 0 | V26: 0 | X26: -41 | Z26: 0 | AA26: 0 | AC26: 64 | AD26: 175 | AE26: 97 | AF26: 142 | AG26: 179 | AH26: 60 | AI26: 239 | AJ26: 0 | AK26: 239 | AL26: 0 | AN26: 0 | AP26: 0 | AQ26: 0 | AS26: 0 | AT26: 0 | AU26: 0 | AV26: 0 | AW26: 0 | AX26: 0 | AY26: 0 | AZ26: 0 | BA26: 0 | BB26: 0
B27: ORANGE | C27: ADOC D30 CESIÓN | D27: 0 | E27: 3.75 | F27: FIXED STYLE | G27: - | H27: - | J27: - | K27: - | M27: - | N27: - | O27: - | P27: - | Q27: - | R27: - | S27: - | T27: - | U27: - | V27: - | X27: 0 | Z27: 0 | AA27: 0 | AC27: 0 | AD27: 0 | AE27: 0 | AF27: 0 | AG27: 0 | AH27: 0 | AI27: 0 | AJ27: 0 | AK27: 0 | AL27: 0 | AN27: 0 | AP27: 0 | AQ27: 0 | AS27: 0 | AT27: 0 | AU27: 0 | AV27: 0 | AW27: 0 | AX27: 0 | AY27: 0 | AZ27: 0 | BA27: 0 | BB27: 0
B28: AD HOC | C28: ADOC SC01 | D28: 64 | E28: 1.1 | F28: VOZ | G28: - | H28: - | J28: - | K28: - | M28: - | N28: - | O28: - | P28: - | Q28: - | R28: - | S28: - | T28: - | U28: - | V28: - | X28: 0 | Z28: 0 | AA28: 0 | AC28: 0 | AD28: 0 | AE28: 0 | AF28: 0 | AG28: 0 | AH28: 0 | AI28: 0 | AJ28: 0 | AK28: 0 | AL28: 0 | AN28: 0 | AP28: 0 | AQ28: 0 | AS28: 0 | AT28: 0 | AU28: 0 | AV28: 0 | AW28: 0 | AX28: 0 | AY28: 0 | AZ28: 0 | BA28: 0 | BB28: 0
B29: ADOC | C29: ADOC SC04 | D29: 77 | E29: 1.1 | F29: VOZ | G29: 24 | H29: 93 | J29: - | K29: - | M29: 0 | N29: 0 | O29: 0 | P29: 0 | Q29: 0 | R29: 0 | S29: 0 | T29: 0 | U29: 0 | V29: 0 | X29: -16 | Z29: 0 | AA29: 0 | AC29: 77 | AD29: 0 | AE29: 77 | AF29: 0 | AG29: 77 | AH29: 0 | AI29: 77 | AJ29: 0 | AK29: 77 | AL29: 0 | AN29: 0 | AP29: 0 | AQ29: 0 | AS29: 0 | AT29: 0 | AU29: 0 | AV29: 0 | AW29: 0 | AX29: 0 | AY29: 0 | AZ29: 0 | BA29: 0 | BB29: 0
B30: APPLE | C30: APPLE AIRPODS 4 | D30: 137 | E30: 0 | F30: OC_AURICULARES | G30: 24 | H30: 165 | J30: - | K30: - | M30: 0 | N30: 4 | O30: 0 | P30: 2.6 | Q30: 0 | R30: 0 | S30: 0 | T30: 0 | U30: 0 | V30: 0 | X30: -28 | Z30: 0 | AA30: 0 | AC30: 41 | AD30: 96 | AE30: 75 | AF30: 62 | AG30: 137 | AH30: 0 | AI30: 137 | AJ30: 0 | AK30: 137 | AL30: 0 | AN30: 0 | AP30: 0 | AQ30: 0 | AS30: 0 | AT30: 0 | AU30: 0 | AV30: 0 | AW30: 0 | AX30: 0 | AY30: 0 | AZ30: 0 | BA30: 0 | BB30: 0
B31: APPLE | C31: APPLE AIRPODS 4 CON CANCELACION ACTIVA RUIDO | D31: 184 | E31: 0 | F31: OC_AURICULARES | G31: 24 | H31: 222 | J31: - | K31: - | M31: 0 | N31: 5.6 | O31: 0 | P31: 4.2 | Q31: 0 | R31: 0 | S31: 0 | T31: 0 | U31: 0 | V31: 0 | X31: -38 | Z31: 0 | AA31: 0 | AC31: 50 | AD31: 134 | AE31: 83 | AF31: 101 | AG31: 184 | AH31: 0 | AI31: 184 | AJ31: 0 | AK31: 184 | AL31: 0 | AN31: 0 | AP31: 0 | AQ31: 0 | AS31: 0 | AT31: 0 | AU31: 0 | AV31: 0 | AW31: 0 | AX31: 0 | AY31: 0 | AZ31: 0 | BA31: 0 | BB31: 0
B32: APPLE | C32: APPLE AIRPODS PRO 2a GENERACION MAGSAFE USBC | D32: 279 | E32: 0 | F32: OC_AURICULARES | G32: 24 | H32: 336 | J32: - | K32: - | M32: 0 | N32: 8.1 | O32: 0 | P32: 6.7 | Q32: 0 | R32: 3.4 | S32: 0 | T32: 1.8 | U32: 0 | V32: 0 | X32: -57 | Z32: 0 | AA32: 0 | AC32: 85 | AD32: 194 | AE32: 118 | AF32: 161 | AG32: 197 | AH32: 82 | AI32: 236 | AJ32: 43 | AK32: 279 | AL32: 0 | AN32: 0 | AP32: 0 | AQ32: 0 | AS32: 0 | AT32: 0 | AU32: 0 | AV32: 0 | AW32: 0 | AX32: 0 | AY32: 0 | AZ32: 0 | BA32: 0 | BB32: 0
B33: APPLE | C33: APPLE WATCH S10 CELLULAR 42MM | D33: 532 | E33: 2.5 | F33: OC_SMART WATCH | G33: 24 | H33: 643 | J33: - | K33: - | M33: 39 | N33: 16.4 | O33: 19 | P33: 15.6 | Q33: 0 | R33: 13.1 | S33: 0 | T33: 11.5 | U33: 0 | V33: 6.8 | X33: -111 | Z33: 0 | AA33: 0 | AC33: 99 | AD33: 394 | AE33: 139 | AF33: 374 | AG33: 218 | AH33: 314 | AI33: 256 | AJ33: 276 | AK33: 369 | AL33: 163 | AN33: 0 | AP33: 0 | AQ33: 0 | AS33: 0 | AT33: 0 | AU33: 0 | AV33: 0 | AW33: 0 | AX33: 0 | AY33: 0 | AZ33: 0 | BA33: 0 | BB33: 0
B34: APPLE | C34: APPLE WATCH S10 CELLULAR 46MM | D34: 555 | E34: 2.5 | F34: OC_SMART WATCH | G34: 24 | H34: 671 | J34: - | K34: - | M34: 39 | N34: 17.4 | O34: 19 | P34: 16.6 | Q34: 0 | R34: 14.1 | S34: 0 | T34: 12.4 | U34: 0 | V34: 7.8 | X34: -116 | Z34: 0 | AA34: 0 | AC34: 98 | AD34: 418 | AE34: 138 | AF34: 398 | AG34: 217 | AH34: 338 | AI34: 257 | AJ34: 298 | AK34: 368 | AL34: 187 | AN34: 0 | AP34: 0 | AQ34: 0 | AS34: 0 | AT34: 0 | AU34: 0 | AV34: 0 | AW34: 0 | AX34: 0 | AY34: 0 | AZ34: 0 | BA34: 0 | BB34: 0
B35: AD HOC | C35: AURICULARES AD HOC BT01 | D35: 71 | E35: 0 | F35: OC_AURICULARES | G35: 24 | H35: 57.024793 | J35: - | K35: - | M35: 0 | N35: 0 | O35: 0 | P35: 0 | Q35: 0 | R35: 0 | S35: 0 | T35: 0 | U35: 0 | V35: 0 | X35: 14 | Z35: 0 | AA35: 0 | AC35: 71 | AD35: 0 | AE35: 71 | AF35: 0 | AG35: 71 | AH35: 0 | AI35: 71 | AJ35: 0 | AK35: 71 | AL35: 0 | AN35: 0 | AP35: 0 | AQ35: 0 | AS35: 0 | AT35: 0 | AU35: 0 | AV35: 0 | AW35: 0 | AX35: 0 | AY35: 0 | AZ35: 0 | BA35: 0 | BB35: 0
B36: AD HOC | C36: AURICULARES AD HOC HC01 | D36: 49 | E36: 0 | F36: OC_AURICULARES | G36: 24 | H36: 35.53719 | J36: - | K36: - | M36: 0 | N36: 0 | O36: 0 | P36: 0 | Q36: 0 | R36: 0 | S36: 0 | T36: 0 | U36: 0 | V36: 0 | X36: 13 | Z36: 0 | AA36: 0 | AC36: 49 | AD36: 0 | AE36: 49 | AF36: 0 | AG36: 49 | AH36: 0 | AI36: 49 | AJ36: 0 | AK36: 49 | AL36: 0 | AN36: 0 | AP36: 0 | AQ36: 0 | AS36: 0 | AT36: 0 | AU36: 0 | AV36: 0 | AW36: 0 | AX36: 0 | AY36: 0 | AZ36: 0 | BA36: 0 | BB36: 0
B37: SAMSUNG | C37: AURICULARES SAMSUNG GALAXY BUDS 3 | D37: 172 | E37: 0 | F37: OC_AURICULARES | G37: 24 | H37: 158 | J37: - | K37: - | M37: 0 | N37: 3.7 | O37: 0 | P37: 2.3 | Q37: 0 | R37: 0 | S37: 0 | T37: 0 | U37: 0 | V37: 0 | X37: 14 | Z37: 0 | AA37: 0 | AC37: 83 | AD37: 89 | AE37: 117 | AF37: 55 | AG37: 172 | AH37: 0 | AI37: 172 | AJ37: 0 | AK37: 172 | AL37: 0 | AN37: 0 | AP37: 0 | AQ37: 0 | AS37: 0 | AT37: 0 | AU37: 0 | AV37: 0 | AW37: 0 | AX37: 0 | AY37: 0 | AZ37: 0 | BA37: 0 | BB37: 0
B38: SAMSUNG | C38: AURICULARES SAMSUNG GALAXY BUDS 3 PRO | D38: 240 | E38: 0 | F38: OC_AURICULARES | G38: 24 | H38: 227 | J38: - | K38: - | M38: 0 | N38: 5.8 | O38: 0 | P38: 4.4 | Q38: 0 | R38: 1 | S38: 0 | T38: 0 | U38: 0 | V38: 0 | X38: 13 | Z38: 0 | AA38: 0 | AC38: 101 | AD38: 139 | AE38: 134 | AF38: 106 | AG38: 216 | AH38: 24 | AI38: 240 | AJ38: 0 | AK38: 240 | AL38: 0 | AN38: 0 | AP38: 0 | AQ38: 0 | AS38: 0 | AT38: 0 | AU38: 0 | AV38: 0 | AW38: 0 | AX38: 0 | AY38: 0 | AZ38: 0 | BA38: 0 | BB38: 0
B39: SPC | C39: AURICULARES SPC BRAVE PRO | D39: 44 | E39: 0 | F39: OC_AURICULARES | G39: 24 | H39: 47.933884 | J39: - | K39: - | M39: 0 | N39: 0 | O39: 0 | P39: 0 | Q39: 0 | R39: 0 | S39: 0 | T39: 0 | U39: 0 | V39: 0 | X39: -4 | Z39: 0 | AA39: 0 | AC39: 44 | AD39: 0 | AE39: 44 | AF39: 0 | AG39: 44 | AH39: 0 | AI39: 44 | AJ39: 0 | AK39: 44 | AL39: 0 | AN39: 0 | AP39: 0 | AQ39: 0 | AS39: 0 | AT39: 0 | AU39: 0 | AV39: 0 | AW39: 0 | AX39: 0 | AY39: 0 | AZ39: 0 | BA39: 0 | BB39: 0
B40: SPC | C40: AURICULARES SPC DREAMER PRO | D40: 77 | E40: 0 | F40: OC_AURICULARES | G40: 24 | H40: 59.504132 | J40: - | K40: - | M40: 0 | N40: 0 | O40: 0 | P40: 0 | Q40: 0 | R40: 0 | S40: 0 | T40: 0 | U40: 0 | V40: 0 | X40: 17 | Z40: 0 | AA40: 0 | AC40: 77 | AD40: 0 | AE40: 77 | AF40: 0 | AG40: 77 | AH40: 0 | AI40: 77 | AJ40: 0 | AK40: 77 | AL40: 0 | AN40: 0 | AP40: 0 | AQ40: 0 | AS40: 0 | AT40: 0 | AU40: 0 | AV40: 0 | AW40: 0 | AX40: 0 | AY40: 0 | AZ40: 0 | BA40: 0 | BB40: 0
... B44: GOOGLE | C44: GOOGLE PIXEL 8A 256GB 5G | D44: 564 | E44: 3.25 | F44: SMARTPHONE | G44: 24 | H44: 549 | J44: - | K44: - | M44: 39 | N44: 13.9 | O44: 19 | P44: 13.1 | Q44: 0 | R44: 10.6 | S44: 0 | T44: 9 | U44: 0 | V44: 4.3 | X44: 15 | Z44: 0 | AA44: 0 | AC44: 191 | AD44: 334 | AE44: 231 | AF44: 314 | AG44: 310 | AH44: 254 | AI44: 348 | AJ44: 216 | AK44: 461 | AL44: 103 | AN44: 0 | AP44: 0 | AQ44: 0 | AS44: 0 | AT44: 0 | AU44: 0 | AV44: 0 | AW44: 0 | AX44: 0 | AY44: 0 | AZ44: 0 | BA44: 0 | BB44: 0
B45: GOOGLE | C45: GOOGLE PIXEL 9 128GB 5G | D45: 823 | E45: 3.25 | F45: SMARTPHONE | G45: 24 | H45: 795 | J45: - | K45: - | M45: - | N45: - | O45: 19 | P45: 21 | Q45: 0 | R45: 18.5 | S45: 0 | T45: 15.8 | U45: 0 | V45: 10.9 | X45: 28 | Z45: 0 | AA45: 0 | AC45: 0 | AD45: 0 | AE45: 300 | AF45: 504 | AG45: 379 | AH45: 444 | AI45: 444 | AJ45: 379 | AK45: 561 | AL45: 262 | AN45: 0 | AP45: 0 | AQ45: 0 | AS45: 0 | AT45: 0 | AU45: 0 | AV45: 0 | AW45: 0 | AX45: 0 | AY45: 0 | AZ45: 0 | BA45: 0 | BB45: 0
B46: GOOGLE | C46: GOOGLE PIXEL 9 PRO 256GB 5G | D46: 1062 | E46: 3.25 | F46: SMARTPHONE | G46: 24 | H46: 1060 | J46: - | K46: - | M46: - | N46: - | O46: 49 | P46: 26.9 | Q46: 39 | R46: 24 | S46: 0 | T46: 23 | U46: 0 | V46: 18.1 | X46: 2 | Z46: 0 | AA46: 0 | AC46: 0 | AD46: 0 | AE46: 367 | AF46: 646 | AG46: 447 | AH46: 576 | AI46: 510 | AJ46: 552 | AK46: 628 | AL46: 434 | AN46: 0 | AP46: 0 | AQ46: 0 | AS46: 0 | AT46: 0 | AU46: 0 | AV46: 0 | AW46: 0 | AX46: 0 | AY46: 0 | AZ46: 0 | BA46: 0 | BB46: 0
B47: GOOGLE | C47: GOOGLE PIXEL 9 PRO XL 512GB 5G | D47: 1234 | E47: 3.25 | F47: SMARTPHONE | G47: 24 | H47: 1233 | J47: - | K47: - | M47: - | N47: - | O47: 79 | P47: 31.9 | Q47: 39 | R47: 30.2 | S47: 0 | T47: 29.2 | U47: 0 | V47: 24.3 | X47: 1 | Z47: 0 | AA47: 0 | AC47: 0 | AD47: 0 | AE47: 389 | AF47: 766 | AG47: 470 | AH47: 725 | AI47: 533 | AJ47: 701 | AK47: 651 | AL47: 583 | AN47: 0 | AP47: 0 | AQ47: 0 | AS47: 0 | AT47: 0 | AU47: 0 | AV47: 0 | AW47: 0 | AX47: 0 | AY47: 0 | AZ47: 0 | BA47: 0 | BB47: 0
B48: HONOR | C48: HONOR 200 512GB 5G | D48: 539 | E48: 3.25 | F48: SMARTPHONE | G48: 24 | H48: 518 | J48: - | K48: - | M48: 0 | N48: 9.2 | O48: 0 | P48: 7.8 | Q48: 0 | R48: 4.4 | S48: 0 | T48: 2.8 | U48: 0 | V48: 0 | X48: 21 | Z48: 0 | AA48: 0 | AC48: 318 | AD48: 221 | AE48: 352 | AF48: 187 | AG48: 433 | AH48: 106 | AI48: 472 | AJ48: 67 | AK48: 539 | AL48: 0 | AN48: 0 | AP48: 0 | AQ48: 0 | AS48: 0 | AT48: 0 | AU48: 0 | AV48: 0 | AW48: 0 | AX48: 0 | AY48: 0 | AZ48: 0 | BA48: 0 | BB48: 0
B49: HONOR | C49: HONOR 200 LITE 256GB 5G | D49: 309 | E49: 3.25 | F49: SMARTPHONE | G49: 24 | H49: 291 | J49: - | K49: - | M49: 0 | N49: 5.8 | O49: 0 | P49: 4.4 | Q49: 0 | R49: 1.1 | S49: 0 | T49: 0 | U49: 0 | V49: 0 | X49: 18 | Z49: 0 | AA49: 0 | AC49: 170 | AD49: 139 | AE49: 203 | AF49: 106 | AG49: 283 | AH49: 26 | AI49: 309 | AJ49: 0 | AK49: 309 | AL49: 0 | AN49: 0 | AP49: 0 | AQ49: 0 | AS49: 0 | AT49: 0.6 | AU49: 0 | AV49: 0.6 | AW49: 0 | AX49: 1.1 | AY49: 0 | AZ49: 0 | BA49: 0 | BB49: 0
B50: HONOR | C50: HONOR 200 PRO 512GB 5G | D50: 661 | E50: 3.25 | F50: SMARTPHONE | G50: 24 | H50: 663 | J50: - | K50: - | M50: 39 | N50: 12.8 | O50: 19 | P50: 12 | Q50: 0 | R50: 9.4 | S50: 0 | T50: 7.8 | U50: 0 | V50: 3.1 | X50: -2 | Z50: 0 | AA50: 0 | AC50: 315 | AD50: 307 | AE50: 354 | AF50: 288 | AG50: 435 | AH50: 226 | AI50: 474 | AJ50: 187 | AK50: 587 | AL50: 74 | AN50: 0 | AP50: 0 | AQ50: 0 | AS50: 0 | AT50: -2.6 | AU50: 0 | AV50: -2.6 | AW50: 0 | AX50: -2.7 | AY50: 0 | AZ50: -2.6 | BA50: 0 | BB50: -2.7
B51: HONOR | C51: HONOR 200 SMART 256GB 5G | D51: 181 | E51: 3.25 | F51: SMARTPHONE | G51: 24 | H51: 134 | J51: - | K51: - | M51: 0 | N51: 3.3 | O51: 0 | P51: 1.9 | Q51: 0 | R51: 0 | S51: 0 | T51: 0 | U51: 0 | V51: 0 | X51: 47 | Z51: 0 | AA51: 0 | AC51: 102 | AD51: 79 | AE51: 135 | AF51: 46 | AG51: 181 | AH51: 0 | AI51: 181 | AJ51: 0 | AK51: 181 | AL51: 0 | AN51: 15 | AP51: 0 | AQ51: 0 | AS51: 0 | AT51: 0.5 | AU51: 0 | AV51: 0.5 | AW51: 0 | AX51: 0 | AY51: 0 | AZ51: 0 | BA51: 0 | BB51: 0
B52: HONOR | C52: HONOR MAGIC V3 512GB 5G | D52: 1653 | E52: 3.25 | F52: SMARTPHONE | G52: 24 | H52: 1552 | J52: - | K52: - | M52: - | N52: - | O52: 129 | P52: 41.1 | Q52: 99 | R52: 39.1 | S52: 49 | T52: 38.6 | U52: 29 | V52: 34.5 | X52: 101 | Z52: 0 | AA52: 0 | AC52: 0 | AD52: 0 | AE52: 538 | AF52: 986 | AG52: 616 | AH52: 938 | AI52: 678 | AJ52: 926 | AK52: 796 | AL52: 828 | AN52: 121 | AP52: 0 | AQ52: 0 | AS52: 0 | AT52: 0 | AU52: 0 | AV52: 4.3 | AW52: 0 | AX52: 4.3 | AY52: 0 | AZ52: 4.4 | BA52: 0 | BB52: 4.3
B53: HONOR | C53: HONOR MAGIC6 LITE 256GB 5G | D53: 358 | E53: 3.25 | F53: SMARTPHONE | G53: 24 | H53: 360 | J53: - | K53: - | M53: 0 | N53: 9 | O53: 0 | P53: 7.6 | Q53: 0 | R53: 4.2 | S53: 0 | T53: 2.6 | U53: 0 | V53: 0 | X53: -2 | Z53: 0 | AA53: 0 | AC53: 142 | AD53: 216 | AE53: 176 | AF53: 182 | AG53: 257 | AH53: 101 | AI53: 296 | AJ53: 62 | AK53: 358 | AL53: 0 | AN53: 0 | AP53: 0 | AQ53: 0 | AS53: 0 | AT53: 0 | AU53: 0 | AV53: 0 | AW53: 0 | AX53: 0 | AY53: 0 | AZ53: 0 | BA53: 0 | BB53: 0
B54: HONOR | C54: HONOR MAGIC6 PRO 5G | D54: 1074 | E54: 3.25 | F54: SMARTPHONE | G54: 24 | H54: 978 | J54: - | K54: - | M54: - | N54: - | O54: 39 | P54: 25 | Q54: 39 | R54: 21.7 | S54: 0 | T54: 20.7 | U54: 0 | V54: 15.8 | X54: 96 | Z54: 0 | AA54: 0 | AC54: 0 | AD54: 0 | AE54: 435 | AF54: 600 | AG54: 514 | AH54: 521 | AI54: 577 | AJ54: 497 | AK54: 695 | AL54: 379 | AN54: 0 | AP54: 0 | AQ54: 0 | AS54: 0 | AT54: 0 | AU54: 0 | AV54: 0 | AW54: 0 | AX54: 0 | AY54: 0 | AZ54: 0 | BA54: 0 | BB54: 0
B55: HONOR | C55: HONOR PAD X8a 11" 4+128GB WIFI | D55: 137 | E55: 3.75 | F55: TABLETS | G55: 24 | H55: 165 | J55: - | K55: - | M55: 0 | N55: 4 | O55: 0 | P55: 2.6 | Q55: 0 | R55: 0 | S55: 0 | T55: 0 | U55: 0 | V55: 0 | X55: -28 | Z55: 0 | AA55: 0 | AC55: 41 | AD55: 96 | AE55: 75 | AF55: 62 | AG55: 137 | AH55: 0 | AI55: 137 | AJ55: 0 | AK55: 137 | AL55: 0 | AN55: 0 | AP55: 0 | AQ55: 0 | AS55: #N/A | AT55: #N/A | AU55: #N/A | AV55: #N/A | AW55: #N/A | AX55: #N/A | AY55: #N/A | AZ55: #N/A | BA55: #N/A | BB55: #N/A
B56: HONOR | C56: HONOR PAD X9 WIFI | D56: 204 | E56: 3.75 | F56: TABLET | G56: 24 | H56: 210 | J56: - | K56: - | M56: 0 | N56: 5.2 | O56: 0 | P56: 3.8 | Q56: 0 | R56: 0 | S56: 0 | T56: 0 | U56: 0 | V56: 0 | X56: -6 | Z56: 0 | AA56: 0 | AC56: 79 | AD56: 125 | AE56: 113 | AF56: 91 | AG56: 204 | AH56: 0 | AI56: 204 | AJ56: 0 | AK56: 204 | AL56: 0 | AN56: 0 | AP56: 0 | AQ56: 0 | AS56: 0 | AT56: 0 | AU56: 0 | AV56: 0 | AW56: 0 | AX56: 0 | AY56: 0 | AZ56: 0 | BA56: 0 | BB56: 0
B57: HUAWEI | C57: HUAWEI PC MATEBOOK D 14" I5 12 GEN | D57: 751 | E57: 5.33 | F57: PC | G57: 24 | H57: 752 | J57: - | K57: - | M57: 39 | N57: 20.3 | O57: 19 | P57: 19.5 | Q57: 0 | R57: 17 | S57: 0 | T57: 15.4 | U57: 0 | V57: 10.7 | X57: -1 | Z57: 0 | AA57: 0 | AC57: 225 | AD57: 487 | AE57: 264 | AF57: 468 | AG57: 343 | AH57: 408 | AI57: 381 | AJ57: 370 | AK57: 494 | AL57: 257 | AN57: 0 | AP57: 0 | AQ57: 0 | AS57: 0 | AT57: 0 | AU57: 0 | AV57: 0 | AW57: 0 | AX57: 0 | AY57: 0 | AZ57: 0 | BA57: 0 | BB57: 0
B58: HUAWEI | C58: HUAWEI PC MATEBOOK D 16" I5 12 GEN | D58: 915 | E58: 5.33 | F58: PC | G58: 24 | H58: 824 | J58: - | K58: - | M58: - | N58: - | O58: 19 | P58: 22.1 | Q58: 0 | R58: 19.6 | S58: 0 | T58: 16.9 | U58: 0 | V58: 12 | X58: 91 | Z58: 0 | AA58: 0 | AC58: 0 | AD58: 0 | AE58: 366 | AF58: 530 | AG58: 445 | AH58: 470 | AI58: 509 | AJ58: 406 | AK58: 627 | AL58: 288 | AN58: 0 | AP58: 0 | AQ58: 0 | AS58: 0 | AT58: 0 | AU58: 0 | AV58: 0 | AW58: 0 | AX58: 0 | AY58: 0 | AZ58: 0 | BA58: 0 | BB58: 0
B59: APPLE | C59: IPAD 10a GEN 64GB 2024 WIFI | D59: 367 | E59: 3.75 | F59: TABLETS | G59: 24 | H59: 443 | J59: - | K59: - | M59: 0 | N59: 12 | O59: 0 | P59: 10.6 | Q59: 0 | R59: 7.2 | S59: 0 | T59: 5.6 | U59: 0 | V59: 0 | X59: -76 | Z59: 0 | AA59: 0 | AC59: 79 | AD59: 288 | AE59: 113 | AF59: 254 | AG59: 194 | AH59: 173 | AI59: 233 | AJ59: 134 | AK59: 367 | AL59: 0 | AN59: 0 | AP59: 0 | AQ59: 0 | AS59: #N/A | AT59: #N/A | AU59: #N/A | AV59: #N/A | AW59: #N/A | AX59: #N/A | AY59: #N/A | AZ59: #N/A | BA59: #N/A | BB59: #N/A
B60: APPLE | C60: IPAD AIR M2 WIFI 11" 128GB | D60: 623 | E60: 3.75 | F60: TABLET | G60: 24 | H60: 753 | J60: - | K60: - | M60: 39 | N60: 20.3 | O60: 19 | P60: 19.5 | Q60: 0 | R60: 17 | S60: 0 | T60: 15.4 | U60: 0 | V60: 10.7 | X60: -130 | Z60: 0 | AA60: 0 | AC60: 97 | AD60: 487 | AE60: 136 | AF60: 468 | AG60: 215 | AH60: 408 | AI60: 253 | AJ60: 370 | AK60: 366 | AL60: 257 | AN60: 0 | AP60: 0 | AQ60: 0 | AS60: 0 | AT60: 0 | AU60: 0 | AV60: 0 | AW60: 0 | AX60: 0 | AY60: 0 | AZ60: 0 | BA60: 0 | BB60: 0
B61: APPLE | C61: IPAD AIR M2 WIFI 13" 128GB | D61: 847 | E61: 3.75 | F61: TABLET | G61: 24 | H61: 1024 | J61: - | K61: - | M61: - | N61: - | O61: 49 | P61: 26.2 | Q61: 39 | R61: 23.3 | S61: 0 | T61: 22.3 | U61: 0 | V61: 17.4 | X61: -177 | Z61: 0 | AA61: 0 | AC61: 0 | AD61: 0 | AE61: 169 | AF61: 629 | AG61: 249 | AH61: 559 | AI61: 312 | AJ61: 535 | AK61: 429 | AL61: 418 | AN61: 0 | AP61: 0 | AQ61: 0 | AS61: 0 | AT61: 0 | AU61: 0 | AV61: 0 | AW61: 0 | AX61: 0 | AY61: 0 | AZ61: 0 | BA61: 0 | BB61: 0
B62: APPLE | C62: IPAD PRO M4 WIFI 11" 256GB | D62: 1044 | E62: 3.75 | F62: TABLET | G62: 24 | H62: 1263 | J62: - | K62: - | M62: - | N62: - | O62: 79 | P62: 32.9 | Q62: 39 | R62: 31.3 | S62: 0 | T62: 30.3 | U62: 0 | V62: 25.4 | X62: -219 | Z62: 0 | AA62: 0 | AC62: 0 | AD62: 0 | AE62: 175 | AF62: 790 | AG62: 254 | AH62: 751 | AI62: 317 | AJ62: 727 | AK62: 434 | AL62: 610 | AN62: 0 | AP62: 0 | AQ62: 0 | AS62: 0 | AT62: 0 | AU62: 0 | AV62: 0 | AW62: 0 | AX62: 0 | AY62: 0 | AZ62: 0 | BA62: 0 | BB62: 0
B63: APPLE | C63: IPHONE 14 128GB CON 5G | D63: 920 | E63: 3.25 | F63: SMARTPHONE | G63: 24 | H63: 741 | J63: - | K63: - | M63: - | N63: - | O63: 19 | P63: 21.2 | Q63: 0 | R63: 18.7 | S63: 0 | T63: 16 | U63: 0 | V63: 11.1 | X63: 179 | Z63: 0 | AA63: 0 | AC63: 0 | AD63: 0 | AE63: 392 | AF63: 509 | AG63: 471 | AH63: 449 | AI63: 536 | AJ63: 384 | AK63: 654 | AL63: 266 | AN63: 0 | AP63: 0 | AQ63: 0 | AS63: 0 | AT63: 0 | AU63: 0 | AV63: 0 | AW63: 0 | AX63: 0 | AY63: 0 | AZ63: 0 | BA63: 0 | BB63: 0
B64: APPLE | C64: IPHONE 15 128GB CON 5G | D64: 883 | E64: 3.25 | F64: SMARTPHONE | G64: 24 | H64: 864 | J64: - | K64: - | M64: - | N64: - | O64: 29 | P64: 23.1 | Q64: 0 | R64: 21.1 | S64: 0 | T64: 18.4 | U64: 0 | V64: 13.4 | X64: 19 | Z64: 0 | AA64: 0 | AC64: 0 | AD64: 0 | AE64: 300 | AF64: 554 | AG64: 377 | AH64: 506 | AI64: 441 | AJ64: 442 | AK64: 561 | AL64: 322 | AN64: 0 | AP64: 0 | AQ64: 0 | AS64: 0 | AT64: 0 | AU64: 0 | AV64: -1.7 | AW64: 0 | AX64: -1.6 | AY64: 0 | AZ64: -1.6 | BA64: 0 | BB64: -1.7
B65: APPLE | C65: IPHONE 16 128GB CON 5G | D65: 883 | E65: 3.25 | F65: SMARTPHONE | G65: 24 | H65: 967 | J65: - | K65: - | M65: - | N65: - | O65: 49 | P65: 25.6 | Q65: 39 | R65: 22.7 | S65: 0 | T65: 21.7 | U65: 0 | V65: 16.8 | X65: -84 | Z65: 0 | AA65: 0 | AC65: 0 | AD65: 0 | AE65: 220 | AF65: 614 | AG65: 299 | AH65: 545 | AI65: 362 | AJ65: 521 | AK65: 480 | AL65: 403 | AN65: 0 | AP65: 0 | AQ65: 0 | AS65: 0 | AT65: 0 | AU65: 0 | AV65: -1.6 | AW65: 0 | AX65: -1.6 | AY65: 0 | AZ65: -1.6 | BA65: 0 | BB65: -1.6
B66: APPLE | C66: IPHONE 16 256GB CON 5G | D66: 983 | E66: 3.25 | F66: SMARTPHONE | G66: 24 | H66: 1101 | J66: - | K66: - | M66: - | N66: - | O66: 49 | P66: 29.9 | Q66: 39 | R66: 27 | S66: 0 | T66: 26 | U66: 0 | V66: 21.1 | X66: -118 | Z66: 0 | AA66: 0 | AC66: 0 | AD66: 0 | AE66: 216 | AF66: 718 | AG66: 296 | AH66: 648 | AI66: 359 | AJ66: 624 | AK66: 477 | AL66: 506 | AN66: 0 | AP66: 0 | AQ66: 0 | AS66: 0 | AT66: 0 | AU66: 0 | AV66: -1.7 | AW66: 0 | AX66: -1.7 | AY66: 0 | AZ66: -1.7 | BA66: 0 | BB66: -1.7
B67: APPLE | C67: IPHONE 16 PLUS 128GB CON 5G | D67: 998 | E67: 3.25 | F67: SMARTPHONE | G67: 24 | H67: 1121 | J67: - | K67: - | M67: - | N67: - | O67: 49 | P67: 30.6 | Q67: 39 | R67: 27.7 | S67: 0 | T67: 26.7 | U67: 0 | V67: 21.8 | X67: -123 | Z67: 0 | AA67: 0 | AC67: 0 | AD67: 0 | AE67: 215 | AF67: 734 | AG67: 294 | AH67: 665 | AI67: 357 | AJ67: 641 | AK67: 475 | AL67: 523 | AN67: 0 | AP67: 0 | AQ67: 0 | AS67: 0 | AT67: 0 | AU67: 0 | AV67: -1.6 | AW67: 0 | AX67: -1.6 | AY67: 0 | AZ67: -1.6 | BA67: 0 | BB67: -1.6
B68: APPLE | C68: IPHONE 16 PLUS 256GB CON 5G | D68: 1097 | E68: 3.25 | F68: SMARTPHONE | G68: 24 | H68: 1254 | J68: - | K68: - | M68: - | N68: - | O68: 79 | P68: 33.6 | Q68: 39 | R68: 32 | S68: 0 | T68: 31 | U68: 0 | V68: 26.1 | X68: -157 | Z68: 0 | AA68: 0 | AC68: 0 | AD68: 0 | AE68: 212 | AF68: 806 | AG68: 290 | AH68: 768 | AI68: 353 | AJ68: 744 | AK68: 471 | AL68: 626 | AN68: 0 | AP68: 0 | AQ68: 0 | AS68: 0 | AT68: 0 | AU68: 0 | AV68: -1.6 | AW68: 0 | AX68: -1.6 | AY68: 0 | AZ68: -1.6 | BA68: 0 | BB68: -1.6
B69: APPLE | C69: IPHONE 16 PRO 128GB CON 5G | D69: 1074 | E69: 3.25 | F69: SMARTPHONE | G69: 24 | H69: 1223 | J69: - | K69: - | M69: - | N69: - | O69: 79 | P69: 32.5 | Q69: 39 | R69: 30.9 | S69: 0 | T69: 29.9 | U69: 0 | V69: 25 | X69: -149 | Z69: 0 | AA69: 0 | AC69: 0 | AD69: 0 | AE69: 215 | AF69: 780 | AG69: 293 | AH69: 742 | AI69: 356 | AJ69: 718 | AK69: 474 | AL69: 600 | AN69: 0 | AP69: 0 | AQ69: 0 | AS69: 0 | AT69: 0 | AU69: 0 | AV69: -1.7 | AW69: 0 | AX69: -1.7 | AY69: 0 | AZ69: -1.7 | BA69: 0 | BB69: -1.7
B70: APPLE | C70: IPHONE 16 PRO 256GB CON 5G | D70: 1174 | E70: 3.25 | F70: SMARTPHONE | G70: 24 | H70: 1357 | J70: - | K70: - | M70: - | N70: - | O70: 129 | P70: 34.7 | Q70: 99 | R70: 32.6 | S70: 49 | T70: 32.1 | U70: 29 | V70: 28.1 | X70: -183 | Z70: 0 | AA70: 0 | AC70: 0 | AD70: 0 | AE70: 212 | AF70: 833 | AG70: 293 | AH70: 782 | AI70: 355 | AJ70: 770 | AK70: 471 | AL70: 674 | AN70: 0 | AP70: 0 | AQ70: 0 | AS70: 0 | AT70: 0 | AU70: 0 | AV70: -1.7 | AW70: 0 | AX70: -1.8 | AY70: 0 | AZ70: -1.7 | BA70: 0 | BB70: -1.7
B71: APPLE | C71: IPHONE 16 PRO MAX 256 CON 5G | D71: 1265 | E71: 3.25 | F71: SMARTPHONE | G71: 24 | H71: 1480 | J71: - | K71: - | M71: - | N71: - | O71: 129 | P71: 38.6 | Q71: 99 | R71: 36.6 | S71: 49 | T71: 36.1 | U71: 29 | V71: 32 | X71: -215 | Z71: 0 | AA71: 0 | AC71: 0 | AD71: 0 | AE71: 210 | AF71: 926 | AG71: 288 | AH71: 878 | AI71: 350 | AJ71: 866 | AK71: 468 | AL71: 768 | AN71: 0 | AP71: 0 | AQ71: 0 | AS71: 0 | AT71: 0 | AU71: 0 | AV71: -1.8 | AW71: 0 | AX71: -1.7 | AY71: 0 | AZ71: -1.7 | BA71: 0 | BB71: -1.8
B72: APPLE | C72: IPHONE 16 PRO MAX 512 CON 5G | D72: 1456 | E72: 3.25 | F72: SMARTPHONE | G72: 24 | H72: 1736 | J72: - | K72: - | M72: - | N72: - | O72: 139 | P72: 46.5 | Q72: 129 | R72: 43.6 | S72: 109 | T72: 41.8 | U72: 89 | V72: 37.7 | X72: -280 | Z72: 0 | AA72: 0 | AC72: 0 | AD72: 0 | AE72: 201 | AF72: 1116 | AG72: 281 | AH72: 1046 | AI72: 344 | AJ72: 1003 | AK72: 462 | AL72: 905 | AN72: 0 | AP72: 0 | AQ72: 0 | AS72: 0 | AT72: 0 | AU72: 0 | AV72: -1.7 | AW72: 0 | AX72: -1.7 | AY72: 0 | AZ72: -1.7 | BA72: 0 | BB72: -1.7
B73: LENOVO | C73: LENOVO IDEAPAD 1 15ADA7 4120 8+256GB | D73: 462 | E73: 5.33 | F73: PC | G73: 24 | H73: 522 | J73: - | K73: - | M73: 39 | N73: 12.9 | O73: 19 | P73: 12.1 | Q73: 0 | R73: 9.6 | S73: 0 | T73: 8 | U73: 0 | V73: 3.3 | X73: -60 | Z73: 0 | AA73: 0 | AC73: 113 | AD73: 310 | AE73: 153 | AF73: 290 | AG73: 232 | AH73: 230 | AI73: 270 | AJ73: 192 | AK73: 383 | AL73: 79 | AN73: 61 | AP73: 0 | AQ73: 0 | AS73: 0 | AT73: 1.7 | AU73: 0 | AV73: 1.7 | AW73: 0 | AX73: 1.8 | AY73: 0 | AZ73: 1.8 | BA73: 0 | BB73: 1.8
B74: LENOVO | C74: LENOVO IDEAPAD 3 15IAH8 CI5 8+512GB | D74: 620 | E74: 5.33 | F74: PC | G74: 24 | H74: 689 | J74: - | K74: - | M74: 39 | N74: 18.1 | O74: 19 | P74: 17.2 | Q74: 0 | R74: 14.7 | S74: 0 | T74: 12 | U74: 0 | V74: 7.1 | X74: -69 | Z74: 0 | AA74: 0 | AC74: 147 | AD74: 434 | AE74: 188 | AF74: 413 | AG74: 267 | AH74: 353 | AI74: 332 | AJ74: 288 | AK74: 450 | AL74: 170 | AN74: -61 | AP74: 0 | AQ74: 0 | AS74: 0 | AT74: -2.1 | AU74: 0 | AV74: -2.2 | AW74: 0 | AX74: -2.2 | AY74: 0 | AZ74: -2.2 | BA74: 0 | BB74: -2.2
B75: LENOVO | C75: LENOVO IDEAPAD 3 15ITL6 CI5 | D75: 638 | E75: 5.33 | F75: PC | G75: 24 | H75: 750 | J75: - | K75: - | M75: 39 | N75: 20.2 | O75: 19 | P75: 19.4 | Q75: 0 | R75: 16.9 | S75: 0 | T75: 12 | U75: 0 | V75: 9.3 | X75: -112 | Z75: 0 | AA75: 0 | AC75: 114 | AD75: 485 | AE75: 153 | AF75: 466 | AG75: 232 | AH75: 406 | AI75: 350 | AJ75: 288 | AK75: 415 | AL75: 223 | AN75: 0 | AP75: 0 | AQ75: 0 | AS75: 0 | AT75: 0 | AU75: 0 | AV75: 0 | AW75: 0 | AX75: 0 | AY75: 0 | AZ75: 0 | BA75: 0 | BB75: 0
B76: LENOVO | C76: LENOVO IDEAPAD 5 16IRL8 I7 13GEN 16GB+1TB | D76: 915 | E76: 5.33 | F76: PC | G76: 24 | H76: 1029 | J76: - | K76: - | M76: - | N76: - | O76: 49 | P76: 26.4 | Q76: 39 | R76: 23.5 | S76: 0 | T76: 22.5 | U76: 0 | V76: 17.6 | X76: -114 | Z76: 0 | AA76: 0 | AC76: 0 | AD76: 0 | AE76: 232 | AF76: 634 | AG76: 312 | AH76: 564 | AI76: 375 | AJ76: 540 | AK76: 493 | AL76: 422 | AN76: 0 | AP76: 0 | AQ76: 0 | AS76: 0 | AT76: 0 | AU76: 0 | AV76: 0 | AW76: 0 | AX76: 0 | AY76: 0 | AZ76: 0 | BA76: 0 | BB76: 0
B77: LENOVO | C77: LENOVO LOQ 3 15IRH8 i5 RTX 2050 | D77: 948 | E77: 5.33 | F77: PC | G77: 24 | H77: 1149 | J77: - | K77: - | M77: - | N77: - | O77: 49 | P77: 30.1 | Q77: 39 | R77: 27.2 | S77: 0 | T77: 26.2 | U77: 0 | V77: 21.3 | X77: -201 | Z77: 0 | AA77: 0 | AC77: 0 | AD77: 0 | AE77: 177 | AF77: 722 | AG77: 256 | AH77: 653 | AI77: 319 | AJ77: 629 | AK77: 437 | AL77: 511 | AN77: 36 | AP77: 0 | AQ77: 0 | AS77: 0 | AT77: 0 | AU77: 0 | AV77: 1.3 | AW77: 0 | AX77: 1.3 | AY77: 0 | AZ77: 1.3 | BA77: 0 | BB77: 1.3
B78: LG | C78: LG SMART TV 32" LQ | D78: 215 | E78: 0 | F78: SMART TV | G78: 24 | H78: 259 | J78: - | K78: - | M78: 0 | N78: 5.5 | O78: 0 | P78: 4.1 | Q78: 0 | R78: 0 | S78: 0 | T78: 0 | U78: 0 | V78: 0 | X78: -44 | Z78: 0 | AA78: 0 | AC78: 83 | AD78: 132 | AE78: 117 | AF78: 98 | AG78: 215 | AH78: 0 | AI78: 215 | AJ78: 0 | AK78: 215 | AL78: 0 | AN78: 0 | AP78: 0 | AQ78: 0 | AS78: 0 | AT78: 0 | AU78: 0 | AV78: 0 | AW78: 0 | AX78: 0 | AY78: 0 | AZ78: 0 | BA78: 0 | BB78: 0
B79: LG | C79: LG SMART TV 43" UR78 4K | D79: 396 | E79: 0 | F79: SMART TV | G79: 24 | H79: 479 | J79: - | K79: - | M79: 0 | N79: 10 | O79: 0 | P79: 8.7 | Q79: 0 | R79: 5.3 | S79: 0 | T79: 3.7 | U79: 0 | V79: 0 | X79: -83 | Z79: 0 | AA79: 0 | AC79: 156 | AD79: 240 | AE79: 187 | AF79: 209 | AG79: 269 | AH79: 127 | AI79: 307 | AJ79: 89 | AK79: 396 | AL79: 0 | AN79: 0 | AP79: 0 | AQ79: 0 | AS79: 0 | AT79: 0 | AU79: 0 | AV79: 0 | AW79: 0 | AX79: 0 | AY79: 0 | AZ79: 0 | BA79: 0 | BB79: 0
B80: LG | C80: LG SMART TV 50" UR78 4K | D80: 479 | E80: 0 | F80: SMART TV | G80: 24 | H80: 579 | J80: - | K80: - | M80: 0 | N80: 13.2 | O80: 0 | P80: 11.8 | Q80: 0 | R80: 8.5 | S80: 0 | T80: 6.9 | U80: 0 | V80: 2.2 | X80: -100 | Z80: 0 | AA80: 0 | AC80: 162 | AD80: 317 | AE80: 196 | AF80: 283 | AG80: 275 | AH80: 204 | AI80: 313 | AJ80: 166 | AK80: 426 | AL80: 53 | AN80: 0 | AP80: 0 | AQ80: 0 | AS80: 0 | AT80: 0.9 | AU80: 0 | AV80: 0.8 | AW80: 0 | AX80: 0.9 | AY80: 0 | AZ80: 0.9 | BA80: 0 | BB80: 0.9
B81: LG | C81: LG SMART TV 55" OLED C46 4K | D81: 1735 | E81: 0 | F81: SMART TV | G81: 24 | H81: 2099 | J81: - | K81: - | M81: - | N81: - | O81: 139 | P81: 31.6 | Q81: 89 | R81: 30.5 | S81: 79 | T81: 29.3 | U81: 69 | V81: 25 | X81: -364 | Z81: 0 | AA81: 0 | AC81: 0 | AD81: 0 | AE81: 838 | AF81: 758 | AG81: 914 | AH81: 732 | AI81: 953 | AJ81: 703 | AK81: 1066 | AL81: 600 | AN81: 0 | AP81: 0 | AQ81: 0 | AS81: 0 | AT81: 0 | AU81: 0 | AV81: 0 | AW81: 0 | AX81: 0 | AY81: 0 | AZ81: 0 | BA81: 0 | BB81: 0
B82: LG | C82: LG SMART TV 55" UR78 4K | D82: 537 | E82: 0 | F82: SMART TV | G82: 24 | H82: 649 | J82: - | K82: - | M82: 0 | N82: 15.2 | O82: 0 | P82: 13.8 | Q82: 0 | R82: 10.4 | S82: 0 | T82: 8.8 | U82: 0 | V82: 4.1 | X82: -112 | Z82: 0 | AA82: 0 | AC82: 172 | AD82: 365 | AE82: 206 | AF82: 331 | AG82: 287 | AH82: 250 | AI82: 326 | AJ82: 211 | AK82: 439 | AL82: 98 | AN82: 0 | AP82: 0 | AQ82: 0 | AS82: 0 | AT82: 0.9 | AU82: 0 | AV82: 0.9 | AW82: 0 | AX82: 0.8 | AY82: 0 | AZ82: 0.9 | BA82: 0 | BB82: 0.8
B83: LG | C83: LG SMART TV 65" OLED C46 4K | D83: 2396 | E83: 0 | F83: SMART TV | G83: 24 | H83: 2899 | J83: - | K83: - | M83: - | N83: - | O83: 139 | P83: 45.8 | Q83: 89 | R83: 44.6 | S83: 79 | T83: 43.4 | U83: 69 | V83: 39.2 | X83: -503 | Z83: 0 | AA83: 0 | AC83: 0 | AD83: 0 | AE83: 1158 | AF83: 1099 | AG83: 1237 | AH83: 1070 | AI83: 1275 | AJ83: 1042 | AK83: 1386 | AL83: 941 | AN83: 0 | AP83: 0 | AQ83: 0 | AS83: 0 | AT83: 0 | AU83: 0 | AV83: 0 | AW83: 0 | AX83: 0 | AY83: 0 | AZ83: 0 | BA83: 0 | BB83: 0
B84: LG | C84: LG SMART TV 65" UR78 4K | D84: 686 | E84: 0 | F84: SMART TV | G84: 24 | H84: 829 | J84: - | K84: - | M84: - | N84: - | O84: 39 | P84: 15.3 | Q84: 0 | R84: 13.7 | S84: 0 | T84: 12.1 | U84: 0 | V84: 7.4 | X84: -143 | Z84: 0 | AA84: 0 | AC84: 0 | AD84: 0 | AE84: 280 | AF84: 367 | AG84: 357 | AH84: 329 | AI84: 396 | AJ84: 290 | AK84: 508 | AL84: 178 | AN84: 0 | AP84: 0 | AQ84: 0 | AS84: 0 | AT84: 0 | AU84: 0 | AV84: 0.6 | AW84: 0 | AX84: 0.7 | AY84: 0 | AZ84: 0.7 | BA84: 0 | BB84: 0.7
B85: LG | C85: LG SMART TV 75" UT80 4K | D85: 1157 | E85: 0 | F85: SMART TV | G85: 24 | H85: 1399 | J85: - | K85: - | M85: - | N85: - | O85: 139 | P85: 22.9 | Q85: 89 | R85: 21.7 | S85: 79 | T85: 20.6 | U85: 0 | V85: 19.3 | X85: -242 | Z85: 0 | AA85: 0 | AC85: 0 | AD85: 0 | AE85: 468 | AF85: 550 | AG85: 547 | AH85: 521 | AI85: 584 | AJ85: 494 | AK85: 694 | AL85: 463 | AN85: 0 | AP85: 0 | AQ85: 0 | AS85: 0 | AT85: 0 | AU85: 0 | AV85: 0 | AW85: 0 | AX85: 0 | AY85: 0 | AZ85: 0 | BA85: 0 | BB85: 0
B86: LG | C86: LG ULTRA 16" U70R R5 16+512GB | D86: 867 | E86: 5.33 | F86: PC | G86: 24 | H86: 842 | J86: - | K86: - | M86: - | N86: - | O86: 29 | P86: 22.3 | Q86: 0 | R86: 20.2 | S86: 0 | T86: 17.5 | U86: 0 | V86: 12.6 | X86: 25 | Z86: 0 | AA86: 0 | AC86: 0 | AD86: 0 | AE86: 303 | AF86: 535 | AG86: 382 | AH86: 485 | AI86: 447 | AJ86: 420 | AK86: 565 | AL86: 302 | AN86: 0 | AP86: 0 | AQ86: 0 | AS86: 0 | AT86: 0 | AU86: 0 | AV86: 0 | AW86: 0 | AX86: 0 | AY86: 0 | AZ86: 0 | BA86: 0 | BB86: 0
B87: LENOVO | C87: MONITOR LENOVO 27" L27i-40 ALTAVOCES INTEGRADOS | D87: 140 | E87: 0 | F87: OC_PERIFERICOS INFORMATICA | G87: 24 | H87: 157 | J87: - | K87: - | M87: 0 | N87: 3.7 | O87: 0 | P87: 2.3 | Q87: 0 | R87: 0 | S87: 0 | T87: 0 | U87: 0 | V87: 0 | X87: -17 | Z87: 0 | AA87: 0 | AC87: 51 | AD87: 89 | AE87: 85 | AF87: 55 | AG87: 140 | AH87: 0 | AI87: 140 | AJ87: 0 | AK87: 140 | AL87: 0 | AN87: 0 | AP87: 0 | AQ87: 0 | AS87: 0 | AT87: 0 | AU87: 0 | AV87: 0 | AW87: 0 | AX87: 0 | AY87: 0 | AZ87: 0 | BA87: 0 | BB87: 0
B88: MOTOROLA | C88: MOTOROLA EDGE 50 NEO 512GB 5G | D88: 481 | E88: 3.25 | F88: SMARTPHONE | G88: 24 | H88: 509 | J88: - | K88: - | M88: 0 | N88: 11.7 | O88: 0 | P88: 10.3 | Q88: 0 | R88: 7 | S88: 0 | T88: 5.3 | U88: 0 | V88: 0 | X88: -28 | Z88: 0 | AA88: 0 | AC88: 200 | AD88: 281 | AE88: 234 | AF88: 247 | AG88: 313 | AH88: 168 | AI88: 354 | AJ88: 127 | AK88: 481 | AL88: 0 | AN88: 0 | AP88: 0 | AQ88: 0 | AS88: 0 | AT88: 0 | AU88: 0 | AV88: 0 | AW88: 0 | AX88: 0 | AY88: 0 | AZ88: 0 | BA88: 0 | BB88: 0
B89: MOTOROLA | C89: MOTOROLA EDGE 50 PRO 5G | D89: 658 | E89: 3.25 | F89: SMARTPHONE | G89: 24 | H89: 520 | J89: - | K89: - | M89: 39 | N89: 12.9 | O89: 19 | P89: 12 | Q89: 0 | R89: 9.5 | S89: 0 | T89: 7.9 | U89: 0 | V89: 3.2 | X89: 138 | Z89: 0 | AA89: 0 | AC89: 309 | AD89: 310 | AE89: 351 | AF89: 288 | AG89: 430 | AH89: 228 | AI89: 468 | AJ89: 190 | AK89: 581 | AL89: 77 | AN89: -24 | AP89: 0 | AQ89: 0 | AS89: 0 | AT89: -0.8 | AU89: 0 | AV89: -0.9 | AW89: 0 | AX89: -0.9 | AY89: 0 | AZ89: -0.9 | BA89: 0 | BB89: -0.9
B90: MOTOROLA | C90: MOTOROLA MOTO G34 5G | D90: 177 | E90: 3.25 | F90: SMARTPHONE | G90: 24 | H90: 119 | J90: - | K90: - | M90: 0 | N90: 2.8 | O90: 0 | P90: 1.4 | Q90: 0 | R90: 0 | S90: 0 | T90: 0 | U90: 0 | V90: 0 | X90: 58 | Z90: 0 | AA90: 0 | AC90: 110 | AD90: 67 | AE90: 143 | AF90: 34 | AG90: 177 | AH90: 0 | AI90: 177 | AJ90: 0 | AK90: 177 | AL90: 0 | AN90: 0 | AP90: 0 | AQ90: 0 | AS90: 0 | AT90: 0.5 | AU90: 0 | AV90: 1.4 | AW90: 0 | AX90: 0 | AY90: 0 | AZ90: 0 | BA90: 0 | BB90: 0
B91: MOTOROLA | C91: MOTOROLA MOTO G35 128GB 5G | D91: 183 | E91: 3.25 | F91: SMARTPHONE | G91: 24 | H91: 138 | J91: - | K91: - | M91: 0 | N91: 3.5 | O91: 0 | P91: 2.1 | Q91: 0 | R91: 0 | S91: 0 | T91: 0 | U91: 0 | V91: 0 | X91: 45 | Z91: 0 | AA91: 0 | AC91: 99 | AD91: 84 | AE91: 133 | AF91: 50 | AG91: 183 | AH91: 0 | AI91: 183 | AJ91: 0 | AK91: 183 | AL91: 0 | AN91: 0 | AP91: 0 | AQ91: 0 | AS91: #N/A | AT91: #N/A | AU91: #N/A | AV91: #N/A | AW91: #N/A | AX91: #N/A | AY91: #N/A | AZ91: #N/A | BA91: #N/A | BB91: #N/A
B92: MOTOROLA | C92: MOTOROLA MOTO G54 256GB 5G | D92: 199 | E92: 3.25 | F92: SMARTPHONE | G92: 24 | H92: 193 | J92: - | K92: - | M92: 0 | N92: 4.5 | O92: 0 | P92: 3.2 | Q92: 0 | R92: 0 | S92: 0 | T92: 0 | U92: 0 | V92: 0 | X92: 6 | Z92: 0 | AA92: 0 | AC92: 91 | AD92: 108 | AE92: 122 | AF92: 77 | AG92: 199 | AH92: 0 | AI92: 199 | AJ92: 0 | AK92: 199 | AL92: 0 | AN92: 0 | AP92: 0 | AQ92: 0 | AS92: 0 | AT92: 0.6 | AU92: 0 | AV92: 0.7 | AW92: 0 | AX92: 0 | AY92: 0 | AZ92: 0 | BA92: 0 | BB92: 0
B93: MOTOROLA | C93: MOTOROLA MOTO G55 256GB 5G | D93: 255 | E93: 3.25 | F93: SMARTPHONE | G93: 24 | H93: 215 | J93: - | K93: - | M93: 0 | N93: 5.3 | O93: 0 | P93: 3.9 | Q93: 0 | R93: 0 | S93: 0 | T93: 0 | U93: 0 | V93: 0 | X93: 40 | Z93: 0 | AA93: 0 | AC93: 128 | AD93: 127 | AE93: 161 | AF93: 94 | AG93: 255 | AH93: 0 | AI93: 255 | AJ93: 0 | AK93: 255 | AL93: 0 | AN93: -34 | AP93: 0 | AQ93: 0 | AS93: 0 | AT93: -0.9 | AU93: 0 | AV93: -0.9 | AW93: 0 | AX93: -1.5 | AY93: 0 | AZ93: 0 | BA93: 0 | BB93: 0
B94: MOTOROLA | C94: MOTOROLA MOTO G85 256GB 5G | D94: 353 | E94: 3.25 | F94: SMARTPHONE | G94: 24 | H94: 378 | J94: - | K94: - | M94: 0 | N94: 9.6 | O94: 0 | P94: 8.2 | Q94: 0 | R94: 4.9 | S94: 0 | T94: 3.3 | U94: 0 | V94: 0 | X94: -25 | Z94: 0 | AA94: 0 | AC94: 123 | AD94: 230 | AE94: 156 | AF94: 197 | AG94: 235 | AH94: 118 | AI94: 274 | AJ94: 79 | AK94: 353 | AL94: 0 | AN94: 0 | AP94: 0 | AQ94: 0 | AS94: 0 | AT94: 0 | AU94: 0 | AV94: 0 | AW94: 0 | AX94: 0 | AY94: 0 | AZ94: 0 | BA94: 0 | BB94: 0
B95: MOTOROLA | C95: MOTOROLA MOTO THINKPHONE 25 256GB 5G | D95: 481 | E95: 3.25 | F95: SMARTPHONE | G95: 24 | H95: 499 | J95: - | K95: - | M95: 0 | N95: 12.1 | O95: 0 | P95: 10.7 | Q95: 0 | R95: 7.4 | S95: 0 | T95: 5.8 | U95: 0 | V95: 1.1 | X95: -18 | Z95: 0 | AA95: 0 | AC95: 191 | AD95: 290 | AE95: 224 | AF95: 257 | AG95: 303 | AH95: 178 | AI95: 342 | AJ95: 139 | AK95: 455 | AL95: 26 | AN95: 0 | AP95: 0 | AQ95: 0 | AS95: 0 | AT95: -0.9 | AU95: 0 | AV95: -0.9 | AW95: 0 | AX95: -0.9 | AY95: 0 | AZ95: -0.9 | BA95: 0 | BB95: -0.9
B96: MOTOROLA | C96: MOTOROLA RAZR 50 256GB 5G | D96: 869 | E96: 3.25 | F96: SMARTPHONE | G96: 24 | H96: 793 | J96: - | K96: - | M96: - | N96: - | O96: 29 | P96: 20.6 | Q96: 0 | R96: 18.5 | S96: 0 | T96: 15.8 | U96: 0 | V96: 10.9 | X96: 76 | Z96: 0 | AA96: 0 | AC96: 0 | AD96: 0 | AE96: 346 | AF96: 494 | AG96: 425 | AH96: 444 | AI96: 490 | AJ96: 379 | AK96: 607 | AL96: 262 | AN96: -61 | AP96: 0 | AQ96: 0 | AS96: 0 | AT96: 0 | AU96: 0 | AV96: -2.1 | AW96: 0 | AX96: -2.1 | AY96: 0 | AZ96: -2.1 | BA96: 0 | BB96: -2.1
B97: OPPO | C97: OPPO A40 128GB | D97: 160 | E97: 3.25 | F97: SMARTPHONE | G97: 24 | H97: 107 | J97: - | K97: - | M97: 0 | N97: 2.3 | O97: 0 | P97: 1 | Q97: 0 | R97: 0 | S97: 0 | T97: 0 | U97: 0 | V97: 0 | X97: 53 | Z97: 0 | AA97: 0 | AC97: 105 | AD97: 55 | AE97: 136 | AF97: 24 | AG97: 160 | AH97: 0 | AI97: 160 | AJ97: 0 | AK97: 160 | AL97: 0 | AN97: 0 | AP97: 0 | AQ97: 0 | AS97: 0 | AT97: 0 | AU97: 0 | AV97: 0 | AW97: 0 | AX97: 0 | AY97: 0 | AZ97: 0 | BA97: 0 | BB97: 0
B98: OPPO | C98: OPPO A60 128GB 5G | D98: 176 | E98: 3.25 | F98: SMARTPHONE | G98: 24 | H98: 191 | J98: - | K98: - | M98: 0 | N98: 2.8 | O98: 0 | P98: 1.4 | Q98: 0 | R98: 0 | S98: 0 | T98: 0 | U98: 0 | V98: 0 | X98: -15 | Z98: 0 | AA98: 0 | AC98: 109 | AD98: 67 | AE98: 142 | AF98: 34 | AG98: 176 | AH98: 0 | AI98: 176 | AJ98: 0 | AK98: 176 | AL98: 0 | AN98: 0 | AP98: 0 | AQ98: 0 | AS98: 0 | AT98: -0.2 | AU98: 0 | AV98: -0.2 | AW98: 0 | AX98: 0 | AY98: 0 | AZ98: 0 | BA98: 0 | BB98: 0
B99: OPPO | C99: OPPO A80 256GB 5G | D99: 245 | E99: 3.25 | F99: SMARTPHONE | G99: 24 | H99: 246 | J99: - | K99: - | M99: 0 | N99: 4.8 | O99: 0 | P99: 3.4 | Q99: 0 | R99: 0 | S99: 0 | T99: 0 | U99: 0 | V99: 0 | X99: -1 | Z99: 0 | AA99: 0 | AC99: 130 | AD99: 115 | AE99: 163 | AF99: 82 | AG99: 245 | AH99: 0 | AI99: 245 | AJ99: 0 | AK99: 245 | AL99: 0 | AN99: 0 | AP99: 0 | AQ99: 0 | AS99: 0 | AT99: 0 | AU99: 0 | AV99: 0 | AW99: 0 | AX99: 0 | AY99: 0 | AZ99: 0 | BA99: 0 | BB99: 0
B100: OPPO | C100: OPPO FIND X8 PRO 512GB 5G | D100: 1072 | E100: 3.25 | F100: SMARTPHONE | G100: 24 | H100: 1151 | J100: - | K100: - | M100: - | N100: - | O100: 49 | P100: 25.8 | Q100: 39 | R100: 22.9 | S100: 0 | T100: 21.9 | U100: 0 | V100: 17 | X100: -79 | Z100: 0 | AA100: 0 | AC100: 0 | AD100: 0 | AE100: 404 | AF100: 619 | AG100: 483 | AH100: 550 | AI100: 546 | AJ100: 526 | AK100: 664 | AL100: 408 | AN100: 0 | AP100: 0 | AQ100: 0 | AS100: 0 | AT100: 0 | AU100: 0 | AV100: -4.4 | AW100: 0 | AX100: -4.4 | AY100: 0 | AZ100: -4.4 | BA100: 0 | BB100: -4.4
B101: OPPO | C101: OPPO RENO12 256GB 5G | D101: 428 | E101: 3.25 | F101: SMARTPHONE | G101: 24 | H101: 432 | J101: - | K101: - | M101: 0 | N101: 9.4 | O101: 0 | P101: 8 | Q101: 0 | R101: 4.6 | S101: 0 | T101: 3 | U101: 0 | V101: 0 | X101: -4 | Z101: 0 | AA101: 0 | AC101: 202 | AD101: 226 | AE101: 236 | AF101: 192 | AG101: 318 | AH101: 110 | AI101: 356 | AJ101: 72 | AK101: 428 | AL101: 0 | AN101: 0 | AP101: 0 | AQ101: 0 | AS101: 0 | AT101: 0 | AU101: 0 | AV101: 0 | AW101: 0 | AX101: 0 | AY101: 0 | AZ101: 0 | BA101: 0 | BB101: 0
B102: OPPO | C102: OPPO RENO12 FS 512GB 5G | D102: 364 | E102: 3.25 | F102: SMARTPHONE | G102: 24 | H102: 373 | J102: - | K102: - | M102: 0 | N102: 8.8 | O102: 0 | P102: 7.4 | Q102: 0 | R102: 4.1 | S102: 0 | T102: 2.4 | U102: 0 | V102: 0 | X102: -9 | Z102: 0 | AA102: 0 | AC102: 153 | AD102: 211 | AE102: 186 | AF102: 178 | AG102: 266 | AH102: 98 | AI102: 306 | AJ102: 58 | AK102: 364 | AL102: 0 | AN102: 6 | AP102: 0 | AQ102: 0 | AS102: 0 | AT102: 0.4 | AU102: 0 | AV102: 0.4 | AW102: 0 | AX102: 0.5 | AY102: 0 | AZ102: 0.4 | BA102: 0 | BB102: 0
B103: OPPO | C103: OPPO RENO12 PRO 512GB 5G | D103: 524 | E103: 3.25 | F103: SMARTPHONE | G103: 24 | H103: 518 | J103: - | K103: - | M103: 39 | N103: 11.9 | O103: 19 | P103: 11.1 | Q103: 0 | R103: 8.6 | S103: 0 | T103: 7 | U103: 0 | V103: 2.3 | X103: 6 | Z103: 0 | AA103: 0 | AC103: 199 | AD103: 286 | AE103: 239 | AF103: 266 | AG103: 318 | AH103: 206 | AI103: 356 | AJ103: 168 | AK103: 469 | AL103: 55 | AN103: 0 | AP103: 0 | AQ103: 0 | AS103: 0 | AT103: 0 | AU103: 0 | AV103: 0 | AW103: 0 | AX103: 0 | AY103: 0 | AZ103: 0 | BA103: 0 | BB103: 0
B104: ORANGE | C104: ORANGE GAMA 120 4G | D104: 74 | E104: 1.1 | F104: FIXED STYLE | G104: - | H104: - | J104: - | K104: - | M104: - | N104: - | O104: - | P104: - | Q104: - | R104: - | S104: - | T104: - | U104: - | V104: - | X104: 0 | Z104: 0 | AA104: 0 | AC104: 0 | AD104: 0 | AE104: 0 | AF104: 0 | AG104: 0 | AH104: 0 | AI104: 0 | AJ104: 0 | AK104: 0 | AL104: 0 | AN104: 0 | AP104: 0 | AQ104: 0 | AS104: 0 | AT104: 0 | AU104: 0 | AV104: 0 | AW104: 0 | AX104: 0 | AY104: 0 | AZ104: 0 | BA104: 0 | BB104: 0
B105: ORANGE | C105: ORANGE GAMA 402 | D105: 70 | E105: 1.1 | F105: FIXED STYLE | G105: - | H105: - | J105: - | K105: - | M105: - | N105: - | O105: - | P105: - | Q105: - | R105: - | S105: - | T105: - | U105: - | V105: - | X105: 0 | Z105: 0 | AA105: 0 | AC105: 0 | AD105: 0 | AE105: 0 | AF105: 0 | AG105: 0 | AH105: 0 | AI105: 0 | AJ105: 0 | AK105: 0 | AL105: 0 | AN105: 0 | AP105: 0 | AQ105: 0 | AS105: 0 | AT105: 0 | AU105: 0 | AV105: 0 | AW105: 0 | AX105: 0 | AY105: 0 | AZ105: 0 | BA105: 0 | BB105: 0
B106: ORANGE | C106: ORANGE GAMA 402 CESIÓN | D106: 0 | E106: 1.1 | F106: FIXED STYLE | G106: - | H106: - | J106: - | K106: - | M106: - | N106: - | O106: - | P106: - | Q106: - | R106: - | S106: - | T106: - | U106: - | V106: - | X106: 0 | Z106: 0 | AA106: 0 | AC106: 0 | AD106: 0 | AE106: 0 | AF106: 0 | AG106: 0 | AH106: 0 | AI106: 0 | AJ106: 0 | AK106: 0 | AL106: 0 | AN106: 0 | AP106: 0 | AQ106: 0 | AS106: 0 | AT106: 0 | AU106: 0 | AV106: 0 | AW106: 0 | AX106: 0 | AY106: 0 | AZ106: 0 | BA106: 0 | BB106: 0
B107: ORANGE | C107: ORANGE GAMA 704 | D107: 104 | E107: 1.1 | F107: FIXED STYLE | G107: - | H107: - | J107: - | K107: - | M107: - | N107: - | O107: - | P107: - | Q107: - | R107: - | S107: - | T107: - | U107: - | V107: - | X107: 0 | Z107: 0 | AA107: 0 | AC107: 0 | AD107: 0 | AE107: 0 | AF107: 0 | AG107: 0 | AH107: 0 | AI107: 0 | AJ107: 0 | AK107: 0 | AL107: 0 | AN107: 0 | AP107: 0 | AQ107: 0 | AS107: 0 | AT107: 0 | AU107: 0 | AV107: 0 | AW107: 0 | AX107: 0 | AY107: 0 | AZ107: 0 | BA107: 0 | BB107: 0
B108: ORANGE | C108: ORANGE GAMA 704 CESIÓN | D108: 0 | E108: 1.1 | F108: FIXED STYLE | G108: - | H108: - | J108: - | K108: - | M108: - | N108: - | O108: - | P108: - | Q108: - | R108: - | S108: - | T108: - | U108: - | V108: - | X108: 0 | Z108: 0 | AA108: 0 | AC108: 0 | AD108: 0 | AE108: 0 | AF108: 0 | AG108: 0 | AH108: 0 | AI108: 0 | AJ108: 0 | AK108: 0 | AL108: 0 | AN108: 0 | AP108: 0 | AQ108: 0 | AS108: 0 | AT108: 0 | AU108: 0 | AV108: 0 | AW108: 0 | AX108: 0 | AY108: 0 | AZ108: 0 | BA108: 0 | BB108: 0
B109: ORANGE | C109: ORANGE GAMA 803 CESIÓN | D109: 0 | E109: 1.1 | F109: FIXED STYLE | G109: - | H109: - | J109: - | K109: - | M109: - | N109: - | O109: - | P109: - | Q109: - | R109: - | S109: - | T109: - | U109: - | V109: - | X109: 0 | Z109: 0 | AA109: 0 | AC109: 0 | AD109: 0 | AE109: 0 | AF109: 0 | AG109: 0 | AH109: 0 | AI109: 0 | AJ109: 0 | AK109: 0 | AL109: 0 | AN109: 0 | AP109: 0 | AQ109: 0 | AS109: 0 | AT109: 0 | AU109: 0 | AV109: 0 | AW109: 0 | AX109: 0 | AY109: 0 | AZ109: 0 | BA109: 0 | BB109: 0
B110: ORANGE | C110: ORANGE GAMA 804 | D110: 115 | E110: 1.1 | F110: FIXED STYLE | G110: - | H110: - | J110: - | K110: - | M110: - | N110: - | O110: - | P110: - | Q110: - | R110: - | S110: - | T110: - | U110: - | V110: - | X110: 0 | Z110: 0 | AA110: 0 | AC110: 0 | AD110: 0 | AE110: 0 | AF110: 0 | AG110: 0 | AH110: 0 | AI110: 0 | AJ110: 0 | AK110: 0 | AL110: 0 | AN110: 0 | AP110: 0 | AQ110: 0 | AS110: 0 | AT110: 0 | AU110: 0 | AV110: 0 | AW110: 0 | AX110: 0 | AY110: 0 | AZ110: 0 | BA110: 0 | BB110: 0
B111: ORANGE | C111: ORANGE GAMA 804 CESIÓN | D111: 0 | E111: 1.1 | F111: FIXED STYLE | G111: - | H111: - | J111: - | K111: - | M111: - | N111: - | O111: - | P111: - | Q111: - | R111: - | S111: - | T111: - | U111: - | V111: - | X111: 0 | Z111: 0 | AA111: 0 | AC111: 0 | AD111: 0 | AE111: 0 | AF111: 0 | AG111: 0 | AH111: 0 | AI111: 0 | AJ111: 0 | AK111: 0 | AL111: 0 | AN111: 0 | AP111: 0 | AQ111: 0 | AS111: 0 | AT111: 0 | AU111: 0 | AV111: 0 | AW111: 0 | AX111: 0 | AY111: 0 | AZ111: 0 | BA111: 0 | BB111: 0
B112: NEXTIVITY | C112: REPETIDOR NEXTIVITY CELFI CONNECT C41 | D112: 547 | E112: 0 | F112: OC_OTROS DISPOSITIVOS | G112: 24 | H112: 499 | J112: - | K112: - | M112: 0 | N112: 18.4 | O112: 0 | P112: 17 | Q112: 0 | R112: 13.7 | S112: 0 | T112: 12.1 | U112: 0 | V112: 7.4 | X112: 48 | Z112: 0 | AA112: 0 | AC112: 105 | AD112: 442 | AE112: 139 | AF112: 408 | AG112: 218 | AH112: 329 | AI112: 257 | AJ112: 290 | AK112: 369 | AL112: 178 | AN112: 0 | AP112: 0 | AQ112: 0 | AS112: 0 | AT112: 0 | AU112: 0 | AV112: 0 | AW112: 0 | AX112: 0 | AY112: 0 | AZ112: 0 | BA112: 0 | BB112: 0
B113: SAMSUNG | C113: SAMSUNG GALAXY A15 | D113: 186 | E113: 3.25 | F113: SMARTPHONE | G113: 24 | H113: 201 | J113: - | K113: - | M113: 0 | N113: 5.7 | O113: 0 | P113: 4.3 | Q113: 0 | R113: 1 | S113: 0 | T113: 0 | U113: 0 | V113: 0 | X113: -15 | Z113: 0 | AA113: 0 | AC113: 49 | AD113: 137 | AE113: 83 | AF113: 103 | AG113: 162 | AH113: 24 | AI113: 186 | AJ113: 0 | AK113: 186 | AL113: 0 | AN113: 0 | AP113: 0 | AQ113: 0 | AS113: 0 | AT113: 0 | AU113: 0 | AV113: 0 | AW113: 0 | AX113: 0 | AY113: 0 | AZ113: 0 | BA113: 0 | BB113: 0
B114: SAMSUNG | C114: SAMSUNG GALAXY A15 5G | D114: 215 | E114: 3.25 | F114: SMARTPHONE | G114: 24 | H114: 231 | J114: - | K114: - | M114: 0 | N114: 6.8 | O114: 0 | P114: 5.4 | Q114: 0 | R114: 2.1 | S114: 0 | T114: 0 | U114: 0 | V114: 0 | X114: -16 | Z114: 0 | AA114: 0 | AC114: 52 | AD114: 163 | AE114: 85 | AF114: 130 | AG114: 165 | AH114: 50 | AI114: 215 | AJ114: 0 | AK114: 215 | AL114: 0 | AN114: 0 | AP114: 0 | AQ114: 0 | AS114: 0 | AT114: 0 | AU114: 0 | AV114: 0 | AW114: 0 | AX114: 0 | AY114: 0 | AZ114: 0 | BA114: 0 | BB114: 0
B115: SAMSUNG | C115: SAMSUNG GALAXY A16 128GB | D115: 186 | E115: 3.25 | F115: SMARTPHONE | G115: 24 | H115: 201 | J115: - | K115: - | M115: 0 | N115: 3.5 | O115: 0 | P115: 2.1 | Q115: 0 | R115: 0 | S115: 0 | T115: 0 | U115: 0 | V115: 0 | X115: -15 | Z115: 0 | AA115: 0 | AC115: 102 | AD115: 84 | AE115: 136 | AF115: 50 | AG115: 186 | AH115: 0 | AI115: 186 | AJ115: 0 | AK115: 186 | AL115: 0 | AN115: 0 | AP115: 0 | AQ115: 0 | AS115: 0 | AT115: 0 | AU115: 0 | AV115: 0 | AW115: 0 | AX115: 0 | AY115: 0 | AZ115: 0 | BA115: 0 | BB115: 0
...

Sheet PVP VaP IEW Pro - Pyme
B2: OFERTA TÁCTICA EMPRESAS | H2: Pago Único | J2: CAPTA | M2: PORTABILIDAD
B4: ='PVP VaP - Pyme'!B4 -> 45658 | C4: 01/01 al 31/01 | J4: - | M4: ENTRADA PRO | O4: NORMAL PRO | Q4: VALOR PRO | S4: PREMIUM PRO
B5: 1. CONDICIONES DE LA OFERTA VENTA A PLAZOS (según tarifa y situación del cliente) | D5: Tarifas | H5: Todas Tarifas | J5: Todas Tarifas | M5: Internet Movil 3GB Empresa | O5: Internet Movil 10GB Empresa | Q5: Internet Movil 25GB Empresa Fibra Oro (**) | S5: Internet Movil 90GB Empresa Internet 4G en tu Negocio (excepto router) Internet Empresa Ilimitado
D13: Ampliaciones (meses antigüedad) | H13: - | J13: - | M13: + 4 M - 4 M doble capta | O13: + 4 M - 4 M doble capta | Q13: + 4 M - 4 M doble capta | S13: + 4 M - 4 M doble capta
D14: Origen (Portabilidad / Migración) | H14: Capta Pos / Pre Migra | J14: (*) Capta de cliente nuevo o de cliente -4 M, solo tienen acceso a Pago Único | M14: Pos / Migra | O14: Pos / Migra | Q14: Pos / Migra | S14: Pos / Migra
D15: CP Tarifa | H15: - | J15: - | M15: 12 M / 24 M | O15: 12 M / 24 M | Q15: 12 M / 24 M | S15: 12 M / 24 M
D16: (*) Para Capta de cliente nuevo o cliente de -4 meses que activen en el mismo acto comercial tarifas de voz y tarifas de IEW Pro, aplican las condiciones de Portabilidad origen Pospago
D17: (**) La tarifa Fibra Oro solo puede activarse con el router Alctel Airbox 4G MW40 2018
B18: 2. PRECIO DEL TERMINAL POR GRUPO DE TARIFAS | H18: Pago Único | J18: PVPR CAPTA | M18: PVPR PORTABILIDAD | V18: DxC Pago Único | X18: DxC CAPTA | AA18: DxC PORTABILIDAD
M20: GRUPOS DE TARIFAS IEW Pro | AA20: GRUPOS DE TARIFAS IEW Pro
J22: - | M22: ENTRADA PRO | O22: NORMAL PRO | Q22: VALOR PRO | S22: PREMIUM PRO | X22: - | AA22: ENTRADA PRO | AC22: NORMAL PRO | AE22: VALOR PRO | AG22: PREMIUM PRO
B24: MARCA | C24: Modelo (Novedades) | D24: Precio Cesión | E24: Canon Digital | F24: Gama | G24: Meses Cuota | H24: Pago Unico (sin IVA) | J24: Pago Inicial (sin IVA) | K24: Cuota Mes (sin IVA) | M24: Pago Inicial (sin IVA) | N24: Cuota Mes (sin IVA) | O24: Pago Inicial (sin IVA) | P24: Cuota Mes (sin IVA) | Q24: Pago Inicial (sin IVA) | R24: Cuota Mes (sin IVA) | S24: Pago Inicial (sin IVA) | T24: Cuota Mes (sin IVA) | V24: DxC Pago Unico | X24: DxC Precio | Y24: DxC VaP | AA24: DxC Precio | AB24: DxC VaP | AC24: DxC Precio | AD24: DxC VaP | AE24: DxC Precio | AF24: DxC VaP | AG24: DxC Precio | AH24: DxC VaP
B25: ALCATEL | C25: ALCATEL AIRBOX 4G MW45 | D25: 49 | E25: 0 | F25: MBB | G25: 12 | H25: 42.14876 | J25: - | K25: - | M25: 0 | N25: 3 | O25: 0 | P25: 1 | Q25: 0 | R25: 1 | S25: 0 | T25: 0 | V25: 6.8512397 | X25: - | Y25: - | AA25: 13 | AB25: 36 | AC25: 37 | AD25: 12 | AE25: 37 | AF25: 12 | AG25: 49 | AH25: 0
B26: HUAWEI | C26: HUAWEI AIRBOX E5576-320 IEW 4G | D26: 66 | E26: 0 | F26: MBB | G26: 12 | H26: 57.024793 | J26: - | K26: - | M26: 0 | N26: 3 | O26: 0 | P26: 2 | Q26: 0 | R26: 2 | S26: 0 | T26: 0 | V26: 8.9752066 | X26: - | Y26: - | AA26: 30 | AB26: 36 | AC26: 42 | AD26: 24 | AE26: 42 | AF26: 24 | AG26: 66 | AH26: 0
B27: TP-LINK | C27: ROUTER TPLINK MR200 IEW 4G | D27: 58 | E27: 0 | F27: MBB | G27: 12 | H27: 48 | J27: - | K27: - | M27: 0 | N27: 4 | O27: 0 | P27: 2 | Q27: 0 | R27: 2 | S27: 0 | T27: 1 | V27: 10 | X27: - | Y27: - | AA27: 10 | AB27: 48 | AC27: 34 | AD27: 24 | AE27: 34 | AF27: 24 | AG27: 46 | AH27: 12
B28: TP-LINK | C28: ROUTER TPLINK MR200 IEW 4G (2) | D28: 58 | E28: 0 | F28: MBB | G28: - | H28: 48 | J28: - | K28: - | M28: - | N28: - | O28: - | P28: - | Q28: - | R28: - | S28: - | T28: - | V28: 10 | X28: - | Y28: - | AA28: - | AB28: - | AC28: - | AD28: - | AE28: - | AF28: - | AG28: - | AH28: -
B29: TP-LINK | C29: TP-LINK FLYBOX 4G (1) | D29: 0 | E29: 0 | F29: MBB | G29: 12 | H29: 0 | J29: - | K29: - | M29: - | N29: - | O29: - | P29: - | Q29: - | R29: - | S29: 0 | T29: 0 | V29: 0 | X29: - | Y29: - | AA29: - | AB29: - | AC29: - | AD29: - | AE29: - | AF29: - | AG29: 0 | AH29: 0
B30: ZTE | C30: ZTE AIRBOX MF920U 4G | D30: 66 | E30: 0 | F30: MBB | G30: 12 | H30: 45.454545 | J30: - | K30: - | M30: 0 | N30: 3 | O30: 0 | P30: 2 | Q30: 0 | R30: 2 | S30: 0 | T30: 0 | V30: 20.545455 | X30: - | Y30: - | AA30: 30 | AB30: 36 | AC30: 42 | AD30: 24 | AE30: 42 | AF30: 24 | AG30: 66 | AH30: 0
B31: ZTE | C31: ZTE AIRBOX MU5001 5G | D31: 244 | E31: 0 | F31: MBB | G31: 24 | H31: 243.80165 | M31: 39 | N31: 6 | O31: 0 | P31: 7 | Q31: 0 | R31: 7 | S31: 0 | T31: 6 | V31: 0.19834711 | AA31: 61 | AB31: 144 | AC31: 76 | AD31: 168 | AE31: 76 | AF31: 168 | AG31: 100 | AH31: 144
B32: ZTE | C32: ZTE FLYBOX MC801A 5G | D32: 200 | E32: 0 | F32: MBB | G32: 24 | H32: 200 | J32: - | K32: - | M32: 29 | N32: 6 | O32: 0 | P32: 6 | Q32: 0 | R32: 6 | S32: 0 | T32: 6 | V32: 0 | X32: - | Y32: - | AA32: 27 | AB32: 144 | AC32: 56 | AD32: 144 | AE32: 56 | AF32: 144 | AG32: 56 | AH32: 144
B33: NOKIA | C33: FLYBOX NOKIA FASTMILE 5G | D33: 207 | E33: 0 | F33: MBB | G33: 24 | H33: 177.68595 | J33: - | K33: - | M33: 29 | N33: 5 | O33: 0 | P33: 6 | Q33: 0 | R33: 6 | S33: 0 | T33: 5 | V33: 29.31405 | X33: - | Y33: - | AA33: 58 | AB33: 120 | AC33: 63 | AD33: 144 | AE33: 63 | AF33: 144 | AG33: 87 | AH33: 120
B34: HUAWEI | C34: FLYBOX HUAWEI H153-381 5G | D34: 248 | E34: 0 | F34: MBB | G34: 24 | H34: 132 | J34: - | K34: - | M34: 0 | N34: 4 | O34: 0 | P34: 4 | Q34: 0 | R34: 4 | S34: 0 | T34: 3 | V34: 116 | X34: - | Y34: - | AA34: 152 | AB34: 96 | AC34: 152 | AD34: 96 | AE34: 152 | AF34: 96 | AG34: 176 | AH34: 72
B35: HUAWEI | C35: FLYBOX HUAWEI H153-381 5G CESIÓN (1) | D35: 0 | E35: 0 | F35: MBB | G35: 12 | H35: 0 | J35: - | K35: - | M35: - | N35: - | O35: - | P35: - | Q35: - | R35: - | S35: 0 | T35: 0 | V35: 0 | X35: - | Y35: - | AA35: - | AB35: - | AC35: - | AD35: - | AE35: - | AF35: - | AG35: 0 | AH35: 0
B36: SAMSUNG | C36: SAMSUNG GALAXY TAB A9 8,7" WIFI | D36: 182 | E36: 3.75 | F36: TABLET | G36: 24 | H36: 161.98347 | J36: - | K36: - | M36: 29 | N36: 4 | O36: 0 | P36: 5 | Q36: 0 | R36: 5 | S36: 0 | T36: 4 | V36: 20.016529 | X36: - | Y36: - | AA36: 57 | AB36: 96 | AC36: 62 | AD36: 120 | AE36: 62 | AF36: 120 | AG36: 86 | AH36: 96
B37: XIAOMI | C37: XIAOMI REDMI PAD SE 8.7" WIFI 4+128GB | D37: 167 | E37: 3.75 | F37: TABLET | G37: 24 | H37: 123.1405 | J37: - | K37: - | M37: 0 | N37: 4 | O37: 0 | P37: 4 | Q37: 0 | R37: 4 | S37: 0 | T37: 3 | V37: 43.859504 | X37: - | Y37: - | AA37: - | AB37: - | AC37: - | AD37: - | AE37: - | AF37: - | AG37: 95 | AH37: 72
B40: Condiciones especiales para Fibra Oro
B41: ZTE | C41: ZTE AIRBOX MF920U 4G | D41: 66 | E41: 0 | F41: MBB | G41: 12 | H41: 47.11 | J41: - | K41: - | M41: - | N41: - | O41: - | P41: - | Q41: 0 | R41: 0 | S41: - | T41: - | V41: 18.89 | X41: - | Y41: - | AA41: - | AB41: - | AC41: - | AD41: - | AE41: 66 | AF41: 0 | AG41: - | AH41: -
B42: ALCATEL | C42: ALCATEL AIRBOX 4G MW45 | D42: 49 | E42: 0 | F42: MBB | G42: 12 | H42: 43.801653 | J42: - | K42: - | M42: - | N42: - | O42: - | P42: - | Q42: 0 | R42: 0 | S42: - | T42: - | V42: 5.1983471 | X42: - | Y42: - | AA42: - | AB42: - | AC42: - | AD42: - | AE42: 49 | AF42: 0 | AG42: - | AH42: -
B43: Formato
C47: (1) Solo oferta en VaP (cesión) para 4G en tu Negocio e Internet Empresas Ilimitado
C48: (2) Solo oferta en Pago único para 4G en tu Negocio e Internet Empresas Ilimitado

Sheet PVP Subv - Optima Pyme
B2: OFERTA TÁCTICA EMPRESAS | I2: CAPTA | O2: PORTABILIDAD | U2: CAPTA | AA2: PORTABILIDAD
B4: ='PVP VaP - Pyme'!B4 -> 45658 | C4: 01/01 al 31/01 | I4: ENTRADA PRO | J4: NORMAL PRO | K4: VALOR PRO | L4: PREMIUM PRO | M4: TOP PRO | O4: ENTRADA PRO | P4: NORMAL PRO | Q4: VALOR PRO | R4: PREMIUM PRO | S4: TOP PRO | U4: ENTRADA PRO | V4: NORMAL PRO | W4: VALOR PRO | X4: PREMIUM PRO | Y4: TOP PRO | AA4: ENTRADA PRO | AB4: NORMAL PRO | AC4: VALOR PRO | AD4: PREMIUM PRO | AE4: TOP PRO
B5: 1. CONDICIONES DE LA OFERTA SUBVENCIONADA (según tarifa y situación del cliente) | D5: Tarifas | I5: Sol P. RPV T. Optima T. Optima RPV + Tarifa 150min+1GB (en term VOZ / FIX solo tarifa voz) | J5: Sol P. RPV T. Optima T. Optima RPV + Tarifa ilimitada+2GB (en term VOZ / FIX solo tarifa voz) | K5: Sol P. RPV T. Optima T. Optima RPV + Tarifa ilimitada+5GB | L5: Sol P. RPV T. Optima T. Optima RPV + Tarifa ilimitada+12GB | M5: Sol P. RPV T. Optima T. Optima RPV + Tarifa ilimitada+30GB | O5: Sol P. RPV T. Optima T. Optima RPV + Tarifa 150min+1GB (en term VOZ / FIX solo tarifa voz) | P5: Sol P. RPV T. Optima T. Optima RPV + Tarifa ilimitada+2GB (en term VOZ / FIX solo tarifa voz) | Q5: Sol P. RPV T. Optima T. Optima RPV + Tarifa ilimitada+5GB | R5: Sol P. RPV T. Optima T. Optima RPV + Tarifa ilimitada+12GB | S5: Sol P. RPV T. Optima T. Optima RPV + Tarifa ilimitada+30GB | U5: T. Optima Plus Empresas T. Optima Plus Empresas Big + Empresas Voz y Empresas 1 | V5: T. Optima Plus Empresas T. Optima Plus Empresas Big + Empresas 5 y Empresas Intranet | W5: T. Optima Plus Empresas T. Optima Plus Empresas Big + Empresas 20 | X5: T. Optima Plus Empresas T. Optima Plus Empresas Big + Empresas Infinita | Y5: T. Optima Plus Empresas T. Optima Plus Empresas Big + Empresas Internacional | AA5: T. Optima Plus Empresas T. Optima Plus Empresas Big + Empresas Voz y Empresas 1 | AB5: T. Optima Plus Empresas T. Optima Plus Empresas Big + Empresas 5 y Empresas Intranet | AC5: T. Optima Plus Empresas T. Optima Plus Empresas Big + Empresas 20 | AD5: T. Optima Plus Empresas T. Optima Plus Empresas Big + Empresas Infinita | AE5: T. Optima Plus Empresas T. Optima Plus Empresas Big + Empresas Internacional
D12: Ampliaciones (meses antigüedad) | I12: Todos | J12: Todos | K12: Todos | L12: Todos | M12: Todos | O12: Todos | P12: Todos | Q12: Todos | R12: Todos | S12: Todos | U12: Todos | V12: Todos | W12: Todos | X12: Todos | Y12: Todos | AA12: Todos | AB12: Todos | AC12: Todos | AD12: Todos | AE12: Todos
D13: Origen (Portabilidad / Migración) | I13: Capta Prepago Migracion | J13: Capta Prepago Migracion | K13: Capta Prepago Migracion | L13: Capta Prepago Migracion | M13: Capta Prepago Migracion | O13: Pospago | P13: Pospago | Q13: Pospago | R13: Pospago | S13: Pospago | U13: Capta Prepago Migracion | V13: Capta Prepago Migracion | W13: Capta Prepago Migracion | X13: Capta Prepago Migracion | Y13: Capta Prepago Migracion | AA13: Pospago | AB13: Pospago | AC13: Pospago | AD13: Pospago | AE13: Pospago
D14: CP Tarifa Voz | I14: 12 M | J14: 12 M | K14: 12 M | L14: 12 M | M14: 12 M | O14: 12 M | P14: 12 M | Q14: 12 M | R14: 12 M | S14: 12 M | U14: 24 M | V14: 24 M | W14: 24 M | X14: 24 M | Y14: 24 M | AA14: 24 M | AB14: 24 M | AC14: 24 M | AD14: 24 M | AE14: 24 M
D15: CP Tarifa Datos | I15: 24 M | J15: 24 M | K15: 24 M Plus | L15: 24 M Plus | M15: 24 M Plus | O15: 24 M | P15: 24 M | Q15: 24 M Plus | R15: 24 M Plus | S15: 24 M Plus | U15: 24 M | V15: 24 M | W15: 24 M Plus | X15: 24 M Plus | Y15: 24 M Plus | AA15: 24 M | AB15: 24 M | AC15: 24 M Plus | AD15: 24 M Plus | AE15: 24 M Plus
D16: CP Operador | I16: 24 M | J16: 24 M | K16: 24 M | L16: 24 M | M16: 24 M | O16: 24 M | P16: 24 M | Q16: 24 M | R16: 24 M | S16: 24 M | U16: 24 M | V16: 24 M | W16: 24 M | X16: 24 M | Y16: 24 M | AA16: 24 M | AB16: 24 M | AC16: 24 M | AD16: 24 M | AE16: 24 M
I17: Las condiciones de los modulos Entrada Pro y Normal Pro aplican para los terminales VOZ y FIX tanto si activan sólo voz como si activan el paquete de voz + datos | U17: Las condiciones de los modulos Entrada Pro y Normal Pro aplican para los terminales VOZ y FIX tanto si activan sólo voz como si activan el paquete de voz + datos | AG17: DIFERENCIAS Vs MES ANTERIOR | BE17: CP 36
B19: 2. PRECIO DEL TERMINAL POR GRUPO DE TARIFAS | I19: PVPR CAPTA | O19: PVPR PORTABILIDAD | U19: DxC CAPTA | AA19: DxC PORTABILIDAD | AG19: DxC CAPTA | AM19: DxC PORTABILIDAD | AS19: PVPR CAPTA | AY19: PVPR PORTABILIDAD | BE19: DxC CAPTA | BK19: DxC PORTABILIDAD
I21: GRUPOS DE TARIFAS MOVIL | O21: GRUPOS DE TARIFAS MOVIL | U21: GRUPOS DE TARIFAS MOVIL | AA21: GRUPOS DE TARIFAS MOVIL | AG21: GRUPOS DE TARIFAS MOVIL | AM21: GRUPOS DE TARIFAS MOVIL | AS21: GRUPOS DE TARIFAS MOVIL | AY21: GRUPOS DE TARIFAS MOVIL | BE21: GRUPOS DE TARIFAS MOVIL | BK21: GRUPOS DE TARIFAS MOVIL
I23: ENTRADA PRO | J23: NORMAL PRO | K23: VALOR PRO | L23: PREMIUM PRO | M23: TOP PRO | O23: ENTRADA PRO | P23: NORMAL PRO | Q23: VALOR PRO | R23: PREMIUM PRO | S23: TOP PRO | U23: ENTRADA PRO | V23: NORMAL PRO | W23: VALOR PRO | X23: PREMIUM PRO | Y23: TOP PRO | AA23: ENTRADA PRO | AB23: NORMAL PRO | AC23: VALOR PRO | AD23: PREMIUM PRO | AE23: TOP PRO | AG23: ENTRADA PRO | AH23: NORMAL PRO | AI23: VALOR PRO | AJ23: PREMIUM PRO | AK23: TOP PRO | AM23: ENTRADA PRO | AN23: NORMAL PRO | AO23: VALOR PRO | AP23: PREMIUM PRO | AQ23: TOP PRO | AS23: ENTRADA PRO | AT23: NORMAL PRO | AU23: VALOR PRO | AV23: PREMIUM PRO | AW23: TOP PRO | AY23: ENTRADA PRO | AZ23: NORMAL PRO | BA23: VALOR PRO | BB23: PREMIUM PRO | BC23: TOP PRO | BE23: ENTRADA PRO | BF23: NORMAL PRO | BG23: VALOR PRO | BH23: PREMIUM PRO | BI23: TOP PRO | BK23: ENTRADA PRO | BL23: NORMAL PRO | BM23: VALOR PRO | BN23: PREMIUM PRO | BO23: TOP PRO
B25: MARCA | C25: Modelo (Novedades) | D25: Precio Cesión | E25: Canon Digital | F25: Gama | I25: PVP (sin IVA) | J25: PVP (sin IVA) | K25: PVP (sin IVA) | L25: PVP (sin IVA) | M25: PVP (sin IVA) | O25: PVP (sin IVA) | P25: PVP (sin IVA) | Q25: PVP (sin IVA) | R25: PVP (sin IVA) | S25: PVP (sin IVA) | U25: DxC (sin IVA) | V25: DxC (sin IVA) | W25: DxC (sin IVA) | X25: DxC (sin IVA) | Y25: DxC (sin IVA) | AA25: DxC (sin IVA) | AB25: DxC (sin IVA) | AC25: DxC (sin IVA) | AD25: DxC (sin IVA) | AE25: DxC (sin IVA) | AG25: DxC (sin IVA) | AH25: DxC (sin IVA) | AI25: DxC (sin IVA) | AJ25: DxC (sin IVA) | AK25: DxC (sin IVA) | AM25: DxC (sin IVA) | AN25: DxC (sin IVA) | AO25: DxC (sin IVA) | AP25: DxC (sin IVA) | AQ25: DxC (sin IVA) | AS25: PVP (sin IVA) | AT25: PVP (sin IVA) | AU25: PVP (sin IVA) | AV25: PVP (sin IVA) | AW25: PVP (sin IVA) | AY25: PVP (sin IVA) | AZ25: PVP (sin IVA) | BA25: PVP (sin IVA) | BB25: PVP (sin IVA) | BC25: PVP (sin IVA) | BE25: DxC (sin IVA) | BF25: DxC (sin IVA) | BG25: DxC (sin IVA) | BH25: DxC (sin IVA) | BI25: DxC (sin IVA) | BK25: DxC (sin IVA) | BL25: DxC (sin IVA) | BM25: DxC (sin IVA) | BN25: DxC (sin IVA) | BO25: DxC (sin IVA)
B26: ORANGE | C26: AD HOC H3 CESIÓN | D26: 0 | E26: 1.1 | F26: FIXED STYLE | I26: 0 | J26: 0 | K26: 0 | L26: 0 | M26: 0 | O26: 0 | P26: 0 | Q26: 0 | R26: 0 | S26: 0 | U26: 0 | V26: 0 | W26: 0 | X26: 0 | Y26: 0 | AA26: 0 | AB26: 0 | AC26: 0 | AD26: 0 | AE26: 0 | AG26: 0 | AH26: 0 | AI26: 0 | AJ26: 0 | AK26: 0 | AM26: 0 | AN26: 0 | AO26: 0 | AP26: 0 | AQ26: 0 | AS26: - | AT26: - | AU26: - | AV26: - | AW26: - | AY26: - | AZ26: - | BA26: - | BB26: - | BC26: - | BE26: 0 | BF26: 0 | BG26: 0 | BH26: 0 | BI26: 0 | BK26: 0 | BL26: 0 | BM26: 0 | BN26: 0 | BO26: 0
B27: ORANGE | C27: ADOC D30 | D27: 239 | E27: 3.75 | F27: FIXED STYLE | I27: 39 | J27: 54 | K27: 78 | L27: 112 | M27: 145 | O27: 79 | P27: 124 | Q27: 184 | R27: 234 | S27: 241 | U27: 116 | V27: 166 | W27: 215 | X27: 239 | Y27: 239 | AA27: 116 | AB27: 166 | AC27: 215 | AD27: 239 | AE27: 239 | AG27: 0 | AH27: 0 | AI27: 0 | AJ27: 0 | AK27: 0 | AM27: 0 | AN27: 0 | AO27: 0 | AP27: 0 | AQ27: 0 | AS27: 123 | AT27: 73 | AU27: 24 | AV27: 0 | AW27: 0 | AY27: 123 | AZ27: 73 | BA27: 24 | BB27: 0 | BC27: 0 | BE27: 116 | BF27: 166 | BG27: 215 | BH27: 239 | BI27: 239 | BK27: 116 | BL27: 166 | BM27: 215 | BN27: 239 | BO27: 239
B28: ORANGE | C28: ADOC D30 CESIÓN | D28: 0 | E28: 3.75 | F28: FIXED STYLE | I28: 51 | J28: 60 | K28: 67 | L28: 67 | M28: 67 | O28: 51 | P28: 60 | Q28: 67 | R28: 67 | S28: 67 | U28: 0 | V28: 0 | W28: 0 | X28: 0 | Y28: 0 | AA28: 0 | AB28: 0 | AC28: 0 | AD28: 0 | AE28: 0 | AG28: 0 | AH28: 0 | AI28: 0 | AJ28: 0 | AK28: 0 | AM28: 0 | AN28: 0 | AO28: 0 | AP28: 0 | AQ28: 0 | AS28: - | AT28: - | AU28: - | AV28: - | AW28: - | AY28: - | AZ28: - | BA28: - | BB28: - | BC28: - | BE28: 0 | BF28: 0 | BG28: 0 | BH28: 0 | BI28: 0 | BK28: 0 | BL28: 0 | BM28: 0 | BN28: 0 | BO28: 0
B29: AD HOC | C29: ADOC SC01 | D29: 64 | E29: 1.1 | F29: VOZ | I29: 34 | J29: 0 | K29: 0 | L29: 0 | M29: 0 | O29: 34 | P29: 0 | Q29: 0 | R29: 0 | S29: 0 | U29: 64 | V29: 64 | W29: 0 | X29: 0 | Y29: 0 | AA29: 64 | AB29: 64 | AC29: 0 | AD29: 0 | AE29: 0 | AG29: 0 | AH29: 0 | AI29: 0 | AJ29: 0 | AK29: 0 | AM29: 0 | AN29: 0 | AO29: 0 | AP29: 0 | AQ29: 0 | AS29: 0 | AT29: 0 | AU29: - | AV29: - | AW29: - | AY29: 0 | AZ29: 0 | BA29: - | BB29: - | BC29: - | BE29: 64 | BF29: 64 | BG29: 0 | BH29: 0 | BI29: 0 | BK29: 64 | BL29: 64 | BM29: 0 | BN29: 0 | BO29: 0
B30: ADOC | C30: ADOC SC04 | D30: 77 | E30: 1.1 | F30: VOZ | I30: 33 | J30: 0 | K30: 0 | L30: 0 | M30: 0 | O30: 33 | P30: 0 | Q30: 0 | R30: 0 | S30: 0 | U30: 77 | V30: 77 | W30: 0 | X30: 0 | Y30: 0 | AA30: 77 | AB30: 77 | AC30: 0 | AD30: 0 | AE30: 0 | AG30: 0 | AH30: 0 | AI30: 0 | AJ30: 0 | AK30: 0 | AM30: 0 | AN30: 0 | AO30: 0 | AP30: 0 | AQ30: 0 | AS30: 0 | AT30: 0 | AU30: - | AV30: - | AW30: - | AY30: 0 | AZ30: 0 | BA30: - | BB30: - | BC30: - | BE30: 77 | BF30: 77 | BG30: 0 | BH30: 0 | BI30: 0 | BK30: 77 | BL30: 77 | BM30: 0 | BN30: 0 | BO30: 0
B31: APPLE | C31: APPLE AIRPODS 4 | D31: 137 | E31: 0 | F31: OC_AURICULARES | I31: 43 | J31: 0 | K31: 0 | L31: 0 | M31: 0 | O31: 43 | P31: 0 | Q31: 0 | R31: 0 | S31: 0 | U31: 39 | V31: 59 | W31: 82 | X31: 99 | Y31: 132 | AA31: 97 | AB31: 127 | AC31: 176 | AD31: 224 | AE31: 224 | AG31: 13 | AH31: 13 | AI31: 13 | AJ31: 13 | AK31: 13 | AM31: 0 | AN31: 0 | AO31: 0 | AP31: 0 | AQ31: 0 | AS31: 98 | AT31: 78 | AU31: 55 | AV31: 38 | AW31: 5 | AY31: 40 | AZ31: 10 | BA31: -39 | BB31: -86.54 | BC31: -86.54 | BE31: 39 | BF31: 59 | BG31: 82 | BH31: 99 | BI31: 132 | BK31: 97 | BL31: 127 | BM31: 176 | BN31: 224 | BO31: 224
B32: APPLE | C32: APPLE AIRPODS 4 CON CANCELACION ACTIVA RUIDO | D32: 184 | E32: 0 | F32: OC_AURICULARES | I32: 55 | J32: 0 | K32: 0 | L32: 0 | M32: 0 | O32: 55 | P32: 0 | Q32: 0 | R32: 0 | S32: 0 | U32: 52 | V32: 72 | W32: 95 | X32: 112 | Y32: 145 | AA32: 97 | AB32: 127 | AC32: 176 | AD32: 241 | AE32: 250 | AG32: 0 | AH32: 0 | AI32: 0 | AJ32: 0 | AK32: 0 | AM32: 0 | AN32: 0 | AO32: 0 | AP32: 0 | AQ32: 0 | AS32: 132 | AT32: 112 | AU32: 89 | AV32: 72 | AW32: 39 | AY32: 87 | AZ32: 57 | BA32: 8 | BB32: -57 | BC32: -66.08 | BE32: 52 | BF32: 72 | BG32: 95 | BH32: 112 | BI32: 145 | BK32: 97 | BL32: 127 | BM32: 176 | BN32: 241 | BO32: 250
B33: APPLE | C33: APPLE AIRPODS PRO 2a GENERACION MAGSAFE USBC | D33: 279 | E33: 0 | F33: OC_AURICULARES | I33: 54 | J33: 0 | K33: 0 | L33: 0 | M33: 0 | O33: 54 | P33: 0 | Q33: 0 | R33: 0 | S33: 0 | U33: 89 | V33: 109 | W33: 132 | X33: 149 | Y33: 182 | AA33: 134 | AB33: 164 | AC33: 213 | AD33: 278 | AE33: 373 | AG33: 0 | AH33: 0 | AI33: 0 | AJ33: 0 | AK33: 0 | AM33: 0 | AN33: 0 | AO33: 0 | AP33: 0 | AQ33: 0 | AS33: 190.46 | AT33: 170.46 | AU33: 147.46 | AV33: 130.46 | AW33: 97.46 | AY33: 145.46 | AZ33: 115.46 | BA33: 66.46 | BB33: 1.46 | BC33: -94.23 | BE33: 89 | BF33: 109 | BG33: 132 | BH33: 149 | BI33: 182 | BK33: 134 | BL33: 164 | BM33: 213 | BN33: 278 | BO33: 373
B34: APPLE | C34: APPLE WATCH S10 CELLULAR 42MM | D34: 532 | E34: 2.5 | F34: OC_SMART WATCH | I34: 79 | J34: 99 | K34: 99 | L34: 99 | M34: 99 | O34: 79 | P34: 99 | Q34: 99 | R34: 99 | S34: 99 | U34: 52 | V34: 138 | W34: 161 | X34: 178 | Y34: 211 | AA34: 97 | AB34: 193 | AC34: 242 | AD34: 307 | AE34: 419 | AG34: 0 | AH34: 0 | AI34: 0 | AJ34: 0 | AK34: 0 | AM34: 0 | AN34: 0 | AO34: 0 | AP34: 0 | AQ34: 0 | AS34: 480 | AT34: 393.81 | AU34: 370.81 | AV34: 353.81 | AW34: 320.81 | AY34: 435 | AZ34: 338.81 | BA34: 289.81 | BB34: 224.81 | BC34: 112.81 | BE34: 52 | BF34: 138 | BG34: 161 | BH34: 178 | BI34: 211 | BK34: 97 | BL34: 223 | BM34: 292 | BN34: 347 | BO34: 479
B35: APPLE | C35: APPLE WATCH S10 CELLULAR 46MM | D35: 555 | E35: 2.5 | F35: OC_SMART WATCH | I35: 39 | J35: 54 | K35: 78 | L35: 112 | M35: 145 | O35: 79 | P35: 124 | Q35: 190 | R35: 300 | S35: 447 | U35: 52 | V35: 139 | W35: 162 | X35: 179 | Y35: 212 | AA35: 97 | AB35: 194 | AC35: 243 | AD35: 308 | AE35: 420 | AG35: 0 | AH35: 0 | AI35: 0 | AJ35: 0 | AK35: 0 | AM35: 0 | AN35: 0 | AO35: 0 | AP35: 0 | AQ35: 0 | AS35: 503 | AT35: 416.25 | AU35: 393.25 | AV35: 376.25 | AW35: 343.25 | AY35: 458 | AZ35: 361.25 | BA35: 312.25 | BB35: 247.25 | BC35: 135.25 | BE35: 52 | BF35: 139 | BG35: 162 | BH35: 179 | BI35: 212 | BK35: 97 | BL35: 224 | BM35: 293 | BN35: 348 | BO35: 480
B36: AD HOC | C36: AURICULARES AD HOC BT01 | D36: 71 | E36: 0 | F36: OC_AURICULARES | I36: 39 | J36: 54 | K36: 145 | L36: 179 | M36: 212 | O36: 79 | P36: 124 | Q36: 257 | R36: 367 | S36: 514 | U36: 71 | V36: 71 | W36: 71 | X36: 71 | Y36: 71 | AA36: 71 | AB36: 71 | AC36: 71 | AD36: 71 | AE36: 71 | AG36: 0 | AH36: 0 | AI36: 0 | AJ36: 0 | AK36: 0 | AM36: 0 | AN36: 0 | AO36: 0 | AP36: 0 | AQ36: 0 | AS36: 0 | AT36: 0 | AU36: 0 | AV36: 0 | AW36: 0 | AY36: 0 | AZ36: 0 | BA36: 0 | BB36: 0 | BC36: 0 | BE36: 71 | BF36: 71 | BG36: 71 | BH36: 71 | BI36: 71 | BK36: 71 | BL36: 71 | BM36: 71 | BN36: 71 | BO36: 71
B37: AD HOC | C37: AURICULARES AD HOC HC01 | D37: 49 | E37: 0 | F37: OC_AURICULARES | I37: 39 | J37: 54 | K37: 78 | L37: 112 | M37: 145 | O37: 79 | P37: 124 | Q37: 190 | R37: 300 | S37: 447 | U37: 49 | V37: 49 | W37: 49 | X37: 49 | Y37: 49 | AA37: 49 | AB37: 49 | AC37: 49 | AD37: 49 | AE37: 49 | AG37: 0 | AH37: 0 | AI37: 0 | AJ37: 0 | AK37: 0 | AM37: 0 | AN37: 0 | AO37: 0 | AP37: 0 | AQ37: 0 | AS37: 0 | AT37: 0 | AU37: 0 | AV37: 0 | AW37: 0 | AY37: 0 | AZ37: 0 | BA37: 0 | BB37: 0 | BC37: 0 | BE37: 49 | BF37: 49 | BG37: 49 | BH37: 49 | BI37: 49 | BK37: 49 | BL37: 49 | BM37: 49 | BN37: 49 | BO37: 49
B38: SAMSUNG | C38: AURICULARES SAMSUNG GALAXY BUDS 3 | D38: 172 | E38: 0 | F38: OC_AURICULARES | I38: 39 | J38: 54 | K38: 78 | L38: 112 | M38: 145 | O38: 79 | P38: 124 | Q38: 190 | R38: 300 | S38: 447 | U38: 82 | V38: 102 | W38: 125 | X38: 142 | Y38: 175 | AA38: 127 | AB38: 157 | AC38: 206 | AD38: 244 | AE38: 244 | AG38: 0 | AH38: 0 | AI38: 0 | AJ38: 0 | AK38: 0 | AM38: 0 | AN38: 0 | AO38: 0 | AP38: 0 | AQ38: 0 | AS38: 90 | AT38: 70 | AU38: 47 | AV38: 30 | AW38: -3 | AY38: 45 | AZ38: 15 | BA38: -34 | BB38: -72 | BC38: -72 | BE38: 82 | BF38: 102 | BG38: 125 | BH38: 142 | BI38: 175 | BK38: 127 | BL38: 157 | BM38: 206 | BN38: 244 | BO38: 244
B39: SAMSUNG | C39: AURICULARES SAMSUNG GALAXY BUDS 3 PRO | D39: 240 | E39: 0 | F39: OC_AURICULARES | I39: 39 | J39: 54 | K39: 125 | L39: 159 | M39: 192 | O39: 79 | P39: 124 | Q39: 237 | R39: 347 | S39: 494 | U39: 103 | V39: 123 | W39: 146 | X39: 163 | Y39: 196 | AA39: 148 | AB39: 178 | AC39: 227 | AD39: 292 | AE39: 308 | AG39: 0 | AH39: 0 | AI39: 0 | AJ39: 0 | AK39: 0 | AM39: 0 | AN39: 0 | AO39: 0 | AP39: 0 | AQ39: 0 | AS39: 137 | AT39: 117 | AU39: 94 | AV39: 77 | AW39: 44 | AY39: 92 | AZ39: 62 | BA39: 13 | BB39: -52 | BC39: -67.5 | BE39: 103 | BF39: 123 | BG39: 146 | BH39: 163 | BI39: 196 | BK39: 148 | BL39: 178 | BM39: 227 | BN39: 292 | BO39: 308
B40: SPC | C40: AURICULARES SPC BRAVE PRO | D40: 44 | E40: 0 | F40: OC_AURICULARES | I40: 39 | J40: 54 | K40: 145 | L40: 179 | M40: 212 | O40: 79 | P40: 124 | Q40: 257 | R40: 367 | S40: 514 | U40: 44 | V40: 44 | W40: 44 | X40: 44 | Y40: 44 | AA40: 44 | AB40: 44 | AC40: 44 | AD40: 44 | AE40: 44 | AG40: 0 | AH40: 0 | AI40: 0 | AJ40: 0 | AK40: 0 | AM40: 0 | AN40: 0 | AO40: 0 | AP40: 0 | AQ40: 0 | AS40: 0 | AT40: 0 | AU40: 0 | AV40: 0 | AW40: 0 | AY40: 0 | AZ40: 0 | BA40: 0 | BB40: 0 | BC40: 0 | BE40: 44 | BF40: 44 | BG40: 44 | BH40: 44 | BI40: 44 | BK40: 44 | BL40: 44 | BM40: 44 | BN40: 44 | BO40: 44
B41: SPC | C41: AURICULARES SPC DREAMER PRO | D41: 77 | E41: 0 | F41: OC_AURICULARES | I41: 39 | J41: 54 | K41: 124 | L41: 158 | M41: 191 | O41: 79 | P41: 124 | Q41: 236 | R41: 346 | S41: 493 | U41: 77 | V41: 77 | W41: 77 | X41: 77 | Y41: 77 | AA41: 77 | AB41: 77 | AC41: 77 | AD41: 77 | AE41: 77 | AG41: 0 | AH41: 0 | AI41: 0 | AJ41: 0 | AK41: 0 | AM41: 0 | AN41: 0 | AO41: 0 | AP41: 0 | AQ41: 0 | AS41: 0 | AT41: 0 | AU41: 0 | AV41: 0 | AW41: 0 | AY41: 0 | AZ41: 0 | BA41: 0 | BB41: 0 | BC41: 0 | BE41: 77 | BF41: 77 | BG41: 77 | BH41: 77 | BI41: 77 | BK41: 77 | BL41: 77 | BM41: 77 | BN41: 77 | BO41: 77
B42: XIAOMI | C42: AURICULARES XIAOMI BUDS 5 | D42: 93 | E42: 0 | F42: OC_AURICULARES | I42: 39 | J42: 54 | K42: 124 | L42: 158 | M42: 191 | O42: 79 | P42: 124 | Q42: 236 | R42: 346 | S42: 492 | U42: 52 | V42: 72 | W42: 95 | X42: 112 | Y42: 145 | AA42: 97 | AB42: 127 | AC42: 176 | AD42: 173 | AE42: 173 | AG42: 0 | AH42: 0 | AI42: 0 | AJ42: 0 | AK42: 0 | AM42: 0 | AN42: 0 | AO42: 0 | AP42: 0 | AQ42: 0 | AS42: 41 | AT42: 21 | AU42: -2 | AV42: -19 | AW42: -52 | AY42: -4 | AZ42: -34 | BA42: -83 | BB42: -79.78 | BC42: -79.78 | BE42: 52 | BF42: 72 | BG42: 95 | BH42: 112 | BI42: 145 | BK42: 97 | BL42: 127 | BM42: 176 | BN42: 173 | BO42: 173
... B55: HONOR | C55: HONOR MAGIC6 PRO 5G | D55: 1074 | E55: 3.25 | F55: SMARTPHONE | I55: 39 | J55: 54 | K55: 123 | L55: 157 | M55: 190 | O55: 79 | P55: 124 | Q55: 236 | R55: 346 | S55: 492 | U55: 52 | V55: 444 | W55: 467 | X55: 484 | Y55: 517 | AA55: 97 | AB55: 499 | AC55: 548 | AD55: 613 | AE55: 725 | AG55: 0 | AH55: 0 | AI55: 0 | AJ55: 0 | AK55: 0 | AM55: 0 | AN55: 0 | AO55: 0 | AP55: 0 | AQ55: 0 | AS55: 1022 | AT55: 630.25 | AU55: 607.25 | AV55: 590.25 | AW55: 557.25 | AY55: 977 | AZ55: 575.25 | BA55: 526.25 | BB55: 461.25 | BC55: 349.25 | BE55: 52 | BF55: 444 | BG55: 467 | BH55: 484 | BI55: 517 | BK55: 97 | BL55: 529 | BM55: 598 | BN55: 653 | BO55: 785
B56: HONOR | C56: HONOR PAD X8a 11" 4+128GB WIFI | D56: 137 | E56: 3.75 | F56: TABLETS | I56: 39 | J56: 54 | K56: 96 | L56: 130 | M56: 163 | O56: 79 | P56: 124 | Q56: 208 | R56: 318 | S56: 465 | U56: 52 | V56: 72 | W56: 95 | X56: 112 | Y56: 145 | AA56: 97 | AB56: 127 | AC56: 176 | AD56: 223 | AE56: 223 | AG56: #N/A | AH56: #N/A | AI56: #N/A | AJ56: #N/A | AK56: #N/A | AM56: #N/A | AN56: #N/A | AO56: #N/A | AP56: #N/A | AQ56: #N/A | AS56: 85 | AT56: 65 | AU56: 42 | AV56: 25 | AW56: -8 | AY56: 40 | AZ56: 10 | BA56: -39 | BB56: -86.375 | BC56: -86.375 | BE56: 52 | BF56: 72 | BG56: 95 | BH56: 112 | BI56: 145 | BK56: 97 | BL56: 127 | BM56: 176 | BN56: 223 | BO56: 223
B57: HONOR | C57: HONOR PAD X9 WIFI | D57: 204 | E57: 3.75 | F57: TABLET | I57: 39 | J57: 54 | K57: 198 | L57: 232 | M57: 265 | O57: 79 | P57: 124 | Q57: 310 | R57: 420 | S57: 567 | U57: 81 | V57: 101 | W57: 124 | X57: 141 | Y57: 174 | AA57: 126 | AB57: 156 | AC57: 205 | AD57: 270 | AE57: 270 | AG57: 0 | AH57: 0 | AI57: 0 | AJ57: 0 | AK57: 0 | AM57: 0 | AN57: 0 | AO57: 0 | AP57: 0 | AQ57: 0 | AS57: 122.75 | AT57: 102.75 | AU57: 79.75 | AV57: 62.75 | AW57: 29.75 | AY57: 77.75 | AZ57: 47.75 | BA57: -1.25 | BB57: -66.25 | BC57: -66.25 | BE57: 81 | BF57: 101 | BG57: 124 | BH57: 141 | BI57: 174 | BK57: 126 | BL57: 156 | BM57: 205 | BN57: 270 | BO57: 270
B58: HUAWEI | C58: HUAWEI PC MATEBOOK D 14" I5 12 GEN | D58: 751 | E58: 5.33 | F58: PC | I58: 39 | J58: 54 | K58: 92 | L58: 126 | M58: 159 | O58: 79 | P58: 124 | Q58: 204 | R58: 314 | S58: 460 | U58: 52 | V58: 268 | W58: 291 | X58: 308 | Y58: 341 | AA58: 97 | AB58: 323 | AC58: 372 | AD58: 437 | AE58: 549 | AG58: 0 | AH58: 0 | AI58: 0 | AJ58: 0 | AK58: 0 | AM58: 0 | AN58: 0 | AO58: 0 | AP58: 20 | AQ58: 20 | AS58: 699 | AT58: 483.33 | AU58: 460.33 | AV58: 443.33 | AW58: 410.33 | AY58: 654 | AZ58: 428.33 | BA58: 379.33 | BB58: 314.33 | BC58: 202.33 | BE58: 52 | BF58: 268 | BG58: 291 | BH58: 308 | BI58: 341 | BK58: 97 | BL58: 353 | BM58: 422 | BN58: 477 | BO58: 609
B59: HUAWEI | C59: HUAWEI PC MATEBOOK D 16" I5 12 GEN | D59: 915 | E59: 5.33 | F59: PC | I59: 39 | J59: 54 | K59: 78 | L59: 112 | M59: 145 | O59: 79 | P59: 124 | Q59: 190 | R59: 300 | S59: 447 | U59: 52 | V59: 372 | W59: 395 | X59: 412 | Y59: 445 | AA59: 97 | AB59: 427 | AC59: 476 | AD59: 561 | AE59: 673 | AG59: 0 | AH59: 0 | AI59: 0 | AJ59: 0 | AK59: 0 | AM59: 0 | AN59: 0 | AO59: 0 | AP59: 0 | AQ59: 0 | AS59: 863 | AT59: 543.33 | AU59: 520.33 | AV59: 503.33 | AW59: 470.33 | AY59: 818 | AZ59: 488.33 | BA59: 439.33 | BB59: 354.33 | BC59: 242.33 | BE59: 52 | BF59: 372 | BG59: 395 | BH59: 412 | BI59: 445 | BK59: 97 | BL59: 457 | BM59: 526 | BN59: 601 | BO59: 733
B60: APPLE | C60: IPAD 10a GEN 64GB 2024 WIFI | D60: 367 | E60: 3.75 | F60: TABLETS | I60: 39 | J60: 54 | K60: 271 | L60: 305 | M60: 338 | O60: 79 | P60: 124 | Q60: 378 | R60: 483 | S60: 625 | U60: 88 | V60: 108 | W60: 131 | X60: 148 | Y60: 181 | AA60: 133 | AB60: 163 | AC60: 212 | AD60: 277 | AE60: 389 | AG60: #N/A | AH60: #N/A | AI60: #N/A | AJ60: #N/A | AK60: #N/A | AM60: #N/A | AN60: #N/A | AO60: #N/A | AP60: #N/A | AQ60: #N/A | AS60: 278.95 | AT60: 258.95 | AU60: 235.95 | AV60: 218.95 | AW60: 185.95 | AY60: 233.95 | AZ60: 203.95 | BA60: 154.95 | BB60: 89.95 | BC60: -22.05 | BE60: 88 | BF60: 108 | BG60: 131 | BH60: 148 | BI60: 181 | BK60: 133 | BL60: 193 | BM60: 253 | BN60: 317 | BO60: 430
B61: APPLE | C61: IPAD AIR M2 WIFI 11" 128GB | D61: 623 | E61: 3.75 | F61: TABLET | I61: 39 | J61: 54 | K61: 279 | L61: 313 | M61: 346 | O61: 79 | P61: 124 | Q61: 386 | R61: 491 | S61: 633 | U61: 52 | V61: 139 | W61: 162 | X61: 179 | Y61: 212 | AA61: 97 | AB61: 194 | AC61: 243 | AD61: 308 | AE61: 420 | AG61: 0 | AH61: 0 | AI61: 0 | AJ61: 0 | AK61: 0 | AM61: 0 | AN61: 0 | AO61: 0 | AP61: 0 | AQ61: 0 | AS61: 571 | AT61: 483.99 | AU61: 460.99 | AV61: 443.99 | AW61: 410.99 | AY61: 526 | AZ61: 428.99 | BA61: 379.99 | BB61: 314.99 | BC61: 202.99 | BE61: 52 | BF61: 139 | BG61: 162 | BH61: 179 | BI61: 212 | BK61: 97 | BL61: 224 | BM61: 293 | BN61: 348 | BO61: 480
B62: APPLE | C62: IPAD AIR M2 WIFI 13" 128GB | D62: 847 | E62: 3.75 | F62: TABLET | I62: 39 | J62: 54 | K62: 268 | L62: 302 | M62: 335 | O62: 79 | P62: 124 | Q62: 375 | R62: 480 | S62: 622 | U62: 52 | V62: 179 | W62: 202 | X62: 219 | Y62: 252 | AA62: 97 | AB62: 234 | AC62: 283 | AD62: 348 | AE62: 460 | AG62: 0 | AH62: 0 | AI62: 0 | AJ62: 0 | AK62: 0 | AM62: 0 | AN62: 0 | AO62: 0 | AP62: 0 | AQ62: 0 | AS62: 795 | AT62: 668.39 | AU62: 645.39 | AV62: 628.39 | AW62: 595.39 | AY62: 750 | AZ62: 613.39 | BA62: 564.39 | BB62: 499.39 | BC62: 387.39 | BE62: 52 | BF62: 179 | BG62: 202 | BH62: 219 | BI62: 252 | BK62: 97 | BL62: 264 | BM62: 333 | BN62: 388 | BO62: 520
B63: APPLE | C63: IPAD PRO M4 WIFI 11" 256GB | D63: 1044 | E63: 3.75 | F63: TABLET | I63: 39 | J63: 54 | K63: 186 | L63: 220 | M63: 253 | O63: 79 | P63: 124 | Q63: 293 | R63: 398 | S63: 540 | U63: 52 | V63: 191 | W63: 214 | X63: 231 | Y63: 264 | AA63: 97 | AB63: 246 | AC63: 295 | AD63: 360 | AE63: 472 | AG63: 0 | AH63: 0 | AI63: 0 | AJ63: 0 | AK63: 0 | AM63: 0 | AN63: 0 | AO63: 0 | AP63: 0 | AQ63: 0 | AS63: 992 | AT63: 852.79 | AU63: 829.79 | AV63: 812.79 | AW63: 779.79 | AY63: 947 | AZ63: 797.79 | BA63: 748.79 | BB63: 683.79 | BC63: 571.79 | BE63: 52 | BF63: 191 | BG63: 214 | BH63: 231 | BI63: 264 | BK63: 97 | BL63: 276 | BM63: 345 | BN63: 400 | BO63: 532
B64: APPLE | C64: IPHONE 14 128GB CON 5G | D64: 920 | E64: 3.25 | F64: SMARTPHONE | I64: 39 | J64: 54 | K64: 183 | L64: 217 | M64: 250 | O64: 79 | P64: 124 | Q64: 290 | R64: 395 | S64: 537 | U64: 52 | V64: 397 | W64: 420 | X64: 437 | Y64: 470 | AA64: 97 | AB64: 452 | AC64: 496 | AD64: 556 | AE64: 663 | AG64: 0 | AH64: 0 | AI64: 0 | AJ64: 0 | AK64: 0 | AM64: 0 | AN64: 0 | AO64: 0 | AP64: 0 | AQ64: 0 | AS64: 868 | AT64: 523.25 | AU64: 500.25 | AV64: 483.25 | AW64: 450.25 | AY64: 823 | AZ64: 468.25 | BA64: 424.25 | BB64: 364.25 | BC64: 257.25 | BE64: 52 | BF64: 397 | BG64: 420 | BH64: 437 | BI64: 470 | BK64: 97 | BL64: 482 | BM64: 546 | BN64: 596 | BO64: 723
B65: APPLE | C65: IPHONE 15 128GB CON 5G | D65: 883 | E65: 3.25 | F65: SMARTPHONE | I65: 39 | J65: 54 | K65: 195 | L65: 229 | M65: 262 | O65: 79 | P65: 124 | Q65: 302 | R65: 407 | S65: 549 | U65: 52 | V65: 306 | W65: 329 | X65: 346 | Y65: 379 | AA65: 97 | AB65: 361 | AC65: 410 | AD65: 465 | AE65: 572 | AG65: 0 | AH65: -38 | AI65: -38 | AJ65: -38 | AK65: -38 | AM65: 0 | AN65: -38 | AO65: -38 | AP65: 19 | AQ65: 12 | AS65: 831 | AT65: 577.25 | AU65: 554.25 | AV65: 537.25 | AW65: 504.25 | AY65: 786 | AZ65: 522.25 | BA65: 473.25 | BB65: 418.25 | BC65: 311.25 | BE65: 52 | BF65: 306 | BG65: 329 | BH65: 346 | BI65: 379 | BK65: 97 | BL65: 391 | BM65: 460 | BN65: 505 | BO65: 632
B66: APPLE | C66: IPHONE 16 128GB CON 5G | D66: 883 | E66: 3.25 | F66: SMARTPHONE | I66: 39 | J66: 54 | K66: 192 | L66: 226 | M66: 259 | O66: 79 | P66: 124 | Q66: 299 | R66: 404 | S66: 546 | U66: 52 | V66: 230 | W66: 253 | X66: 270 | Y66: 303 | AA66: 97 | AB66: 285 | AC66: 329 | AD66: 389 | AE66: 496 | AG66: 0 | AH66: -38 | AI66: -38 | AJ66: -38 | AK66: -38 | AM66: 0 | AN66: -38 | AO66: -38 | AP66: -38 | AQ66: -38 | AS66: 831 | AT66: 653.25 | AU66: 630.25 | AV66: 613.25 | AW66: 580.25 | AY66: 786 | AZ66: 598.25 | BA66: 554.25 | BB66: 494.25 | BC66: 387.25 | BE66: 52 | BF66: 230 | BG66: 253 | BH66: 270 | BI66: 303 | BK66: 97 | BL66: 315 | BM66: 379 | BN66: 429 | BO66: 556
B67: APPLE | C67: IPHONE 16 256GB CON 5G | D67: 983 | E67: 3.25 | F67: SMARTPHONE | I67: 39 | J67: 54 | K67: 184 | L67: 218 | M67: 251 | O67: 79 | P67: 124 | Q67: 291 | R67: 396 | S67: 538 | U67: 52 | V67: 230 | W67: 253 | X67: 270 | Y67: 303 | AA67: 97 | AB67: 285 | AC67: 329 | AD67: 389 | AE67: 496 | AG67: 0 | AH67: -38 | AI67: -38 | AJ67: -38 | AK67: -38 | AM67: 0 | AN67: -38 | AO67: -38 | AP67: -38 | AQ67: -38 | AS67: 931 | AT67: 753.25 | AU67: 730.25 | AV67: 713.25 | AW67: 680.25 | AY67: 886 | AZ67: 698.25 | BA67: 654.25 | BB67: 594.25 | BC67: 487.25 | BE67: 52 | BF67: 230 | BG67: 253 | BH67: 270 | BI67: 303 | BK67: 97 | BL67: 315 | BM67: 379 | BN67: 429 | BO67: 556
B68: APPLE | C68: IPHONE 16 PLUS 128GB CON 5G | D68: 998 | E68: 3.25 | F68: SMARTPHONE | I68: 39 | J68: 54 | K68: 198 | L68: 232 | M68: 265 | O68: 79 | P68: 124 | Q68: 305 | R68: 410 | S68: 552 | U68: 52 | V68: 230 | W68: 253 | X68: 270 | Y68: 303 | AA68: 97 | AB68: 285 | AC68: 329 | AD68: 389 | AE68: 496 | AG68: 0 | AH68: -38 | AI68: -38 | AJ68: -38 | AK68: -38 | AM68: 0 | AN68: -38 | AO68: -38 | AP68: -38 | AQ68: -38 | AS68: 946 | AT68: 768.25 | AU68: 745.25 | AV68: 728.25 | AW68: 695.25 | AY68: 901 | AZ68: 713.25 | BA68: 669.25 | BB68: 609.25 | BC68: 502.25 | BE68: 52 | BF68: 230 | BG68: 253 | BH68: 270 | BI68: 303 | BK68: 97 | BL68: 315 | BM68: 379 | BN68: 429 | BO68: 556
B69: APPLE | C69: IPHONE 16 PLUS 256GB CON 5G | D69: 1097 | E69: 3.25 | F69: SMARTPHONE | I69: 39 | J69: 54 | K69: 184 | L69: 218 | M69: 251 | O69: 79 | P69: 124 | Q69: 291 | R69: 396 | S69: 538 | U69: 52 | V69: 230 | W69: 253 | X69: 270 | Y69: 303 | AA69: 97 | AB69: 285 | AC69: 329 | AD69: 389 | AE69: 496 | AG69: 0 | AH69: -38 | AI69: -38 | AJ69: -38 | AK69: -38 | AM69: 0 | AN69: -38 | AO69: -38 | AP69: -38 | AQ69: -38 | AS69: 1045 | AT69: 867.25 | AU69: 844.25 | AV69: 827.25 | AW69: 794.25 | AY69: 1000 | AZ69: 812.25 | BA69: 768.25 | BB69: 708.25 | BC69: 601.25 | BE69: 52 | BF69: 230 | BG69: 253 | BH69: 270 | BI69: 303 | BK69: 97 | BL69: 315 | BM69: 379 | BN69: 429 | BO69: 556
B70: APPLE | C70: IPHONE 16 PRO 128GB CON 5G | D70: 1074 | E70: 3.25 | F70: SMARTPHONE | I70: 39 | J70: 54 | K70: 184 | L70: 218 | M70: 251 | O70: 79 | P70: 124 | Q70: 291 | R70: 396 | S70: 538 | U70: 52 | V70: 232 | W70: 255 | X70: 272 | Y70: 305 | AA70: 97 | AB70: 287 | AC70: 331 | AD70: 391 | AE70: 498 | AG70: 0 | AH70: -40 | AI70: -40 | AJ70: -40 | AK70: -40 | AM70: 0 | AN70: -40 | AO70: -40 | AP70: -40 | AQ70: -40 | AS70: 1022 | AT70: 842.25 | AU70: 819.25 | AV70: 802.25 | AW70: 769.25 | AY70: 977 | AZ70: 787.25 | BA70: 743.25 | BB70: 683.25 | BC70: 576.25 | BE70: 52 | BF70: 232 | BG70: 255 | BH70: 272 | BI70: 305 | BK70: 97 | BL70: 317 | BM70: 381 | BN70: 431 | BO70: 558
B71: APPLE | C71: IPHONE 16 PRO 256GB CON 5G | D71: 1174 | E71: 3.25 | F71: SMARTPHONE | I71: 39 | J71: 54 | K71: 198 | L71: 232 | M71: 265 | O71: 79 | P71: 124 | Q71: 305 | R71: 410 | S71: 552 | U71: 52 | V71: 232 | W71: 255 | X71: 272 | Y71: 305 | AA71: 97 | AB71: 287 | AC71: 331 | AD71: 391 | AE71: 498 | AG71: 0 | AH71: -40 | AI71: -40 | AJ71: -40 | AK71: -40 | AM71: 0 | AN71: -40 | AO71: -40 | AP71: -40 | AQ71: -40 | AS71: 1122 | AT71: 942.25 | AU71: 919.25 | AV71: 902.25 | AW71: 869.25 | AY71: 1077 | AZ71: 887.25 | BA71: 843.25 | BB71: 783.25 | BC71: 676.25 | BE71: 52 | BF71: 232 | BG71: 255 | BH71: 272 | BI71: 305 | BK71: 97 | BL71: 317 | BM71: 381 | BN71: 431 | BO71: 558
B72: APPLE | C72: IPHONE 16 PRO MAX 256 CON 5G | D72: 1265 | E72: 3.25 | F72: SMARTPHONE | I72: 39 | J72: 54 | K72: 198 | L72: 232 | M72: 265 | O72: 79 | P72: 124 | Q72: 305 | R72: 410 | S72: 552 | U72: 52 | V72: 232 | W72: 255 | X72: 272 | Y72: 305 | AA72: 97 | AB72: 287 | AC72: 331 | AD72: 391 | AE72: 498 | AG72: 0 | AH72: -40 | AI72: -40 | AJ72: -40 | AK72: -40 | AM72: 0 | AN72: -40 | AO72: -40 | AP72: -40 | AQ72: -40 | AS72: 1213 | AT72: 1033.25 | AU72: 1010.25 | AV72: 993.25 | AW72: 960.25 | AY72: 1168 | AZ72: 978.25 | BA72: 934.25 | BB72: 874.25 | BC72: 767.25 | BE72: 52 | BF72: 232 | BG72: 255 | BH72: 272 | BI72: 305 | BK72: 97 | BL72: 317 | BM72: 381 | BN72: 431 | BO72: 558
... B91: MOTOROLA | C91: MOTOROLA MOTO G34 5G | D91: 177 | E91: 3.25 | F91: SMARTPHONE | I91: 39 | J91: 54 | K91: 164 | L91: 198 | M91: 231 | O91: 79 | P91: 124 | Q91: 276 | R91: 386 | S91: 533 | U91: 109 | V91: 129 | W91: 152 | X91: 169 | Y91: 202 | AA91: 154 | AB91: 184 | AC91: 233 | AD91: 238 | AE91: 238 | AG91: 10 | AH91: 10 | AI91: 10 | AJ91: 10 | AK91: 10 | AM91: 10 | AN91: 19 | AO91: 19 | AP91: 4 | AQ91: 13 | AS91: 67.71 | AT91: 47.71 | AU91: 24.71 | AV91: 7.71 | AW91: -25.29 | AY91: 22.71 | AZ91: -7.29 | BA91: -56.29 | BB91: -60.855 | BC91: -60.855 | BE91: 109 | BF91: 129 | BG91: 152 | BH91: 169 | BI91: 202 | BK91: 154 | BL91: 184 | BM91: 233 | BN91: 238 | BO91: 238
B92: MOTOROLA | C92: MOTOROLA MOTO G35 128GB 5G | D92: 183 | E92: 3.25 | F92: SMARTPHONE | I92: 39 | J92: 54 | K92: 195 | L92: 229 | M92: 262 | O92: 79 | P92: 124 | Q92: 307 | R92: 417 | S92: 564 | U92: 99 | V92: 119 | W92: 142 | X92: 159 | Y92: 192 | AA92: 144 | AB92: 174 | AC92: 223 | AD92: 252 | AE92: 252 | AG92: #N/A | AH92: #N/A | AI92: #N/A | AJ92: #N/A | AK92: #N/A | AM92: #N/A | AN92: #N/A | AO92: #N/A | AP92: #N/A | AQ92: #N/A | AS92: 83.79 | AT92: 63.79 | AU92: 40.79 | AV92: 23.79 | AW92: -9.21 | AY92: 38.79 | AZ92: 8.79 | BA92: -40.21 | BB92: -68.895 | BC92: -68.895 | BE92: 99 | BF92: 119 | BG92: 142 | BH92: 159 | BI92: 192 | BK92: 144 | BL92: 174 | BM92: 223 | BN92: 252 | BO92: 252
B93: MOTOROLA | C93: MOTOROLA MOTO G54 256GB 5G | D93: 199 | E93: 3.25 | F93: SMARTPHONE | I93: 39 | J93: 54 | K93: 258 | L93: 292 | M93: 325 | O93: 79 | P93: 124 | Q93: 370 | R93: 480 | S93: 627 | U93: 91 | V93: 111 | W93: 134 | X93: 151 | Y93: 184 | AA93: 136 | AB93: 166 | AC93: 215 | AD93: 280 | AE93: 280 | AG93: 15 | AH93: 15 | AI93: 15 | AJ93: 15 | AK93: 15 | AM93: 15 | AN93: 23 | AO93: 23 | AP93: 1 | AQ93: 9 | AS93: 108.49 | AT93: 88.49 | AU93: 65.49 | AV93: 48.49 | AW93: 15.49 | AY93: 63.49 | AZ93: 33.49 | BA93: -15.51 | BB93: -80.51 | BC93: -80.51 | BE93: 91 | BF93: 111 | BG93: 134 | BH93: 151 | BI93: 184 | BK93: 136 | BL93: 166 | BM93: 215 | BN93: 280 | BO93: 280
B94: MOTOROLA | C94: MOTOROLA MOTO G55 256GB 5G | D94: 255 | E94: 3.25 | F94: SMARTPHONE | I94: 79 | J94: 124 | K94: 165 | L94: 165 | M94: 165 | O94: 79 | P94: 124 | Q94: 165 | R94: 165 | S94: 165 | U94: 128 | V94: 148 | W94: 171 | X94: 188 | Y94: 221 | AA94: 173 | AB94: 203 | AC94: 252 | AD94: 317 | AE94: 317 | AG94: -20 | AH94: -20 | AI94: -20 | AJ94: -20 | AK94: -20 | AM94: -20 | AN94: -20 | AO94: -20 | AP94: -20 | AQ94: 10 | AS94: 126.75 | AT94: 106.75 | AU94: 83.75 | AV94: 66.75 | AW94: 33.75 | AY94: 81.75 | AZ94: 51.75 | BA94: 2.75 | BB94: -62.25 | BC94: -62.375 | BE94: 128 | BF94: 148 | BG94: 171 | BH94: 188 | BI94: 221 | BK94: 173 | BL94: 203 | BM94: 252 | BN94: 317 | BO94: 317
B95: MOTOROLA | C95: MOTOROLA MOTO G85 256GB 5G | D95: 353 | E95: 3.25 | F95: SMARTPHONE | I95: 97 | J95: 97 | K95: 97 | L95: 97 | M95: 97 | O95: 97 | P95: 97 | Q95: 97 | R95: 97 | S95: 97 | U95: 128 | V95: 148 | W95: 171 | X95: 188 | Y95: 221 | AA95: 173 | AB95: 203 | AC95: 252 | AD95: 353 | AE95: 429 | AG95: 0 | AH95: 0 | AI95: 0 | AJ95: 0 | AK95: 0 | AM95: 0 | AN95: 0 | AO95: 0 | AP95: 0 | AQ95: 0 | AS95: 225.26 | AT95: 205.26 | AU95: 182.26 | AV95: 165.26 | AW95: 132.26 | AY95: 180.26 | AZ95: 150.26 | BA95: 101.26 | BB95: 0.26 | BC95: -75.74 | BE95: 128 | BF95: 148 | BG95: 171 | BH95: 188 | BI95: 221 | BK95: 173 | BL95: 203 | BM95: 252 | BN95: 353 | BO95: 429
B96: MOTOROLA | C96: MOTOROLA MOTO THINKPHONE 25 256GB 5G | D96: 481 | E96: 3.25 | F96: SMARTPHONE | I96: 60 | J96: 75 | K96: 99 | L96: 133 | M96: 166 | O96: 100 | P96: 145 | Q96: 211 | R96: 305 | S96: 311 | U96: 198 | V96: 218 | W96: 241 | X96: 258 | Y96: 291 | AA96: 243 | AB96: 273 | AC96: 322 | AD96: 432 | AE96: 499 | AG96: -20 | AH96: -20 | AI96: -20 | AJ96: -20 | AK96: -20 | AM96: -20 | AN96: -20 | AO96: -20 | AP96: -65 | AQ96: -18 | AS96: 283.03 | AT96: 263.03 | AU96: 240.03 | AV96: 223.03 | AW96: 190.03 | AY96: 238.03 | AZ96: 208.03 | BA96: 159.03 | BB96: 49.03 | BC96: -17.97 | BE96: 198 | BF96: 218 | BG96: 241 | BH96: 258 | BI96: 291 | BK96: 243 | BL96: 303 | BM96: 367 | BN96: 472 | BO96: 544
B97: MOTOROLA | C97: MOTOROLA RAZR 50 256GB 5G | D97: 869 | E97: 3.25 | F97: SMARTPHONE | I97: 66 | J97: 81 | K97: 105 | L97: 139 | M97: 172 | O97: 106 | P97: 151 | Q97: 217 | R97: 318 | S97: 325 | U97: 52 | V97: 351 | W97: 374 | X97: 391 | Y97: 424 | AA97: 97 | AB97: 406 | AC97: 455 | AD97: 520 | AE97: 632 | AG97: 0 | AH97: -50 | AI97: -50 | AJ97: -50 | AK97: -50 | AM97: 0 | AN97: -50 | AO97: -50 | AP97: -50 | AQ97: -50 | AS97: 817 | AT97: 517.78 | AU97: 494.78 | AV97: 477.78 | AW97: 444.78 | AY97: 772 | AZ97: 462.78 | BA97: 413.78 | BB97: 348.78 | BC97: 236.78 | BE97: 52 | BF97: 351 | BG97: 374 | BH97: 391 | BI97: 424 | BK97: 97 | BL97: 436 | BM97: 505 | BN97: 560 | BO97: 692
B98: OPPO | C98: OPPO A40 128GB | D98: 160 | E98: 3.25 | F98: SMARTPHONE | I98: 80 | J98: 95 | K98: 119 | L98: 153 | M98: 186 | O98: 121 | P98: 165 | Q98: 232 | R98: 342 | S98: 394 | U98: 102 | V98: 122 | W98: 145 | X98: 162 | Y98: 195 | AA98: 147 | AB98: 177 | AC98: 226 | AD98: 216 | AE98: 216 | AG98: 0 | AH98: 0 | AI98: 0 | AJ98: 0 | AK98: 0 | AM98: 0 | AN98: 0 | AO98: 0 | AP98: 0 | AQ98: 0 | AS98: 57.98 | AT98: 37.98 | AU98: 14.98 | AV98: -2.02 | AW98: -35.02 | AY98: 12.98 | AZ98: -17.02 | BA98: -66.02 | BB98: -55.99 | BC98: -55.99 | BE98: 102 | BF98: 122 | BG98: 145 | BH98: 162 | BI98: 195 | BK98: 147 | BL98: 177 | BM98: 226 | BN98: 216 | BO98: 216
B99: OPPO | C99: OPPO A60 128GB 5G | D99: 176 | E99: 3.25 | F99: SMARTPHONE | I99: 78 | J99: 93 | K99: 117 | L99: 151 | M99: 184 | O99: 119 | P99: 163 | Q99: 230 | R99: 340 | S99: 356 | U99: 108 | V99: 128 | W99: 151 | X99: 168 | Y99: 201 | AA99: 153 | AB99: 183 | AC99: 232 | AD99: 237 | AE99: 237 | AG99: -5 | AH99: -5 | AI99: -5 | AJ99: -5 | AK99: -5 | AM99: -5 | AN99: -5 | AO99: -5 | AP99: 3 | AQ99: 3 | AS99: 68.18 | AT99: 48.18 | AU99: 25.18 | AV99: 8.18 | AW99: -24.82 | AY99: 23.18 | AZ99: -6.82 | BA99: -55.82 | BB99: -61.09 | BC99: -61.09 | BE99: 108 | BF99: 128 | BG99: 151 | BH99: 168 | BI99: 201 | BK99: 153 | BL99: 183 | BM99: 232 | BN99: 237 | BO99: 237
B100: OPPO | C100: OPPO A80 256GB 5G | D100: 245 | E100: 3.25 | F100: SMARTPHONE | I100: 85 | J100: 100 | K100: 124 | L100: 158 | M100: 191 | O100: 125 | P100: 170 | Q100: 236 | R100: 346 | S100: 446 | U100: 132 | V100: 152 | W100: 175 | X100: 192 | Y100: 225 | AA100: 177 | AB100: 207 | AC100: 256 | AD100: 321 | AE100: 351 | AG100: 0 | AH100: 0 | AI100: 0 | AJ100: 0 | AK100: 0 | AM100: 0 | AN100: 0 | AO100: 0 | AP100: 0 | AQ100: 0 | AS100: 113.32 | AT100: 93.32 | AU100: 70.32 | AV100: 53.32 | AW100: 20.32 | AY100: 68.32 | AZ100: 38.32 | BA100: -10.68 | BB100: -75.68 | BC100: -105.68 | BE100: 132 | BF100: 152 | BG100: 175 | BH100: 192 | BI100: 225 | BK100: 177 | BL100: 207 | BM100: 256 | BN100: 321 | BO100: 351
B101: OPPO | C101: OPPO FIND X8 PRO 512GB 5G | D101: 1072 | E101: 3.25 | F101: SMARTPHONE | I101: 39 | J101: 54 | K101: 184 | L101: 218 | M101: 251 | O101: 79 | P101: 124 | Q101: 297 | R101: 407 | S101: 542 | U101: 52 | V101: 413 | W101: 436 | X101: 453 | Y101: 486 | AA101: 97 | AB101: 468 | AC101: 517 | AD101: 582 | AE101: 694 | AG101: 0 | AH101: -100 | AI101: -100 | AJ101: -100 | AK101: -100 | AM101: 0 | AN101: -100 | AO101: -100 | AP101: -100 | AQ101: -100 | AS101: 1020 | AT101: 659.45 | AU101: 636.45 | AV101: 619.45 | AW101: 586.45 | AY101: 975 | AZ101: 604.45 | BA101: 555.45 | BB101: 490.45 | BC101: 378.45 | BE101: 52 | BF101: 413 | BG101: 436 | BH101: 453 | BI101: 486 | BK101: 97 | BL101: 498 | BM101: 567 | BN101: 622 | BO101: 754
B102: OPPO | C102: OPPO RENO12 256GB 5G | D102: 428 | E102: 3.25 | F102: SMARTPHONE | I102: 39 | J102: 54 | K102: 165 | L102: 199 | M102: 232 | O102: 79 | P102: 124 | Q102: 277 | R102: 387 | S102: 534 | U102: 209 | V102: 229 | W102: 252 | X102: 269 | Y102: 302 | AA102: 254 | AB102: 284 | AC102: 333 | AD102: 428 | AE102: 510 | AG102: 0 | AH102: 0 | AI102: 0 | AJ102: 0 | AK102: 0 | AM102: 0 | AN102: 0 | AO102: 0 | AP102: 0 | AQ102: 0 | AS102: 219.39 | AT102: 199.39 | AU102: 176.39 | AV102: 159.39 | AW102: 126.39 | AY102: 174.39 | AZ102: 144.39 | BA102: 95.39 | BB102: 0.39 | BC102: -81.61 | BE102: 209 | BF102: 229 | BG102: 252 | BH102: 269 | BI102: 302 | BK102: 254 | BL102: 284 | BM102: 333 | BN102: 428 | BO102: 510
B103: OPPO | C103: OPPO RENO12 FS 512GB 5G | D103: 364 | E103: 3.25 | F103: SMARTPHONE | I103: 39 | J103: 54 | K103: 248 | L103: 282 | M103: 315 | O103: 79 | P103: 124 | Q103: 360 | R103: 470 | S103: 617 | U103: 158 | V103: 178 | W103: 201 | X103: 218 | Y103: 251 | AA103: 203 | AB103: 233 | AC103: 282 | AD103: 347 | AE103: 459 | AG103: 10 | AH103: 10 | AI103: 10 | AJ103: 10 | AK103: 10 | AM103: 10 | AN103: 10 | AO103: 10 | AP103: 17 | AQ103: 2 | AS103: 206.2 | AT103: 186.2 | AU103: 163.2 | AV103: 146.2 | AW103: 113.2 | AY103: 161.2 | AZ103: 131.2 | BA103: 82.2 | BB103: 17.2 | BC103: -94.8 | BE103: 158 | BF103: 178 | BG103: 201 | BH103: 218 | BI103: 251 | BK103: 203 | BL103: 233 | BM103: 282 | BN103: 347 | BO103: 459
B104: OPPO | C104: OPPO RENO12 PRO 512GB 5G | D104: 524 | E104: 3.25 | F104: SMARTPHONE | I104: 39 | J104: 54 | K104: 312 | L104: 346 | M104: 379 | O104: 79 | P104: 124 | Q104: 425 | R104: 535 | S104: 681 | U104: 214 | V104: 234 | W104: 257 | X104: 274 | Y104: 307 | AA104: 259 | AB104: 289 | AC104: 338 | AD104: 403 | AE104: 524 | AG104: 0 | AH104: 0 | AI104: 0 | AJ104: 0 | AK104: 0 | AM104: 0 | AN104: 0 | AO104: 0 | AP104: 0 | AQ104: 0 | AS104: 310.42 | AT104: 290.42 | AU104: 267.42 | AV104: 250.42 | AW104: 217.42 | AY104: 265.42 | AZ104: 235.42 | BA104: 186.42 | BB104: 121.42 | BC104: 0.42 | BE104: 214 | BF104: 234 | BG104: 257 | BH104: 274 | BI104: 307 | BK104: 259 | BL104: 319 | BM104: 388 | BN104: 443 | BO104: 584
B105: ORANGE | C105: ORANGE GAMA 120 4G | D105: 74 | E105: 1.1 | F105: FIXED STYLE | I105: 39 | J105: 54 | K105: 338 | L105: 372 | M105: 405 | O105: 79 | P105: 124 | Q105: 450 | R105: 560 | S105: 707 | U105: 74 | V105: 74 | W105: 74 | X105: 74 | Y105: 74 | AA105: 74 | AB105: 0 | AC105: 0 | AD105: 0 | AE105: 0 | AG105: 0 | AH105: 0 | AI105: 0 | AJ105: 0 | AK105: 0 | AM105: 0 | AN105: 0 | AO105: 0 | AP105: 0 | AQ105: 0 | AS105: 0 | AT105: 0 | AU105: 0 | AV105: 0 | AW105: 0 | AY105: 0 | AZ105: - | BA105: - | BB105: - | BC105: - | BE105: 74 | BF105: 74 | BG105: 74 | BH105: 74 | BI105: 74 | BK105: 74 | BL105: 0 | BM105: 0 | BN105: 0 | BO105: 0
B106: ORANGE | C106: ORANGE GAMA 402 | D106: 70 | E106: 1.1 | F106: FIXED STYLE | I106: 39 | J106: 54 | K106: 274 | L106: 308 | M106: 341 | O106: 79 | P106: 124 | Q106: 387 | R106: 497 | S106: 643 | U106: 70 | V106: 0 | W106: 0 | X106: 0 | Y106: 0 | AA106: 70 | AB106: 0 | AC106: 0 | AD106: 0 | AE106: 0 | AG106: 0 | AH106: 0 | AI106: 0 | AJ106: 0 | AK106: 0 | AM106: 0 | AN106: 0 | AO106: 0 | AP106: 0 | AQ106: 0 | AS106: 0 | AT106: - | AU106: - | AV106: - | AW106: - | AY106: 0 | AZ106: - | BA106: - | BB106: - | BC106: - | BE106: 70 | BF106: 0 | BG106: 0 | BH106: 0 | BI106: 0 | BK106: 70 | BL106: 0 | BM106: 0 | BN106: 0 | BO106: 0
B107: ORANGE | C107: ORANGE GAMA 402 CESIÓN | D107: 0 | E107: 1.1 | F107: FIXED STYLE | I107: 71 | J107: 0 | K107: 0 | L107: 0 | M107: 0 | O107: 71 | P107: 0 | Q107: 0 | R107: 0 | S107: 0 | U107: 0 | V107: 0 | W107: 0 | X107: 0 | Y107: 0 | AA107: 0 | AB107: 0 | AC107: 0 | AD107: 0 | AE107: 0 | AG107: 0 | AH107: 0 | AI107: 0 | AJ107: 0 | AK107: 0 | AM107: 0 | AN107: 0 | AO107: 0 | AP107: 0 | AQ107: 0 | AS107: - | AT107: - | AU107: - | AV107: - | AW107: - | AY107: - | AZ107: - | BA107: - | BB107: - | BC107: - | BE107: 0 | BF107: 0 | BG107: 0 | BH107: 0 | BI107: 0 | BK107: 0 | BL107: 0 | BM107: 0 | BN107: 0 | BO107: 0
B108: ORANGE | C108: ORANGE GAMA 704 | D108: 104 | E108: 1.1 | F108: FIXED STYLE | I108: 32 | J108: 0 | K108: 0 | L108: 0 | M108: 0 | O108: 32 | P108: 0 | Q108: 0 | R108: 0 | S108: 0 | U108: 80 | V108: 0 | W108: 0 | X108: 0 | Y108: 0 | AA108: 80 | AB108: 0 | AC108: 0 | AD108: 0 | AE108: 0 | AG108: 0 | AH108: 0 | AI108: 0 | AJ108: 0 | AK108: 0 | AM108: 0 | AN108: 0 | AO108: 0 | AP108: 0 | AQ108: 0 | AS108: 24 | AT108: - | AU108: - | AV108: - | AW108: - | AY108: 24 | AZ108: - | BA108: - | BB108: - | BC108: - | BE108: 80 | BF108: 0 | BG108: 0 | BH108: 0 | BI108: 0 | BK108: 80 | BL108: 0 | BM108: 0 | BN108: 0 | BO108: 0
B109: ORANGE | C109: ORANGE GAMA 704 CESIÓN | D109: 0 | E109: 1.1 | F109: FIXED STYLE | I109: 0 | J109: 0 | K109: 0 | L109: 0 | M109: 0 | O109: 0 | P109: 0 | Q109: 0 | R109: 0 | S109: 0 | U109: 0 | V109: 0 | W109: 0 | X109: 0 | Y109: 0 | AA109: 0 | AB109: 0 | AC109: 0 | AD109: 0 | AE109: 0 | AG109: 0 | AH109: 0 | AI109: 0 | AJ109: 0 | AK109: 0 | AM109: 0 | AN109: 0 | AO109: 0 | AP109: 0 | AQ109: 0 | AS109: - | AT109: - | AU109: - | AV109: - | AW109: - | AY109: - | AZ109: - | BA109: - | BB109: - | BC109: - | BE109: 0 | BF109: 0 | BG109: 0 | BH109: 0 | BI109: 0 | BK109: 0 | BL109: 0 | BM109: 0 | BN109: 0 | BO109: 0
B110: ORANGE | C110: ORANGE GAMA 803 CESIÓN | D110: 0 | E110: 1.1 | F110: FIXED STYLE | I110: 40 | J110: 0 | K110: 0 | L110: 0 | M110: 0 | O110: 40 | P110: 0 | Q110: 0 | R110: 0 | S110: 0 | U110: 0 | V110: 0 | W110: 0 | X110: 0 | Y110: 0 | AA110: 0 | AB110: 0 | AC110: 0 | AD110: 0 | AE110: 0 | AG110: 0 | AH110: 0 | AI110: 0 | AJ110: 0 | AK110: 0 | AM110: 0 | AN110: 0 | AO110: 0 | AP110: 0 | AQ110: 0 | AS110: - | AT110: - | AU110: - | AV110: - | AW110: - | AY110: - | AZ110: - | BA110: - | BB110: - | BC110: - | BE110: 0 | BF110: 0 | BG110: 0 | BH110: 0 | BI110: 0 | BK110: 0 | BL110: 0 | BM110: 0 | BN110: 0 | BO110: 0
B111: ORANGE | C111: ORANGE GAMA 804 | D111: 115 | E111: 1.1 | F111: FIXED STYLE | I111: 0 | J111: 0 | K111: 0 | L111: 0 | M111: 0 | O111: 0 | P111: 0 | Q111: 0 | R111: 0 | S111: 0 | U111: 77 | V111: 0 | W111: 0 | X111: 0 | Y111: 0 | AA111: 77 | AB111: 0 | AC111: 0 | AD111: 0 | AE111: 0 | AG111: #N/A | AH111: #N/A | AI111: #N/A | AJ111: #N/A | AK111: #N/A | AM111: #N/A | AN111: #N/A | AO111: #N/A | AP111: #N/A | AQ111: #N/A | AS111: 38 | AT111: - | AU111: - | AV111: - | AW111: - | AY111: 38 | AZ111: - | BA111: - | BB111: - | BC111: - | BE111: 77 | BF111: 0 | BG111: 0 | BH111: 0 | BI111: 0 | BK111: 77 | BL111: 0 | BM111: 0 | BN111: 0 | BO111: 0
B112: ORANGE | C112: ORANGE GAMA 804 CESIÓN | D112: 0 | E112: 1.1 | F112: FIXED STYLE | I112: 0 | J112: 0 | K112: 0 | L112: 0 | M112: 0 | O112: 0 | P112: 0 | Q112: 0 | R112: 0 | S112: 0 | U112: 0 | V112: 0 | W112: 0 | X112: 0 | Y112: 0 | AA112: 0 | AB112: 0 | AC112: 0 | AD112: 0 | AE112: 0 | AG112: #N/A | AH112: #N/A | AI112: #N/A | AJ112: #N/A | AK112: #N/A | AM112: #N/A | AN112: #N/A | AO112: #N/A | AP112: #N/A | AQ112: #N/A | AS112: - | AT112: - | AU112: - | AV112: - | AW112: - | AY112: - | AZ112: - | BA112: - | BB112: - | BC112: - | BE112: 0 | BF112: 0 | BG112: 0 | BH112: 0 | BI112: 0 | BK112: 0 | BL112: 0 | BM112: 0 | BN112: 0 | BO112: 0
B113: NEXTIVITY | C113: REPETIDOR NEXTIVITY CELFI CONNECT C41 | D113: 547 | E113: 0 | F113: OC_OTROS DISPOSITIVOS | I113: 0 | J113: 0 | K113: 0 | L113: 0 | M113: 0 | O113: 0 | P113: 0 | Q113: 0 | R113: 0 | S113: 0 | U113: 352 | V113: 352 | W113: 352 | X113: 352 | Y113: 352 | AA113: 352 | AB113: 352 | AC113: 352 | AD113: 352 | AE113: 352 | AG113: 0 | AH113: 0 | AI113: 0 | AJ113: 0 | AK113: 0 | AM113: 0 | AN113: 0 | AO113: 0 | AP113: 0 | AQ113: 0 | AS113: 195 | AT113: 195 | AU113: 195 | AV113: 195 | AW113: 195 | AY113: 195 | AZ113: 195 | BA113: 195 | BB113: 195 | BC113: 195 | BE113: 352 | BF113: 352 | BG113: 352 | BH113: 352 | BI113: 352 | BK113: 352 | BL113: 352 | BM113: 352 | BN113: 352 | BO113: 352
B114: SAMSUNG | C114: SAMSUNG GALAXY A15 | D114: 186 | E114: 3.25 | F114: SMARTPHONE | I114: 0 | J114: 0 | K114: 0 | L114: 0 | M114: 0 | O114: 0 | P114: 0 | Q114: 0 | R114: 0 | S114: 0 | U114: 52 | V114: 72 | W114: 95 | X114: 112 | Y114: 145 | AA114: 97 | AB114: 127 | AC114: 176 | AD114: 241 | AE114: 254 | AG114: 0 | AH114: 0 | AI114: 0 | AJ114: 0 | AK114: 0 | AM114: 0 | AN114: 0 | AO114: 0 | AP114: 0 | AQ114: 0 | AS114: 134 | AT114: 114 | AU114: 91 | AV114: 74 | AW114: 41 | AY114: 89 | AZ114: 59 | BA114: 10 | BB114: -55 | BC114: -67.875 | BE114: 52 | BF114: 72 | BG114: 95 | BH114: 112 | BI114: 145 | BK114: 97 | BL114: 127 | BM114: 176 | BN114: 241 | BO114: 254
B115: SAMSUNG | C115: SAMSUNG GALAXY A15 5G | D115: 215 | E115: 3.25 | F115: SMARTPHONE | I115: 0 | J115: 0 | K115: 0 | L115: 0 | M115: 0 | O115: 0 | P115: 0 | Q115: 0 | R115: 0 | S115: 0 | U115: 52 | V115: 72 | W115: 95 | X115: 112 | Y115: 145 | AA115: 97 | AB115: 127 | AC115: 176 | AD115: 241 | AE115: 291 | AG115: 0 | AH115: 0 | AI115: 0 | AJ115: 0 | AK115: 0 | AM115: 0 | AN115: 0 | AO115: 0 | AP115: 0 | AQ115: 0 | AS115: 163 | AT115: 143 | AU115: 120 | AV115: 103 | AW115: 70 | AY115: 118 | AZ115: 88 | BA115: 39 | BB115: -26 | BC115: -76.375 | BE115: 52 | BF115: 72 | BG115: 95 | BH115: 112 | BI115: 145 | BK115: 97 | BL115: 127 | BM115: 176 | BN115: 241 | BO115: 291
B116: SAMSUNG | C116: SAMSUNG GALAXY A16 128GB | D116: 186 | E116: 3.25 | F116: SMARTPHONE | I116: 0 | J116: 0 | K116: 0 | L116: 0 | M116: 0 | O116: 0 | P116: 0 | Q116: 0 | R116: 0 | S116: 0 | U116: 101 | V116: 121 | W116: 144 | X116: 161 | Y116: 194 | AA116: 146 | AB116: 176 | AC116: 225 | AD116: 256 | AE116: 256 | AG116: 0 | AH116: 0 | AI116: 0 | AJ116: 0 | AK116: 0 | AM116: 0 | AN116: 0 | AO116: 0 | AP116: 0 | AQ116: 0 | AS116: 85.25 | AT116: 65.25 | AU116: 42.25 | AV116: 25.25 | AW116: -7.75 | AY116: 40.25 | AZ116: 10.25 | BA116: -38.75 | BB116: -69.625 | BC116: -69.625 | BE116: 101 | BF116: 121 | BG116: 144 | BH116: 161 | BI116: 194 | BK116: 146 | BL116: 176 | BM116: 225 | BN116: 256 | BO116: 256
B117: SAMSUNG | C117: SAMSUNG GALAXY A16 128GB 5G | D117: 248 | E117: 3.25 | F117: SMARTPHONE | I117: 112 | J117: 156 | K117: 148 | L117: 148 | M117: 148 | O117: 112 | P117: 156 | Q117: 148 | R117: 148 | S117: 148 | U117: 150 | V117: 170 | W117: 193 | X117: 210 | Y117: 243 | AA117: 195 | AB117: 225 | AC117: 274 | AD117: 324 | AE117: 324 | AG117: 0 | AH117: 0 | AI117: 0 | AJ117: 0 | AK117: 0 | AM117: 0 | AN117: 0 | AO117: 0 | AP117: 0 | AQ117: 0 | AS117: 98 | AT117: 78 | AU117: 55 | AV117: 38 | AW117: 5 | AY117: 53 | AZ117: 23 | BA117: -26 | BB117: -76 | BC117: -76 | BE117: 150 | BF117: 170 | BG117: 193 | BH117: 210 | BI117: 243 | BK117: 195 | BL117: 225 | BM117: 274 | BN117: 324 | BO117: 324
B118: SAMSUNG | C118: SAMSUNG GALAXY A25 5G | D118: 299 | E118: 3.25 | F118: SMARTPHONE | I118: 39 | J118: 54 | K118: 78 | L118: 112 | M118: 145 | O118: 79 | P118: 124 | Q118: 190 | R118: 255 | S118: 262 | U118: 108 | V118: 128 | W118: 151 | X118: 168 | Y118: 201 | AA118: 153 | AB118: 183 | AC118: 232 | AD118: 299 | AE118: 394 | AG118: 0 | AH118: 0 | AI118: 0 | AJ118: 0 | AK118: 0 | AM118: 0 | AN118: 0 | AO118: 0 | AP118: 0 | AQ118: 0 | AS118: 191.25 | AT118: 171.25 | AU118: 148.25 | AV118: 131.25 | AW118: 98.25 | AY118: 146.25 | AZ118: 116.25 | BA118: 67.25 | BB118: 0.25 | BC118: -94.625 | BE118: 108 | BF118: 128 | BG118: 151 | BH118: 168 | BI118: 201 | BK118: 153 | BL118: 183 | BM118: 232 | BN118: 299 | BO118: 394
B119: SAMSUNG | C119: SAMSUNG GALAXY A35 5G | D119: 358 | E119: 3.25 | F119: SMARTPHONE | I119: 39 | J119: 54 | K119: 78 | L119: 112 | M119: 145 | O119: 79 | P119: 124 | Q119: 190 | R119: 282 | S119: 289 | U119: 124 | V119: 144 | W119: 167 | X119: 184 | Y119: 217 | AA119: 169 | AB119: 199 | AC119: 248 | AD119: 343 | AE119: 425 | AG119: 0 | AH119: 0 | AI119: 0 | AJ119: 0 | AK119: 0 | AM119: 0 | AN119: 0 | AO119: 0 | AP119: 0 | AQ119: 0 | AS119: 234.25 | AT119: 214.25 | AU119: 191.25 | AV119: 174.25 | AW119: 141.25 | AY119: 189.25 | AZ119: 159.25 | BA119: 110.25 | BB119: 15.25 | BC119: -66.75 | BE119: 124 | BF119: 144 | BG119: 167 | BH119: 184 | BI119: 217 | BK119: 169 | BL119: 199 | BM119: 248 | BN119: 343 | BO119: 425
B120: SAMSUNG | C120: SAMSUNG GALAXY A55 5G | D120: 442 | E120: 3.25 | F120: SMARTPHONE | I120: 83 | J120: 98 | K120: 122 | L120: 156 | M120: 189 | O120: 123 | P120: 168 | Q120: 234 | R120: 319 | S120: 325 | U120: 209 | V120: 229 | W120: 252 | X120: 269 | Y120: 302 | AA120: 254 | AB120: 284 | AC120: 333 | AD120: 412 | AE120: 510 | AG120: -30 | AH120: -30 | AI120: -30 | AJ120: -30 | AK120: -30 | AM120: -30 | AN120: -30 | AO120: -30 | AP120: 0 | AQ120: -30 | AS120: 233.25 | AT120: 213.25 | AU120: 190.25 | AV120: 173.25 | AW120: 140.25 | AY120: 188.25 | AZ120: 158.25 | BA120: 109.25 | BB120: 30.25 | BC120: -67.75 | BE120: 209 | BF120: 229 | BG120: 252 | BH120: 269 | BI120: 302 | BK120: 254 | BL120: 284 | BM120: 333 | BN120: 412 | BO120: 510
B121: SAMSUNG | C121: SAMSUNG GALAXY BOOK2 GO 14" | D121: 533 | E121: 5.33 | F121: PC | I121: 84 | J121: 99 | K121: 123 | L121: 157 | M121: 190 | O121: 124 | P121: 169 | Q121: 235 | R121: 345 | S121: 404 | U121: 209 | V121: 229 | W121: 252 | X121: 269 | Y121: 302 | AA121: 254 | AB121: 284 | AC121: 333 | AD121: 439 | AE121: 533 | AG121: 0 | AH121: 0 | AI121: 0 | AJ121: 0 | AK121: 0 | AM121: 0 | AN121: 0 | AO121: 0 | AP121: 0 | AQ121: 0 | AS121: 324.12 | AT121: 304.12 | AU121: 281.12 | AV121: 264.12 | AW121: 231.12 | AY121: 279.12 | AZ121: 249.12 | BA121: 200.12 | BB121: 94.12 | BC121: 0.12 | BE121: 209 | BF121: 229 | BG121: 252 | BH121: 269 | BI121: 302 | BK121: 254 | BL121: 314 | BM121: 383 | BN121: 479 | BO121: 593
B122: SAMSUNG | C122: SAMSUNG GALAXY BOOK4 15,6" i5 13GEN 16+512GB W PRO | D122: 921 | E122: 5.33 | F122: PC | I122: 83 | J122: 98 | K122: 122 | L122: 156 | M122: 189 | O122: 123 | P122: 168 | Q122: 234 | R122: 344 | S122: 466 | U122: 52 | V122: 307 | W122: 330 | X122: 347 | Y122: 380 | AA122: 97 | AB122: 362 | AC122: 411 | AD122: 476 | AE122: 588 | AG122: #N/A | AH122: #N/A | AI122: #N/A | AJ122: #N/A | AK122: #N/A | AM122: #N/A | AN122: #N/A | AO122: #N/A | AP122: #N/A | AQ122: #N/A | AS122: 869 | AT122: 614.33 | AU122: 591.33 | AV122: 574.33 | AW122: 541.33 | AY122: 824 | AZ122: 559.33 | BA122: 510.33 | BB122: 445.33 | BC122: 333.33 | BE122: 52 | BF122: 307 | BG122: 330 | BH122: 347 | BI122: 380 | BK122: 97 | BL122: 392 | BM122: 461 | BN122: 516 | BO122: 648
B123: SAMSUNG | C123: SAMSUNG GALAXY BOOK4 EDGE15 16+256GB | D123: 801 | E123: 5.33 | F123: PC | I123: 39 | J123: 54 | K123: 195 | L123: 229 | M123: 262 | O123: 79 | P123: 124 | Q123: 307 | R123: 417 | S123: 564 | U123: 52 | V123: 268 | W123: 291 | X123: 308 | Y123: 341 | AA123: 97 | AB123: 323 | AC123: 372 | AD123: 537 | AE123: 649 | AG123: 0 | AH123: 0 | AI123: 0 | AJ123: 0 | AK123: 0 | AM123: 0 | AN123: 0 | AO123: 0 | AP123: 0 | AQ123: 0 | AS123: 749 | AT123: 533.09 | AU123: 510.09 | AV123: 493.09 | AW123: 460.09 | AY123: 704 | AZ123: 478.09 | BA123: 429.09 | BB123: 264.09 | BC123: 152.09 | BE123: 52 | BF123: 268 | BG123: 291 | BH123: 308 | BI123: 341 | BK123: 97 | BL123: 353 | BM123: 422 | BN123: 577 | BO123: 709
B124: SAMSUNG | C124: SAMSUNG GALAXY BOOK4 PRO 16" i5 | D124: 1487 | E124: 5.33 | F124: PC | I124: 39 | J124: 54 | K124: 249 | L124: 283 | M124: 316 | O124: 79 | P124: 124 | Q124: 361 | R124: 471 | S124: 618 | U124: 52 | V124: 450 | W124: 473 | X124: 490 | Y124: 523 | AA124: 97 | AB124: 505 | AC124: 554 | AD124: 669 | AE124: 781 | AG124: 0 | AH124: 0 | AI124: 0 | AJ124: 0 | AK124: 0 | AM124: 0 | AN124: 0 | AO124: 0 | AP124: 0 | AQ124: 0 | AS124: 1435 | AT124: 1037.33 | AU124: 1014.33 | AV124: 997.33 | AW124: 964.33 | AY124: 1390 | AZ124: 982.33 | BA124: 933.33 | BB124: 818.33 | BC124: 706.33 | BE124: 52 | BF124: 450 | BG124: 473 | BH124: 490 | BI124: 523 | BK124: 97 | BL124: 535 | BM124: 604 | BN124: 709 | BO124: 841
B125: SAMSUNG | C125: SAMSUNG GALAXY BOOK5 PRO16 16" i5 ULTRA 16+512GB | D125: 1487 | E125: 5.33 | F125: PC | I125: 39 | J125: 54 | K125: 289 | L125: 323 | M125: 356 | O125: 79 | P125: 124 | Q125: 401 | R125: 511 | S125: 658 | U125: 52 | V125: 250 | W125: 273 | X125: 290 | Y125: 323 | AA125: 97 | AB125: 305 | AC125: 354 | AD125: 419 | AE125: 531 | AG125: #N/A | AH125: #N/A | AI125: #N/A | AJ125: #N/A | AK125: #N/A | AM125: #N/A | AN125: #N/A | AO125: #N/A | AP125: #N/A | AQ125: #N/A | AS125: 1435 | AT125: 1237.33 | AU125: 1214.33 | AV125: 1197.33 | AW125: 1164.33 | AY125: 1390 | AZ125: 1182.33 | BA125: 1133.33 | BB125: 1068.33 | BC125: 956.33 | BE125: 52 | BF125: 250 | BG125: 273 | BH125: 290 | BI125: 323 | BK125: 97 | BL125: 335 | BM125: 404 | BN125: 459 | BO125: 591
B126: SAMSUNG | C126: SAMSUNG GALAXY S23 256GB 5G | D126: 938 | E126: 3.25 | F126: SMARTPHONE | I126: 39 | J126: 54 | K126: 195 | L126: 229 | M126: 262 | O126: 79 | P126: 124 | Q126: 307 | R126: 417 | S126: 564 | U126: 52 | V126: 506 | W126: 529 | X126: 546 | Y126: 579 | AA126: 97 | AB126: 561 | AC126: 610 | AD126: 675 | AE126: 789 | AG126: 0 | AH126: -50 | AI126: -50 | AJ126: -50 | AK126: -50 | AM126: 0 | AN126: -50 | AO126: -50 | AP126: -16 | AQ126: 0 | AS126: 886 | AT126: 432.25 | AU126: 409.25 | AV126: 392.25 | AW126: 359.25 | AY126: 841 | AZ126: 377.25 | BA126: 328.25 | BB126: 263.25 | BC126: 149.25 | BE126: 52 | BF126: 506 | BG126: 529 | BH126: 546 | BI126: 579 | BK126: 97 | BL126: 591 | BM126: 660 | BN126: 715 | BO126: 950
