Workbook

Sheet PVP VaP - Pyme
B2: OFERTA TÁCTICA EMPRESAS | H2: Pago Único | J2: CAPTA | M2: PORTABILIDAD
B4: 45627 | C4: 01/12 al 31/12 | J4: - | M4: ENTRADA PRO | O4: NORMAL PRO | Q4: VALOR PRO | S4: PREMIUM PRO | U4: TOP PRO
B5: 1. CONDICIONES DE LA OFERTA VENTA A PLAZOS (según tarifa y situación del cliente) | D5: Tarifas | H5: Todas Tarifas | J5: - | M5: T. Optima Plus Empresas T. Optima Plus Empresas Big + Empresas Voz y Empresas 1 | O5: T. Optima Plus Empresas T. Optima Plus Empresas Big + Empresas 5 y Empresas Intranet | Q5: T. Optima Plus Empresas T. Optima Plus Empresas Big + Empresas 20 | S5: T. Optima Plus Empresas T. Optima Plus Empresas Big + Empresas Infinita | U5: T. Optima Plus Empresas T. Optima Plus Empresas Big + Empresas Internacional
D13: Ampliaciones (meses antigüedad) | H13: Todos | J13: cliente -4 M, solo accede a Pago Único | M13: + 4 M | O13: + 4 M | Q13: + 4 M | S13: + 4 M | U13: + 4 M
D14: Origen (Portabilidad / Migración) | H14: Pos | J14: Capta de cliente nuevo, solo accede a Pago Único | M14: Pospago | O14: Pospago | Q14: Pospago | S14: Pospago | U14: Pospago
D15: CP Tarifa | H15: 24 M | J15: - | M15: 24 M | O15: 24 M | Q15: 24 M | S15: 24 M | U15: 24 M
D16: CP Terminal | H16: - | J16: - | M16: 24 M | O16: 24 M | Q16: 24 M | S16: 24 M | U16: 24 M | AN16: DIFERENCIAS Vs MES ANTERIOR
AN17: 6 | AO17: 7 | AP17: 8 | AQ17: 9 | AR17: 10 | AS17: 11 | AT17: 12 | AU17: 13 | AV17: 14 | AW17: 15 | AX17: 16 | AY17: 17 | AZ17: 18 | BA17: 19 | BB17: 20
B18: 2. PRECIO DEL TERMINAL POR GRUPO DE TARIFAS | H18: Pago Único | J18: PVPR CAPTA (tarifas móvil y convergentes) | M18: PVPR PORTABILIDAD | X18: DxC Pago Único | Z18: DxC CAPTA (tarifas móvil y convergentes) | AC18: DxC PORTABILIDAD | AN18: Pago Único | AP18: PVPR CAPTA (tarifas móvil y convergentes) | AS18: PVPR PORTABILIDAD
M20: GRUPOS DE TARIFAS MÓVIL | AC20: GRUPOS DE TARIFAS MÓVIL | AS20: GRUPOS DE TARIFAS MÓVIL
J22: - | M22: ENTRADA PRO | O22: NORMAL PRO | Q22: VALOR PRO | S22: PREMIUM PRO | U22: TOP PRO | Z22: - | AC22: ENTRADA PRO | AE22: NORMAL PRO | AG22: VALOR PRO | AI22: PREMIUM PRO | AK22: TOP PRO | AP22: ENTRADA PRO | AS22: ENTRADA PRO | AU22: NORMAL PRO | AW22: VALOR PRO | AY22: PREMIUM PRO | BA22: TOP PRO
B24: MARCA | C24: Modelo (Novedades) | D24: Precio Cesión | E24: Canon Digital | F24: Gama | G24: Meses Cuota | H24: Pago Unico (sin IVA) | J24: Pago Inicial (sin IVA) | K24: Cuota Mes (sin IVA) | M24: Pago Inicial (sin IVA) | N24: Cuota Mes (sin IVA) | O24: Pago Inicial (sin IVA) | P24: Cuota Mes (sin IVA) | Q24: Pago Inicial (sin IVA) | R24: Cuota Mes (sin IVA) | S24: Pago Inicial (sin IVA) | T24: Cuota Mes (sin IVA) | U24: Pago Inicial (sin IVA) | V24: Cuota Mes (sin IVA) | X24: DxC Pago Unico | Z24: DxC Precio | AA24: DxC VaP | AC24: DxC Precio | AD24: DxC VaP | AE24: DxC Precio | AF24: DxC VaP | AG24: DxC Precio | AH24: DxC VaP | AI24: DxC Precio | AJ24: DxC VaP | AK24: DxC Precio | AL24: DxC VaP | AN24: Pago Unico (sin IVA) | AP24: Pago Inicial (sin IVA) | AQ24: Cuota Mes (sin IVA) | AS24: Pago Inicial (sin IVA) | AT24: Cuota Mes (sin IVA) | AU24: Pago Inicial (sin IVA) | AV24: Cuota Mes (sin IVA) | AW24: Pago Inicial (sin IVA) | AX24: Cuota Mes (sin IVA) | AY24: Pago Inicial (sin IVA) | AZ24: Cuota Mes (sin IVA) | BA24: Pago Inicial (sin IVA) | BB24: Cuota Mes (sin IVA)
B25: ORANGE | C25: AD HOC H3 CESIÓN | D25: 0 | E25: 1.1 | F25: FIXED STYLE | G25: - | H25: - | J25: - | K25: - | M25: - | N25: - | O25: - | P25: - | Q25: - | R25: - | S25: - | T25: - | U25: - | V25: - | X25: 0 | Z25: 0 | AA25: 0 | AC25: 0 | AD25: 0 | AE25: 0 | AF25: 0 | AG25: 0 | AH25: 0 | AI25: 0 | AJ25: 0 | AK25: 0 | AL25: 0 | AN25: 0 | AP25: 0 | AQ25: 0 | AS25: 0 | AT25: 0 | AU25: 0 | AV25: 0 | AW25: 0 | AX25: 0 | AY25: 0 | AZ25: 0 | BA25: 0 | BB25: 0
B26: ORANGE | C26: ADOC D30 | D26: 239 | E26: 3.75 | F26: FIXED STYLE | G26: 24 | H26: 280 | J26: - | K26: - | M26: 0 | N26: 7.3 | O26: 0 | P26: 5.9 | Q26: 0 | R26: 2.5 | S26: 0 | T26: 0 | U26: 0 | V26: 0 | X26: -41 | Z26: 0 | AA26: 0 | AC26: 64 | AD26: 175 | AE26: 97 | AF26: 142 | AG26: 179 | AH26: 60 | AI26: 239 | AJ26: 0 | AK26: 239 | AL26: 0 | AN26: 0 | AP26: 0 | AQ26: 0 | AS26: 0 | AT26: 0 | AU26: 0 | AV26: 0 | AW26: 0 | AX26: 0 | AY26: 0 | AZ26: 0 | BA26: 0 | BB26: 0
B27: ORANGE | C27: ADOC D30 CESIÓN | D27: 0 | E27: 3.75 | F27: FIXED STYLE | G27: - | H27: - | J27: - | K27: - | M27: - | N27: - | O27: - | P27: - | Q27: - | R27: - | S27: - | T27: - | U27: - | V27: - | X27: 0 | Z27: 0 | AA27: 0 | AC27: 0 | AD27: 0 | AE27: 0 | AF27: 0 | AG27: 0 | AH27: 0 | AI27: 0 | AJ27: 0 | AK27: 0 | AL27: 0 | AN27: 0 | AP27: 0 | AQ27: 0 | AS27: 0 | AT27: 0 | AU27: 0 | AV27: 0 | AW27: 0 | AX27: 0 | AY27: 0 | AZ27: 0 | BA27: 0 | BB27: 0
B28: AD HOC | C28: ADOC SC01 | D28: 64 | E28: 1.1 | F28: VOZ | G28: - | H28: - | J28: - | K28: - | M28: - | N28: - | O28: - | P28: - | Q28: - | R28: - | S28: - | T28: - | U28: - | V28: - | X28: 0 | Z28: 0 | AA28: 0 | AC28: 0 | AD28: 0 | AE28: 0 | AF28: 0 | AG28: 0 | AH28: 0 | AI28: 0 | AJ28: 0 | AK28: 0 | AL28: 0 | AN28: 0 | AP28: 0 | AQ28: 0 | AS28: 0 | AT28: 0 | AU28: 0 | AV28: 0 | AW28: 0 | AX28: 0 | AY28: 0 | AZ28: 0 | BA28: 0 | BB28: 0
B29: ADOC | C29: ADOC SC04 | D29: 77 | E29: 1.1 | F29: VOZ | G29: 24 | H29: 93 | J29: - | K29: - | M29: 0 | N29: 0 | O29: 0 | P29: 0 | Q29: 0 | R29: 0 | S29: 0 | T29: 0 | U29: 0 | V29: 0 | X29: -16 | Z29: 0 | AA29: 0 | AC29: 77 | AD29: 0 | AE29: 77 | AF29: 0 | AG29: 77 | AH29: 0 | AI29: 77 | AJ29: 0 | AK29: 77 | AL29: 0 | AN29: 0 | AP29: 0 | AQ29: 0 | AS29: 0 | AT29: 0 | AU29: 0 | AV29: 0 | AW29: 0 | AX29: 0 | AY29: 0 | AZ29: 0 | BA29: 0 | BB29: 0
B30: APPLE | C30: APPLE AIRPODS 4 | D30: 137 | E30: 0 | F30: OC_AURICULARES | G30: 24 | H30: 165 | J30: - | K30: - | M30: 0 | N30: 4 | O30: 0 | P30: 2.6 | Q30: 0 | R30: 0 | S30: 0 | T30: 0 | U30: 0 | V30: 0 | X30: -28 | Z30: 0 | AA30: 0 | AC30: 41 | AD30: 96 | AE30: 75 | AF30: 62 | AG30: 137 | AH30: 0 | AI30: 137 | AJ30: 0 | AK30: 137 | AL30: 0 | AN30: 0 | AP30: 0 | AQ30: 0 | AS30: 0 | AT30: 0 | AU30: 0 | AV30: 0 | AW30: 0 | AX30: 0 | AY30: 0 | AZ30: 0 | BA30: 0 | BB30: 0
B31: APPLE | C31: APPLE AIRPODS 4 CON CANCELACION ACTIVA RUIDO | D31: 184 | E31: 0 | F31: OC_AURICULARES | G31: 24 | H31: 222 | J31: - | K31: - | M31: 0 | N31: 5.6 | O31: 0 | P31: 4.2 | Q31: 0 | R31: 0 | S31: 0 | T31: 0 | U31: 0 | V31: 0 | X31: -38 | Z31: 0 | AA31: 0 | AC31: 50 | AD31: 134 | AE31: 83 | AF31: 101 | AG31: 184 | AH31: 0 | AI31: 184 | AJ31: 0 | AK31: 184 | AL31: 0 | AN31: 0 | AP31: 0 | AQ31: 0 | AS31: 0 | AT31: 0 | AU31: 0 | AV31: 0 | AW31: 0 | AX31: 0 | AY31: 0 | AZ31: 0 | BA31: 0 | BB31: 0
B32: APPLE | C32: APPLE AIRPODS PRO 2a GENERACION MAGSAFE USBC | D32: 279 | E32: 0 | F32: OC_AURICULARES | G32: 24 | H32: 336 | J32: - | K32: - | M32: 0 | N32: 8.1 | O32: 0 | P32: 6.7 | Q32: 0 | R32: 3.4 | S32: 0 | T32: 1.8 | U32: 0 | V32: 0 | X32: -57 | Z32: 0 | AA32: 0 | AC32: 85 | AD32: 194 | AE32: 118 | AF32: 161 | AG32: 197 | AH32: 82 | AI32: 236 | AJ32: 43 | AK32: 279 | AL32: 0 | AN32: 0 | AP32: 0 | AQ32: 0 | AS32: 0 | AT32: 0 | AU32: 0 | AV32: 0 | AW32: 0 | AX32: 0 | AY32: 0 | AZ32: 0 | BA32: 0 | BB32: 0
B33: APPLE | C33: APPLE WATCH S10 CELLULAR 42MM | D33: 532 | E33: 2.5 | F33: OC_SMART WATCH | G33: 24 | H33: 643 | J33: - | K33: - | M33: 39 | N33: 16.4 | O33: 19 | P33: 15.6 | Q33: 0 | R33: 13.1 | S33: 0 | T33: 11.5 | U33: 0 | V33: 6.8 | X33: -111 | Z33: 0 | AA33: 0 | AC33: 99 | AD33: 394 | AE33: 139 | AF33: 374 | AG33: 218 | AH33: 314 | AI33: 256 | AJ33: 276 | AK33: 369 | AL33: 163 | AN33: 0 | AP33: 0 | AQ33: 0 | AS33: 0 | AT33: 0 | AU33: 0 | AV33: 0 | AW33: 0 | AX33: 0 | AY33: 0 | AZ33: 0 | BA33: 0 | BB33: 0
B34: APPLE | C34: APPLE WATCH S10 CELLULAR 46MM | D34: 555 | E34: 2.5 | F34: OC_SMART WATCH | G34: 24 | H34: 671 | J34: - | K34: - | M34: 39 | N34: 17.4 | O34: 19 | P34: 16.6 | Q34: 0 | R34: 14.1 | S34: 0 | T34: 12.4 | U34: 0 | V34: 7.8 | X34: -116 | Z34: 0 | AA34: 0 | AC34: 98 | AD34: 418 | AE34: 138 | AF34: 398 | AG34: 217 | AH34: 338 | AI34: 257 | AJ34: 298 | AK34: 368 | AL34: 187 | AN34: 0 | AP34: 0 | AQ34: 0 | AS34: 0 | AT34: 0 | AU34: 0 | AV34: 0 | AW34: 0 | AX34: 0 | AY34: 0 | AZ34: 0 | BA34: 0 | BB34: 0
B35: APPLE | C35: APPLE WATCH S9 CELLULAR 45MM | D35: 555 | E35: 2.5 | F35: OC_SMART WATCH | G35: 24 | H35: 671 | J35: - | K35: - | M35: 39 | N35: 17.4 | O35: 19 | P35: 16.6 | Q35: 0 | R35: 14.1 | S35: 0 | T35: 12.4 | U35: 0 | V35: 7.8 | X35: -116 | Z35: 0 | AA35: 0 | AC35: 98 | AD35: 418 | AE35: 138 | AF35: 398 | AG35: 217 | AH35: 338 | AI35: 257 | AJ35: 298 | AK35: 368 | AL35: 187 | AN35: 0 | AP35: 0 | AQ35: 0 | AS35: 0 | AT35: 0 | AU35: 0 | AV35: 0 | AW35: 0 | AX35: 0 | AY35: 0 | AZ35: 0 | BA35: 0 | BB35: 0
B36: AD HOC | C36: AURICULARES AD HOC BT01 | D36: 71 | E36: 0 | F36: OC_AURICULARES | G36: 24 | H36: 57.024793 | J36: - | K36: - | M36: 0 | N36: 0 | O36: 0 | P36: 0 | Q36: 0 | R36: 0 | S36: 0 | T36: 0 | U36: 0 | V36: 0 | X36: 14 | Z36: 0 | AA36: 0 | AC36: 71 | AD36: 0 | AE36: 71 | AF36: 0 | AG36: 71 | AH36: 0 | AI36: 71 | AJ36: 0 | AK36: 71 | AL36: 0 | AN36: 0 | AP36: 0 | AQ36: 0 | AS36: 0 | AT36: 0 | AU36: 0 | AV36: 0 | AW36: 0 | AX36: 0 | AY36: 0 | AZ36: 0 | BA36: 0 | BB36: 0
B37: AD HOC | C37: AURICULARES AD HOC HC01 | D37: 49 | E37: 0 | F37: OC_AURICULARES | G37: 24 | H37: 35.53719 | J37: - | K37: - | M37: 0 | N37: 0 | O37: 0 | P37: 0 | Q37: 0 | R37: 0 | S37: 0 | T37: 0 | U37: 0 | V37: 0 | X37: 13 | Z37: 0 | AA37: 0 | AC37: 49 | AD37: 0 | AE37: 49 | AF37: 0 | AG37: 49 | AH37: 0 | AI37: 49 | AJ37: 0 | AK37: 49 | AL37: 0 | AN37: 0 | AP37: 0 | AQ37: 0 | AS37: 0 | AT37: 0 | AU37: 0 | AV37: 0 | AW37: 0 | AX37: 0 | AY37: 0 | AZ37: 0 | BA37: 0 | BB37: 0
B38: SAMSUNG | C38: AURICULARES SAMSUNG GALAXY BUDS 3 | D38: 172 | E38: 0 | F38: OC_AURICULARES | G38: 24 | H38: 158 | J38: - | K38: - | M38: 0 | N38: 3.7 | O38: 0 | P38: 2.3 | Q38: 0 | R38: 0 | S38: 0 | T38: 0 | U38: 0 | V38: 0 | X38: 14 | Z38: 0 | AA38: 0 | AC38: 83 | AD38: 89 | AE38: 117 | AF38: 55 | AG38: 172 | AH38: 0 | AI38: 172 | AJ38: 0 | AK38: 172 | AL38: 0 | AN38: 0 | AP38: 0 | AQ38: 0 | AS38: 0 | AT38: 0 | AU38: 0 | AV38: 0 | AW38: 0 | AX38: 0 | AY38: 0 | AZ38: 0 | BA38: 0 | BB38: 0
B39: SAMSUNG | C39: AURICULARES SAMSUNG GALAXY BUDS 3 PRO | D39: 240 | E39: 0 | F39: OC_AURICULARES | G39: 24 | H39: 227 | J39: - | K39: - | M39: 0 | N39: 5.8 | O39: 0 | P39: 4.4 | Q39: 0 | R39: 1 | S39: 0 | T39: 0 | U39: 0 | V39: 0 | X39: 13 | Z39: 0 | AA39: 0 | AC39: 101 | AD39: 139 | AE39: 134 | AF39: 106 | AG39: 216 | AH39: 24 | AI39: 240 | AJ39: 0 | AK39: 240 | AL39: 0 | AN39: 0 | AP39: 0 | AQ39: 0 | AS39: 0 | AT39: 0 | AU39: 0 | AV39: 0 | AW39: 0 | AX39: 0 | AY39: 0 | AZ39: 0 | BA39: 0 | BB39: 0
B40: SPC | C40: AURICULARES SPC BRAVE PRO | D40: 44 | E40: 0 | F40: OC_AURICULARES | G40: 24 | H40: 47.933884 | J40: - | K40: - | M40: 0 | N40: 0 | O40: 0 | P40: 0 | Q40: 0 | R40: 0 | S40: 0 | T40: 0 | U40: 0 | V40: 0 | X40: -4 | Z40: 0 | AA40: 0 | AC40: 44 | AD40: 0 | AE40: 44 | AF40: 0 | AG40: 44 | AH40: 0 | AI40: 44 | AJ40: 0 | AK40: 44 | AL40: 0 | AN40: 0 | AP40: 0 | AQ40: 0 | AS40: 0 | AT40: 0 | AU40: 0 | AV40: 0 | AW40: 0 | AX40: 0 | AY40: 0 | AZ40: 0 | BA40: 0 | BB40: 0
... B46: GOOGLE | C46: GOOGLE PIXEL 9 128GB 5G | D46: 823 | E46: 3.25 | F46: SMARTPHONE | G46: 24 | H46: 795 | J46: - | K46: - | M46: 39 | N46: 21.9 | O46: 19 | P46: 21 | Q46: 0 | R46: 18.5 | S46: 0 | T46: 15.8 | U46: 0 | V46: 10.9 | X46: 28 | Z46: 0 | AA46: 0 | AC46: 258 | AD46: 526 | AE46: 300 | AF46: 504 | AG46: 379 | AH46: 444 | AI46: 444 | AJ46: 379 | AK46: 561 | AL46: 262 | AN46: 0 | AP46: 0 | AQ46: 0 | AS46: 0 | AT46: 0 | AU46: 0 | AV46: 0 | AW46: 0 | AX46: 0 | AY46: 0 | AZ46: 0 | BA46: 0 | BB46: 0
B47: GOOGLE | C47: GOOGLE PIXEL 9 PRO 256GB 5G | D47: 1062 | E47: 3.25 | F47: SMARTPHONE | G47: 24 | H47: 1060 | J47: - | K47: - | M47: - | N47: - | O47: 49 | P47: 26.9 | Q47: 39 | R47: 24 | S47: 0 | T47: 23 | U47: 0 | V47: 18.1 | X47: 2 | Z47: 0 | AA47: 0 | AC47: 0 | AD47: 0 | AE47: 367 | AF47: 646 | AG47: 447 | AH47: 576 | AI47: 510 | AJ47: 552 | AK47: 628 | AL47: 434 | AN47: 0 | AP47: 0 | AQ47: 0 | AS47: 0 | AT47: 0 | AU47: 0 | AV47: 0 | AW47: 0 | AX47: 0 | AY47: 0 | AZ47: 0 | BA47: 0 | BB47: 0
B48: GOOGLE | C48: GOOGLE PIXEL 9 PRO XL 512GB 5G | D48: 1234 | E48: 3.25 | F48: SMARTPHONE | G48: 24 | H48: 1233 | J48: - | K48: - | M48: - | N48: - | O48: 79 | P48: 31.9 | Q48: 39 | R48: 30.2 | S48: 0 | T48: 29.2 | U48: 0 | V48: 24.3 | X48: 1 | Z48: 0 | AA48: 0 | AC48: 0 | AD48: 0 | AE48: 389 | AF48: 766 | AG48: 470 | AH48: 725 | AI48: 533 | AJ48: 701 | AK48: 651 | AL48: 583 | AN48: 0 | AP48: 0 | AQ48: 0 | AS48: 0 | AT48: 0 | AU48: 0 | AV48: 0 | AW48: 0 | AX48: 0 | AY48: 0 | AZ48: 0 | BA48: 0 | BB48: 0
B49: HONOR | C49: HONOR 200 512GB 5G | D49: 539 | E49: 3.25 | F49: SMARTPHONE | G49: 24 | H49: 518 | J49: - | K49: - | M49: 0 | N49: 9.2 | O49: 0 | P49: 7.8 | Q49: 0 | R49: 4.4 | S49: 0 | T49: 2.8 | U49: 0 | V49: 0 | X49: 21 | Z49: 0 | AA49: 0 | AC49: 318 | AD49: 221 | AE49: 352 | AF49: 187 | AG49: 433 | AH49: 106 | AI49: 472 | AJ49: 67 | AK49: 539 | AL49: 0 | AN49: 0 | AP49: 0 | AQ49: 0 | AS49: 0 | AT49: 0 | AU49: 0 | AV49: 0 | AW49: 0 | AX49: 0 | AY49: 0 | AZ49: 0 | BA49: 0 | BB49: 0
B50: HONOR | C50: HONOR 200 LITE 256GB 5G | D50: 309 | E50: 3.25 | F50: SMARTPHONE | G50: 24 | H50: 291 | J50: - | K50: - | M50: 0 | N50: 5.2 | O50: 0 | P50: 3.8 | Q50: 0 | R50: 0 | S50: 0 | T50: 0 | U50: 0 | V50: 0 | X50: 18 | Z50: 0 | AA50: 0 | AC50: 184 | AD50: 125 | AE50: 218 | AF50: 91 | AG50: 309 | AH50: 0 | AI50: 309 | AJ50: 0 | AK50: 309 | AL50: 0 | AN50: 0 | AP50: 0 | AQ50: 0 | AS50: 0 | AT50: 0 | AU50: 0 | AV50: 0 | AW50: 0 | AX50: 0 | AY50: 0 | AZ50: 0 | BA50: 0 | BB50: 0
B51: HONOR | C51: HONOR 200 PRO 512GB 5G | D51: 661 | E51: 3.25 | F51: SMARTPHONE | G51: 24 | H51: 663 | J51: - | K51: - | M51: 39 | N51: 15.4 | O51: 19 | P51: 14.6 | Q51: 0 | R51: 12.1 | S51: 0 | T51: 10.4 | U51: 0 | V51: 5.8 | X51: -2 | Z51: 0 | AA51: 0 | AC51: 252 | AD51: 370 | AE51: 292 | AF51: 350 | AG51: 371 | AH51: 290 | AI51: 411 | AJ51: 250 | AK51: 522 | AL51: 139 | AN51: 0 | AP51: 0 | AQ51: 0 | AS51: 0 | AT51: 0 | AU51: 0 | AV51: 0 | AW51: 0 | AX51: 0 | AY51: 0 | AZ51: 0 | BA51: 0 | BB51: 0
B52: HONOR | C52: HONOR 200 SMART 256GB 5G | D52: 181 | E52: 3.25 | F52: SMARTPHONE | G52: 24 | H52: 119 | J52: - | K52: - | M52: 0 | N52: 2.8 | O52: 0 | P52: 1.4 | Q52: 0 | R52: 0 | S52: 0 | T52: 0 | U52: 0 | V52: 0 | X52: 62 | Z52: 0 | AA52: 0 | AC52: 114 | AD52: 67 | AE52: 147 | AF52: 34 | AG52: 181 | AH52: 0 | AI52: 181 | AJ52: 0 | AK52: 181 | AL52: 0 | AN52: 0 | AP52: 0 | AQ52: 0 | AS52: 0 | AT52: 0 | AU52: 0 | AV52: 0 | AW52: 0 | AX52: 0 | AY52: 0 | AZ52: 0 | BA52: 0 | BB52: 0
B53: HONOR | C53: HONOR 90 SMART 5G | D53: 218 | E53: 3.25 | F53: SMARTPHONE | G53: 24 | H53: 226 | J53: - | K53: - | M53: 0 | N53: 4.1 | O53: 0 | P53: 2.7 | Q53: 0 | R53: 0 | S53: 0 | T53: 0 | U53: 0 | V53: 0 | X53: -8 | Z53: 0 | AA53: 0 | AC53: 120 | AD53: 98 | AE53: 153 | AF53: 65 | AG53: 218 | AH53: 0 | AI53: 218 | AJ53: 0 | AK53: 218 | AL53: 0 | AN53: 0 | AP53: 0 | AQ53: 0 | AS53: 0 | AT53: 0 | AU53: 0 | AV53: 0 | AW53: 0 | AX53: 0 | AY53: 0 | AZ53: 0 | BA53: 0 | BB53: 0
B54: HONOR | C54: HONOR MAGIC V3 512GB 5G | D54: 1653 | E54: 3.25 | F54: SMARTPHONE | G54: 24 | H54: 1431 | J54: - | K54: - | M54: - | N54: - | O54: 129 | P54: 36.8 | Q54: 99 | R54: 34.8 | S54: 49 | T54: 34.2 | U54: 29 | V54: 30.2 | X54: 222 | Z54: 0 | AA54: 0 | AC54: 0 | AD54: 0 | AE54: 641 | AF54: 883 | AG54: 719 | AH54: 835 | AI54: 783 | AJ54: 821 | AK54: 899 | AL54: 725 | AN54: 0 | AP54: 0 | AQ54: 0 | AS54: 0 | AT54: 0 | AU54: 0 | AV54: 0 | AW54: 0 | AX54: 0 | AY54: 0 | AZ54: 1.7 | BA54: 0 | BB54: 0
B55: HONOR | C55: HONOR MAGIC6 LITE 256GB 5G | D55: 358 | E55: 3.25 | F55: SMARTPHONE | G55: 24 | H55: 360 | J55: - | K55: - | M55: 0 | N55: 9 | O55: 0 | P55: 7.6 | Q55: 0 | R55: 4.2 | S55: 0 | T55: 2.6 | U55: 0 | V55: 0 | X55: -2 | Z55: 0 | AA55: 0 | AC55: 142 | AD55: 216 | AE55: 176 | AF55: 182 | AG55: 257 | AH55: 101 | AI55: 296 | AJ55: 62 | AK55: 358 | AL55: 0 | AN55: 0 | AP55: 0 | AQ55: 0 | AS55: 0 | AT55: 0 | AU55: 0 | AV55: 0 | AW55: 0 | AX55: 0 | AY55: 0 | AZ55: 0 | BA55: 0 | BB55: 0
B56: HONOR | C56: HONOR MAGIC6 PRO 5G | D56: 1074 | E56: 3.25 | F56: SMARTPHONE | G56: 24 | H56: 978 | J56: - | K56: - | M56: - | N56: - | O56: 39 | P56: 25 | Q56: 39 | R56: 21.7 | S56: 0 | T56: 20.7 | U56: 0 | V56: 15.8 | X56: 96 | Z56: 0 | AA56: 0 | AC56: 0 | AD56: 0 | AE56: 435 | AF56: 600 | AG56: 514 | AH56: 521 | AI56: 577 | AJ56: 497 | AK56: 695 | AL56: 379 | AN56: 0 | AP56: 0 | AQ56: 0 | AS56: 0 | AT56: 0 | AU56: 0 | AV56: 0 | AW56: 0 | AX56: 0 | AY56: 0 | AZ56: 0 | BA56: 0 | BB56: 0
B57: HONOR | C57: HONOR PAD X9 WIFI | D57: 204 | E57: 3.75 | F57: TABLET | G57: 24 | H57: 210 | J57: - | K57: - | M57: 0 | N57: 5.2 | O57: 0 | P57: 3.8 | Q57: 0 | R57: 0 | S57: 0 | T57: 0 | U57: 0 | V57: 0 | X57: -6 | Z57: 0 | AA57: 0 | AC57: 79 | AD57: 125 | AE57: 113 | AF57: 91 | AG57: 204 | AH57: 0 | AI57: 204 | AJ57: 0 | AK57: 204 | AL57: 0 | AN57: 0 | AP57: 0 | AQ57: 0 | AS57: 0 | AT57: 0 | AU57: 0 | AV57: 0 | AW57: 0 | AX57: 0 | AY57: 0 | AZ57: 0 | BA57: 0 | BB57: 0
B58: HUAWEI | C58: HUAWEI PC MATEBOOK D 14" I5 12 GEN | D58: 751 | E58: 5.33 | F58: PC | G58: 24 | H58: 752 | J58: - | K58: - | M58: 39 | N58: 20.3 | O58: 19 | P58: 19.5 | Q58: 0 | R58: 17 | S58: 0 | T58: 15.4 | U58: 0 | V58: 10.7 | X58: -1 | Z58: 0 | AA58: 0 | AC58: 225 | AD58: 487 | AE58: 264 | AF58: 468 | AG58: 343 | AH58: 408 | AI58: 381 | AJ58: 370 | AK58: 494 | AL58: 257 | AN58: 0 | AP58: 0 | AQ58: 0 | AS58: 0 | AT58: 0 | AU58: 0 | AV58: 0 | AW58: 0 | AX58: 0 | AY58: 0 | AZ58: 0 | BA58: 0 | BB58: 0
B59: HUAWEI | C59: HUAWEI PC MATEBOOK D 16" I5 12 GEN | D59: 915 | E59: 5.33 | F59: PC | G59: 24 | H59: 824 | J59: - | K59: - | M59: 39 | N59: 22.9 | O59: 19 | P59: 22.1 | Q59: 0 | R59: 19.6 | S59: 0 | T59: 16.9 | U59: 0 | V59: 12 | X59: 91 | Z59: 0 | AA59: 0 | AC59: 326 | AD59: 550 | AE59: 366 | AF59: 530 | AG59: 445 | AH59: 470 | AI59: 509 | AJ59: 406 | AK59: 627 | AL59: 288 | AN59: 0 | AP59: 0 | AQ59: 0 | AS59: 0 | AT59: 0 | AU59: 0 | AV59: 0 | AW59: 0 | AX59: 0 | AY59: 0 | AZ59: 0 | BA59: 0 | BB59: 0
B60: APPLE | C60: IPAD AIR M2 WIFI 11" 128GB | D60: 623 | E60: 3.75 | F60: TABLET | G60: 24 | H60: 753 | J60: - | K60: - | M60: 39 | N60: 20.3 | O60: 19 | P60: 19.5 | Q60: 0 | R60: 17 | S60: 0 | T60: 15.4 | U60: 0 | V60: 10.7 | X60: -130 | Z60: 0 | AA60: 0 | AC60: 97 | AD60: 487 | AE60: 136 | AF60: 468 | AG60: 215 | AH60: 408 | AI60: 253 | AJ60: 370 | AK60: 366 | AL60: 257 | AN60: 0 | AP60: 0 | AQ60: 0 | AS60: 0 | AT60: 0 | AU60: 0 | AV60: 0 | AW60: 0 | AX60: 0 | AY60: 0 | AZ60: 0 | BA60: 0 | BB60: 0
B61: APPLE | C61: IPAD AIR M2 WIFI 13" 128GB | D61: 847 | E61: 3.75 | F61: TABLET | G61: 24 | H61: 1024 | J61: - | K61: - | M61: - | N61: - | O61: 49 | P61: 26.2 | Q61: 39 | R61: 23.3 | S61: 0 | T61: 22.3 | U61: 0 | V61: 17.4 | X61: -177 | Z61: 0 | AA61: 0 | AC61: 0 | AD61: 0 | AE61: 169 | AF61: 629 | AG61: 249 | AH61: 559 | AI61: 312 | AJ61: 535 | AK61: 429 | AL61: 418 | AN61: 0 | AP61: 0 | AQ61: 0 | AS61: 0 | AT61: 0 | AU61: 0 | AV61: 0 | AW61: 0 | AX61: 0 | AY61: 0 | AZ61: 0 | BA61: 0 | BB61: 0
B62: APPLE | C62: IPAD PRO M4 WIFI 11" 256GB | D62: 1044 | E62: 3.75 | F62: TABLET | G62: 24 | H62: 1263 | J62: - | K62: - | M62: - | N62: - | O62: 79 | P62: 32.9 | Q62: 39 | R62: 31.3 | S62: 0 | T62: 30.3 | U62: 0 | V62: 25.4 | X62: -219 | Z62: 0 | AA62: 0 | AC62: 0 | AD62: 0 | AE62: 175 | AF62: 790 | AG62: 254 | AH62: 751 | AI62: 317 | AJ62: 727 | AK62: 434 | AL62: 610 | AN62: 0 | AP62: 0 | AQ62: 0 | AS62: 0 | AT62: 0 | AU62: 0 | AV62: 0 | AW62: 0 | AX62: 0 | AY62: 0 | AZ62: 0 | BA62: 0 | BB62: 0
B63: APPLE | C63: IPHONE 14 128GB CON 5G | D63: 920 | E63: 3.25 | F63: SMARTPHONE | G63: 24 | H63: 741 | J63: - | K63: - | M63: 39 | N63: 22 | O63: 19 | P63: 21.2 | Q63: 0 | R63: 18.7 | S63: 0 | T63: 16 | U63: 0 | V63: 11.1 | X63: 179 | Z63: 0 | AA63: 0 | AC63: 353 | AD63: 528 | AE63: 392 | AF63: 509 | AG63: 471 | AH63: 449 | AI63: 536 | AJ63: 384 | AK63: 654 | AL63: 266 | AN63: 0 | AP63: 0 | AQ63: 0 | AS63: 0 | AT63: 0 | AU63: 0 | AV63: 0 | AW63: 0 | AX63: 0 | AY63: 0 | AZ63: 0 | BA63: 0 | BB63: 0
B64: APPLE | C64: IPHONE 15 128GB CON 5G | D64: 883 | E64: 3.25 | F64: SMARTPHONE | G64: 24 | H64: 864 | J64: - | K64: - | M64: - | N64: - | O64: 29 | P64: 24.8 | Q64: 0 | R64: 22.7 | S64: 0 | T64: 20 | U64: 0 | V64: 15.1 | X64: 19 | Z64: 0 | AA64: 0 | AC64: 0 | AD64: 0 | AE64: 259 | AF64: 595 | AG64: 338 | AH64: 545 | AI64: 403 | AJ64: 480 | AK64: 521 | AL64: 362 | AN64: 0 | AP64: 0 | AQ64: 0 | AS64: 0 | AT64: 0 | AU64: 0 | AV64: 0 | AW64: 0 | AX64: 0 | AY64: 0 | AZ64: 0 | BA64: 0 | BB64: 0
B65: APPLE | C65: IPHONE 16 128GB CON 5G | D65: 883 | E65: 3.25 | F65: SMARTPHONE | G65: 24 | H65: 967 | J65: - | K65: - | M65: - | N65: - | O65: 49 | P65: 27.2 | Q65: 39 | R65: 24.3 | S65: 0 | T65: 23.3 | U65: 0 | V65: 18.4 | X65: -84 | Z65: 0 | AA65: 0 | AC65: 0 | AD65: 0 | AE65: 181 | AF65: 653 | AG65: 261 | AH65: 583 | AI65: 324 | AJ65: 559 | AK65: 441 | AL65: 442 | AN65: 0 | AP65: 0 | AQ65: 0 | AS65: 0 | AT65: 0 | AU65: 0 | AV65: 0 | AW65: 0 | AX65: 0 | AY65: 0 | AZ65: 0 | BA65: 0 | BB65: 0
B66: APPLE | C66: IPHONE 16 256GB CON 5G | D66: 983 | E66: 3.25 | F66: SMARTPHONE | G66: 24 | H66: 1101 | J66: - | K66: - | M66: - | N66: - | O66: 49 | P66: 31.6 | Q66: 39 | R66: 28.7 | S66: 0 | T66: 27.7 | U66: 0 | V66: 22.8 | X66: -118 | Z66: 0 | AA66: 0 | AC66: 0 | AD66: 0 | AE66: 176 | AF66: 758 | AG66: 255 | AH66: 689 | AI66: 318 | AJ66: 665 | AK66: 436 | AL66: 547 | AN66: 0 | AP66: 0 | AQ66: 0 | AS66: 0 | AT66: 0 | AU66: 0 | AV66: 0 | AW66: 0 | AX66: 0 | AY66: 0 | AZ66: 0 | BA66: 0 | BB66: 0
B67: APPLE | C67: IPHONE 16 PLUS 128GB CON 5G | D67: 998 | E67: 3.25 | F67: SMARTPHONE | G67: 24 | H67: 1121 | J67: - | K67: - | M67: - | N67: - | O67: 49 | P67: 32.2 | Q67: 39 | R67: 29.3 | S67: 0 | T67: 28.3 | U67: 0 | V67: 23.4 | X67: -123 | Z67: 0 | AA67: 0 | AC67: 0 | AD67: 0 | AE67: 176 | AF67: 773 | AG67: 256 | AH67: 703 | AI67: 319 | AJ67: 679 | AK67: 436 | AL67: 562 | AN67: 0 | AP67: 0 | AQ67: 0 | AS67: 0 | AT67: 0 | AU67: 0 | AV67: 0 | AW67: 0 | AX67: 0 | AY67: 0 | AZ67: 0 | BA67: 0 | BB67: 0
B68: APPLE | C68: IPHONE 16 PLUS 256GB CON 5G | D68: 1097 | E68: 3.25 | F68: SMARTPHONE | G68: 24 | H68: 1254 | J68: - | K68: - | M68: - | N68: - | O68: 79 | P68: 35.2 | Q68: 39 | R68: 33.6 | S68: 0 | T68: 32.6 | U68: 0 | V68: 27.7 | X68: -157 | Z68: 0 | AA68: 0 | AC68: 0 | AD68: 0 | AE68: 173 | AF68: 845 | AG68: 252 | AH68: 806 | AI68: 315 | AJ68: 782 | AK68: 432 | AL68: 665 | AN68: 0 | AP68: 0 | AQ68: 0 | AS68: 0 | AT68: 0 | AU68: 0 | AV68: 0 | AW68: 0 | AX68: 0 | AY68: 0 | AZ68: 0 | BA68: 0 | BB68: 0
B69: APPLE | C69: IPHONE 16 PRO 128GB CON 5G | D69: 1074 | E69: 3.25 | F69: SMARTPHONE | G69: 24 | H69: 1223 | J69: - | K69: - | M69: - | N69: - | O69: 79 | P69: 34.2 | Q69: 39 | R69: 32.6 | S69: 0 | T69: 31.6 | U69: 0 | V69: 26.7 | X69: -149 | Z69: 0 | AA69: 0 | AC69: 0 | AD69: 0 | AE69: 174 | AF69: 821 | AG69: 253 | AH69: 782 | AI69: 316 | AJ69: 758 | AK69: 433 | AL69: 641 | AN69: 0 | AP69: 0 | AQ69: 0 | AS69: 0 | AT69: 0 | AU69: 0 | AV69: 0 | AW69: 0 | AX69: 0 | AY69: 0 | AZ69: 0 | BA69: 0 | BB69: 0
B70: APPLE | C70: IPHONE 16 PRO 256GB CON 5G | D70: 1174 | E70: 3.25 | F70: SMARTPHONE | G70: 24 | H70: 1357 | J70: - | K70: - | M70: - | N70: - | O70: 129 | P70: 36.4 | Q70: 99 | R70: 34.4 | S70: 49 | T70: 33.8 | U70: 29 | V70: 29.8 | X70: -183 | Z70: 0 | AA70: 0 | AC70: 0 | AD70: 0 | AE70: 171 | AF70: 874 | AG70: 249 | AH70: 826 | AI70: 314 | AJ70: 811 | AK70: 430 | AL70: 715 | AN70: 0 | AP70: 0 | AQ70: 0 | AS70: 0 | AT70: 0 | AU70: 0 | AV70: 0 | AW70: 0 | AX70: 0 | AY70: 0 | AZ70: 0 | BA70: 0 | BB70: 0
B71: APPLE | C71: IPHONE 16 PRO MAX 256 CON 5G | D71: 1265 | E71: 3.25 | F71: SMARTPHONE | G71: 24 | H71: 1480 | J71: - | K71: - | M71: - | N71: - | O71: 129 | P71: 40.4 | Q71: 99 | R71: 38.3 | S71: 49 | T71: 37.8 | U71: 29 | V71: 33.8 | X71: -215 | Z71: 0 | AA71: 0 | AC71: 0 | AD71: 0 | AE71: 166 | AF71: 970 | AG71: 247 | AH71: 919 | AI71: 309 | AJ71: 907 | AK71: 425 | AL71: 811 | AN71: 0 | AP71: 0 | AQ71: 0 | AS71: 0 | AT71: 0 | AU71: 0 | AV71: 0 | AW71: 0 | AX71: 0 | AY71: 0 | AZ71: 2.6 | BA71: 0 | BB71: 0
B72: APPLE | C72: IPHONE 16 PRO MAX 512 CON 5G | D72: 1456 | E72: 3.25 | F72: SMARTPHONE | G72: 24 | H72: 1736 | J72: - | K72: - | M72: - | N72: - | O72: 139 | P72: 48.2 | Q72: 129 | R72: 45.3 | S72: 109 | T72: 43.5 | U72: 89 | V72: 39.4 | X72: -280 | Z72: 0 | AA72: 0 | AC72: 0 | AD72: 0 | AE72: 160 | AF72: 1157 | AG72: 240 | AH72: 1087 | AI72: 303 | AJ72: 1044 | AK72: 421 | AL72: 946 | AN72: 0 | AP72: 0 | AQ72: 0 | AS72: 0 | AT72: 0 | AU72: 0 | AV72: 0 | AW72: 0 | AX72: 0 | AY72: 0 | AZ72: 0 | BA72: 0 | BB72: 0
B73: LENOVO | C73: LENOVO IDEAPAD 1 15ADA7 4120 8+256GB | D73: 462 | E73: 5.33 | F73: PC | G73: 24 | H73: 461 | J73: - | K73: - | M73: 39 | N73: 11.2 | O73: 19 | P73: 10.4 | Q73: 0 | R73: 7.8 | S73: 0 | T73: 6.2 | U73: 0 | V73: 1.5 | X73: 1 | Z73: 0 | AA73: 0 | AC73: 154 | AD73: 269 | AE73: 193 | AF73: 250 | AG73: 275 | AH73: 187 | AI73: 313 | AJ73: 149 | AK73: 426 | AL73: 36 | AN73: -49 | AP73: 0 | AQ73: 0 | AS73: 0 | AT73: -1.3 | AU73: 0 | AV73: -1.3 | AW73: 0 | AX73: -1.3 | AY73: 0 | AZ73: 3.2 | BA73: 0 | BB73: 1.5
B74: LENOVO | C74: LENOVO IDEAPAD 3 15IAH8 CI5 8+512GB | D74: 620 | E74: 5.33 | F74: PC | G74: 24 | H74: 750 | J74: - | K74: - | M74: 39 | N74: 20.2 | O74: 19 | P74: 19.4 | Q74: 0 | R74: 16.9 | S74: 0 | T74: 14.2 | U74: 0 | V74: 9.3 | X74: -130 | Z74: 0 | AA74: 0 | AC74: 96 | AD74: 485 | AE74: 135 | AF74: 466 | AG74: 214 | AH74: 406 | AI74: 279 | AJ74: 341 | AK74: 397 | AL74: 223 | AN74: 0 | AP74: 0 | AQ74: 0 | AS74: =NA() -> #N/A | AT74: =NA() -> #N/A | AU74: =NA() -> #N/A | AV74: =NA() -> #N/A | AW74: =NA() -> #N/A | AX74: =NA() -> #N/A | AY74: =NA() -> #N/A | AZ74: =NA() -> #N/A | ... BB74: =NA() -> #N/A
B75: LENOVO | C75: LENOVO IDEAPAD 3 15IAH8 CI5 8+512GB + TAB M11 WIFI | D75: 620 | E75: 5.33 | F75: PC | G75: 24 | H75: 750 | J75: - | K75: - | M75: 39 | N75: 20.2 | O75: 19 | P75: 19.4 | Q75: 0 | R75: 16.9 | S75: 0 | T75: 14.2 | U75: 0 | V75: 9.3 | X75: -130 | Z75: 0 | AA75: 0 | AC75: 96 | AD75: 485 | AE75: 135 | AF75: 466 | AG75: 214 | AH75: 406 | AI75: 279 | AJ75: 341 | AK75: 397 | AL75: 223 | AN75: 0 | AP75: 0 | AQ75: 0 | AS75: =NA() -> #N/A | AT75: =NA() -> #N/A | AU75: =NA() -> #N/A | AV75: =NA() -> #N/A | AW75: =NA() -> #N/A | AX75: =NA() -> #N/A | AY75: =NA() -> #N/A | AZ75: =NA() -> #N/A | ... BB75: =NA() -> #N/A
B76: LENOVO | C76: LENOVO IDEAPAD 3 15ITL6 CI5 | D76: 638 | E76: 5.33 | F76: PC | G76: 24 | H76: 750 | J76: - | K76: - | M76: 39 | N76: 20.2 | O76: 19 | P76: 19.4 | Q76: 0 | R76: 16.9 | S76: 0 | T76: 12 | U76: 0 | V76: 9.3 | X76: -112 | Z76: 0 | AA76: 0 | AC76: 114 | AD76: 485 | AE76: 153 | AF76: 466 | AG76: 232 | AH76: 406 | AI76: 350 | AJ76: 288 | AK76: 415 | AL76: 223 | AN76: 61 | AP76: 0 | AQ76: 0 | AS76: 0 | AT76: 2.1 | AU76: 0 | AV76: 2.2 | AW76: 0 | AX76: 2.2 | AY76: 0 | AZ76: 0 | BA76: 0 | BB76: 2.2
B77: LENOVO | C77: LENOVO IDEAPAD 5 16IRL8 I7 13GEN 16GB+1TB | D77: 915 | E77: 5.33 | F77: PC | G77: 24 | H77: 1029 | J77: - | K77: - | M77: - | N77: - | O77: 49 | P77: 26.4 | Q77: 39 | R77: 23.5 | S77: 0 | T77: 22.5 | U77: 0 | V77: 17.6 | X77: -114 | Z77: 0 | AA77: 0 | AC77: 0 | AD77: 0 | AE77: 232 | AF77: 634 | AG77: 312 | AH77: 564 | AI77: 375 | AJ77: 540 | AK77: 493 | AL77: 422 | AN77: 0 | AP77: 0 | AQ77: 0 | AS77: 0 | AT77: 0 | AU77: 0 | AV77: 0 | AW77: 0 | AX77: 0 | AY77: 0 | AZ77: 0 | BA77: 0 | BB77: 0
B78: LENOVO | C78: LENOVO LOQ 3 15IRH8 i5 RTX 2050 | D78: 948 | E78: 5.33 | F78: PC | G78: 24 | H78: 1113 | J78: - | K78: - | M78: - | N78: - | O78: 49 | P78: 28.8 | Q78: 39 | R78: 25.9 | S78: 0 | T78: 24.9 | U78: 0 | V78: 20 | X78: -165 | Z78: 0 | AA78: 0 | AC78: 0 | AD78: 0 | AE78: 208 | AF78: 691 | AG78: 287 | AH78: 622 | AI78: 350 | AJ78: 598 | AK78: 468 | AL78: 480 | AN78: 0 | AP78: 0 | AQ78: 0 | AS78: 0 | AT78: 0 | AU78: 0 | AV78: 0 | AW78: 0 | AX78: 0 | AY78: 0 | AZ78: -2.8 | BA78: 0 | BB78: 0
B79: LENOVO | C79: LENOVO P3 CHROMEBOOK PLUS 14" i3 8+256GB | D79: 525 | E79: 5.33 | F79: PC | G79: 24 | H79: 489 | J79: - | K79: - | M79: 0 | N79: 13.2 | O79: 0 | P79: 11.8 | Q79: 0 | R79: 8.4 | S79: 0 | T79: 6.8 | U79: 0 | V79: 2.1 | X79: 36 | Z79: 0 | AA79: 0 | AC79: 208 | AD79: 317 | AE79: 242 | AF79: 283 | AG79: 323 | AH79: 202 | AI79: 362 | AJ79: 163 | AK79: 475 | AL79: 50 | AN79: 0 | AP79: 0 | AQ79: 0 | AS79: 0 | AT79: 0 | AU79: 0 | AV79: 0 | AW79: 0 | AX79: 0 | AY79: 0 | AZ79: 4.8 | BA79: 0 | BB79: 0.1
B80: LG | C80: LG SMART TV 32" LQ | D80: 215 | E80: 0 | F80: SMART TV | G80: 24 | H80: 259 | J80: - | K80: - | M80: 0 | N80: 5.5 | O80: 0 | P80: 4.1 | Q80: 0 | R80: 0 | S80: 0 | T80: 0 | U80: 0 | V80: 0 | X80: -44 | Z80: 0 | AA80: 0 | AC80: 83 | AD80: 132 | AE80: 117 | AF80: 98 | AG80: 215 | AH80: 0 | AI80: 215 | AJ80: 0 | AK80: 215 | AL80: 0 | AN80: 0 | AP80: 0 | AQ80: 0 | AS80: 0 | AT80: 0 | AU80: 0 | AV80: 0 | AW80: 0 | AX80: 0 | AY80: 0 | AZ80: 0 | BA80: 0 | BB80: 0
B81: LG | C81: LG SMART TV 43" UR78 4K | D81: 396 | E81: 0 | F81: SMART TV | G81: 24 | H81: 479 | J81: - | K81: - | M81: 0 | N81: 10 | O81: 0 | P81: 8.7 | Q81: 0 | R81: 5.3 | S81: 0 | T81: 3.7 | U81: 0 | V81: 0 | X81: -83 | Z81: 0 | AA81: 0 | AC81: 156 | AD81: 240 | AE81: 187 | AF81: 209 | AG81: 269 | AH81: 127 | AI81: 307 | AJ81: 89 | AK81: 396 | AL81: 0 | AN81: 0 | AP81: 0 | AQ81: 0 | AS81: 0 | AT81: 0 | AU81: 0 | AV81: 0 | AW81: 0 | AX81: 0 | AY81: 0 | AZ81: 0 | BA81: 0 | BB81: 0
B82: LG | C82: LG SMART TV 50" UR78 4K | D82: 479 | E82: 0 | F82: SMART TV | G82: 24 | H82: 579 | J82: - | K82: - | M82: 0 | N82: 12.3 | O82: 0 | P82: 11 | Q82: 0 | R82: 7.6 | S82: 0 | T82: 6 | U82: 0 | V82: 1.3 | X82: -100 | Z82: 0 | AA82: 0 | AC82: 184 | AD82: 295 | AE82: 215 | AF82: 264 | AG82: 297 | AH82: 182 | AI82: 335 | AJ82: 144 | AK82: 448 | AL82: 31 | AN82: 0 | AP82: 0 | AQ82: 0 | AS82: 0 | AT82: 0 | AU82: 0 | AV82: 0 | AW82: 0 | AX82: 0 | AY82: 0 | AZ82: 0 | BA82: 0 | BB82: 0
B83: LG | C83: LG SMART TV 55" OLED C46 4K | D83: 1735 | E83: 0 | F83: SMART TV | G83: 24 | H83: 2099 | J83: - | K83: - | M83: - | N83: - | O83: 139 | P83: 31.6 | Q83: 89 | R83: 30.5 | S83: 79 | T83: 29.3 | U83: 69 | V83: 25 | X83: -364 | Z83: 0 | AA83: 0 | AC83: 0 | AD83: 0 | AE83: 838 | AF83: 758 | AG83: 914 | AH83: 732 | AI83: 953 | AJ83: 703 | AK83: 1066 | AL83: 600 | AN83: 0 | AP83: 0 | AQ83: 0 | AS83: 0 | AT83: 0 | AU83: 0 | AV83: 0 | AW83: 0 | AX83: 0 | AY83: 0 | AZ83: 0 | BA83: 0 | BB83: 0
B84: LG | C84: LG SMART TV 55" UR78 4K | D84: 537 | E84: 0 | F84: SMART TV | G84: 24 | H84: 649 | J84: - | K84: - | M84: 0 | N84: 14.3 | O84: 0 | P84: 12.9 | Q84: 0 | R84: 9.6 | S84: 0 | T84: 7.9 | U84: 0 | V84: 3.3 | X84: -112 | Z84: 0 | AA84: 0 | AC84: 194 | AD84: 343 | AE84: 227 | AF84: 310 | AG84: 307 | AH84: 230 | AI84: 347 | AJ84: 190 | AK84: 458 | AL84: 79 | AN84: 0 | AP84: 0 | AQ84: 0 | AS84: 0 | AT84: 0 | AU84: 0 | AV84: 0 | AW84: 0 | AX84: 0 | AY84: 0 | AZ84: 0 | BA84: 0 | BB84: 0
B85: LG | C85: LG SMART TV 65" OLED C46 4K | D85: 2396 | E85: 0 | F85: SMART TV | G85: 24 | H85: 2899 | J85: - | K85: - | M85: - | N85: - | O85: 139 | P85: 45.8 | Q85: 89 | R85: 44.6 | S85: 79 | T85: 43.4 | U85: 69 | V85: 39.2 | X85: -503 | Z85: 0 | AA85: 0 | AC85: 0 | AD85: 0 | AE85: 1158 | AF85: 1099 | AG85: 1237 | AH85: 1070 | AI85: 1275 | AJ85: 1042 | AK85: 1386 | AL85: 941 | AN85: 0 | AP85: 0 | AQ85: 0 | AS85: 0 | AT85: 0 | AU85: 0 | AV85: 0 | AW85: 0 | AX85: 0 | AY85: 0 | AZ85: 0 | BA85: 0 | BB85: 0
B86: LG | C86: LG SMART TV 65" UR78 4K | D86: 686 | E86: 0 | F86: SMART TV | G86: 24 | H86: 829 | J86: - | K86: - | M86: - | N86: - | O86: 39 | P86: 14.7 | Q86: 0 | R86: 13 | S86: 0 | T86: 11.4 | U86: 0 | V86: 6.7 | X86: -143 | Z86: 0 | AA86: 0 | AC86: 0 | AD86: 0 | AE86: 294 | AF86: 353 | AG86: 374 | AH86: 312 | AI86: 412 | AJ86: 274 | AK86: 525 | AL86: 161 | AN86: 0 | AP86: 0 | AQ86: 0 | AS86: 0 | AT86: 0 | AU86: 0 | AV86: 0 | AW86: 0 | AX86: 0 | AY86: 0 | AZ86: 0 | BA86: 0 | BB86: 0
B87: LG | C87: LG SMART TV 75" UT80 4K | D87: 1157 | E87: 0 | F87: SMART TV | G87: 24 | H87: 1399 | J87: - | K87: - | M87: - | N87: - | O87: 139 | P87: 22.9 | Q87: 89 | R87: 21.7 | S87: 79 | T87: 20.6 | U87: 0 | V87: 19.3 | X87: -242 | Z87: 0 | AA87: 0 | AC87: 0 | AD87: 0 | AE87: 468 | AF87: 550 | AG87: 547 | AH87: 521 | AI87: 584 | AJ87: 494 | AK87: 694 | AL87: 463 | AN87: 0 | AP87: 0 | AQ87: 0 | AS87: 0 | AT87: 0 | AU87: 0 | AV87: 0 | AW87: 0 | AX87: 0 | AY87: 0 | AZ87: 0 | BA87: 0 | BB87: 0
B88: LG | C88: LG ULTRA 16" U70R R5 16+512GB | D88: 867 | E88: 5.33 | F88: PC | G88: 24 | H88: 842 | J88: - | K88: - | M88: - | N88: - | O88: 29 | P88: 22.3 | Q88: 0 | R88: 20.2 | S88: 0 | T88: 17.5 | U88: 0 | V88: 12.6 | X88: 25 | Z88: 0 | AA88: 0 | AC88: 0 | AD88: 0 | AE88: 303 | AF88: 535 | AG88: 382 | AH88: 485 | AI88: 447 | AJ88: 420 | AK88: 565 | AL88: 302 | AN88: -84 | AP88: 0 | AQ88: 0 | AS88: 0 | AT88: 0 | AU88: 0 | AV88: -1.3 | AW88: 0 | AX88: -1.3 | AY88: 0 | AZ88: -1.3 | BA88: 0 | BB88: -1.3
B89: LENOVO | C89: MONITOR LENOVO 27" L27i-40 ALTAVOCES INTEGRADOS | D89: 140 | E89: 0 | F89: OC_PERIFERICOS INFORMATICA | G89: 24 | H89: 157 | J89: - | K89: - | M89: 0 | N89: 3.7 | O89: 0 | P89: 2.3 | Q89: 0 | R89: 0 | S89: 0 | T89: 0 | U89: 0 | V89: 0 | X89: -17 | Z89: 0 | AA89: 0 | AC89: 51 | AD89: 89 | AE89: 85 | AF89: 55 | AG89: 140 | AH89: 0 | AI89: 140 | AJ89: 0 | AK89: 140 | AL89: 0 | AN89: 0 | AP89: 0 | AQ89: 0 | AS89: 0 | AT89: 0 | AU89: 0 | AV89: 0 | AW89: 0 | AX89: 0 | AY89: 0 | AZ89: 0 | BA89: 0 | BB89: 0
B90: MOTOROLA | C90: MOTOROLA EDGE 50 NEO 512GB 5G | D90: 481 | E90: 3.25 | F90: SMARTPHONE | G90: 24 | H90: 509 | J90: - | K90: - | M90: 0 | N90: 11.7 | O90: 0 | P90: 10.3 | Q90: 0 | R90: 7 | S90: 0 | T90: 5.3 | U90: 0 | V90: 0 | X90: -28 | Z90: 0 | AA90: 0 | AC90: 200 | AD90: 281 | AE90: 234 | AF90: 247 | AG90: 313 | AH90: 168 | AI90: 354 | AJ90: 127 | AK90: 481 | AL90: 0 | AN90: 0 | AP90: 0 | AQ90: 0 | AS90: 0 | AT90: 0 | AU90: 0 | AV90: 0 | AW90: 0 | AX90: 0 | AY90: 0 | AZ90: 0 | BA90: 0 | BB90: 0
B91: MOTOROLA | C91: MOTOROLA EDGE 50 PRO 5G | D91: 658 | E91: 3.25 | F91: SMARTPHONE | G91: 24 | H91: 544 | J91: - | K91: - | M91: 39 | N91: 13.7 | O91: 19 | P91: 12.9 | Q91: 0 | R91: 10.4 | S91: 0 | T91: 8.8 | U91: 0 | V91: 4.1 | X91: 114 | Z91: 0 | AA91: 0 | AC91: 290 | AD91: 329 | AE91: 329 | AF91: 310 | AG91: 408 | AH91: 250 | AI91: 447 | AJ91: 211 | AK91: 560 | AL91: 98 | AN91: 0 | AP91: 0 | AQ91: 0 | AS91: 0 | AT91: 0 | AU91: 0 | AV91: 0 | AW91: 0 | AX91: 0 | AY91: 0 | AZ91: 0 | BA91: 0 | BB91: 0
B92: MOTOROLA | C92: MOTOROLA MOTO G34 5G | D92: 177 | E92: 3.25 | F92: SMARTPHONE | G92: 24 | H92: 119 | J92: - | K92: - | M92: 0 | N92: 2.3 | O92: 0 | P92: 0 | Q92: 0 | R92: 0 | S92: 0 | T92: 0 | U92: 0 | V92: 0 | X92: 58 | Z92: 0 | AA92: 0 | AC92: 122 | AD92: 55 | AE92: 177 | AF92: 0 | AG92: 177 | AH92: 0 | AI92: 177 | AJ92: 0 | AK92: 177 | AL92: 0 | AN92: 0 | AP92: 0 | AQ92: 0 | AS92: 0 | AT92: 0 | AU92: 0 | AV92: 0 | AW92: 0 | AX92: 0 | AY92: 0 | AZ92: 0 | BA92: 0 | BB92: 0
B93: MOTOROLA | C93: MOTOROLA MOTO G54 256GB 5G | D93: 199 | E93: 3.25 | F93: SMARTPHONE | G93: 24 | H93: 193 | J93: - | K93: - | M93: 0 | N93: 3.9 | O93: 0 | P93: 2.5 | Q93: 0 | R93: 0 | S93: 0 | T93: 0 | U93: 0 | V93: 0 | X93: 6 | Z93: 0 | AA93: 0 | AC93: 105 | AD93: 94 | AE93: 139 | AF93: 60 | AG93: 199 | AH93: 0 | AI93: 199 | AJ93: 0 | AK93: 199 | AL93: 0 | AN93: 0 | AP93: 0 | AQ93: 0 | AS93: 0 | AT93: 0 | AU93: 0 | AV93: 0 | AW93: 0 | AX93: 0 | AY93: 0 | AZ93: 0 | BA93: 0 | BB93: 0
B94: MOTOROLA | C94: MOTOROLA MOTO G55 256GB 5G | D94: 255 | E94: 3.25 | F94: SMARTPHONE | G94: 24 | H94: 249 | J94: - | K94: - | M94: 0 | N94: 6.2 | O94: 0 | P94: 4.8 | Q94: 0 | R94: 1.5 | S94: 0 | T94: 0 | U94: 0 | V94: 0 | X94: 6 | Z94: 0 | AA94: 0 | AC94: 106 | AD94: 149 | AE94: 140 | AF94: 115 | AG94: 219 | AH94: 36 | AI94: 255 | AJ94: 0 | AK94: 255 | AL94: 0 | AN94: 0 | AP94: 0 | AQ94: 0 | AS94: =NA() -> #N/A | AT94: =NA() -> #N/A | AU94: =NA() -> #N/A | AV94: =NA() -> #N/A | AW94: =NA() -> #N/A | AX94: =NA() -> #N/A | AY94: =NA() -> #N/A | AZ94: =NA() -> #N/A | ... BB94: =NA() -> #N/A
B95: MOTOROLA | C95: MOTOROLA MOTO G85 256GB 5G | D95: 353 | E95: 3.25 | F95: SMARTPHONE | G95: 24 | H95: 378 | J95: - | K95: - | M95: 0 | N95: 9.6 | O95: 0 | P95: 8.2 | Q95: 0 | R95: 4.9 | S95: 0 | T95: 3.3 | U95: 0 | V95: 0 | X95: -25 | Z95: 0 | AA95: 0 | AC95: 123 | AD95: 230 | AE95: 156 | AF95: 197 | AG95: 235 | AH95: 118 | AI95: 274 | AJ95: 79 | AK95: 353 | AL95: 0 | AN95: 0 | AP95: 0 | AQ95: 0 | AS95: 0 | AT95: 0 | AU95: 0 | AV95: 0 | AW95: 0 | AX95: 0 | AY95: 0 | AZ95: 0 | BA95: 0 | BB95: 0
B96: MOTOROLA | C96: MOTOROLA MOTO THINKPHONE 25 256GB 5G | D96: 481 | E96: 3.25 | F96: SMARTPHONE | G96: 24 | H96: 499 | J96: - | K96: - | M96: 0 | N96: 13 | O96: 0 | P96: 11.6 | Q96: 0 | R96: 8.3 | S96: 0 | T96: 6.7 | U96: 0 | V96: 2 | X96: -18 | Z96: 0 | AA96: 0 | AC96: 169 | AD96: 312 | AE96: 203 | AF96: 278 | AG96: 282 | AH96: 199 | AI96: 320 | AJ96: 161 | AK96: 433 | AL96: 48 | AN96: 0 | AP96: 0 | AQ96: 0 | AS96: =NA() -> #N/A | AT96: =NA() -> #N/A | AU96: =NA() -> #N/A | AV96: =NA() -> #N/A | AW96: =NA() -> #N/A | AX96: =NA() -> #N/A | AY96: =NA() -> #N/A | AZ96: =NA() -> #N/A | ... BB96: =NA() -> #N/A
B97: MOTOROLA | C97: MOTOROLA RAZR 50 256GB 5G | D97: 869 | E97: 3.25 | F97: SMARTPHONE | G97: 24 | H97: 854 | J97: - | K97: - | M97: - | N97: - | O97: 29 | P97: 22.7 | Q97: 0 | R97: 20.6 | S97: 0 | T97: 17.9 | U97: 0 | V97: 13 | X97: 15 | Z97: 0 | AA97: 0 | AC97: 0 | AD97: 0 | AE97: 295 | AF97: 545 | AG97: 375 | AH97: 494 | AI97: 439 | AJ97: 430 | AK97: 557 | AL97: 312 | AN97: 0 | AP97: 0 | AQ97: 0 | AS97: 0 | AT97: 0 | AU97: 0 | AV97: 0 | AW97: 0 | AX97: 0 | AY97: 0 | AZ97: 0 | BA97: 0 | BB97: 0
B98: OPPO | C98: OPPO A38 | D98: 191 | E98: 3.25 | F98: SMARTPHONE | G98: 24 | H98: 110 | J98: - | K98: - | M98: 0 | N98: 2.4 | O98: 0 | P98: 1.1 | Q98: 0 | R98: 0 | S98: 0 | T98: 0 | U98: 0 | V98: 0 | X98: 81 | Z98: 0 | AA98: 0 | AC98: 133 | AD98: 58 | AE98: 165 | AF98: 26 | AG98: 191 | AH98: 0 | AI98: 191 | AJ98: 0 | AK98: 191 | AL98: 0 | AN98: 0 | AP98: 0 | AQ98: 0 | AS98: 0 | AT98: 0 | AU98: 0 | AV98: 0 | AW98: 0 | AX98: 0 | AY98: 0 | AZ98: 0 | BA98: 0 | BB98: 0
B99: OPPO | C99: OPPO A40 128GB | D99: 160 | E99: 3.25 | F99: SMARTPHONE | G99: 24 | H99: 107 | J99: - | K99: - | M99: 0 | N99: 1 | O99: 0 | P99: 1 | Q99: 0 | R99: 0 | S99: 0 | T99: 0 | U99: 0 | V99: 0 | X99: 53 | Z99: 0 | AA99: 0 | AC99: 105 | AD99: 55 | AE99: 136 | AF99: 24 | AG99: 160 | AH99: 0 | AI99: 160 | AJ99: 0 | AK99: 160 | AL99: 0 | AN99: -52 | AP99: 0 | AQ99: 0 | AS99: 0 | AT99: 0 | AU99: 0 | AV99: 0 | AW99: 0 | AX99: 0 | AY99: 0 | AZ99: 0 | BA99: 0 | BB99: 0
B100: OPPO | C100: OPPO A60 128GB 5G | D100: 176 | E100: 3.25 | F100: SMARTPHONE | G100: 24 | H100: 191 | J100: - | K100: - | M100: 0 | N100: 3 | O100: 0 | P100: 1.6 | Q100: 0 | R100: 0 | S100: 0 | T100: 0 | U100: 0 | V100: 0 | X100: -15 | Z100: 0 | AA100: 0 | AC100: 104 | AD100: 72 | AE100: 138 | AF100: 38 | AG100: 176 | AH100: 0 | AI100: 176 | AJ100: 0 | AK100: 176 | AL100: 0 | AN100: 0 | AP100: 0 | AQ100: 0 | AS100: 0 | AT100: 0 | AU100: 0 | AV100: 0 | AW100: 0 | AX100: 0 | AY100: 0 | AZ100: 0 | BA100: 0 | BB100: 0
B101: OPPO | C101: OPPO A80 256GB 5G | D101: 245 | E101: 3.25 | F101: SMARTPHONE | G101: 24 | H101: 246 | J101: - | K101: - | M101: 0 | N101: 4.8 | O101: 0 | P101: 3.4 | Q101: 0 | R101: 0 | S101: 0 | T101: 0 | U101: 0 | V101: 0 | X101: -1 | Z101: 0 | AA101: 0 | AC101: 130 | AD101: 115 | AE101: 163 | AF101: 82 | AG101: 245 | AH101: 0 | AI101: 245 | AJ101: 0 | AK101: 245 | AL101: 0 | AN101: 0 | AP101: 0 | AQ101: 0 | AS101: 0 | AT101: 0 | AU101: 0 | AV101: 0 | AW101: 0 | AX101: 0 | AY101: 0 | AZ101: 0 | BA101: 0 | BB101: 0
B102: OPPO | C102: OPPO FIND X8 PRO 512GB 5G | D102: 1072 | E102: 3.25 | F102: SMARTPHONE | G102: 24 | H102: 1151 | J102: - | K102: - | M102: - | N102: - | O102: 49 | P102: 30.2 | Q102: 39 | R102: 27.3 | S102: 0 | T102: 26.3 | U102: 0 | V102: 21.4 | X102: -79 | Z102: 0 | AA102: 0 | AC102: 0 | AD102: 0 | AE102: 298 | AF102: 725 | AG102: 378 | AH102: 655 | AI102: 441 | AJ102: 631 | AK102: 558 | AL102: 514 | AN102: 0 | AP102: 0 | AQ102: 0 | AS102: 0 | AT102: 0 | AU102: =NA() -> #N/A | AV102: =NA() -> #N/A | AW102: =NA() -> #N/A | AX102: =NA() -> #N/A | AY102: =NA() -> #N/A | AZ102: =NA() -> #N/A | BA102: =NA() -> #N/A | BB102: =NA() -> #N/A
B103: OPPO | C103: OPPO RENO12 256GB 5G | D103: 428 | E103: 3.25 | F103: SMARTPHONE | G103: 24 | H103: 432 | J103: - | K103: - | M103: 0 | N103: 9.4 | O103: 0 | P103: 8 | Q103: 0 | R103: 4.6 | S103: 0 | T103: 3 | U103: 0 | V103: 0 | X103: -4 | Z103: 0 | AA103: 0 | AC103: 202 | AD103: 226 | AE103: 236 | AF103: 192 | AG103: 318 | AH103: 110 | AI103: 356 | AJ103: 72 | AK103: 428 | AL103: 0 | AN103: 0 | AP103: 0 | AQ103: 0 | AS103: 0 | AT103: 0 | AU103: 0 | AV103: 0 | AW103: 0 | AX103: 0 | AY103: 0 | AZ103: 0 | BA103: 0 | BB103: 0
B104: OPPO | C104: OPPO RENO12 FS 512GB 5G | D104: 364 | E104: 3.25 | F104: SMARTPHONE | G104: 24 | H104: 367 | J104: - | K104: - | M104: 0 | N104: 8.4 | O104: 0 | P104: 7 | Q104: 0 | R104: 3.6 | S104: 0 | T104: 2 | U104: 0 | V104: 0 | X104: -3 | Z104: 0 | AA104: 0 | AC104: 162 | AD104: 202 | AE104: 196 | AF104: 168 | AG104: 278 | AH104: 86 | AI104: 316 | AJ104: 48 | AK104: 364 | AL104: 0 | AN104: 24 | AP104: 0 | AQ104: 0 | AS104: 0 | AT104: 0 | AU104: 0 | AV104: 0 | AW104: 0 | AX104: 0 | AY104: 0 | AZ104: 0 | BA104: 0 | BB104: 0
B105: OPPO | C105: OPPO RENO12 PRO 512GB 5G | D105: 524 | E105: 3.25 | F105: SMARTPHONE | G105: 24 | H105: 518 | J105: - | K105: - | M105: 39 | N105: 11.9 | O105: 19 | P105: 11.1 | Q105: 0 | R105: 8.6 | S105: 0 | T105: 7 | U105: 0 | V105: 2.3 | X105: 6 | Z105: 0 | AA105: 0 | AC105: 199 | AD105: 286 | AE105: 239 | AF105: 266 | AG105: 318 | AH105: 206 | AI105: 356 | AJ105: 168 | AK105: 469 | AL105: 55 | AN105: 0 | AP105: 0 | AQ105: 0 | AS105: 0 | AT105: 0 | AU105: 0 | AV105: 0 | AW105: 0 | AX105: 0 | AY105: 0 | AZ105: 0 | BA105: 0 | BB105: 0
B106: ORANGE | C106: ORANGE GAMA 120 4G | D106: 74 | E106: 1.1 | F106: FIXED STYLE | G106: - | H106: - | J106: - | K106: - | M106: - | N106: - | O106: - | P106: - | Q106: - | R106: - | S106: - | T106: - | U106: - | V106: - | X106: 0 | Z106: 0 | AA106: 0 | AC106: 0 | AD106: 0 | AE106: 0 | AF106: 0 | AG106: 0 | AH106: 0 | AI106: 0 | AJ106: 0 | AK106: 0 | AL106: 0 | AN106: 0 | AP106: 0 | AQ106: 0 | AS106: 0 | AT106: 0 | AU106: 0 | AV106: 0 | AW106: 0 | AX106: 0 | AY106: 0 | AZ106: 0 | BA106: 0 | BB106: 0
B107: ORANGE | C107: ORANGE GAMA 401 CESIÓN | D107: 0 | E107: 1.1 | F107: FIXED STYLE | G107: - | H107: - | J107: - | K107: - | M107: - | N107: - | O107: - | P107: - | Q107: - | R107: - | S107: - | T107: - | U107: - | V107: - | X107: 0 | Z107: 0 | AA107: 0 | AC107: 0 | AD107: 0 | AE107: 0 | AF107: 0 | AG107: 0 | AH107: 0 | AI107: 0 | AJ107: 0 | AK107: 0 | AL107: 0 | AN107: 0 | AP107: 0 | AQ107: 0 | AS107: 0 | AT107: 0 | AU107: 0 | AV107: 0 | AW107: 0 | AX107: 0 | AY107: 0 | AZ107: 0 | BA107: 0 | BB107: 0
B108: ORANGE | C108: ORANGE GAMA 402 | D108: 70 | E108: 1.1 | F108: FIXED STYLE | G108: - | H108: - | J108: - | K108: - | M108: - | N108: - | O108: - | P108: - | Q108: - | R108: - | S108: - | T108: - | U108: - | V108: - | X108: 0 | Z108: 0 | AA108: 0 | AC108: 0 | AD108: 0 | AE108: 0 | AF108: 0 | AG108: 0 | AH108: 0 | AI108: 0 | AJ108: 0 | AK108: 0 | AL108: 0 | AN108: 0 | AP108: 0 | AQ108: 0 | AS108: 0 | AT108: 0 | AU108: 0 | AV108: 0 | AW108: 0 | AX108: 0 | AY108: 0 | AZ108: 0 | BA108: 0 | BB108: 0
B109: ORANGE | C109: ORANGE GAMA 402 CESIÓN | D109: 0 | E109: 1.1 | F109: FIXED STYLE | G109: - | H109: - | J109: - | K109: - | M109: - | N109: - | O109: - | P109: - | Q109: - | R109: - | S109: - | T109: - | U109: - | V109: - | X109: 0 | Z109: 0 | AA109: 0 | AC109: 0 | AD109: 0 | AE109: 0 | AF109: 0 | AG109: 0 | AH109: 0 | AI109: 0 | AJ109: 0 | AK109: 0 | AL109: 0 | AN109: 0 | AP109: 0 | AQ109: 0 | AS109: 0 | AT109: 0 | AU109: 0 | AV109: 0 | AW109: 0 | AX109: 0 | AY109: 0 | AZ109: 0 | BA109: 0 | BB109: 0
B110: ORANGE | C110: ORANGE GAMA 704 | D110: 104 | E110: 1.1 | F110: FIXED STYLE | G110: - | H110: - | J110: - | K110: - | M110: - | N110: - | O110: - | P110: - | Q110: - | R110: - | S110: - | T110: - | U110: - | V110: - | X110: 0 | Z110: 0 | AA110: 0 | AC110: 0 | AD110: 0 | AE110: 0 | AF110: 0 | AG110: 0 | AH110: 0 | AI110: 0 | AJ110: 0 | AK110: 0 | AL110: 0 | AN110: 0 | AP110: 0 | AQ110: 0 | AS110: 0 | AT110: 0 | AU110: 0 | AV110: 0 | AW110: 0 | AX110: 0 | AY110: 0 | AZ110: 0 | BA110: 0 | BB110: 0
B111: ORANGE | C111: ORANGE GAMA 704 CESIÓN | D111: 0 | E111: 1.1 | F111: FIXED STYLE | G111: - | H111: - | J111: - | K111: - | M111: - | N111: - | O111: - | P111: - | Q111: - | R111: - | S111: - | T111: - | U111: - | V111: - | X111: 0 | Z111: 0 | AA111: 0 | AC111: 0 | AD111: 0 | AE111: 0 | AF111: 0 | AG111: 0 | AH111: 0 | AI111: 0 | AJ111: 0 | AK111: 0 | AL111: 0 | AN111: 0 | AP111: 0 | AQ111: 0 | AS111: 0 | AT111: 0 | AU111: 0 | AV111: 0 | AW111: 0 | AX111: 0 | AY111: 0 | AZ111: 0 | BA111: 0 | BB111: 0
B112: ORANGE | C112: ORANGE GAMA 803 CESIÓN | D112: 0 | E112: 1.1 | F112: FIXED STYLE | G112: - | H112: - | J112: - | K112: - | M112: - | N112: - | O112: - | P112: - | Q112: - | R112: - | S112: - | T112: - | U112: - | V112: - | X112: 0 | Z112: 0 | AA112: 0 | AC112: 0 | AD112: 0 | AE112: 0 | AF112: 0 | AG112: 0 | AH112: 0 | AI112: 0 | AJ112: 0 | AK112: 0 | AL112: 0 | AN112: 0 | AP112: 0 | AQ112: 0 | AS112: 0 | AT112: 0 | AU112: 0 | AV112: 0 | AW112: 0 | AX112: 0 | AY112: 0 | AZ112: 0 | BA112: 0 | BB112: 0
B113: DEF | C113: PACK BALIZA CONECTADA DGT 2 UNIDADES | D113: 96 | E113: 0 | F113: OC_OTROS DISPOSITIVOS | G113: 24 | H113: 92 | J113: - | K113: - | M113: 0 | N113: 0 | O113: 0 | P113: 0 | Q113: 0 | R113: 0 | S113: 0 | T113: 0 | U113: 0 | V113: 0 | X113: 4 | Z113: 0 | AA113: 0 | AC113: 96 | AD113: 0 | AE113: 96 | AF113: 0 | AG113: 96 | AH113: 0 | AI113: 96 | AJ113: 0 | AK113: 96 | AL113: 0 | AN113: 0 | AP113: 0 | AQ113: 0 | AS113: 0 | AT113: 0 | AU113: 0 | AV113: 0 | AW113: 0 | AX113: 0 | AY113: 0 | AZ113: 0 | BA113: 0 | BB113: 0
B114: NEXTIVITY | C114: REPETIDOR NEXTIVITY CELFI CONNECT C41 | D114: 547 | E114: 0 | F114: OC_OTROS DISPOSITIVOS | G114: 24 | H114: 499 | J114: - | K114: - | M114: 0 | N114: 18.4 | O114: 0 | P114: 17 | Q114: 0 | R114: 13.7 | S114: 0 | T114: 12.1 | U114: 0 | V114: 7.4 | X114: 48 | Z114: 0 | AA114: 0 | AC114: 105 | AD114: 442 | AE114: 139 | AF114: 408 | AG114: 218 | AH114: 329 | AI114: 257 | AJ114: 290 | AK114: 369 | AL114: 178 | AN114: 0 | AP114: 0 | AQ114: 0 | AS114: 0 | AT114: 0 | AU114: 0 | AV114: 0 | AW114: 0 | AX114: 0 | AY114: 0 | AZ114: 0 | BA114: 0 | BB114: 0
B115: SAMSUNG | C115: SAMSUNG GALAXY A15 | D115: 186 | E115: 3.25 | F115: SMARTPHONE | G115: 24 | H115: 201 | J115: - | K115: - | M115: 0 | N115: 5.7 | O115: 0 | P115: 4.3 | Q115: 0 | R115: 1 | S115: 0 | T115: 0 | U115: 0 | V115: 0 | X115: -15 | Z115: 0 | AA115: 0 | AC115: 49 | AD115: 137 | AE115: 83 | AF115: 103 | AG115: 162 | AH115: 24 | AI115: 186 | AJ115: 0 | AK115: 186 | AL115: 0 | AN115: 0 | AP115: 0 | AQ115: 0 | AS115: 0 | AT115: 0.9 | AU115: 0 | AV115: 0.9 | AW115: 0 | AX115: 1 | AY115: 0 | AZ115: 0 | BA115: 0 | BB115: 0
B116: SAMSUNG | C116: SAMSUNG GALAXY A15 5G | D116: 215 | E116: 3.25 | F116: SMARTPHONE | G116: 24 | H116: 231 | J116: - | K116: - | M116: 0 | N116: 6.8 | O116: 0 | P116: 5.4 | Q116: 0 | R116: 2.1 | S116: 0 | T116: 0 | U116: 0 | V116: 0 | X116: -16 | Z116: 0 | AA116: 0 | AC116: 52 | AD116: 163 | AE116: 85 | AF116: 130 | AG116: 165 | AH116: 50 | AI116: 215 | AJ116: 0 | AK116: 215 | AL116: 0 | AN116: 0 | AP116: 0 | AQ116: 0 | AS116: 0 | AT116: 0.9 | AU116: 0 | AV116: 0.9 | AW116: 0 | AX116: 0.9 | AY116: 0 | AZ116: 0 | BA116: 0 | BB116: 0
B117: SAMSUNG | C117: SAMSUNG GALAXY A16 128GB | D117: 186 | E117: 3.25 | F117: SMARTPHONE | G117: 24 | H117: 201 | J117: - | K117: - | M117: 0 | N117: 3.5 | O117: 0 | P117: 2.1 | Q117: 0 | R117: 0 | S117: 0 | T117: 0 | U117: 0 | V117: 0 | X117: -15 | Z117: 0 | AA117: 0 | AC117: 102 | AD117: 84 | AE117: 136 | AF117: 50 | AG117: 186 | AH117: 0 | AI117: 186 | AJ117: 0 | AK117: 186 | AL117: 0 | AN117: 0 | AP117: 0 | AQ117: 0 | AS117: 0 | AT117: 0 | AU117: 0 | AV117: 0 | AW117: 0 | AX117: 0 | AY117: 0 | AZ117: 0 | BA117: 0 | BB117: 0
...

Sheet PVP VaP IEW Pro - Pyme
B2: OFERTA TÁCTICA EMPRESAS | H2: Pago Único | J2: CAPTA | M2: PORTABILIDAD
B4: ='PVP VaP - Pyme'!B4 -> 45627 | C4: ='PVP VaP - Pyme'!C4 -> 01/12 al 31/12 | J4: - | M4: ENTRADA PRO | O4: NORMAL PRO | Q4: VALOR PRO | S4: PREMIUM PRO
B5: 1. CONDICIONES DE LA OFERTA VENTA A PLAZOS (según tarifa y situación del cliente) | D5: Tarifas | H5: Todas Tarifas | J5: Todas Tarifas | M5: Internet Movil 3GB Empresa | O5: Internet Movil 10GB Empresa | Q5: Internet Movil 25GB Empresa Fibra Oro (**) | S5: Internet Movil 90GB Empresa Internet 4G en tu Negocio (excepto router) Internet Empresa Ilimitado
D13: Ampliaciones (meses antigüedad) | H13: - | J13: - | M13: + 4 M - 4 M doble capta | O13: + 4 M - 4 M doble capta | Q13: + 4 M - 4 M doble capta | S13: + 4 M - 4 M doble capta
D14: Origen (Portabilidad / Migración) | H14: Capta Pos / Pre Migra | J14: (*) Capta de cliente nuevo o de cliente -4 M, solo tienen acceso a Pago Único | M14: Pos / Migra | O14: Pos / Migra | Q14: Pos / Migra | S14: Pos / Migra
D15: CP Tarifa | H15: - | J15: - | M15: 12 M / 24 M | O15: 12 M / 24 M | Q15: 12 M / 24 M | S15: 12 M / 24 M
D16: (*) Para Capta de cliente nuevo o cliente de -4 meses que activen en el mismo acto comercial tarifas de voz y tarifas de IEW Pro, aplican las condiciones de Portabilidad origen Pospago
D17: (**) La tarifa Fibra Oro solo puede activarse con el router Alctel Airbox 4G MW40 2018
B18: 2. PRECIO DEL TERMINAL POR GRUPO DE TARIFAS | H18: Pago Único | J18: PVPR CAPTA | M18: PVPR PORTABILIDAD | V18: DxC Pago Único | X18: DxC CAPTA | AA18: DxC PORTABILIDAD
M20: GRUPOS DE TARIFAS IEW Pro | AA20: GRUPOS DE TARIFAS IEW Pro
J22: - | M22: ENTRADA PRO | O22: NORMAL PRO | Q22: VALOR PRO | S22: PREMIUM PRO | X22: - | AA22: ENTRADA PRO | AC22: NORMAL PRO | AE22: VALOR PRO | AG22: PREMIUM PRO
B24: MARCA | C24: Modelo (Novedades) | D24: Precio Cesión | E24: Canon Digital | F24: Gama | G24: Meses Cuota | H24: Pago Unico (sin IVA) | J24: Pago Inicial (sin IVA) | K24: Cuota Mes (sin IVA) | M24: Pago Inicial (sin IVA) | N24: Cuota Mes (sin IVA) | O24: Pago Inicial (sin IVA) | P24: Cuota Mes (sin IVA) | Q24: Pago Inicial (sin IVA) | R24: Cuota Mes (sin IVA) | S24: Pago Inicial (sin IVA) | T24: Cuota Mes (sin IVA) | V24: DxC Pago Unico | X24: DxC Precio | Y24: DxC VaP | AA24: DxC Precio | AB24: DxC VaP | AC24: DxC Precio | AD24: DxC VaP | AE24: DxC Precio | AF24: DxC VaP | AG24: DxC Precio | AH24: DxC VaP
B25: ALCATEL | C25: ALCATEL AIRBOX 4G MW45 | D25: 49 | E25: 0 | F25: MBB | G25: 12 | H25: 42.14876 | J25: - | K25: - | M25: 0 | N25: 3 | O25: 0 | P25: 1 | Q25: 0 | R25: 1 | S25: 0 | T25: 0 | V25: 6.8512397 | X25: - | Y25: - | AA25: 13 | AB25: 36 | AC25: 37 | AD25: 12 | AE25: 37 | AF25: 12 | AG25: 49 | AH25: 0
B26: ALCATEL | C26: ALCATEL AIRBOX 4G MW70 | D26: 59 | E26: 0 | F26: MBB | G26: 12 | H26: 61.157025 | J26: - | K26: - | M26: 0 | N26: 4 | O26: 0 | P26: 3 | Q26: 0 | R26: 3 | S26: 0 | T26: 1 | V26: -2.1570248 | X26: - | Y26: - | AA26: 11 | AB26: 48 | AC26: 23 | AD26: 36 | AE26: 23 | AF26: 36 | AG26: 47 | AH26: 12
B27: HUAWEI | C27: FLYBOX HUAWEI B535 232A 4G | D27: 132 | E27: 0 | F27: MBB | G27: 12 | H27: 59 | J27: - | K27: - | M27: 0 | N27: 4 | O27: 0 | P27: 3 | Q27: 0 | R27: 3 | S27: 0 | T27: 1 | V27: 73 | X27: - | Y27: - | AA27: 84 | AB27: 48 | AC27: 96 | AD27: 36 | AE27: 96 | AF27: 36 | AG27: 120 | AH27: 12
B28: HUAWEI | C28: FLYBOX HUAWEI B535 232A 4G (1) | D28: 0 | E28: 0 | F28: MBB | G28: 12 | H28: 0 | J28: - | K28: - | M28: - | N28: - | O28: - | P28: - | Q28: - | R28: - | S28: 0 | T28: 0 | V28: 0 | X28: - | Y28: - | AA28: - | AB28: - | AC28: - | AD28: - | AE28: - | AF28: - | AG28: 0 | AH28: 0
B29: HUAWEI | C29: HUAWEI AIRBOX E5576-320 IEW 4G | D29: 66 | E29: 0 | F29: MBB | G29: 12 | H29: 57.024793 | J29: - | K29: - | M29: 0 | N29: 3 | O29: 0 | P29: 2 | Q29: 0 | R29: 2 | S29: 0 | T29: 0 | V29: 8.9752066 | X29: - | Y29: - | AA29: 30 | AB29: 36 | AC29: 42 | AD29: 24 | AE29: 42 | AF29: 24 | AG29: 66 | AH29: 0
B30: TP-LINK | C30: ROUTER TPLINK MR200 IEW 4G | D30: 58 | E30: 0 | F30: MBB | G30: 12 | H30: 48 | J30: - | K30: - | M30: 0 | N30: 4 | O30: 0 | P30: 2 | Q30: 0 | R30: 2 | S30: 0 | T30: 1 | V30: 10 | X30: - | Y30: - | AA30: 10 | AB30: 48 | AC30: 34 | AD30: 24 | AE30: 34 | AF30: 24 | AG30: 46 | AH30: 12
B31: TP-LINK | C31: ROUTER TPLINK MR200 IEW 4G (2) | D31: 58 | E31: 0 | F31: MBB | G31: - | H31: 48 | J31: - | K31: - | M31: - | N31: - | O31: - | P31: - | Q31: - | R31: - | S31: - | T31: - | V31: 10 | X31: - | Y31: - | AA31: - | AB31: - | AC31: - | AD31: - | AE31: - | AF31: - | AG31: - | AH31: -
B32: TP-LINK | C32: TP-LINK FLYBOX 4G (1) | D32: 0 | E32: 0 | F32: MBB | G32: 12 | H32: 0 | J32: - | K32: - | M32: - | N32: - | O32: - | P32: - | Q32: - | R32: - | S32: 0 | T32: 0 | V32: 0 | X32: - | Y32: - | AA32: - | AB32: - | AC32: - | AD32: - | AE32: - | AF32: - | AG32: 0 | AH32: 0
B33: ZTE | C33: ZTE AIRBOX MF920U 4G | D33: 66 | E33: 0 | F33: MBB | G33: 12 | H33: 45.454545 | J33: - | K33: - | M33: 0 | N33: 3 | O33: 0 | P33: 2 | Q33: 0 | R33: 2 | S33: 0 | T33: 0 | V33: 20.545455 | X33: - | Y33: - | AA33: 30 | AB33: 36 | AC33: 42 | AD33: 24 | AE33: 42 | AF33: 24 | AG33: 66 | AH33: 0
B34: ZTE | C34: ZTE AIRBOX MU5001 5G | D34: 244 | E34: 0 | F34: MBB | G34: 24 | H34: 295 | J34: - | K34: - | M34: 39 | N34: 7 | O34: 0 | P34: 7 | Q34: 0 | R34: 7 | S34: 0 | T34: 6 | V34: -51 | AA34: 37 | AB34: 168 | AC34: 76 | AD34: 168 | AE34: 76 | AF34: 168 | AG34: 100 | AH34: 144
B35: ZTE | C35: ZTE FLYBOX MC801A 5G | D35: 200 | E35: 0 | F35: MBB | G35: 24 | H35: 242 | J35: - | K35: - | M35: 29 | N35: 6 | O35: 0 | P35: 6 | Q35: 0 | R35: 6 | S35: 0 | T35: 6 | V35: -42 | X35: - | Y35: - | AA35: 27 | AB35: 144 | AC35: 56 | AD35: 144 | AE35: 56 | AF35: 144 | AG35: 56 | AH35: 144
B36: NOKIA | C36: FLYBOX NOKIA FASTMILE 5G | D36: 207 | E36: 0 | F36: MBB | G36: 24 | H36: 177.68595 | J36: - | K36: - | M36: 29 | N36: 5 | O36: 0 | P36: 5 | Q36: 0 | R36: 5 | S36: 0 | T36: 5 | V36: 29.31405 | X36: - | Y36: - | AA36: 58 | AB36: 120 | AC36: 87 | AD36: 120 | AE36: 87 | AF36: 120 | AG36: 87 | AH36: 120
B37: HUAWEI | C37: FLYBOX HUAWEI H153-381 5G | D37: 248 | E37: 0 | F37: MBB | G37: 24 | H37: 132 | J37: - | K37: - | M37: 0 | N37: 4 | O37: 0 | P37: 4 | Q37: 0 | R37: 4 | S37: 0 | T37: 3 | V37: 116 | X37: - | Y37: - | AA37: 152 | AB37: 96 | AC37: 152 | AD37: 96 | AE37: 152 | AF37: 96 | AG37: 176 | AH37: 72
B38: SAMSUNG | C38: SAMSUNG GALAXY TAB A9 8,7" WIFI | D38: 182 | E38: 3.75 | F38: TABLET | G38: 24 | H38: 161.98347 | J38: - | K38: - | M38: 29 | N38: 4 | O38: 0 | P38: 5 | Q38: 0 | R38: 5 | S38: 0 | T38: 4 | V38: 20.016529 | X38: - | Y38: - | AA38: 57 | AB38: 96 | AC38: 62 | AD38: 120 | AE38: 62 | AF38: 120 | AG38: 86 | AH38: 96
B39: XIAOMI | C39: XIAOMI REDMI PAD SE 8.7" WIFI 4+128GB | D39: 167 | E39: 3.75 | F39: TABLET | G39: 24 | H39: 123.1405 | J39: - | K39: - | M39: 0 | N39: 4 | O39: 0 | P39: 4 | Q39: 0 | R39: 4 | S39: 0 | T39: 3 | V39: 43.859504 | X39: - | Y39: - | AA39: 71 | AB39: 96 | AC39: 71 | AD39: 96 | AE39: 71 | AF39: 96 | AG39: 95 | AH39: 72
B42: Condiciones especiales para Fibra Oro
B43: ZTE | C43: ZTE AIRBOX MF920U 4G | D43: 66 | E43: 0 | F43: MBB | G43: 12 | H43: 47.11 | J43: - | K43: - | M43: - | N43: - | O43: - | P43: - | Q43: 0 | R43: 0 | S43: - | T43: - | V43: 18.89 | X43: - | Y43: - | AA43: - | AB43: - | AC43: - | AD43: - | AE43: 66 | AF43: 0 | AG43: - | AH43: -
B44: ALCATEL | C44: ALCATEL AIRBOX 4G MW45 | D44: 49 | E44: 0 | F44: MBB | G44: 12 | H44: 43.801653 | J44: - | K44: - | M44: - | N44: - | O44: - | P44: - | Q44: 0 | R44: 0 | S44: - | T44: - | V44: 5.1983471 | X44: - | Y44: - | AA44: - | AB44: - | AC44: - | AD44: - | AE44: 49 | AF44: 0 | AG44: - | AH44: -
C48: (1) Solo oferta en VaP (cesión) para 4G en tu Negocio e Internet Empresas Ilimitado
C49: (2) Solo oferta en Pago único para 4G en tu Negocio e Internet Empresas Ilimitado

Sheet PVP Subv - Optima Pyme
B2: OFERTA TÁCTICA EMPRESAS | I2: CAPTA | O2: PORTABILIDAD
B4: ='PVP VaP - Pyme'!B4 -> 45627 | C4: ='PVP VaP - Pyme'!C4 -> 01/12 al 31/12 | I4: ENTRADA PRO | J4: NORMAL PRO | K4: VALOR PRO | L4: PREMIUM PRO | M4: TOP PRO | O4: ENTRADA PRO | P4: NORMAL PRO | Q4: VALOR PRO | R4: PREMIUM PRO | S4: TOP PRO
B5: 1. CONDICIONES DE LA OFERTA SUBVENCIONADA (según tarifa y situación del cliente) | D5: Tarifas | I5: T. Optima Plus Empresas T. Optima Plus Empresas Big + Empresas Voz y Empresas 1 | J5: T. Optima Plus Empresas T. Optima Plus Empresas Big + Empresas 5 y Empresas Intranet | K5: T. Optima Plus Empresas T. Optima Plus Empresas Big + Empresas 20 | L5: T. Optima Plus Empresas T. Optima Plus Empresas Big + Empresas Infinita | M5: T. Optima Plus Empresas T. Optima Plus Empresas Big + Empresas Internacional | O5: T. Optima Plus Empresas T. Optima Plus Empresas Big + Empresas Voz y Empresas 1 | P5: T. Optima Plus Empresas T. Optima Plus Empresas Big + Empresas 5 y Empresas Intranet | Q5: T. Optima Plus Empresas T. Optima Plus Empresas Big + Empresas 20 | R5: T. Optima Plus Empresas T. Optima Plus Empresas Big + Empresas Infinita | S5: T. Optima Plus Empresas T. Optima Plus Empresas Big + Empresas Internacional
D12: Ampliaciones (meses antigüedad) | I12: Todos | J12: Todos | K12: Todos | L12: Todos | M12: Todos | O12: Todos | P12: Todos | Q12: Todos | R12: Todos | S12: Todos
D13: Origen (Portabilidad / Migración) | I13: Capta Prepago Migracion | J13: Capta Prepago Migracion | K13: Capta Prepago Migracion | L13: Capta Prepago Migracion | M13: Capta Prepago Migracion | O13: Pospago | P13: Pospago | Q13: Pospago | R13: Pospago | S13: Pospago
D14: CP Tarifa | I14: CMPT24AG | J14: CMPT24AG | K14: CMPT24AG | L14: CMPT24AG | M14: CMPT24AG | O14: CMPT24AG | P14: CMPT24AG | Q14: CMPT24AG | R14: CMPT24AG | S14: CMPT24AG
D15: CP Terminal | I15: CPTE224 | J15: CPTE324 | K15: CPTE324 | L15: CPTE424 | M15: CPTE424 | O15: CPTE224 | P15: CPTE324 | Q15: CPTE324 | R15: CPTE424 | S15: CPTE424
I16: Las condiciones de los modulos Entrada Pro y Normal Pro aplican para los terminales VOZ y FIX tanto si activan sólo voz como si activan el paquete de voz + datos | U16: DIFERENCIAS Vs MES ANTERIOR
B19: 2. PRECIO DEL TERMINAL POR GRUPO DE TARIFAS | I19: DxC CAPTA | O19: DxC PORTABILIDAD | U19: DxC CAPTA | AA19: DxC PORTABILIDAD | AG19: PVPR CAPTA | AM19: PVPR PORTABILIDAD
I21: GRUPOS DE TARIFAS MOVIL | O21: GRUPOS DE TARIFAS MOVIL | U21: GRUPOS DE TARIFAS MOVIL | AA21: GRUPOS DE TARIFAS MOVIL | AG21: GRUPOS DE TARIFAS MOVIL | AM21: GRUPOS DE TARIFAS MOVIL
I23: ENTRADA PRO | J23: NORMAL PRO | K23: VALOR PRO | L23: PREMIUM PRO | M23: TOP PRO | O23: ENTRADA PRO | P23: NORMAL PRO | Q23: VALOR PRO | R23: PREMIUM PRO | S23: TOP PRO | U23: ENTRADA PRO | V23: NORMAL PRO | W23: VALOR PRO | X23: PREMIUM PRO | Y23: TOP PRO | AA23: ENTRADA PRO | AB23: NORMAL PRO | AC23: VALOR PRO | AD23: PREMIUM PRO | AE23: TOP PRO | AG23: ENTRADA PRO | AH23: NORMAL PRO | AI23: VALOR PRO | AJ23: PREMIUM PRO | AK23: TOP PRO | AM23: ENTRADA PRO | AN23: NORMAL PRO | AO23: VALOR PRO | AP23: PREMIUM PRO | AQ23: TOP PRO
B25: MARCA | C25: Modelo (Novedades) | D25: Precio Cesión | E25: Canon Digital | F25: Gama | I25: DxC (sin IVA) | J25: DxC (sin IVA) | K25: DxC (sin IVA) | L25: DxC (sin IVA) | M25: DxC (sin IVA) | O25: DxC (sin IVA) | P25: DxC (sin IVA) | Q25: DxC (sin IVA) | R25: DxC (sin IVA) | S25: DxC (sin IVA) | U25: DxC (sin IVA) | V25: DxC (sin IVA) | W25: DxC (sin IVA) | X25: DxC (sin IVA) | Y25: DxC (sin IVA) | AA25: DxC (sin IVA) | AB25: DxC (sin IVA) | AC25: DxC (sin IVA) | AD25: DxC (sin IVA) | AE25: DxC (sin IVA) | AG25: PVP (sin IVA) | AH25: PVP (sin IVA) | AI25: PVP (sin IVA) | AJ25: PVP (sin IVA) | AK25: PVP (sin IVA) | AM25: PVP (sin IVA) | AN25: PVP (sin IVA) | AO25: PVP (sin IVA) | AP25: PVP (sin IVA) | AQ25: PVP (sin IVA)
B26: ORANGE | C26: AD HOC H3 CESIÓN | D26: 0 | E26: 1.1 | F26: FIXED STYLE | I26: 0 | J26: 0 | K26: 0 | L26: 0 | M26: 0 | O26: 0 | P26: 0 | Q26: 0 | R26: 0 | S26: 0 | U26: 0 | V26: 0 | W26: 0 | X26: 0 | Y26: 0 | AA26: 0 | AB26: 0 | AC26: 0 | AD26: 0 | AE26: 0 | AG26: - | AH26: - | AI26: - | AJ26: - | AK26: - | AM26: - | AN26: - | AO26: - | AP26: - | AQ26: -
B27: ORANGE | C27: ADOC D30 | D27: 239 | E27: 3.75 | F27: FIXED STYLE | I27: 116 | J27: 166 | K27: 215 | L27: 239 | M27: 239 | O27: 116 | P27: 166 | Q27: 215 | R27: 239 | S27: 239 | U27: 0 | V27: 0 | W27: 0 | X27: 0 | Y27: 0 | AA27: 0 | AB27: 0 | AC27: 0 | AD27: 0 | AE27: 0 | AG27: 123 | AH27: 73 | AI27: 24 | AJ27: 0 | AK27: 0 | AM27: 123 | AN27: 73 | AO27: 24 | AP27: 0 | AQ27: 0
B28: ORANGE | C28: ADOC D30 CESIÓN | D28: 0 | E28: 3.75 | F28: FIXED STYLE | I28: 0 | J28: 0 | K28: 0 | L28: 0 | M28: 0 | O28: 0 | P28: 0 | Q28: 0 | R28: 0 | S28: 0 | U28: 0 | V28: 0 | W28: 0 | X28: 0 | Y28: 0 | AA28: 0 | AB28: 0 | AC28: 0 | AD28: 0 | AE28: 0 | AG28: - | AH28: - | AI28: - | AJ28: - | AK28: - | AM28: - | AN28: - | AO28: - | AP28: - | AQ28: -
B29: AD HOC | C29: ADOC SC01 | D29: 64 | E29: 1.1 | F29: VOZ | I29: 64 | J29: 64 | K29: 0 | L29: 0 | M29: 0 | O29: 64 | P29: 64 | Q29: 0 | R29: 0 | S29: 0 | U29: 0 | V29: 0 | W29: 0 | X29: 0 | Y29: 0 | AA29: 0 | AB29: 0 | AC29: 0 | AD29: 0 | AE29: 0 | AG29: 0 | AH29: 0 | AI29: - | AJ29: - | AK29: - | AM29: 0 | AN29: 0 | AO29: - | AP29: - | AQ29: -
B30: ADOC | C30: ADOC SC04 | D30: 77 | E30: 1.1 | F30: VOZ | I30: 77 | J30: 77 | K30: 0 | L30: 0 | M30: 0 | O30: 77 | P30: 77 | Q30: 0 | R30: 0 | S30: 0 | U30: 0 | V30: 0 | W30: 0 | X30: 0 | Y30: 0 | AA30: 0 | AB30: 0 | AC30: 0 | AD30: 0 | AE30: 0 | AG30: 0 | AH30: 0 | AI30: - | AJ30: - | AK30: - | AM30: 0 | AN30: 0 | AO30: - | AP30: - | AQ30: -
B31: APPLE | C31: APPLE AIRPODS 4 | D31: 137 | E31: 0 | F31: OC_AURICULARES | I31: 52 | J31: 72 | K31: 95 | L31: 112 | M31: 145 | O31: 97 | P31: 127 | Q31: 176 | R31: 224 | S31: 224 | U31: 0 | V31: 0 | W31: 0 | X31: 0 | Y31: 0 | AA31: 0 | AB31: 0 | AC31: 0 | AD31: 0 | AE31: 0 | AG31: 85 | AH31: 65 | AI31: 42 | AJ31: 25 | AK31: -8 | AM31: 40 | AN31: 10 | AO31: -39 | AP31: -86.54 | AQ31: -86.54
B32: APPLE | C32: APPLE AIRPODS 4 CON CANCELACION ACTIVA RUIDO | D32: 184 | E32: 0 | F32: OC_AURICULARES | I32: 52 | J32: 72 | K32: 95 | L32: 112 | M32: 145 | O32: 97 | P32: 127 | Q32: 176 | R32: 241 | S32: 250 | U32: 0 | V32: 0 | W32: 0 | X32: 0 | Y32: 0 | AA32: 0 | AB32: 0 | AC32: 0 | AD32: 0 | AE32: 0 | AG32: 132 | AH32: 112 | AI32: 89 | AJ32: 72 | AK32: 39 | AM32: 87 | AN32: 57 | AO32: 8 | AP32: -57 | AQ32: -66.08
B33: APPLE | C33: APPLE AIRPODS PRO 2a GENERACION MAGSAFE USBC | D33: 279 | E33: 0 | F33: OC_AURICULARES | I33: 89 | J33: 109 | K33: 132 | L33: 149 | M33: 182 | O33: 134 | P33: 164 | Q33: 213 | R33: 278 | S33: 373 | U33: 0 | V33: 0 | W33: 0 | X33: 0 | Y33: 0 | AA33: 0 | AB33: 0 | AC33: 0 | AD33: 0 | AE33: 0 | AG33: 190.46 | AH33: 170.46 | AI33: 147.46 | AJ33: 130.46 | AK33: 97.46 | AM33: 145.46 | AN33: 115.46 | AO33: 66.46 | AP33: 1.46 | AQ33: -94.23
B34: APPLE | C34: APPLE WATCH S10 CELLULAR 42MM | D34: 532 | E34: 2.5 | F34: OC_SMART WATCH | I34: 52 | J34: 138 | K34: 161 | L34: 178 | M34: 211 | O34: 97 | P34: 193 | Q34: 242 | R34: 307 | S34: 419 | U34: 0 | V34: 0 | W34: 0 | X34: 0 | Y34: 0 | AA34: 0 | AB34: 0 | AC34: 0 | AD34: 0 | AE34: 0 | AG34: 480 | AH34: 393.81 | AI34: 370.81 | AJ34: 353.81 | AK34: 320.81 | AM34: 435 | AN34: 338.81 | AO34: 289.81 | AP34: 224.81 | AQ34: 112.81
B35: APPLE | C35: APPLE WATCH S10 CELLULAR 46MM | D35: 555 | E35: 2.5 | F35: OC_SMART WATCH | I35: 52 | J35: 139 | K35: 162 | L35: 179 | M35: 212 | O35: 97 | P35: 194 | Q35: 243 | R35: 308 | S35: 420 | U35: 0 | V35: 0 | W35: 0 | X35: 0 | Y35: 0 | AA35: 0 | AB35: 0 | AC35: 0 | AD35: 0 | AE35: 0 | AG35: 503 | AH35: 416.25 | AI35: 393.25 | AJ35: 376.25 | AK35: 343.25 | AM35: 458 | AN35: 361.25 | AO35: 312.25 | AP35: 247.25 | AQ35: 135.25
B36: APPLE | C36: APPLE WATCH S9 CELLULAR 45MM | D36: 555 | E36: 2.5 | F36: OC_SMART WATCH | I36: 52 | J36: 139 | K36: 162 | L36: 179 | M36: 212 | O36: 97 | P36: 194 | Q36: 243 | R36: 308 | S36: 420 | U36: 0 | V36: 0 | W36: 0 | X36: 0 | Y36: 0 | AA36: 0 | AB36: 0 | AC36: 0 | AD36: 0 | AE36: 0 | AG36: 503 | AH36: 416.25 | AI36: 393.25 | AJ36: 376.25 | AK36: 343.25 | AM36: 458 | AN36: 361.25 | AO36: 312.25 | AP36: 247.25 | AQ36: 135.25
B37: AD HOC | C37: AURICULARES AD HOC BT01 | D37: 71 | E37: 0 | F37: OC_AURICULARES | I37: 71 | J37: 71 | K37: 71 | L37: 71 | M37: 71 | O37: 71 | P37: 71 | Q37: 71 | R37: 71 | S37: 71 | U37: 0 | V37: 0 | W37: 0 | X37: 0 | Y37: 0 | AA37: 0 | AB37: 0 | AC37: 0 | AD37: 0 | AE37: 0 | AG37: 0 | AH37: 0 | AI37: 0 | AJ37: 0 | AK37: 0 | AM37: 0 | AN37: 0 | AO37: 0 | AP37: 0 | AQ37: 0
B38: AD HOC | C38: AURICULARES AD HOC HC01 | D38: 49 | E38: 0 | F38: OC_AURICULARES | I38: 49 | J38: 49 | K38: 49 | L38: 49 | M38: 49 | O38: 49 | P38: 49 | Q38: 49 | R38: 49 | S38: 49 | U38: 0 | V38: 0 | W38: 0 | X38: 0 | Y38: 0 | AA38: 0 | AB38: 0 | AC38: 0 | AD38: 0 | AE38: 0 | AG38: 0 | AH38: 0 | AI38: 0 | AJ38: 0 | AK38: 0 | AM38: 0 | AN38: 0 | AO38: 0 | AP38: 0 | AQ38: 0
B39: SAMSUNG | C39: AURICULARES SAMSUNG GALAXY BUDS 3 | D39: 172 | E39: 0 | F39: OC_AURICULARES | I39: 82 | J39: 102 | K39: 125 | L39: 142 | M39: 175 | O39: 127 | P39: 157 | Q39: 206 | R39: 244 | S39: 244 | U39: 0 | V39: 0 | W39: 0 | X39: 0 | Y39: 0 | AA39: 0 | AB39: 0 | AC39: 0 | AD39: 0 | AE39: 0 | AG39: 90 | AH39: 70 | AI39: 47 | AJ39: 30 | AK39: -3 | AM39: 45 | AN39: 15 | AO39: -34 | AP39: -72 | AQ39: -72
B40: SAMSUNG | C40: AURICULARES SAMSUNG GALAXY BUDS 3 PRO | D40: 240 | E40: 0 | F40: OC_AURICULARES | I40: 103 | J40: 123 | K40: 146 | L40: 163 | M40: 196 | O40: 148 | P40: 178 | Q40: 227 | R40: 292 | S40: 308 | U40: 0 | V40: 0 | W40: 0 | X40: 0 | Y40: 0 | AA40: 0 | AB40: 0 | AC40: 0 | AD40: 0 | AE40: 0 | AG40: 137 | AH40: 117 | AI40: 94 | AJ40: 77 | AK40: 44 | AM40: 92 | AN40: 62 | AO40: 13 | AP40: -52 | AQ40: -67.5
B41: SPC | C41: AURICULARES SPC BRAVE PRO | D41: 44 | E41: 0 | F41: OC_AURICULARES | I41: 44 | J41: 44 | K41: 44 | L41: 44 | M41: 44 | O41: 44 | P41: 44 | Q41: 44 | R41: 44 | S41: 44 | U41: 0 | V41: 0 | W41: 0 | X41: 0 | Y41: 0 | AA41: 0 | AB41: 0 | AC41: 0 | AD41: 0 | AE41: 0 | AG41: 0 | AH41: 0 | AI41: 0 | AJ41: 0 | AK41: 0 | AM41: 0 | AN41: 0 | AO41: 0 | AP41: 0 | AQ41: 0
B42: SPC | C42: AURICULARES SPC DREAMER PRO | D42: 77 | E42: 0 | F42: OC_AURICULARES | I42: 77 | J42: 77 | K42: 77 | L42: 77 | M42: 77 | O42: 77 | P42: 77 | Q42: 77 | R42: 77 | S42: 77 | U42: 0 | V42: 0 | W42: 0 | X42: 0 | Y42: 0 | AA42: 0 | AB42: 0 | AC42: 0 | AD42: 0 | AE42: 0 | AG42: 0 | AH42: 0 | AI42: 0 | AJ42: 0 | AK42: 0 | AM42: 0 | AN42: 0 | AO42: 0 | AP42: 0 | AQ42: 0
... B74: LENOVO | C74: LENOVO IDEAPAD 1 15ADA7 4120 8+256GB | D74: 462 | E74: 5.33 | F74: PC | I74: 169 | J74: 189 | K74: 212 | L74: 229 | M74: 262 | O74: 214 | P74: 244 | Q74: 293 | R74: 358 | S74: 470 | U74: -30 | V74: -30 | W74: -30 | X74: -30 | Y74: -30 | AA74: -30 | AB74: -30 | AC74: 6 | AD74: 104 | AE74: -8 | AG74: 293.33 | AH74: 273.33 | AI74: 250.33 | AJ74: 233.33 | AK74: 200.33 | AM74: 248.33 | AN74: 218.33 | AO74: 169.33 | AP74: 104.33 | AQ74: -7.67
B75: LENOVO | C75: LENOVO IDEAPAD 3 15IAH8 CI5 8+512GB | D75: 620 | E75: 5.33 | F75: PC | I75: 52 | J75: 138 | K75: 161 | L75: 178 | M75: 211 | O75: 97 | P75: 193 | Q75: 242 | R75: 307 | S75: 419 | U75: =NA() -> #N/A | V75: =NA() -> #N/A | W75: =NA() -> #N/A | X75: =NA() -> #N/A | Y75: =NA() -> #N/A | AA75: =NA() -> #N/A | AB75: =NA() -> #N/A | AC75: =NA() -> #N/A | AD75: =NA() -> #N/A | AE75: =NA() -> #N/A | AG75: 568 | AH75: 481.59 | AI75: 458.59 | AJ75: 441.59 | AK75: 408.59 | AM75: 523 | AN75: 426.59 | AO75: 377.59 | AP75: 312.59 | AQ75: 200.59
B76: LENOVO | C76: LENOVO IDEAPAD 3 15IAH8 CI5 8+512GB + TAB M11 WIFI | D76: 620 | E76: 5.33 | F76: PC | I76: 52 | J76: 138 | K76: 161 | L76: 178 | M76: 211 | O76: 97 | P76: 193 | Q76: 242 | R76: 307 | S76: 419 | U76: =NA() -> #N/A | V76: =NA() -> #N/A | W76: =NA() -> #N/A | X76: =NA() -> #N/A | Y76: =NA() -> #N/A | AA76: =NA() -> #N/A | AB76: =NA() -> #N/A | AC76: =NA() -> #N/A | AD76: =NA() -> #N/A | AE76: =NA() -> #N/A | AG76: 568 | AH76: 481.59 | AI76: 458.59 | AJ76: 441.59 | AK76: 408.59 | AM76: 523 | AN76: 426.59 | AO76: 377.59 | AP76: 312.59 | AQ76: 200.59
B77: LENOVO | C77: LENOVO IDEAPAD 3 15ITL6 CI5 | D77: 638 | E77: 5.33 | F77: PC | I77: 52 | J77: 156 | K77: 179 | L77: 196 | M77: 229 | O77: 97 | P77: 211 | Q77: 260 | R77: 419 | S77: 529 | U77: 0 | V77: 50 | W77: 50 | X77: 50 | Y77: 50 | AA77: 0 | AB77: 50 | AC77: 50 | AD77: 50 | AE77: 50 | AG77: 586 | AH77: 481.59 | AI77: 458.59 | AJ77: 441.59 | AK77: 408.59 | AM77: 541 | AN77: 426.59 | AO77: 377.59 | AP77: 218.59 | AQ77: 108.59
B78: LENOVO | C78: LENOVO IDEAPAD 5 16IRL8 I7 13GEN 16GB+1TB | D78: 915 | E78: 5.33 | F78: PC | I78: 52 | J78: 243 | K78: 266 | L78: 283 | M78: 316 | O78: 97 | P78: 298 | Q78: 347 | R78: 412 | S78: 524 | U78: 0 | V78: 0 | W78: 0 | X78: 0 | Y78: 0 | AA78: 0 | AB78: 0 | AC78: 0 | AD78: 0 | AE78: 0 | AG78: 863 | AH78: 672.33 | AI78: 649.33 | AJ78: 632.33 | AK78: 599.33 | AM78: 818 | AN78: 617.33 | AO78: 568.33 | AP78: 503.33 | AQ78: 391.33
B79: LENOVO | C79: LENOVO LOQ 3 15IRH8 i5 RTX 2050 | D79: 948 | E79: 5.33 | F79: PC | I79: 52 | J79: 220 | K79: 243 | L79: 260 | M79: 293 | O79: 97 | P79: 275 | Q79: 324 | R79: 389 | S79: 501 | U79: 0 | V79: 0 | W79: 0 | X79: 0 | Y79: 0 | AA79: 0 | AB79: 0 | AC79: 0 | AD79: 0 | AE79: 0 | AG79: 896 | AH79: 728.33 | AI79: 705.33 | AJ79: 688.33 | AK79: 655.33 | AM79: 851 | AN79: 673.33 | AO79: 624.33 | AP79: 559.33 | AQ79: 447.33
B80: LENOVO | C80: LENOVO P3 CHROMEBOOK PLUS 14" i3 8+256GB | D80: 525 | E80: 5.33 | F80: PC | I80: 218 | J80: 238 | K80: 261 | L80: 278 | M80: 311 | O80: 263 | P80: 293 | Q80: 342 | R80: 437 | S80: 549 | U80: 0 | V80: 0 | W80: 0 | X80: 0 | Y80: 0 | AA80: 0 | AB80: 0 | AC80: 0 | AD80: -30 | AE80: -30 | AG80: 306.59 | AH80: 286.59 | AI80: 263.59 | AJ80: 246.59 | AK80: 213.59 | AM80: 261.59 | AN80: 231.59 | AO80: 182.59 | AP80: 87.59 | AQ80: -24.41
B81: LG | C81: LG SMART TV 32" LQ | D81: 215 | E81: 0 | F81: SMART TV | I81: 84 | J81: 104 | K81: 127 | L81: 144 | M81: 177 | O81: 129 | P81: 159 | Q81: 208 | R81: 273 | S81: 280 | U81: 0 | V81: 0 | W81: 0 | X81: 0 | Y81: 0 | AA81: 0 | AB81: 0 | AC81: 0 | AD81: 0 | AE81: 0 | AG81: 131 | AH81: 111 | AI81: 88 | AJ81: 71 | AK81: 38 | AM81: 86 | AN81: 56 | AO81: 7 | AP81: -58 | AQ81: -64.5
B82: LG | C82: LG SMART TV 43" UR78 4K | D82: 396 | E82: 0 | F82: SMART TV | I82: 161 | J82: 181 | K82: 204 | L82: 221 | M82: 254 | O82: 206 | P82: 236 | Q82: 285 | R82: 350 | S82: 462 | U82: 0 | V82: 0 | W82: 0 | X82: 0 | Y82: 0 | AA82: 0 | AB82: 0 | AC82: 0 | AD82: 0 | AE82: 0 | AG82: 235 | AH82: 215 | AI82: 192 | AJ82: 175 | AK82: 142 | AM82: 190 | AN82: 160 | AO82: 111 | AP82: 46 | AQ82: -66
B83: LG | C83: LG SMART TV 50" UR78 4K | D83: 479 | E83: 0 | F83: SMART TV | I83: 191 | J83: 211 | K83: 234 | L83: 251 | M83: 284 | O83: 236 | P83: 266 | Q83: 315 | R83: 380 | S83: 492 | U83: 0 | V83: 0 | W83: 0 | X83: 0 | Y83: 0 | AA83: 0 | AB83: 0 | AC83: 0 | AD83: 0 | AE83: 0 | AG83: 288 | AH83: 268 | AI83: 245 | AJ83: 228 | AK83: 195 | AM83: 243 | AN83: 213 | AO83: 164 | AP83: 99 | AQ83: -13
B84: LG | C84: LG SMART TV 55" OLED C46 4K | D84: 1735 | E84: 0 | F84: SMART TV | I84: 52 | J84: 72 | K84: 875 | L84: 892 | M84: 925 | O84: 97 | P84: 127 | Q84: 956 | R84: 1021 | S84: 1133 | U84: 0 | V84: 0 | W84: 0 | X84: 0 | Y84: 0 | AA84: 0 | AB84: 0 | AC84: 0 | AD84: 0 | AE84: 0 | AG84: 1683 | AH84: 1663 | AI84: 859.8 | AJ84: 842.8 | AK84: 809.8 | AM84: 1638 | AN84: 1608 | AO84: 778.8 | AP84: 713.8 | AQ84: 601.8
B85: LG | C85: LG SMART TV 55" UR78 4K | D85: 537 | E85: 0 | F85: SMART TV | I85: 204 | J85: 224 | K85: 247 | L85: 264 | M85: 297 | O85: 249 | P85: 279 | Q85: 328 | R85: 393 | S85: 505 | U85: 0 | V85: 0 | W85: 0 | X85: 0 | Y85: 0 | AA85: 0 | AB85: 0 | AC85: 0 | AD85: 0 | AE85: 0 | AG85: 332.8 | AH85: 312.8 | AI85: 289.8 | AJ85: 272.8 | AK85: 239.8 | AM85: 287.8 | AN85: 257.8 | AO85: 208.8 | AP85: 143.8 | AQ85: 31.8
B86: LG | C86: LG SMART TV 65" OLED C46 4K | D86: 2396 | E86: 0 | F86: SMART TV | I86: 52 | J86: 72 | K86: 1211 | L86: 1228 | M86: 1261 | O86: 97 | P86: 127 | Q86: 1292 | R86: 1357 | S86: 1469 | U86: 0 | V86: 0 | W86: 0 | X86: 0 | Y86: 0 | AA86: 0 | AB86: 0 | AC86: 0 | AD86: 0 | AE86: 0 | AG86: 2344 | AH86: 2324 | AI86: 1184.8 | AJ86: 1167.8 | AK86: 1134.8 | AM86: 2299 | AN86: 2269 | AO86: 1103.8 | AP86: 1038.8 | AQ86: 926.8
B87: LG | C87: LG SMART TV 65" UR78 4K | D87: 686 | E87: 0 | F87: SMART TV | I87: 52 | J87: 72 | K87: 316 | L87: 333 | M87: 366 | O87: 97 | P87: 127 | Q87: 397 | R87: 462 | S87: 574 | U87: 0 | V87: 0 | W87: 0 | X87: 0 | Y87: 0 | AA87: 0 | AB87: 0 | AC87: 0 | AD87: 0 | AE87: 0 | AG87: 634 | AH87: 614 | AI87: 369.8 | AJ87: 352.8 | AK87: 319.8 | AM87: 589 | AN87: 559 | AO87: 288.8 | AP87: 223.8 | AQ87: 111.8
B88: LG | C88: LG SMART TV 75" UT80 4K | D88: 1157 | E88: 0 | F88: SMART TV | I88: 52 | J88: 72 | K88: 498 | L88: 515 | M88: 548 | O88: 97 | P88: 127 | Q88: 579 | R88: 644 | S88: 756 | U88: 0 | V88: 0 | W88: 0 | X88: 0 | Y88: 0 | AA88: 0 | AB88: 0 | AC88: 0 | AD88: 0 | AE88: 0 | AG88: 1105 | AH88: 1085 | AI88: 658.85 | AJ88: 641.85 | AK88: 608.85 | AM88: 1060 | AN88: 1030 | AO88: 577.85 | AP88: 512.85 | AQ88: 400.85
... B94: MOTOROLA | C94: MOTOROLA MOTO G54 256GB 5G | D94: 199 | E94: 3.25 | F94: SMARTPHONE | I94: 106 | J94: 126 | K94: 149 | L94: 166 | M94: 199 | O94: 151 | P94: 189 | Q94: 238 | R94: 281 | S94: 289 | U94: 0 | V94: 0 | W94: 0 | X94: 0 | Y94: 0 | AA94: 0 | AB94: 0 | AC94: -8 | AD94: -8 | AE94: -16 | AG94: 93.49 | AH94: 73.49 | AI94: 50.49 | AJ94: 33.49 | AK94: 0.49 | AM94: 48.49 | AN94: 10.49 | AO94: -38.51 | AP94: -81.745 | AQ94: -89.745
B95: MOTOROLA | C95: MOTOROLA MOTO G55 256GB 5G | D95: 255 | E95: 3.25 | F95: SMARTPHONE | I95: 108 | J95: 128 | K95: 151 | L95: 168 | M95: 201 | O95: 153 | P95: 183 | Q95: 232 | R95: 297 | S95: 327 | U95: =NA() -> #N/A | V95: =NA() -> #N/A | W95: =NA() -> #N/A | X95: =NA() -> #N/A | Y95: =NA() -> #N/A | AA95: =NA() -> #N/A | AB95: =NA() -> #N/A | AC95: =NA() -> #N/A | AD95: =NA() -> #N/A | AE95: =NA() -> #N/A | AG95: 146.75 | AH95: 126.75 | AI95: 103.75 | AJ95: 86.75 | AK95: 53.75 | AM95: 101.75 | AN95: 71.75 | AO95: 22.75 | AP95: -42.25 | AQ95: -72.375
B96: MOTOROLA | C96: MOTOROLA MOTO G85 256GB 5G | D96: 353 | E96: 3.25 | F96: SMARTPHONE | I96: 128 | J96: 148 | K96: 171 | L96: 188 | M96: 221 | O96: 173 | P96: 203 | Q96: 252 | R96: 353 | S96: 429 | U96: 0 | V96: 0 | W96: 0 | X96: 0 | Y96: 0 | AA96: 0 | AB96: 0 | AC96: 0 | AD96: -36 | AE96: 0 | AG96: 225.26 | AH96: 205.26 | AI96: 182.26 | AJ96: 165.26 | AK96: 132.26 | AM96: 180.26 | AN96: 150.26 | AO96: 101.26 | AP96: 0.26 | AQ96: -75.74
B97: MOTOROLA | C97: MOTOROLA MOTO THINKPHONE 25 256GB 5G | D97: 481 | E97: 3.25 | F97: SMARTPHONE | I97: 178 | J97: 198 | K97: 221 | L97: 238 | M97: 271 | O97: 223 | P97: 253 | Q97: 302 | R97: 367 | S97: 481 | U97: =NA() -> #N/A | V97: =NA() -> #N/A | W97: =NA() -> #N/A | X97: =NA() -> #N/A | Y97: =NA() -> #N/A | AA97: =NA() -> #N/A | AB97: =NA() -> #N/A | AC97: =NA() -> #N/A | AD97: =NA() -> #N/A | AE97: =NA() -> #N/A | AG97: 303.03 | AH97: 283.03 | AI97: 260.03 | AJ97: 243.03 | AK97: 210.03 | AM97: 258.03 | AN97: 228.03 | AO97: 179.03 | AP97: 114.03 | AQ97: 0.03
B98: MOTOROLA | C98: MOTOROLA RAZR 50 256GB 5G | D98: 869 | E98: 3.25 | F98: SMARTPHONE | I98: 52 | J98: 301 | K98: 324 | L98: 341 | M98: 374 | O98: 97 | P98: 356 | Q98: 405 | R98: 470 | S98: 582 | U98: 0 | V98: 0 | W98: 0 | X98: 0 | Y98: 0 | AA98: 0 | AB98: 0 | AC98: 0 | AD98: 0 | AE98: 0 | AG98: 817 | AH98: 567.78 | AI98: 544.78 | AJ98: 527.78 | AK98: 494.78 | AM98: 772 | AN98: 512.78 | AO98: 463.78 | AP98: 398.78 | AQ98: 286.78
B99: OPPO | C99: OPPO A38 | D99: 191 | E99: 3.25 | F99: SMARTPHONE | I99: 131 | J99: 151 | K99: 174 | L99: 191 | M99: 224 | O99: 176 | P99: 206 | Q99: 255 | R99: 248 | S99: 248 | U99: 0 | V99: 0 | W99: 0 | X99: 0 | Y99: 0 | AA99: 0 | AB99: 0 | AC99: 0 | AD99: 0 | AE99: 0 | AG99: 60.29 | AH99: 40.29 | AI99: 17.29 | AJ99: 0.29 | AK99: -32.71 | AM99: 15.29 | AN99: -14.71 | AO99: -63.71 | AP99: -57.145 | AQ99: -57.145
B100: OPPO | C100: OPPO A40 128GB | D100: 160 | E100: 3.25 | F100: SMARTPHONE | I100: 102 | J100: 122 | K100: 145 | L100: 162 | M100: 195 | O100: 147 | P100: 177 | Q100: 226 | R100: 216 | S100: 216 | U100: 0 | V100: 0 | W100: 0 | X100: 0 | Y100: 0 | AA100: 0 | AB100: 0 | AC100: 0 | AD100: 0 | AE100: 0 | AG100: 57.98 | AH100: 37.98 | AI100: 14.98 | AJ100: -2.02 | AK100: -35.02 | AM100: 12.98 | AN100: -17.02 | AO100: -66.02 | AP100: -55.99 | AQ100: -55.99
B101: OPPO | C101: OPPO A60 128GB 5G | D101: 176 | E101: 3.25 | F101: SMARTPHONE | I101: 103 | J101: 123 | K101: 146 | L101: 163 | M101: 196 | O101: 148 | P101: 178 | Q101: 227 | R101: 240 | S101: 240 | U101: 0 | V101: 0 | W101: 0 | X101: 0 | Y101: 0 | AA101: 0 | AB101: 0 | AC101: 0 | AD101: 0 | AE101: 0 | AG101: 73.18 | AH101: 53.18 | AI101: 30.18 | AJ101: 13.18 | AK101: -19.82 | AM101: 28.18 | AN101: -1.82 | AO101: -50.82 | AP101: -63.59 | AQ101: -63.59
B102: OPPO | C102: OPPO A80 256GB 5G | D102: 245 | E102: 3.25 | F102: SMARTPHONE | I102: 132 | J102: 152 | K102: 175 | L102: 192 | M102: 225 | O102: 177 | P102: 207 | Q102: 256 | R102: 321 | S102: 351 | U102: 0 | V102: 0 | W102: 0 | X102: 0 | Y102: 0 | AA102: 0 | AB102: 0 | AC102: 0 | AD102: 0 | AE102: -30 | AG102: 113.32 | AH102: 93.32 | AI102: 70.32 | AJ102: 53.32 | AK102: 20.32 | AM102: 68.32 | AN102: 38.32 | AO102: -10.68 | AP102: -75.68 | AQ102: -105.68
B103: OPPO | C103: OPPO FIND X8 PRO 512GB 5G | D103: 1072 | E103: 3.25 | F103: SMARTPHONE | I103: 52 | J103: 313 | K103: 336 | L103: 353 | M103: 386 | O103: 97 | P103: 368 | Q103: 417 | R103: 482 | S103: 594 | U103: =NA() -> #N/A | V103: =NA() -> #N/A | W103: =NA() -> #N/A | X103: =NA() -> #N/A | Y103: =NA() -> #N/A | AA103: =NA() -> #N/A | AB103: =NA() -> #N/A | AC103: =NA() -> #N/A | AD103: =NA() -> #N/A | AE103: =NA() -> #N/A | AG103: 1020 | AH103: 759.45 | AI103: 736.45 | AJ103: 719.45 | AK103: 686.45 | AM103: 975 | AN103: 704.45 | AO103: 655.45 | AP103: 590.45 | AQ103: 478.45
B104: OPPO | C104: OPPO RENO12 256GB 5G | D104: 428 | E104: 3.25 | F104: SMARTPHONE | I104: 209 | J104: 229 | K104: 252 | L104: 269 | M104: 302 | O104: 254 | P104: 284 | Q104: 333 | R104: 428 | S104: 510 | U104: 0 | V104: 0 | W104: 0 | X104: 0 | Y104: 0 | AA104: 0 | AB104: 0 | AC104: 0 | AD104: -30 | AE104: 0 | AG104: 219.39 | AH104: 199.39 | AI104: 176.39 | AJ104: 159.39 | AK104: 126.39 | AM104: 174.39 | AN104: 144.39 | AO104: 95.39 | AP104: 0.39 | AQ104: -81.61
B105: OPPO | C105: OPPO RENO12 FS 512GB 5G | D105: 364 | E105: 3.25 | F105: SMARTPHONE | I105: 168 | J105: 188 | K105: 211 | L105: 228 | M105: 261 | O105: 213 | P105: 243 | Q105: 292 | R105: 364 | S105: 461 | U105: 0 | V105: 0 | W105: 0 | X105: 0 | Y105: 0 | AA105: 0 | AB105: 0 | AC105: 0 | AD105: -7 | AE105: 0 | AG105: 196.2 | AH105: 176.2 | AI105: 153.2 | AJ105: 136.2 | AK105: 103.2 | AM105: 151.2 | AN105: 121.2 | AO105: 72.2 | AP105: 0.2 | AQ105: -97.1
B106: OPPO | C106: OPPO RENO12 PRO 512GB 5G | D106: 524 | E106: 3.25 | F106: SMARTPHONE | I106: 214 | J106: 234 | K106: 257 | L106: 274 | M106: 307 | O106: 259 | P106: 289 | Q106: 338 | R106: 403 | S106: 524 | U106: 0 | V106: 0 | W106: 0 | X106: 0 | Y106: 0 | AA106: 0 | AB106: 0 | AC106: 0 | AD106: 0 | AE106: -9 | AG106: 310.42 | AH106: 290.42 | AI106: 267.42 | AJ106: 250.42 | AK106: 217.42 | AM106: 265.42 | AN106: 235.42 | AO106: 186.42 | AP106: 121.42 | AQ106: 0.42
B107: ORANGE | C107: ORANGE GAMA 120 4G | D107: 74 | E107: 1.1 | F107: FIXED STYLE | I107: 74 | J107: 74 | K107: 74 | L107: 74 | M107: 74 | O107: 74 | P107: 0 | Q107: 0 | R107: 0 | S107: 0 | U107: 0 | V107: -74 | W107: -74 | X107: -74 | Y107: -74 | AA107: 0 | AB107: 0 | AC107: 0 | AD107: 0 | AE107: 0 | AG107: 0 | AH107: 0 | AI107: 0 | AJ107: 0 | AK107: 0 | AM107: 0 | AN107: - | AO107: - | AP107: - | AQ107: -
B108: ORANGE | C108: ORANGE GAMA 401 CESIÓN | D108: 0 | E108: 1.1 | F108: FIXED STYLE | I108: 0 | J108: 0 | K108: 0 | L108: 0 | M108: 0 | O108: 0 | P108: 0 | Q108: 0 | R108: 0 | S108: 0 | U108: 0 | V108: 0 | W108: 0 | X108: 0 | Y108: 0 | AA108: 0 | AB108: 0 | AC108: 0 | AD108: 0 | AE108: 0 | AG108: - | AH108: - | AI108: - | AJ108: - | AK108: - | AM108: - | AN108: - | AO108: - | AP108: - | AQ108: -
B109: ORANGE | C109: ORANGE GAMA 402 | D109: 70 | E109: 1.1 | F109: FIXED STYLE | I109: 70 | J109: 0 | K109: 0 | L109: 0 | M109: 0 | O109: 70 | P109: 0 | Q109: 0 | R109: 0 | S109: 0 | U109: 0 | V109: 0 | W109: 0 | X109: 0 | Y109: 0 | AA109: 0 | AB109: 0 | AC109: 0 | AD109: 0 | AE109: 0 | AG109: 0 | AH109: - | AI109: - | AJ109: - | AK109: - | AM109: 0 | AN109: - | AO109: - | AP109: - | AQ109: -
B110: ORANGE | C110: ORANGE GAMA 402 CESIÓN | D110: 0 | E110: 1.1 | F110: FIXED STYLE | I110: 0 | J110: 0 | K110: 0 | L110: 0 | M110: 0 | O110: 0 | P110: 0 | Q110: 0 | R110: 0 | S110: 0 | U110: 0 | V110: 0 | W110: 0 | X110: 0 | Y110: 0 | AA110: 0 | AB110: 0 | AC110: 0 | AD110: 0 | AE110: 0 | AG110: - | AH110: - | AI110: - | AJ110: - | AK110: - | AM110: - | AN110: - | AO110: - | AP110: - | AQ110: -
B111: ORANGE | C111: ORANGE GAMA 704 | D111: 104 | E111: 1.1 | F111: FIXED STYLE | I111: 80 | J111: 0 | K111: 0 | L111: 0 | M111: 0 | O111: 80 | P111: 0 | Q111: 0 | R111: 0 | S111: 0 | U111: 0 | V111: 0 | W111: 0 | X111: 0 | Y111: 0 | AA111: 0 | AB111: 0 | AC111: 0 | AD111: 0 | AE111: 0 | AG111: 24 | AH111: - | AI111: - | AJ111: - | AK111: - | AM111: 24 | AN111: - | AO111: - | AP111: - | AQ111: -
B112: ORANGE | C112: ORANGE GAMA 704 CESIÓN | D112: 0 | E112: 1.1 | F112: FIXED STYLE | I112: 0 | J112: 0 | K112: 0 | L112: 0 | M112: 0 | O112: 0 | P112: 0 | Q112: 0 | R112: 0 | S112: 0 | U112: 0 | V112: 0 | W112: 0 | X112: 0 | Y112: 0 | AA112: 0 | AB112: 0 | AC112: 0 | AD112: 0 | AE112: 0 | AG112: - | AH112: - | AI112: - | AJ112: - | AK112: - | AM112: - | AN112: - | AO112: - | AP112: - | AQ112: -
B113: ORANGE | C113: ORANGE GAMA 803 CESIÓN | D113: 0 | E113: 1.1 | F113: FIXED STYLE | I113: 0 | J113: 0 | K113: 0 | L113: 0 | M113: 0 | O113: 0 | P113: 0 | Q113: 0 | R113: 0 | S113: 0 | U113: 0 | V113: 0 | W113: 0 | X113: 0 | Y113: 0 | AA113: 0 | AB113: 0 | AC113: 0 | AD113: 0 | AE113: 0 | AG113: - | AH113: - | AI113: - | AJ113: - | AK113: - | AM113: - | AN113: - | AO113: - | AP113: - | AQ113: -
B114: DEF | C114: PACK BALIZA CONECTADA DGT 2 UNIDADES | D114: 96 | E114: 0 | F114: OC_OTROS DISPOSITIVOS | I114: 91 | J114: 96 | K114: 96 | L114: 96 | M114: 96 | O114: 91 | P114: 96 | Q114: 96 | R114: 96 | S114: 96 | U114: 0 | V114: 0 | W114: 0 | X114: 0 | Y114: 0 | AA114: 0 | AB114: 0 | AC114: 0 | AD114: 0 | AE114: 0 | AG114: 5 | AH114: 0 | AI114: 0 | AJ114: 0 | AK114: 0 | AM114: 5 | AN114: 0 | AO114: 0 | AP114: 0 | AQ114: 0
B115: NEXTIVITY | C115: REPETIDOR NEXTIVITY CELFI CONNECT C41 | D115: 547 | E115: 0 | F115: OC_OTROS DISPOSITIVOS | I115: 352 | J115: 352 | K115: 352 | L115: 352 | M115: 352 | O115: 352 | P115: 352 | Q115: 352 | R115: 352 | S115: 352 | U115: 0 | V115: 0 | W115: 0 | X115: 0 | Y115: 0 | AA115: 0 | AB115: 0 | AC115: 0 | AD115: 0 | AE115: 0 | AG115: 195 | AH115: 195 | AI115: 195 | AJ115: 195 | AK115: 195 | AM115: 195 | AN115: 195 | AO115: 195 | AP115: 195 | AQ115: 195
B116: SAMSUNG | C116: SAMSUNG GALAXY A15 | D116: 186 | E116: 3.25 | F116: SMARTPHONE | I116: 52 | J116: 72 | K116: 95 | L116: 112 | M116: 145 | O116: 97 | P116: 127 | Q116: 176 | R116: 241 | S116: 254 | U116: 13 | V116: 13 | W116: 13 | X116: 13 | Y116: 13 | AA116: 19 | AB116: 24 | AC116: 19 | AD116: 19 | AE116: 6 | AG116: 134 | AH116: 114 | AI116: 91 | AJ116: 74 | AK116: 41 | AM116: 89 | AN116: 59 | AO116: 10 | AP116: -55 | AQ116: -67.875
B117: SAMSUNG | C117: SAMSUNG GALAXY A15 5G | D117: 215 | E117: 3.25 | F117: SMARTPHONE | I117: 52 | J117: 72 | K117: 95 | L117: 112 | M117: 145 | O117: 97 | P117: 127 | Q117: 176 | R117: 241 | S117: 291 | U117: 23 | V117: 23 | W117: 23 | X117: 23 | Y117: 23 | AA117: 23 | AB117: 23 | AC117: 23 | AD117: 23 | AE117: -7 | AG117: 163 | AH117: 143 | AI117: 120 | AJ117: 103 | AK117: 70 | AM117: 118 | AN117: 88 | AO117: 39 | AP117: -26 | AQ117: -76.375
B118: SAMSUNG | C118: SAMSUNG GALAXY A16 128GB | D118: 186 | E118: 3.25 | F118: SMARTPHONE | I118: 101 | J118: 121 | K118: 144 | L118: 161 | M118: 194 | O118: 146 | P118: 176 | Q118: 225 | R118: 256 | S118: 256 | U118: 0 | V118: 0 | W118: 0 | X118: 0 | Y118: 0 | AA118: 0 | AB118: 0 | AC118: 0 | AD118: 0 | AE118: 0 | AG118: 85.25 | AH118: 65.25 | AI118: 42.25 | AJ118: 25.25 | AK118: -7.75 | AM118: 40.25 | AN118: 10.25 | AO118: -38.75 | AP118: -69.625 | AQ118: -69.625
B119: SAMSUNG | C119: SAMSUNG GALAXY A16 128GB 5G | D119: 248 | E119: 3.25 | F119: SMARTPHONE | I119: 150 | J119: 170 | K119: 193 | L119: 210 | M119: 243 | O119: 195 | P119: 225 | Q119: 274 | R119: 324 | S119: 324 | U119: 0 | V119: 0 | W119: 0 | X119: 0 | Y119: 0 | AA119: 0 | AB119: 0 | AC119: 0 | AD119: 0 | AE119: 0 | AG119: 98 | AH119: 78 | AI119: 55 | AJ119: 38 | AK119: 5 | AM119: 53 | AN119: 23 | AO119: -26 | AP119: -76 | AQ119: -76
B120: SAMSUNG | C120: SAMSUNG GALAXY A25 5G | D120: 299 | E120: 3.25 | F120: SMARTPHONE | I120: 108 | J120: 128 | K120: 151 | L120: 168 | M120: 201 | O120: 153 | P120: 183 | Q120: 232 | R120: 299 | S120: 394 | U120: 30 | V120: 30 | W120: 30 | X120: 30 | Y120: 30 | AA120: 30 | AB120: 30 | AC120: 67 | AD120: 28 | AE120: -15 | AG120: 191.25 | AH120: 171.25 | AI120: 148.25 | AJ120: 131.25 | AK120: 98.25 | AM120: 146.25 | AN120: 116.25 | AO120: 67.25 | AP120: 0.25 | AQ120: -94.625
B121: SAMSUNG | C121: SAMSUNG GALAXY A35 5G | D121: 358 | E121: 3.25 | F121: SMARTPHONE | I121: 124 | J121: 144 | K121: 167 | L121: 184 | M121: 217 | O121: 169 | P121: 199 | Q121: 248 | R121: 343 | S121: 425 | U121: 35 | V121: 35 | W121: 35 | X121: 35 | Y121: 35 | AA121: 35 | AB121: 35 | AC121: 35 | AD121: 15 | AE121: 32 | AG121: 234.25 | AH121: 214.25 | AI121: 191.25 | AJ121: 174.25 | AK121: 141.25 | AM121: 189.25 | AN121: 159.25 | AO121: 110.25 | AP121: 15.25 | AQ121: -66.75
B122: SAMSUNG | C122: SAMSUNG GALAXY A55 5G | D122: 442 | E122: 3.25 | F122: SMARTPHONE | I122: 179 | J122: 199 | K122: 222 | L122: 239 | M122: 272 | O122: 224 | P122: 254 | Q122: 303 | R122: 412 | S122: 480 | U122: 0 | V122: 0 | W122: 0 | X122: 0 | Y122: 0 | AA122: 0 | AB122: 0 | AC122: 0 | AD122: 0 | AE122: 0 | AG122: 263.25 | AH122: 243.25 | AI122: 220.25 | AJ122: 203.25 | AK122: 170.25 | AM122: 218.25 | AN122: 188.25 | AO122: 139.25 | AP122: 30.25 | AQ122: -37.75
B123: SAMSUNG | C123: SAMSUNG GALAXY BOOK2 GO 14" | D123: 533 | E123: 5.33 | F123: PC | I123: 209 | J123: 229 | K123: 252 | L123: 269 | M123: 302 | O123: 254 | P123: 284 | Q123: 333 | R123: 439 | S123: 533 | U123: 0 | V123: 0 | W123: 0 | X123: 0 | Y123: 0 | AA123: 0 | AB123: 0 | AC123: 0 | AD123: 0 | AE123: 0 | AG123: 324.12 | AH123: 304.12 | AI123: 281.12 | AJ123: 264.12 | AK123: 231.12 | AM123: 279.12 | AN123: 249.12 | AO123: 200.12 | AP123: 94.12 | AQ123: 0.12
B124: SAMSUNG | C124: SAMSUNG GALAXY BOOK4 EDGE15 16+256GB | D124: 801 | E124: 5.33 | F124: PC | I124: 52 | J124: 268 | K124: 291 | L124: 308 | M124: 341 | O124: 97 | P124: 323 | Q124: 372 | R124: 537 | S124: 649 | U124: 0 | V124: 71 | W124: 71 | X124: 71 | Y124: 71 | AA124: 0 | AB124: 71 | AC124: 71 | AD124: -29 | AE124: -29 | AG124: 749 | AH124: 533.09 | AI124: 510.09 | AJ124: 493.09 | AK124: 460.09 | AM124: 704 | AN124: 478.09 | AO124: 429.09 | AP124: 264.09 | AQ124: 152.09
B125: SAMSUNG | C125: SAMSUNG GALAXY BOOK4 PRO 16" i5 | D125: 1487 | E125: 5.33 | F125: PC | I125: 52 | J125: 450 | K125: 473 | L125: 490 | M125: 523 | O125: 97 | P125: 505 | Q125: 554 | R125: 669 | S125: 781 | U125: 0 | V125: 0 | W125: 0 | X125: 0 | Y125: 0 | AA125: 0 | AB125: 0 | AC125: 0 | AD125: -50 | AE125: -50 | AG125: 1435 | AH125: 1037.33 | AI125: 1014.33 | AJ125: 997.33 | AK125: 964.33 | AM125: 1390 | AN125: 982.33 | AO125: 933.33 | AP125: 818.33 | AQ125: 706.33
... B160: TCL | C160: TCL ANDROID TV 32" S5400A | D160: 159 | E160: 0 | F160: SMART TV | I160: 52 | J160: 72 | K160: 95 | L160: 112 | M160: 145 | O160: 97 | P160: 127 | Q160: 176 | R160: 241 | S160: 241 | U160: 0 | V160: 0 | W160: 0 | X160: 0 | Y160: 0 | AA160: 0 | AB160: 0 | AC160: 0 | AD160: 0 | AE160: 0 | AG160: 107 | AH160: 87 | AI160: 64 | AJ160: 47 | AK160: 14 | AM160: 62 | AN160: 32 | AO160: -17 | AP160: -82 | AQ160: -82
B161: TCL | C161: TCL ONETOUCH 4042s | D161: 49 | E161: 1.1 | F161: VOZ | I161: 49 | J161: 49 | K161: 0 | L161: 0 | M161: 0 | O161: 49 | P161: 49 | Q161: 0 | R161: 0 | S161: 0 | U161: 0 | V161: 0 | W161: 0 | X161: 0 | Y161: 0 | AA161: 0 | AB161: 0 | AC161: 0 | AD161: 0 | AE161: 0 | AG161: 0 | AH161: 0 | AI161: - | AJ161: - | AK161: - | AM161: 0 | AN161: 0 | AO161: - | AP161: - | AQ161: -
B162: TCL | C162: TCL ONETOUCH 4043 | D162: 60 | E162: 1.1 | F162: VOZ | I162: 60 | J162: 60 | K162: 0 | L162: 0 | M162: 0 | O162: 60 | P162: 60 | Q162: 0 | R162: 0 | S162: 0 | U162: 0 | V162: 0 | W162: 0 | X162: 0 | Y162: 0 | AA162: 0 | AB162: 0 | AC162: 0 | AD162: 0 | AE162: 0 | AG162: 0 | AH162: 0 | AI162: - | AJ162: - | AK162: - | AM162: 0 | AN162: 0 | AO162: - | AP162: - | AQ162: -
B163: TCL | C163: TCL TAB 10 2a GEN WIFI | D163: 132 | E163: 3.75 | F163: TABLET | I163: 52 | J163: 72 | K163: 95 | L163: 112 | M163: 145 | O163: 97 | P163: 127 | Q163: 176 | R163: 185 | S163: 185 | U163: 0 | V163: 0 | W163: 0 | X163: 0 | Y163: 0 | AA163: 0 | AB163: 0 | AC163: 0 | AD163: 0 | AE163: 0 | AG163: 80 | AH163: 60 | AI163: 37 | AJ163: 20 | AK163: -13 | AM163: 35 | AN163: 5 | AO163: -44 | AP163: -53.125 | AQ163: -53.125
B164: XACOM | C164: Xacom EasyGate | D164: 159 | E164: 0 | F164: VOZ | I164: 85 | J164: 0 | K164: 0 | L164: 0 | M164: 0 | O164: 85 | P164: 0 | Q164: 0 | R164: 0 | S164: 0 | U164: 0 | V164: 0 | W164: 0 | X164: 0 | Y164: 0 | AA164: 0 | AB164: 0 | AC164: 0 | AD164: 0 | AE164: 0 | AG164: 74 | AH164: - | AI164: - | AJ164: - | AK164: - | AM164: 74 | AN164: - | AO164: - | AP164: - | AQ164: -
B165: XACOM | C165: Xacom Track Digital RDSI | D165: 301 | E165: 0 | F165: VOZ | I165: 62 | J165: 0 | K165: 0 | L165: 0 | M165: 0 | O165: 62 | P165: 0 | Q165: 0 | R165: 0 | S165: 0 | U165: 0 | V165: 0 | W165: 0 | X165: 0 | Y165: 0 | AA165: 0 | AB165: 0 | AC165: 0 | AD165: 0 | AE165: 0 | AG165: 239 | AH165: - | AI165: - | AJ165: - | AK165: - | AM165: 239 | AN165: - | AO165: - | AP165: - | AQ165: -
B166: XIAOMI | C166: XIAOMI 14 5G | D166: 1072 | E166: 3.25 | F166: SMARTPHONE | I166: 52 | J166: 522 | K166: 545 | L166: 562 | M166: 595 | O166: 97 | P166: 577 | Q166: 626 | R166: 691 | S166: 803 | U166: 0 | V166: 0 | W166: 0 | X166: 0 | Y166: 0 | AA166: 0 | AB166: 0 | AC166: 0 | AD166: 0 | AE166: 0 | AG166: 1020 | AH166: 549.51 | AI166: 526.51 | AJ166: 509.51 | AK166: 476.51 | AM166: 975 | AN166: 494.51 | AO166: 445.51 | AP166: 380.51 | AQ166: 268.51
B167: XIAOMI | C167: XIAOMI 14 ULTRA 5G | D167: 1402 | E167: 3.25 | F167: SMARTPHONE | I167: 52 | J167: 592 | K167: 615 | L167: 632 | M167: 665 | O167: 97 | P167: 647 | Q167: 696 | R167: 761 | S167: 873 | U167: 0 | V167: 0 | W167: 0 | X167: 0 | Y167: 0 | AA167: 0 | AB167: 0 | AC167: 0 | AD167: 0 | AE167: 0 | AG167: 1350 | AH167: 810.09 | AI167: 787.09 | AJ167: 770.09 | AK167: 737.09 | AM167: 1305 | AN167: 755.09 | AO167: 706.09 | AP167: 641.09 | AQ167: 529.09
B168: XIAOMI | C168: XIAOMI 14C 128GB | D168: 174 | E168: 3.25 | F168: SMARTPHONE | I168: 116 | J168: 136 | K168: 159 | L168: 176 | M168: 209 | O168: 161 | P168: 191 | Q168: 240 | R168: 230 | S168: 230 | U168: 0 | V168: 0 | W168: 0 | X168: 0 | Y168: 0 | AA168: 0 | AB168: 0 | AC168: 0 | AD168: 0 | AE168: 0 | AG168: 57.68 | AH168: 37.68 | AI168: 14.68 | AJ168: -2.32 | AK168: -35.32 | AM168: 12.68 | AN168: -17.32 | AO168: -66.32 | AP168: -55.84 | AQ168: -55.84
B169: XIAOMI | C169: XIAOMI 14T 256GB 5G | D169: 638 | E169: 3.25 | F169: SMARTPHONE | I169: 52 | J169: 268 | K169: 291 | L169: 308 | M169: 341 | O169: 97 | P169: 323 | Q169: 372 | R169: 437 | S169: 549 | U169: 0 | V169: 0 | W169: 0 | X169: 0 | Y169: 0 | AA169: 0 | AB169: 0 | AC169: 0 | AD169: 0 | AE169: 0 | AG169: 586 | AH169: 369.57 | AI169: 346.57 | AJ169: 329.57 | AK169: 296.57 | AM169: 541 | AN169: 314.57 | AO169: 265.57 | AP169: 200.57 | AQ169: 88.57
B170: XIAOMI | C170: XIAOMI 14T PRO 256GB 5G | D170: 801 | E170: 3.25 | F170: SMARTPHONE | I170: 52 | J170: 324 | K170: 347 | L170: 364 | M170: 397 | O170: 97 | P170: 379 | Q170: 428 | R170: 493 | S170: 605 | U170: 0 | V170: 0 | W170: 0 | X170: 0 | Y170: 0 | AA170: 0 | AB170: 0 | AC170: 0 | AD170: 0 | AE170: 0 | AG170: 749 | AH170: 476.68 | AI170: 453.68 | AJ170: 436.68 | AK170: 403.68 | AM170: 704 | AN170: 421.68 | AO170: 372.68 | AP170: 307.68 | AQ170: 195.68
B171: XIAOMI | C171: XIAOMI 14T PRO 512GB 5G | D171: 895 | E171: 3.25 | F171: SMARTPHONE | I171: 52 | J171: 412 | K171: 435 | L171: 452 | M171: 485 | O171: 97 | P171: 467 | Q171: 516 | R171: 581 | S171: 693 | U171: 0 | V171: 0 | W171: 0 | X171: 0 | Y171: 0 | AA171: 0 | AB171: 0 | AC171: 0 | AD171: 0 | AE171: 0 | AG171: 843 | AH171: 483.08 | AI171: 460.08 | AJ171: 443.08 | AK171: 410.08 | AM171: 798 | AN171: 428.08 | AO171: 379.08 | AP171: 314.08 | AQ171: 202.08
B172: XIAOMI | C172: XIAOMI GOOGLE TV 43" QLED A PRO | D172: 298 | E172: 0 | F172: SMART TV | I172: 103 | J172: 123 | K172: 146 | L172: 163 | M172: 196 | O172: 148 | P172: 178 | Q172: 227 | R172: 292 | S172: 395 | U172: 0 | V172: 0 | W172: 0 | X172: 0 | Y172: 0 | AA172: 0 | AB172: 0 | AC172: 0 | AD172: 0 | AE172: 0 | AG172: 195.4 | AH172: 175.4 | AI172: 152.4 | AJ172: 135.4 | AK172: 102.4 | AM172: 150.4 | AN172: 120.4 | AO172: 71.4 | AP172: 6.4 | AQ172: -96.7
B173: XIAOMI | C173: XIAOMI GOOGLE TV 55" QLED A PRO | D173: 445 | E173: 0 | F173: SMART TV | I173: 98 | J173: 118 | K173: 141 | L173: 158 | M173: 191 | O173: 143 | P173: 173 | Q173: 222 | R173: 287 | S173: 399 | U173: 0 | V173: 0 | W173: 0 | X173: 0 | Y173: 0 | AA173: 0 | AB173: 0 | AC173: 0 | AD173: 0 | AE173: 0 | AG173: 346.77 | AH173: 326.77 | AI173: 303.77 | AJ173: 286.77 | AK173: 253.77 | AM173: 301.77 | AN173: 271.77 | AO173: 222.77 | AP173: 157.77 | AQ173: 45.77
B174: XIAOMI | C174: XIAOMI GOOGLE TV 65" QLED A PRO | D174: 577 | E174: 0 | F174: SMART TV | I174: 52 | J174: 72 | K174: 212 | L174: 229 | M174: 262 | O174: 97 | P174: 127 | Q174: 293 | R174: 358 | S174: 470 | U174: 0 | V174: 0 | W174: 0 | X174: 0 | Y174: 0 | AA174: 0 | AB174: 0 | AC174: 0 | AD174: 0 | AE174: 0 | AG174: 525 | AH174: 505 | AI174: 365.34 | AJ174: 348.34 | AK174: 315.34 | AM174: 480 | AN174: 450 | AO174: 284.34 | AP174: 219.34 | AQ174: 107.34
B175: XIAOMI | C175: XIAOMI MI ELECTRIC SCOOTER 4 | D175: 459 | E175: 0 | F175: OC_TIEMPO LIBRE | I175: 243 | J175: 263 | K175: 286 | L175: 303 | M175: 336 | O175: 288 | P175: 318 | Q175: 367 | R175: 432 | S175: 544 | U175: 0 | V175: 0 | W175: 0 | X175: 0 | Y175: 0 | AA175: 0 | AB175: 0 | AC175: 0 | AD175: 0 | AE175: 0 | AG175: 216.11 | AH175: 196.11 | AI175: 173.11 | AJ175: 156.11 | AK175: 123.11 | AM175: 171.11 | AN175: 141.11 | AO175: 92.11 | AP175: 27.11 | AQ175: -84.89
B176: XIAOMI | C176: XIAOMI MI ELECTRIC SCOOTER 4 PRO 2a GEN | D176: 516 | E176: 0 | F176: OC_TIEMPO LIBRE | I176: 218 | J176: 238 | K176: 261 | L176: 278 | M176: 311 | O176: 263 | P176: 293 | Q176: 342 | R176: 407 | S176: 519 | U176: 0 | V176: 0 | W176: 0 | X176: 0 | Y176: 0 | AA176: 0 | AB176: 0 | AC176: 0 | AD176: 0 | AE176: 0 | AG176: 297.9 | AH176: 277.9 | AI176: 254.9 | AJ176: 237.9 | AK176: 204.9 | AM176: 252.9 | AN176: 222.9 | AO176: 173.9 | AP176: 108.9 | AQ176: -3.1
B177: XIAOMI | C177: XIAOMI PAD 6S PRO WIFI | D177: 647 | E177: 3.75 | F177: TABLET | I177: 52 | J177: 299 | K177: 322 | L177: 339 | M177: 372 | O177: 97 | P177: 354 | Q177: 403 | R177: 468 | S177: 580 | U177: 0 | V177: 0 | W177: 0 | X177: 0 | Y177: 0 | AA177: 0 | AB177: 0 | AC177: 0 | AD177: 0 | AE177: 0 | AG177: 595 | AH177: 348.11 | AI177: 325.11 | AJ177: 308.11 | AK177: 275.11 | AM177: 550 | AN177: 293.11 | AO177: 244.11 | AP177: 179.11 | AQ177: 67.11
... B183: XIAOMI | C183: XIAOMI REDMI NOTE 13 PRO+ 5G | D183: 522 | E183: 3.25 | F183: SMARTPHONE | I183: 238 | J183: 258 | K183: 281 | L183: 298 | M183: 331 | O183: 283 | P183: 313 | Q183: 362 | R183: 427 | S183: 539 | U183: 0 | V183: 0 | W183: 0 | X183: 0 | Y183: 0 | AA183: 0 | AB183: 0 | AC183: 0 | AD183: 0 | AE183: 0 | AG183: 283.65 | AH183: 263.65 | AI183: 240.65 | AJ183: 223.65 | AK183: 190.65 | AM183: 238.65 | AN183: 208.65 | AO183: 159.65 | AP183: 94.65 | AQ183: -17.35
B184: XIAOMI | C184: XIAOMI REDMI NOTE 14 PRO 256GB 5G | D184: 415 | E184: 3.25 | F184: SMARTPHONE | I184: 169 | J184: 189 | K184: 212 | L184: 229 | M184: 262 | O184: 214 | P184: 244 | Q184: 293 | R184: 358 | S184: 470 | U184: =NA() -> #N/A | V184: =NA() -> #N/A | W184: =NA() -> #N/A | X184: =NA() -> #N/A | Y184: =NA() -> #N/A | AA184: =NA() -> #N/A | AB184: =NA() -> #N/A | AC184: =NA() -> #N/A | AD184: =NA() -> #N/A | AE184: =NA() -> #N/A | AG184: 246.06 | AH184: 226.06 | AI184: 203.06 | AJ184: 186.06 | AK184: 153.06 | AM184: 201.06 | AN184: 171.06 | AO184: 122.06 | AP184: 57.06 | AQ184: -54.94
B185: XIAOMI | C185: XIAOMI REDMI NOTE 14 PRO+ 256GB 5G | D185: 516 | E185: 3.25 | F185: SMARTPHONE | I185: 189 | J185: 209 | K185: 232 | L185: 249 | M185: 282 | O185: 234 | P185: 264 | Q185: 313 | R185: 378 | S185: 490 | U185: =NA() -> #N/A | V185: =NA() -> #N/A | W185: =NA() -> #N/A | X185: =NA() -> #N/A | Y185: =NA() -> #N/A | AA185: =NA() -> #N/A | AB185: =NA() -> #N/A | AC185: =NA() -> #N/A | AD185: =NA() -> #N/A | AE185: =NA() -> #N/A | AG185: 327.46 | AH185: 307.46 | AI185: 284.46 | AJ185: 267.46 | AK185: 234.46 | AM185: 282.46 | AN185: 252.46 | AO185: 203.46 | AP185: 138.46 | AQ185: 26.46
B186: XIAOMI | C186: XIAOMI REDMI PAD PRO WIFI | D186: 327 | E186: 3.75 | F186: TABLET | I186: 138 | J186: 158 | K186: 181 | L186: 198 | M186: 231 | O186: 183 | P186: 213 | Q186: 262 | R186: 327 | S186: 420 | U186: -15 | V186: -15 | W186: -15 | X186: -15 | Y186: -15 | AA186: -15 | AB186: -15 | AC186: -15 | AD186: -15 | AE186: 4 | AG186: 188.86 | AH186: 168.86 | AI186: 145.86 | AJ186: 128.86 | AK186: 95.86 | AM186: 143.86 | AN186: 113.86 | AO186: 64.86 | AP186: -0.14 | AQ186: -93.43
B187: XIAOMI | C187: XIAOMI REDMI PAD SE 8.7" WIFI 4+128GB | D187: 167 | E187: 3.75 | F187: TABLET | I187: 82 | J187: 102 | K187: 125 | L187: 142 | M187: 175 | O187: 132 | P187: 162 | Q187: 211 | R187: 234 | S187: 234 | U187: 5 | V187: 5 | W187: 5 | X187: 5 | Y187: 5 | AA187: 0 | AB187: 0 | AC187: 0 | AD187: 0 | AE187: 0 | AG187: 85.25 | AH187: 65.25 | AI187: 42.25 | AJ187: 25.25 | AK187: -7.75 | AM187: 34.89 | AN187: 4.89 | AO187: -44.11 | AP187: -66.945 | AQ187: -66.945
B188: XIAOMI | C188: XIAOMI SMART TV A 32" | D188: 165 | E188: 0 | F188: SMART TV | I188: 52 | J188: 72 | K188: 95 | L188: 112 | M188: 145 | O188: 97 | P188: 127 | Q188: 176 | R188: 241 | S188: 241 | U188: 0 | V188: 0 | W188: 0 | X188: 0 | Y188: 0 | AA188: 0 | AB188: 0 | AC188: 0 | AD188: 0 | AE188: 0 | AG188: 113 | AH188: 93 | AI188: 70 | AJ188: 53 | AK188: 20 | AM188: 68 | AN188: 38 | AO188: -11 | AP188: -75.55 | AQ188: -75.55
...

Sheet PVP Subv - Optima Pyme 36
B2: OFERTA TÁCTICA EMPRESAS | I2: CAPTA | O2: PORTABILIDAD
B4: ='PVP VaP - Pyme'!B4 -> 45627 | C4: ='PVP VaP - Pyme'!C4 -> 01/12 al 31/12 | I4: ENTRADA PRO | J4: NORMAL PRO | K4: VALOR PRO | L4: PREMIUM PRO | M4: TOP PRO | O4: ENTRADA PRO | P4: NORMAL PRO | Q4: VALOR PRO | R4: PREMIUM PRO | S4: TOP PRO
B5: 1. CONDICIONES DE LA OFERTA SUBVENCIONADA (según tarifa y situación del cliente) | D5: Tarifas | I5: T. Optima Plus Empresas T. Optima Plus Empresas Big + Empresas Voz y Empresas 1 | J5: T. Optima Plus Empresas T. Optima Plus Empresas Big + Empresas 5 y Empresas Intranet | K5: T. Optima Plus Empresas T. Optima Plus Empresas Big + Empresas 20 | L5: T. Optima Plus Empresas T. Optima Plus Empresas Big + Empresas Infinita | M5: T. Optima Plus Empresas T. Optima Plus Empresas Big + Empresas Internacional | O5: T. Optima Plus Empresas T. Optima Plus Empresas Big + Empresas Voz y Empresas 1 | P5: T. Optima Plus Empresas T. Optima Plus Empresas Big + Empresas 5 y Empresas Intranet | Q5: T. Optima Plus Empresas T. Optima Plus Empresas Big + Empresas 20 | R5: T. Optima Plus Empresas T. Optima Plus Empresas Big + Empresas Infinita | S5: T. Optima Plus Empresas T. Optima Plus Empresas Big + Empresas Internacional
D12: Ampliaciones (meses antigüedad) | I12: Todos | J12: Todos | K12: Todos | L12: Todos | M12: Todos | O12: Todos | P12: Todos | Q12: Todos | R12: Todos | S12: Todos
D13: Origen (Portabilidad / Migración) | I13: Capta Prepago Migracion | J13: Capta Prepago Migracion | K13: Capta Prepago Migracion | L13: Capta Prepago Migracion | M13: Capta Prepago Migracion | O13: Pospago | P13: Pospago | Q13: Pospago | R13: Pospago | S13: Pospago
D14: CP Tarifa | I14: CPT136 | J14: CPT136 | K14: CPT136 | L14: CPT136 | M14: CPT136 | O14: CPT136 | P14: CPT136 | Q14: CPT136 | R14: CPT136 | S14: CPT136
D15: CP Terminal | I15: CPTE336 | J15: CPTE136 | K15: CPTE136 | L15: CPTE436 | M15: CPTE436 | O15: CPTE336 | P15: CPTE136 | Q15: CPTE136 | R15: CPTE436 | S15: CPTE436
I16: Las condiciones de los modulos Entrada Pro y Normal Pro aplican para los terminales VOZ y FIX tanto si activan sólo voz como si activan el paquete de voz + datos | U16: DIFERENCIAS Vs CP 24 MESES
B19: 2. PRECIO DEL TERMINAL POR GRUPO DE TARIFAS | I19: DxC CAPTA | O19: DxC PORTABILIDAD | U19: DxC CAPTA | AA19: DxC PORTABILIDAD | AG19: PVPR CAPTA | AM19: PVPR PORTABILIDAD
I21: GRUPOS DE TARIFAS MOVIL | O21: GRUPOS DE TARIFAS MOVIL | U21: GRUPOS DE TARIFAS MOVIL | AA21: GRUPOS DE TARIFAS MOVIL | AG21: GRUPOS DE TARIFAS MOVIL | AM21: GRUPOS DE TARIFAS MOVIL
I23: ENTRADA PRO | J23: NORMAL PRO | K23: VALOR PRO | L23: PREMIUM PRO | M23: TOP PRO | O23: ENTRADA PRO | P23: NORMAL PRO | Q23: VALOR PRO | R23: PREMIUM PRO | S23: TOP PRO | U23: ENTRADA PRO | V23: NORMAL PRO | W23: VALOR PRO | X23: PREMIUM PRO | Y23: TOP PRO | AA23: ENTRADA PRO | AB23: NORMAL PRO | AC23: VALOR PRO | AD23: PREMIUM PRO | AE23: TOP PRO | AG23: ENTRADA PRO | AH23: NORMAL PRO | AI23: VALOR PRO | AJ23: PREMIUM PRO | AK23: TOP PRO | AM23: ENTRADA PRO | AN23: NORMAL PRO | AO23: VALOR PRO | AP23: PREMIUM PRO | AQ23: TOP PRO
B25: MARCA | C25: Modelo (Novedades) | D25: Precio Cesión | E25: Canon Digital | F25: Gama | I25: DxC (sin IVA) | J25: DxC (sin IVA) | K25: DxC (sin IVA) | L25: DxC (sin IVA) | M25: DxC (sin IVA) | O25: DxC (sin IVA) | P25: DxC (sin IVA) | Q25: DxC (sin IVA) | R25: DxC (sin IVA) | S25: DxC (sin IVA) | U25: DxC (sin IVA) | V25: DxC (sin IVA) | W25: DxC (sin IVA) | X25: DxC (sin IVA) | Y25: DxC (sin IVA) | AA25: DxC (sin IVA) | AB25: DxC (sin IVA) | AC25: DxC (sin IVA) | AD25: DxC (sin IVA) | AE25: DxC (sin IVA) | AG25: PVP (sin IVA) | AH25: PVP (sin IVA) | AI25: PVP (sin IVA) | AJ25: PVP (sin IVA) | AK25: PVP (sin IVA) | AM25: PVP (sin IVA) | AN25: PVP (sin IVA) | AO25: PVP (sin IVA) | AP25: PVP (sin IVA) | AQ25: PVP (sin IVA)
B26: ORANGE | C26: AD HOC H3 CESIÓN | D26: 0 | E26: 1.1 | F26: FIXED STYLE | I26: 0 | J26: 0 | K26: 0 | L26: 0 | M26: 0 | O26: 0 | P26: 0 | Q26: 0 | R26: 0 | S26: 0 | U26: 0 | V26: 0 | W26: 0 | X26: 0 | Y26: 0 | Z26: 0 | AA26: 0 | AB26: 0 | AC26: 0 | AD26: 0 | AE26: 0 | AG26: - | AH26: - | AI26: - | AJ26: - | AK26: - | AM26: - | AN26: - | AO26: - | AP26: - | AQ26: -
B27: ORANGE | C27: ADOC D30 | D27: 239 | E27: 3.75 | F27: FIXED STYLE | I27: 116 | J27: 166 | K27: 215 | L27: 239 | M27: 239 | O27: 116 | P27: 166 | Q27: 215 | R27: 239 | S27: 239 | U27: 0 | V27: 0 | W27: 0 | X27: 0 | Y27: 0 | Z27: 0 | AA27: 0 | AB27: 0 | AC27: 0 | AD27: 0 | AE27: 0 | AG27: 123 | AH27: 73 | AI27: 24 | AJ27: 0 | AK27: 0 | AM27: 123 | AN27: 73 | AO27: 24 | AP27: 0 | AQ27: 0
B28: ORANGE | C28: ADOC D30 CESIÓN | D28: 0 | E28: 3.75 | F28: FIXED STYLE | I28: 0 | J28: 0 | K28: 0 | L28: 0 | M28: 0 | O28: 0 | P28: 0 | Q28: 0 | R28: 0 | S28: 0 | U28: 0 | V28: 0 | W28: 0 | X28: 0 | Y28: 0 | Z28: 0 | AA28: 0 | AB28: 0 | AC28: 0 | AD28: 0 | AE28: 0 | AG28: - | AH28: - | AI28: - | AJ28: - | AK28: - | AM28: - | AN28: - | AO28: - | AP28: - | AQ28: -
B29: AD HOC | C29: ADOC SC01 | D29: 64 | E29: 1.1 | F29: VOZ | I29: 64 | J29: 64 | K29: 0 | L29: 0 | M29: 0 | O29: 64 | P29: 64 | Q29: 0 | R29: 0 | S29: 0 | U29: 0 | V29: 0 | W29: 0 | X29: 0 | Y29: 0 | Z29: 0 | AA29: 0 | AB29: 0 | AC29: 0 | AD29: 0 | AE29: 0 | AG29: 0 | AH29: 0 | AI29: - | AJ29: - | AK29: - | AM29: 0 | AN29: 0 | AO29: - | AP29: - | AQ29: -
B30: ADOC | C30: ADOC SC04 | D30: 77 | E30: 1.1 | F30: VOZ | I30: 77 | J30: 77 | K30: 0 | L30: 0 | M30: 0 | O30: 77 | P30: 77 | Q30: 0 | R30: 0 | S30: 0 | U30: 0 | V30: 0 | W30: 0 | X30: 0 | Y30: 0 | Z30: 0 | AA30: 0 | AB30: 0 | AC30: 0 | AD30: 0 | AE30: 0 | AG30: 0 | AH30: 0 | AI30: - | AJ30: - | AK30: - | AM30: 0 | AN30: 0 | AO30: - | AP30: - | AQ30: -
B31: APPLE | C31: APPLE AIRPODS 4 | D31: 137 | E31: 0 | F31: OC_AURICULARES | I31: 52 | J31: 72 | K31: 95 | L31: 112 | M31: 145 | O31: 97 | P31: 127 | Q31: 176 | R31: 224 | S31: 224 | U31: 0 | V31: 0 | W31: 0 | X31: 0 | Y31: 0 | Z31: 0 | AA31: 0 | AB31: 0 | AC31: 0 | AD31: 0 | AE31: 0 | AG31: 85 | AH31: 65 | AI31: 42 | AJ31: 25 | AK31: -8 | AM31: 40 | AN31: 10 | AO31: -39 | AP31: -86.54 | AQ31: -86.54
B32: APPLE | C32: APPLE AIRPODS 4 CON CANCELACION ACTIVA RUIDO | D32: 184 | E32: 0 | F32: OC_AURICULARES | I32: 52 | J32: 72 | K32: 95 | L32: 112 | M32: 145 | O32: 97 | P32: 127 | Q32: 176 | R32: 241 | S32: 250 | U32: 0 | V32: 0 | W32: 0 | X32: 0 | Y32: 0 | Z32: 0 | AA32: 0 | AB32: 0 | AC32: 0 | AD32: 0 | AE32: 0 | AG32: 132 | AH32: 112 | AI32: 89 | AJ32: 72 | AK32: 39 | AM32: 87 | AN32: 57 | AO32: 8 | AP32: -57 | AQ32: -66.08
B33: APPLE | C33: APPLE AIRPODS PRO 2a GENERACION MAGSAFE USBC | D33: 279 | E33: 0 | F33: OC_AURICULARES | I33: 89 | J33: 109 | K33: 132 | L33: 149 | M33: 182 | O33: 134 | P33: 164 | Q33: 213 | R33: 278 | S33: 373 | U33: 0 | V33: 0 | W33: 0 | X33: 0 | Y33: 0 | Z33: 0 | AA33: 0 | AB33: 0 | AC33: 0 | AD33: 0 | AE33: 0 | AG33: 190.46 | AH33: 170.46 | AI33: 147.46 | AJ33: 130.46 | AK33: 97.46 | AM33: 145.46 | AN33: 115.46 | AO33: 66.46 | AP33: 1.46 | AQ33: -94.23
B34: APPLE | C34: APPLE WATCH S10 CELLULAR 42MM | D34: 532 | E34: 2.5 | F34: OC_SMART WATCH | I34: 52 | J34: 138 | K34: 161 | L34: 178 | M34: 211 | O34: 97 | P34: 223 | Q34: 292 | R34: 347 | S34: 479 | U34: 0 | V34: 0 | W34: 0 | X34: 0 | Y34: 0 | Z34: 0 | AA34: 0 | AB34: -30 | AC34: -50 | AD34: -40 | AE34: -60 | AG34: 480 | AH34: 393.81 | AI34: 370.81 | AJ34: 353.81 | AK34: 320.81 | AM34: 435 | AN34: 308.81 | AO34: 239.81 | AP34: 184.81 | AQ34: 52.81
B35: APPLE | C35: APPLE WATCH S10 CELLULAR 46MM | D35: 555 | E35: 2.5 | F35: OC_SMART WATCH | I35: 52 | J35: 139 | K35: 162 | L35: 179 | M35: 212 | O35: 97 | P35: 224 | Q35: 293 | R35: 348 | S35: 480 | U35: 0 | V35: 0 | W35: 0 | X35: 0 | Y35: 0 | Z35: 0 | AA35: 0 | AB35: -30 | AC35: -50 | AD35: -40 | AE35: -60 | AG35: 503 | AH35: 416.25 | AI35: 393.25 | AJ35: 376.25 | AK35: 343.25 | AM35: 458 | AN35: 331.25 | AO35: 262.25 | AP35: 207.25 | AQ35: 75.25
B36: APPLE | C36: APPLE WATCH S9 CELLULAR 45MM | D36: 555 | E36: 2.5 | F36: OC_SMART WATCH | I36: 52 | J36: 139 | K36: 162 | L36: 179 | M36: 212 | O36: 97 | P36: 224 | Q36: 293 | R36: 348 | S36: 480 | U36: 0 | V36: 0 | W36: 0 | X36: 0 | Y36: 0 | Z36: 0 | AA36: 0 | AB36: -30 | AC36: -50 | AD36: -40 | AE36: -60 | AG36: 503 | AH36: 416.25 | AI36: 393.25 | AJ36: 376.25 | AK36: 343.25 | AM36: 458 | AN36: 331.25 | AO36: 262.25 | AP36: 207.25 | AQ36: 75.25
B37: AD HOC | C37: AURICULARES AD HOC BT01 | D37: 71 | E37: 0 | F37: OC_AURICULARES | I37: 71 | J37: 71 | K37: 71 | L37: 71 | M37: 71 | O37: 71 | P37: 71 | Q37: 71 | R37: 71 | S37: 71 | U37: 0 | V37: 0 | W37: 0 | X37: 0 | Y37: 0 | Z37: 0 | AA37: 0 | AB37: 0 | AC37: 0 | AD37: 0 | AE37: 0 | AG37: 0 | AH37: 0 | AI37: 0 | AJ37: 0 | AK37: 0 | AM37: 0 | AN37: 0 | AO37: 0 | AP37: 0 | AQ37: 0
B38: AD HOC | C38: AURICULARES AD HOC HC01 | D38: 49 | E38: 0 | F38: OC_AURICULARES | I38: 49 | J38: 49 | K38: 49 | L38: 49 | M38: 49 | O38: 49 | P38: 49 | Q38: 49 | R38: 49 | S38: 49 | U38: 0 | V38: 0 | W38: 0 | X38: 0 | Y38: 0 | Z38: 0 | AA38: 0 | AB38: 0 | AC38: 0 | AD38: 0 | AE38: 0 | AG38: 0 | AH38: 0 | AI38: 0 | AJ38: 0 | AK38: 0 | AM38: 0 | AN38: 0 | AO38: 0 | AP38: 0 | AQ38: 0
B39: SAMSUNG | C39: AURICULARES SAMSUNG GALAXY BUDS 3 | D39: 172 | E39: 0 | F39: OC_AURICULARES | I39: 82 | J39: 102 | K39: 125 | L39: 142 | M39: 175 | O39: 127 | P39: 157 | Q39: 206 | R39: 244 | S39: 244 | U39: 0 | V39: 0 | W39: 0 | X39: 0 | Y39: 0 | Z39: 0 | AA39: 0 | AB39: 0 | AC39: 0 | AD39: 0 | AE39: 0 | AG39: 90 | AH39: 70 | AI39: 47 | AJ39: 30 | AK39: -3 | AM39: 45 | AN39: 15 | AO39: -34 | AP39: -72 | AQ39: -72
B40: SAMSUNG | C40: AURICULARES SAMSUNG GALAXY BUDS 3 PRO | D40: 240 | E40: 0 | F40: OC_AURICULARES | I40: 103 | J40: 123 | K40: 146 | L40: 163 | M40: 196 | O40: 148 | P40: 178 | Q40: 227 | R40: 292 | S40: 308 | U40: 0 | V40: 0 | W40: 0 | X40: 0 | Y40: 0 | Z40: 0 | AA40: 0 | AB40: 0 | AC40: 0 | AD40: 0 | AE40: 0 | AG40: 137 | AH40: 117 | AI40: 94 | AJ40: 77 | AK40: 44 | AM40: 92 | AN40: 62 | AO40: 13 | AP40: -52 | AQ40: -67.5
B41: SPC | C41: AURICULARES SPC BRAVE PRO | D41: 44 | E41: 0 | F41: OC_AURICULARES | I41: 44 | J41: 44 | K41: 44 | L41: 44 | M41: 44 | O41: 44 | P41: 44 | Q41: 44 | R41: 44 | S41: 44 | U41: 0 | V41: 0 | W41: 0 | X41: 0 | Y41: 0 | Z41: 0 | AA41: 0 | AB41: 0 | AC41: 0 | AD41: 0 | AE41: 0 | AG41: 0 | AH41: 0 | AI41: 0 | AJ41: 0 | AK41: 0 | AM41: 0 | AN41: 0 | AO41: 0 | AP41: 0 | AQ41: 0
B42: SPC | C42: AURICULARES SPC DREAMER PRO | D42: 77 | E42: 0 | F42: OC_AURICULARES | I42: 77 | J42: 77 | K42: 77 | L42: 77 | M42: 77 | O42: 77 | P42: 77 | Q42: 77 | R42: 77 | S42: 77 | U42: 0 | V42: 0 | W42: 0 | X42: 0 | Y42: 0 | Z42: 0 | AA42: 0 | AB42: 0 | AC42: 0 | AD42: 0 | AE42: 0 | AG42: 0 | AH42: 0 | AI42: 0 | AJ42: 0 | AK42: 0 | AM42: 0 | AN42: 0 | AO42: 0 | AP42: 0 | AQ42: 0
... B106: OPPO | C106: OPPO RENO12 PRO 512GB 5G | D106: 524 | E106: 3.25 | F106: SMARTPHONE | I106: 214 | J106: 234 | K106: 257 | L106: 274 | M106: 307 | O106: 259 | P106: 319 | Q106: 388 | R106: 443 | S106: 584 | U106: 0 | V106: 0 | W106: 0 | X106: 0 | Y106: 0 | Z106: 0 | AA106: 0 | AB106: -30 | AC106: -50 | AD106: -40 | AE106: -60 | AG106: 310.42 | AH106: 290.42 | AI106: 267.42 | AJ106: 250.42 | AK106: 217.42 | AM106: 265.42 | AN106: 205.42 | AO106: 136.42 | AP106: 81.42 | AQ106: -59.58
B107: ORANGE | C107: ORANGE GAMA 120 4G | D107: 74 | E107: 1.1 | F107: FIXED STYLE | I107: 74 | J107: 74 | K107: 74 | L107: 74 | M107: 74 | O107: 74 | P107: 0 | Q107: 0 | R107: 0 | S107: 0 | U107: 0 | V107: 0 | W107: 0 | X107: 0 | Y107: 0 | Z107: 0 | AA107: 0 | AB107: 0 | AC107: 0 | AD107: 0 | AE107: 0 | AG107: 0 | AH107: 0 | AI107: 0 | AJ107: 0 | AK107: 0 | AM107: 0 | AN107: - | AO107: - | AP107: - | AQ107: -
B108: ORANGE | C108: ORANGE GAMA 401 CESIÓN | D108: 0 | E108: 1.1 | F108: FIXED STYLE | I108: 0 | J108: 0 | K108: 0 | L108: 0 | M108: 0 | O108: 0 | P108: 0 | Q108: 0 | R108: 0 | S108: 0 | U108: 0 | V108: 0 | W108: 0 | X108: 0 | Y108: 0 | Z108: 0 | AA108: 0 | AB108: 0 | AC108: 0 | AD108: 0 | AE108: 0 | AG108: - | AH108: - | AI108: - | AJ108: - | AK108: - | AM108: - | AN108: - | AO108: - | AP108: - | AQ108: -
B109: ORANGE | C109: ORANGE GAMA 402 | D109: 70 | E109: 1.1 | F109: FIXED STYLE | I109: 70 | J109: 0 | K109: 0 | L109: 0 | M109: 0 | O109: 70 | P109: 0 | Q109: 0 | R109: 0 | S109: 0 | U109: 0 | V109: 0 | W109: 0 | X109: 0 | Y109: 0 | Z109: 0 | AA109: 0 | AB109: 0 | AC109: 0 | AD109: 0 | AE109: 0 | AG109: 0 | AH109: - | AI109: - | AJ109: - | AK109: - | AM109: 0 | AN109: - | AO109: - | AP109: - | AQ109: -
B110: ORANGE | C110: ORANGE GAMA 402 CESIÓN | D110: 0 | E110: 1.1 | F110: FIXED STYLE | I110: 0 | J110: 0 | K110: 0 | L110: 0 | M110: 0 | O110: 0 | P110: 0 | Q110: 0 | R110: 0 | S110: 0 | U110: 0 | V110: 0 | W110: 0 | X110: 0 | Y110: 0 | Z110: 0 | AA110: 0 | AB110: 0 | AC110: 0 | AD110: 0 | AE110: 0 | AG110: - | AH110: - | AI110: - | AJ110: - | AK110: - | AM110: - | AN110: - | AO110: - | AP110: - | AQ110: -
B111: ORANGE | C111: ORANGE GAMA 704 | D111: 104 | E111: 1.1 | F111: FIXED STYLE | I111: 80 | J111: 0 | K111: 0 | L111: 0 | M111: 0 | O111: 80 | P111: 0 | Q111: 0 | R111: 0 | S111: 0 | U111: 0 | V111: 0 | W111: 0 | X111: 0 | Y111: 0 | Z111: 0 | AA111: 0 | AB111: 0 | AC111: 0 | AD111: 0 | AE111: 0 | AG111: 24 | AH111: - | AI111: - | AJ111: - | AK111: - | AM111: 24 | AN111: - | AO111: - | AP111: - | AQ111: -
B112: ORANGE | C112: ORANGE GAMA 704 CESIÓN | D112: 0 | E112: 1.1 | F112: FIXED STYLE | I112: 0 | J112: 0 | K112: 0 | L112: 0 | M112: 0 | O112: 0 | P112: 0 | Q112: 0 | R112: 0 | S112: 0 | U112: 0 | V112: 0 | W112: 0 | X112: 0 | Y112: 0 | Z112: 0 | AA112: 0 | AB112: 0 | AC112: 0 | AD112: 0 | AE112: 0 | AG112: - | AH112: - | AI112: - | AJ112: - | AK112: - | AM112: - | AN112: - | AO112: - | AP112: - | AQ112: -
B113: ORANGE | C113: ORANGE GAMA 803 CESIÓN | D113: 0 | E113: 1.1 | F113: FIXED STYLE | I113: 0 | J113: 0 | K113: 0 | L113: 0 | M113: 0 | O113: 0 | P113: 0 | Q113: 0 | R113: 0 | S113: 0 | U113: 0 | V113: 0 | W113: 0 | X113: 0 | Y113: 0 | Z113: 0 | AA113: 0 | AB113: 0 | AC113: 0 | AD113: 0 | AE113: 0 | AG113: - | AH113: - | AI113: - | AJ113: - | AK113: - | AM113: - | AN113: - | AO113: - | AP113: - | AQ113: -
B114: DEF | C114: PACK BALIZA CONECTADA DGT 2 UNIDADES | D114: 96 | E114: 0 | F114: OC_OTROS DISPOSITIVOS | I114: 91 | J114: 96 | K114: 96 | L114: 96 | M114: 96 | O114: 91 | P114: 96 | Q114: 96 | R114: 96 | S114: 96 | U114: 0 | V114: 0 | W114: 0 | X114: 0 | Y114: 0 | Z114: 0 | AA114: 0 | AB114: 0 | AC114: 0 | AD114: 0 | AE114: 0 | AG114: 5 | AH114: 0 | AI114: 0 | AJ114: 0 | AK114: 0 | AM114: 5 | AN114: 0 | AO114: 0 | AP114: 0 | AQ114: 0
B115: NEXTIVITY | C115: REPETIDOR NEXTIVITY CELFI CONNECT C41 | D115: 547 | E115: 0 | F115: OC_OTROS DISPOSITIVOS | I115: 352 | J115: 352 | K115: 352 | L115: 352 | M115: 352 | O115: 352 | P115: 352 | Q115: 352 | R115: 352 | S115: 352 | U115: 0 | V115: 0 | W115: 0 | X115: 0 | Y115: 0 | Z115: 0 | AA115: 0 | AB115: 0 | AC115: 0 | AD115: 0 | AE115: 0 | AG115: 195 | AH115: 195 | AI115: 195 | AJ115: 195 | AK115: 195 | AM115: 195 | AN115: 195 | AO115: 195 | AP115: 195 | AQ115: 195
B116: SAMSUNG | C116: SAMSUNG GALAXY A15 | D116: 186 | E116: 3.25 | F116: SMARTPHONE | I116: 52 | J116: 72 | K116: 95 | L116: 112 | M116: 145 | O116: 97 | P116: 127 | Q116: 176 | R116: 241 | S116: 254 | U116: 0 | V116: 0 | W116: 0 | X116: 0 | Y116: 0 | Z116: 0 | AA116: 0 | AB116: 0 | AC116: 0 | AD116: 0 | AE116: 0 | AG116: 134 | AH116: 114 | AI116: 91 | AJ116: 74 | AK116: 41 | AM116: 89 | AN116: 59 | AO116: 10 | AP116: -55 | AQ116: -67.875
B117: SAMSUNG | C117: SAMSUNG GALAXY A15 5G | D117: 215 | E117: 3.25 | F117: SMARTPHONE | I117: 52 | J117: 72 | K117: 95 | L117: 112 | M117: 145 | O117: 97 | P117: 127 | Q117: 176 | R117: 241 | S117: 291 | U117: 0 | V117: 0 | W117: 0 | X117: 0 | Y117: 0 | Z117: 0 | AA117: 0 | AB117: 0 | AC117: 0 | AD117: 0 | AE117: 0 | AG117: 163 | AH117: 143 | AI117: 120 | AJ117: 103 | AK117: 70 | AM117: 118 | AN117: 88 | AO117: 39 | AP117: -26 | AQ117: -76.375
B118: SAMSUNG | C118: SAMSUNG GALAXY A16 128GB | D118: 186 | E118: 3.25 | F118: SMARTPHONE | I118: 101 | J118: 121 | K118: 144 | L118: 161 | M118: 194 | O118: 146 | P118: 176 | Q118: 225 | R118: 256 | S118: 256 | U118: 0 | V118: 0 | W118: 0 | X118: 0 | Y118: 0 | Z118: 0 | AA118: 0 | AB118: 0 | AC118: 0 | AD118: 0 | AE118: 0 | AG118: 85.25 | AH118: 65.25 | AI118: 42.25 | AJ118: 25.25 | AK118: -7.75 | AM118: 40.25 | AN118: 10.25 | AO118: -38.75 | AP118: -69.625 | AQ118: -69.625
B119: SAMSUNG | C119: SAMSUNG GALAXY A16 128GB 5G | D119: 248 | E119: 3.25 | F119: SMARTPHONE | I119: 150 | J119: 170 | K119: 193 | L119: 210 | M119: 243 | O119: 195 | P119: 225 | Q119: 274 | R119: 324 | S119: 324 | U119: 0 | V119: 0 | W119: 0 | X119: 0 | Y119: 0 | Z119: 0 | AA119: 0 | AB119: 0 | AC119: 0 | AD119: 0 | AE119: 0 | AG119: 98 | AH119: 78 | AI119: 55 | AJ119: 38 | AK119: 5 | AM119: 53 | AN119: 23 | AO119: -26 | AP119: -76 | AQ119: -76
B120: SAMSUNG | C120: SAMSUNG GALAXY A25 5G | D120: 299 | E120: 3.25 | F120: SMARTPHONE | I120: 108 | J120: 128 | K120: 151 | L120: 168 | M120: 201 | O120: 153 | P120: 183 | Q120: 232 | R120: 299 | S120: 394 | U120: 0 | V120: 0 | W120: 0 | X120: 0 | Y120: 0 | Z120: 0 | AA120: 0 | AB120: 0 | AC120: 0 | AD120: 0 | AE120: 0 | AG120: 191.25 | AH120: 171.25 | AI120: 148.25 | AJ120: 131.25 | AK120: 98.25 | AM120: 146.25 | AN120: 116.25 | AO120: 67.25 | AP120: 0.25 | AQ120: -94.625
B121: SAMSUNG | C121: SAMSUNG GALAXY A35 5G | D121: 358 | E121: 3.25 | F121: SMARTPHONE | I121: 124 | J121: 144 | K121: 167 | L121: 184 | M121: 217 | O121: 169 | P121: 199 | Q121: 248 | R121: 343 | S121: 425 | U121: 0 | V121: 0 | W121: 0 | X121: 0 | Y121: 0 | Z121: 0 | AA121: 0 | AB121: 0 | AC121: 0 | AD121: 0 | AE121: 0 | AG121: 234.25 | AH121: 214.25 | AI121: 191.25 | AJ121: 174.25 | AK121: 141.25 | AM121: 189.25 | AN121: 159.25 | AO121: 110.25 | AP121: 15.25 | AQ121: -66.75
B122: SAMSUNG | C122: SAMSUNG GALAXY A55 5G | D122: 442 | E122: 3.25 | F122: SMARTPHONE | I122: 179 | J122: 199 | K122: 222 | L122: 239 | M122: 272 | O122: 224 | P122: 279 | Q122: 328 | R122: 437 | S122: 505 | U122: 0 | V122: 0 | W122: 0 | X122: 0 | Y122: 0 | Z122: 0 | AA122: 0 | AB122: -25 | AC122: -25 | AD122: -25 | AE122: -25 | AG122: 263.25 | AH122: 243.25 | AI122: 220.25 | AJ122: 203.25 | AK122: 170.25 | AM122: 218.25 | AN122: 163 | AO122: 114 | AP122: 5 | AQ122: -63
B123: SAMSUNG | C123: SAMSUNG GALAXY BOOK2 GO 14" | D123: 533 | E123: 5.33 | F123: PC | I123: 209 | J123: 229 | K123: 252 | L123: 269 | M123: 302 | O123: 254 | P123: 314 | Q123: 383 | R123: 479 | S123: 593 | U123: 0 | V123: 0 | W123: 0 | X123: 0 | Y123: 0 | Z123: 0 | AA123: 0 | AB123: -30 | AC123: -50 | AD123: -40 | AE123: -60 | AG123: 324.12 | AH123: 304.12 | AI123: 281.12 | AJ123: 264.12 | AK123: 231.12 | AM123: 279.12 | AN123: 219.12 | AO123: 150.12 | AP123: 54.12 | AQ123: -59.88
B124: SAMSUNG | C124: SAMSUNG GALAXY BOOK4 EDGE15 16+256GB | D124: 801 | E124: 5.33 | F124: PC | I124: 52 | J124: 268 | K124: 291 | L124: 308 | M124: 341 | O124: 97 | P124: 353 | Q124: 422 | R124: 577 | S124: 709 | U124: 0 | V124: 0 | W124: 0 | X124: 0 | Y124: 0 | Z124: 0 | AA124: 0 | AB124: -30 | AC124: -50 | AD124: -40 | AE124: -60 | AG124: 749 | AH124: 533.09 | AI124: 510.09 | AJ124: 493.09 | AK124: 460.09 | AM124: 704 | AN124: 448.09 | AO124: 379.09 | AP124: 224.09 | AQ124: 92.09
B125: SAMSUNG | C125: SAMSUNG GALAXY BOOK4 PRO 16" i5 | D125: 1487 | E125: 5.33 | F125: PC | I125: 52 | J125: 450 | K125: 473 | L125: 490 | M125: 523 | O125: 97 | P125: 535 | Q125: 604 | R125: 709 | S125: 841 | U125: 0 | V125: 0 | W125: 0 | X125: 0 | Y125: 0 | Z125: 0 | AA125: 0 | AB125: -30 | AC125: -50 | AD125: -40 | AE125: -60 | AG125: 1435 | AH125: 1037.33 | AI125: 1014.33 | AJ125: 997.33 | AK125: 964.33 | AM125: 1390 | AN125: 952.33 | AO125: 883.33 | AP125: 778.33 | AQ125: 646.33
... B160: TCL | C160: TCL ANDROID TV 32" S5400A | D160: 159 | E160: 0 | F160: SMART TV | I160: 52 | J160: 72 | K160: 95 | L160: 112 | M160: 145 | O160: 97 | P160: 127 | Q160: 176 | R160: 241 | S160: 241 | U160: 0 | V160: 0 | W160: 0 | X160: 0 | Y160: 0 | Z160: 0 | AA160: 0 | AB160: 0 | AC160: 0 | AD160: 0 | AE160: 0 | AG160: 107 | AH160: 87 | AI160: 64 | AJ160: 47 | AK160: 14 | AM160: 62 | AN160: 32 | AO160: -17 | AP160: -82 | AQ160: -82
B161: TCL | C161: TCL ONETOUCH 4042s | D161: 49 | E161: 1.1 | F161: VOZ | I161: 49 | J161: 49 | K161: 0 | L161: 0 | M161: 0 | O161: 49 | P161: 49 | Q161: 0 | R161: 0 | S161: 0 | U161: 0 | V161: 0 | W161: 0 | X161: 0 | Y161: 0 | Z161: 0 | AA161: 0 | AB161: 0 | AC161: 0 | AD161: 0 | AE161: 0 | AG161: 0 | AH161: 0 | AI161: - | AJ161: - | AK161: - | AM161: 0 | AN161: 0 | AO161: - | AP161: - | AQ161: -
B162: TCL | C162: TCL ONETOUCH 4043 | D162: 60 | E162: 1.1 | F162: VOZ | I162: 60 | J162: 60 | K162: 0 | L162: 0 | M162: 0 | O162: 60 | P162: 60 | Q162: 0 | R162: 0 | S162: 0 | U162: 0 | V162: 0 | W162: 0 | X162: 0 | Y162: 0 | Z162: 0 | AA162: 0 | AB162: 0 | AC162: 0 | AD162: 0 | AE162: 0 | AG162: 0 | AH162: 0 | AI162: - | AJ162: - | AK162: - | AM162: 0 | AN162: 0 | AO162: - | AP162: - | AQ162: -
B163: TCL | C163: TCL TAB 10 2a GEN WIFI | D163: 132 | E163: 3.75 | F163: TABLET | I163: 52 | J163: 72 | K163: 95 | L163: 112 | M163: 145 | O163: 97 | P163: 127 | Q163: 176 | R163: 185 | S163: 185 | U163: 0 | V163: 0 | W163: 0 | X163: 0 | Y163: 0 | Z163: 0 | AA163: 0 | AB163: 0 | AC163: 0 | AD163: 0 | AE163: 0 | AG163: 80 | AH163: 60 | AI163: 37 | AJ163: 20 | AK163: -13 | AM163: 35 | AN163: 5 | AO163: -44 | AP163: -53.125 | AQ163: -53.125
B164: XACOM | C164: Xacom EasyGate | D164: 159 | E164: 0 | F164: VOZ | I164: 85 | J164: 0 | K164: 0 | L164: 0 | M164: 0 | O164: 85 | P164: 0 | Q164: 0 | R164: 0 | S164: 0 | U164: 0 | V164: 0 | W164: 0 | X164: 0 | Y164: 0 | Z164: 0 | AA164: 0 | AB164: 0 | AC164: 0 | AD164: 0 | AE164: 0 | AG164: 74 | AH164: - | AI164: - | AJ164: - | AK164: - | AM164: 74 | AN164: - | AO164: - | AP164: - | AQ164: -
B165: XACOM | C165: Xacom Track Digital RDSI | D165: 301 | E165: 0 | F165: VOZ | I165: 62 | J165: 0 | K165: 0 | L165: 0 | M165: 0 | O165: 62 | P165: 0 | Q165: 0 | R165: 0 | S165: 0 | U165: 0 | V165: 0 | W165: 0 | X165: 0 | Y165: 0 | Z165: 0 | AA165: 0 | AB165: 0 | AC165: 0 | AD165: 0 | AE165: 0 | AG165: 239 | AH165: - | AI165: - | AJ165: - | AK165: - | AM165: 239 | AN165: - | AO165: - | AP165: - | AQ165: -
B166: XIAOMI | C166: XIAOMI 14 5G | D166: 1072 | E166: 3.25 | F166: SMARTPHONE | I166: 52 | J166: 522 | K166: 545 | L166: 562 | M166: 595 | O166: 97 | P166: 607 | Q166: 676 | R166: 731 | S166: 863 | U166: 0 | V166: 0 | W166: 0 | X166: 0 | Y166: 0 | Z166: 0 | AA166: 0 | AB166: -30 | AC166: -50 | AD166: -40 | AE166: -60 | AG166: 1020 | AH166: 549.51 | AI166: 526.51 | AJ166: 509.51 | AK166: 476.51 | AM166: 975 | AN166: 464.51 | AO166: 395.51 | AP166: 340.51 | AQ166: 208.51
B167: XIAOMI | C167: XIAOMI 14 ULTRA 5G | D167: 1402 | E167: 3.25 | F167: SMARTPHONE | I167: 52 | J167: 592 | K167: 615 | L167: 632 | M167: 665 | O167: 97 | P167: 677 | Q167: 746 | R167: 801 | S167: 933 | U167: 0 | V167: 0 | W167: 0 | X167: 0 | Y167: 0 | Z167: 0 | AA167: 0 | AB167: -30 | AC167: -50 | AD167: -40 | AE167: -60 | AG167: 1350 | AH167: 810.09 | AI167: 787.09 | AJ167: 770.09 | AK167: 737.09 | AM167: 1305 | AN167: 725.09 | AO167: 656.09 | AP167: 601.09 | AQ167: 469.09
B168: XIAOMI | C168: XIAOMI 14C 128GB | D168: 174 | E168: 3.25 | F168: SMARTPHONE | I168: 116 | J168: 136 | K168: 159 | L168: 176 | M168: 209 | O168: 161 | P168: 191 | Q168: 240 | R168: 230 | S168: 230 | U168: 0 | V168: 0 | W168: 0 | X168: 0 | Y168: 0 | Z168: 0 | AA168: 0 | AB168: 0 | AC168: 0 | AD168: 0 | AE168: 0 | AG168: 57.68 | AH168: 37.68 | AI168: 14.68 | AJ168: -2.32 | AK168: -35.32 | AM168: 12.68 | AN168: -17.32 | AO168: -66.32 | AP168: -55.84 | AQ168: -55.84
B169: XIAOMI | C169: XIAOMI 14T 256GB 5G | D169: 638 | E169: 3.25 | F169: SMARTPHONE | I169: 52 | J169: 268 | K169: 291 | L169: 308 | M169: 341 | O169: 97 | P169: 353 | Q169: 422 | R169: 477 | S169: 609 | U169: 0 | V169: 0 | W169: 0 | X169: 0 | Y169: 0 | Z169: 0 | AA169: 0 | AB169: -30 | AC169: -50 | AD169: -40 | AE169: -60 | AG169: 586 | AH169: 369.57 | AI169: 346.57 | AJ169: 329.57 | AK169: 296.57 | AM169: 541 | AN169: 284.57 | AO169: 215.57 | AP169: 160.57 | AQ169: 28.57
B170: XIAOMI | C170: XIAOMI 14T PRO 256GB 5G | D170: 801 | E170: 3.25 | F170: SMARTPHONE | I170: 52 | J170: 324 | K170: 347 | L170: 364 | M170: 397 | O170: 97 | P170: 409 | Q170: 478 | R170: 533 | S170: 665 | U170: 0 | V170: 0 | W170: 0 | X170: 0 | Y170: 0 | Z170: 0 | AA170: 0 | AB170: -30 | AC170: -50 | AD170: -40 | AE170: -60 | AG170: 749 | AH170: 476.68 | AI170: 453.68 | AJ170: 436.68 | AK170: 403.68 | AM170: 704 | AN170: 391.68 | AO170: 322.68 | AP170: 267.68 | AQ170: 135.68
B171: XIAOMI | C171: XIAOMI 14T PRO 512GB 5G | D171: 895 | E171: 3.25 | F171: SMARTPHONE | I171: 52 | J171: 412 | K171: 435 | L171: 452 | M171: 485 | O171: 97 | P171: 497 | Q171: 566 | R171: 621 | S171: 753 | U171: 0 | V171: 0 | W171: 0 | X171: 0 | Y171: 0 | Z171: 0 | AA171: 0 | AB171: -30 | AC171: -50 | AD171: -40 | AE171: -60 | AG171: 843 | AH171: 483.08 | AI171: 460.08 | AJ171: 443.08 | AK171: 410.08 | AM171: 798 | AN171: 398.08 | AO171: 329.08 | AP171: 274.08 | AQ171: 142.08
B172: XIAOMI | C172: XIAOMI GOOGLE TV 43" QLED A PRO | D172: 298 | E172: 0 | F172: SMART TV | I172: 103 | J172: 123 | K172: 146 | L172: 163 | M172: 196 | O172: 148 | P172: 178 | Q172: 227 | R172: 292 | S172: 395 | U172: 0 | V172: 0 | W172: 0 | X172: 0 | Y172: 0 | Z172: 0 | AA172: 0 | AB172: 0 | AC172: 0 | AD172: 0 | AE172: 0 | AG172: 195.4 | AH172: 175.4 | AI172: 152.4 | AJ172: 135.4 | AK172: 102.4 | AM172: 150.4 | AN172: 120.4 | AO172: 71.4 | AP172: 6.4 | AQ172: -96.7
B173: XIAOMI | C173: XIAOMI GOOGLE TV 55" QLED A PRO | D173: 445 | E173: 0 | F173: SMART TV | I173: 98 | J173: 118 | K173: 141 | L173: 158 | M173: 191 | O173: 143 | P173: 203 | Q173: 272 | R173: 327 | S173: 459 | U173: 0 | V173: 0 | W173: 0 | X173: 0 | Y173: 0 | Z173: 0 | AA173: 0 | AB173: -30 | AC173: -50 | AD173: -40 | AE173: -60 | AG173: 346.77 | AH173: 326.77 | AI173: 303.77 | AJ173: 286.77 | AK173: 253.77 | AM173: 301.77 | AN173: 241.77 | AO173: 172.77 | AP173: 117.77 | AQ173: -14.23
B174: XIAOMI | C174: XIAOMI GOOGLE TV 65" QLED A PRO | D174: 577 | E174: 0 | F174: SMART TV | I174: 52 | J174: 72 | K174: 212 | L174: 229 | M174: 262 | O174: 97 | P174: 157 | Q174: 343 | R174: 398 | S174: 530 | U174: 0 | V174: 0 | W174: 0 | X174: 0 | Y174: 0 | Z174: 0 | AA174: 0 | AB174: -30 | AC174: -50 | AD174: -40 | AE174: -60 | AG174: 525 | AH174: 505 | AI174: 365.34 | AJ174: 348.34 | AK174: 315.34 | AM174: 480 | AN174: 420 | AO174: 234.34 | AP174: 179.34 | AQ174: 47.34
B175: XIAOMI | C175: XIAOMI MI ELECTRIC SCOOTER 4 | D175: 459 | E175: 0 | F175: OC_TIEMPO LIBRE | I175: 243 | J175: 263 | K175: 286 | L175: 303 | M175: 336 | O175: 288 | P175: 318 | Q175: 449 | R175: 432 | S175: 544 | U175: 0 | V175: 0 | W175: 0 | X175: 0 | Y175: 0 | Z175: 0 | AA175: 0 | AB175: 0 | AC175: -82 | AD175: 0 | AE175: 0 | AG175: 216.11 | AH175: 196.11 | AI175: 173.11 | AJ175: 156.11 | AK175: 123.11 | AM175: 171.11 | AN175: 141.11 | AO175: 10.11 | AP175: 27.11 | AQ175: -84.89
B176: XIAOMI | C176: XIAOMI MI ELECTRIC SCOOTER 4 PRO 2a GEN | D176: 516 | E176: 0 | F176: OC_TIEMPO LIBRE | I176: 218 | J176: 238 | K176: 261 | L176: 278 | M176: 311 | O176: 263 | P176: 323 | Q176: 392 | R176: 447 | S176: 579 | U176: 0 | V176: 0 | W176: 0 | X176: 0 | Y176: 0 | Z176: 0 | AA176: 0 | AB176: -30 | AC176: -50 | AD176: -40 | AE176: -60 | AG176: 297.9 | AH176: 277.9 | AI176: 254.9 | AJ176: 237.9 | AK176: 204.9 | AM176: 252.9 | AN176: 192.9 | AO176: 123.9 | AP176: 68.9 | AQ176: -63
B177: XIAOMI | C177: XIAOMI PAD 6S PRO WIFI | D177: 647 | E177: 3.75 | F177: TABLET | I177: 52 | J177: 299 | K177: 322 | L177: 339 | M177: 372 | O177: 97 | P177: 384 | Q177: 453 | R177: 508 | S177: 640 | U177: 0 | V177: 0 | W177: 0 | X177: 0 | Y177: 0 | Z177: 0 | AA177: 0 | AB177: -30 | AC177: -50 | AD177: -40 | AE177: -60 | AG177: 595 | AH177: 348.11 | AI177: 325.11 | AJ177: 308.11 | AK177: 275.11 | AM177: 550 | AN177: 263.11 | AO177: 194.11 | AP177: 139.11 | AQ177: 7.11
... B189: ZTE | C189: ZTE A75 128GB 5G | D189: 148 | E189: 3.25 | F189: SMARTPHONE | I189: 82 | J189: 102 | K189: 125 | L189: 142 | M189: 175 | O189: 127 | P189: 157 | Q189: 206 | R189: 208 | S189: 208 | U189: 0 | V189: 0 | W189: 0 | X189: 0 | Y189: 0 | Z189: 0 | AA189: 0 | AB189: 0 | AC189: 0 | AD189: 0 | AE189: 0 | AG189: 66.25 | AH189: 46.25 | AI189: 23.25 | AJ189: 6.25 | AK189: -26.75 | AM189: 21.25 | AN189: -8.75 | AO189: -57.75 | AP189: -60.125 | AQ189: -60.125
B190: GENERICO | C190: SUBVENCION GENERICA | D190: 0 | E190: 0 | F190: - | I190: 0 | J190: 30 | K190: 50 | L190: 70 | M190: 80 | O190: 20 | P190: 60 | Q190: 125 | R190: 160 | S190: 220 | U190: 0 | V190: 0 | W190: 0 | X190: 0 | Y190: 0 | AA190: 0 | AB190: 0 | AC190: -30 | AD190: -40 | AE190: -50 | AG190: 0 | AH190: 0 | AI190: -50 | AJ190: -70 | AK190: -80 | AM190: -20 | AN190: -60 | AO190: -125 | AP190: -160 | AQ190: -220

Sheet PVP Subv - Sol Pers Pyme
B2: OFERTA TÁCTICA EMPRESAS | I2: CAPTA | O2: PORTABILIDAD
B4: ='PVP VaP - Pyme'!B4 -> 45627 | C4: ='PVP VaP - Pyme'!C4 -> 01/12 al 31/12 | I4: ENTRADA PRO | J4: NORMAL PRO | K4: VALOR PRO | L4: PREMIUM PRO | M4: TOP PRO | O4: ENTRADA PRO | P4: NORMAL PRO | Q4: VALOR PRO | R4: PREMIUM PRO | S4: TOP PRO
B5: 1. CONDICIONES DE LA OFERTA SUBVENCIONADA (según tarifa y situación del cliente) | D5: Tarifas | I5: T. Optima Plus Empresas T. Optima Plus Empresas Big + Empresas Voz y Empresas 1 | J5: T. Optima Plus Empresas T. Optima Plus Empresas Big + Empresas 5 y Empresas Intranet | K5: T. Optima Plus Empresas T. Optima Plus Empresas Big + Empresas 20 | L5: T. Optima Plus Empresas T. Optima Plus Empresas Big + Empresas Infinita | M5: T. Optima Plus Empresas T. Optima Plus Empresas Big + Empresas Internacional | O5: T. Optima Plus Empresas T. Optima Plus Empresas Big + Empresas Voz y Empresas 1 | P5: T. Optima Plus Empresas T. Optima Plus Empresas Big + Empresas 5 y Empresas Intranet | Q5: T. Optima Plus Empresas T. Optima Plus Empresas Big + Empresas 20 | R5: T. Optima Plus Empresas T. Optima Plus Empresas Big + Empresas Infinita | S5: T. Optima Plus Empresas T. Optima Plus Empresas Big + Empresas Internacional
D12: Ampliaciones (meses antigüedad) | I12: Todos | J12: Todos | K12: Todos | L12: Todos | M12: Todos | O12: Todos | P12: Todos | Q12: Todos | R12: Todos | S12: Todos
D13: Origen (Portabilidad / Migración) | I13: Capta Prepago Migracion | J13: Capta Prepago Migracion | K13: Capta Prepago Migracion | L13: Capta Prepago Migracion | M13: Capta Prepago Migracion | O13: Pospago | P13: Pospago | Q13: Pospago | R13: Pospago | S13: Pospago
D14: CP Tarifa | I14: 24 M | J14: 24 M | K14: 24 M | L14: 24 M | M14: 24 M | O14: 24 M | P14: 24 M | Q14: 24 M | R14: 24 M | S14: 24 M
D15: CP Terminal | I15: 24 M | J15: 24 M | K15: 24 M | L15: 24 M | M15: 24 M | O15: 24 M | P15: 24 M | Q15: 24 M | R15: 24 M | S15: 24 M
I16: Las condiciones de los modulos Entrada Pro y Normal Pro aplican para los terminales VOZ y FIX tanto si activan sólo voz como si activan el paquete de voz + datos | U16: DIFERENCIAS Vs MES ANTERIOR
B19: 2. PRECIO DEL TERMINAL POR GRUPO DE TARIFAS | I19: DxC CAPTA | O19: DxC PORTABILIDAD | U19: DxC CAPTA | AA19: DxC PORTABILIDAD | AG19: PVPR CAPTA | AM19: PVPR PORTABILIDAD
I21: GRUPOS DE TARIFAS MOVIL | O21: GRUPOS DE TARIFAS MOVIL | U21: GRUPOS DE TARIFAS MOVIL | AA21: GRUPOS DE TARIFAS MOVIL | AG21: GRUPOS DE TARIFAS MOVIL | AM21: GRUPOS DE TARIFAS MOVIL
I23: ENTRADA PRO | J23: NORMAL PRO | K23: VALOR PRO | L23: PREMIUM PRO | M23: TOP PRO | O23: ENTRADA PRO | P23: NORMAL PRO | Q23: VALOR PRO | R23: PREMIUM PRO | S23: TOP PRO | U23: ENTRADA PRO | V23: NORMAL PRO | W23: VALOR PRO | X23: PREMIUM PRO | Y23: TOP PRO | AA23: ENTRADA PRO | AB23: NORMAL PRO | AC23: VALOR PRO | AD23: PREMIUM PRO | AE23: TOP PRO | AG23: ENTRADA PRO | AH23: NORMAL PRO | AI23: VALOR PRO | AJ23: PREMIUM PRO | AK23: TOP PRO | AM23: ENTRADA PRO | AN23: NORMAL PRO | AO23: VALOR PRO | AP23: PREMIUM PRO | AQ23: TOP PRO
B25: MARCA | C25: Modelo (Novedades) | D25: Precio Cesión | E25: Canon Digital | F25: Gama | I25: DxC (sin IVA) | J25: DxC (sin IVA) | K25: DxC (sin IVA) | L25: DxC (sin IVA) | M25: DxC (sin IVA) | O25: DxC (sin IVA) | P25: DxC (sin IVA) | Q25: DxC (sin IVA) | R25: DxC (sin IVA) | S25: DxC (sin IVA) | U25: DxC (sin IVA) | V25: DxC (sin IVA) | W25: DxC (sin IVA) | X25: DxC (sin IVA) | Y25: DxC (sin IVA) | AA25: DxC (sin IVA) | AB25: DxC (sin IVA) | AC25: DxC (sin IVA) | AD25: DxC (sin IVA) | AE25: DxC (sin IVA) | AG25: PVP (sin IVA) | AH25: PVP (sin IVA) | AI25: PVP (sin IVA) | AJ25: PVP (sin IVA) | AK25: PVP (sin IVA) | AM25: PVP (sin IVA) | AN25: PVP (sin IVA) | AO25: PVP (sin IVA) | AP25: PVP (sin IVA) | AQ25: PVP (sin IVA)
B26: ORANGE | C26: AD HOC H3 CESIÓN | D26: 0 | E26: 1.1 | F26: FIXED STYLE | I26: 0 | J26: 0 | K26: 0 | L26: 0 | M26: 0 | O26: 0 | P26: 0 | Q26: 0 | R26: 0 | S26: 0 | U26: 0 | V26: 0 | W26: 0 | X26: 0 | Y26: 0 | AA26: 0 | AB26: 0 | AC26: 0 | AD26: 0 | AE26: 0 | AG26: - | AH26: - | AI26: - | AJ26: - | AK26: - | AM26: - | AN26: - | AO26: - | AP26: - | AQ26: -
B27: ORANGE | C27: ADOC D30 | D27: 239 | E27: 3.75 | F27: FIXED STYLE | I27: 116 | J27: 166 | K27: 215 | L27: 239 | M27: 239 | O27: 210 | P27: 220 | Q27: 239 | R27: 239 | S27: 239 | U27: 0 | V27: 0 | W27: 0 | X27: 0 | Y27: 0 | AA27: 0 | AB27: 0 | AC27: 0 | AD27: 0 | AE27: 0 | AG27: 123 | AH27: 73 | AI27: 24 | AJ27: 0 | AK27: 0 | AM27: 29 | AN27: 19 | AO27: 0 | AP27: 0 | AQ27: 0
B28: ORANGE | C28: ADOC D30 CESIÓN | D28: 0 | E28: 3.75 | F28: FIXED STYLE | I28: 0 | J28: 0 | K28: 0 | L28: 0 | M28: 0 | O28: 0 | P28: 0 | Q28: 0 | R28: 0 | S28: 0 | U28: 0 | V28: 0 | W28: 0 | X28: 0 | Y28: 0 | AA28: 0 | AB28: 0 | AC28: 0 | AD28: 0 | AE28: 0 | AG28: - | AH28: - | AI28: - | AJ28: - | AK28: - | AM28: - | AN28: - | AO28: - | AP28: - | AQ28: -
B29: AD HOC | C29: ADOC SC01 | D29: 64 | E29: 1.1 | F29: VOZ | I29: 64 | J29: 64 | K29: 0 | L29: 0 | M29: 0 | O29: 64 | P29: 0 | Q29: 0 | R29: 0 | S29: 0 | U29: 0 | V29: 0 | W29: 0 | X29: 0 | Y29: 0 | AA29: 0 | AB29: 0 | AC29: 0 | AD29: 0 | AE29: 0 | AG29: 0 | AH29: 0 | AI29: - | AJ29: - | AK29: - | AM29: 0 | AN29: - | AO29: - | AP29: - | AQ29: -
B30: ADOC | C30: ADOC SC04 | D30: 77 | E30: 1.1 | F30: VOZ | I30: 77 | J30: 77 | K30: 0 | L30: 0 | M30: 0 | O30: 77 | P30: 0 | Q30: 0 | R30: 0 | S30: 0 | U30: 0 | V30: 0 | W30: 0 | X30: 0 | Y30: 0 | AA30: 0 | AB30: 0 | AC30: 0 | AD30: 0 | AE30: 0 | AG30: 0 | AH30: 0 | AI30: - | AJ30: - | AK30: - | AM30: 0 | AN30: - | AO30: - | AP30: - | AQ30: -
B31: APPLE | C31: APPLE AIRPODS 4 | D31: 137 | E31: 0 | F31: OC_AURICULARES | I31: 52 | J31: 72 | K31: 95 | L31: 112 | M31: 145 | O31: 68 | P31: 87 | Q31: 115 | R31: 160 | S31: 230 | U31: 0 | V31: 0 | W31: 0 | X31: 0 | Y31: 0 | AA31: 0 | AB31: 0 | AC31: 0 | AD31: 0 | AE31: 0 | AG31: 85 | AH31: 65 | AI31: 42 | AJ31: 25 | AK31: -8 | AM31: 69.5 | AN31: 50.5 | AO31: 22 | AP31: -22.5 | AQ31: -92.5
B32: APPLE | C32: APPLE AIRPODS 4 CON CANCELACION ACTIVA RUIDO | D32: 184 | E32: 0 | F32: OC_AURICULARES | I32: 52 | J32: 72 | K32: 95 | L32: 112 | M32: 145 | O32: 68 | P32: 87 | Q32: 115 | R32: 160 | S32: 230 | U32: 0 | V32: 0 | W32: 0 | X32: 0 | Y32: 0 | AA32: 0 | AB32: 0 | AC32: 0 | AD32: 0 | AE32: 0 | AG32: 132 | AH32: 112 | AI32: 89 | AJ32: 72 | AK32: 39 | AM32: 116.5 | AN32: 97.5 | AO32: 69 | AP32: 24.5 | AQ32: -45.5
B33: APPLE | C33: APPLE AIRPODS PRO 2a GENERACION MAGSAFE USBC | D33: 279 | E33: 0 | F33: OC_AURICULARES | I33: 89 | J33: 109 | K33: 132 | L33: 149 | M33: 182 | O33: 104 | P33: 123 | Q33: 152 | R33: 196 | S33: 266 | U33: 0 | V33: 0 | W33: 0 | X33: 0 | Y33: 0 | AA33: 0 | AB33: 0 | AC33: 0 | AD33: 0 | AE33: 0 | AG33: 190.46 | AH33: 170.46 | AI33: 147.46 | AJ33: 130.46 | AK33: 97.46 | AM33: 174.96 | AN33: 155.96 | AO33: 127.46 | AP33: 82.96 | AQ33: 12.96
B34: APPLE | C34: APPLE WATCH S10 CELLULAR 42MM | D34: 532 | E34: 2.5 | F34: OC_SMART WATCH | I34: 52 | J34: 138 | K34: 161 | L34: 178 | M34: 211 | O34: 68 | P34: 153 | Q34: 181 | R34: 226 | S34: 296 | U34: 0 | V34: 0 | W34: 0 | X34: 0 | Y34: 0 | AA34: 0 | AB34: 0 | AC34: 0 | AD34: 0 | AE34: 0 | AG34: 480 | AH34: 393.81 | AI34: 370.81 | AJ34: 353.81 | AK34: 320.81 | AM34: 464.5 | AN34: 379.31 | AO34: 350.81 | AP34: 306.31 | AQ34: 236.31
B35: APPLE | C35: APPLE WATCH S10 CELLULAR 46MM | D35: 555 | E35: 2.5 | F35: OC_SMART WATCH | I35: 52 | J35: 139 | K35: 162 | L35: 179 | M35: 212 | O35: 68 | P35: 153 | Q35: 182 | R35: 226 | S35: 296 | U35: 0 | V35: 0 | W35: 0 | X35: 0 | Y35: 0 | AA35: 0 | AB35: 0 | AC35: 0 | AD35: 0 | AE35: 0 | AG35: 503 | AH35: 416.25 | AI35: 393.25 | AJ35: 376.25 | AK35: 343.25 | AM35: 487.5 | AN35: 401.75 | AO35: 373.25 | AP35: 328.75 | AQ35: 258.75
B36: APPLE | C36: APPLE WATCH S9 CELLULAR 45MM | D36: 555 | E36: 2.5 | F36: OC_SMART WATCH | I36: 52 | J36: 139 | K36: 162 | L36: 179 | M36: 212 | O36: 68 | P36: 153 | Q36: 182 | R36: 226 | S36: 296 | U36: 0 | V36: 0 | W36: 0 | X36: 0 | Y36: 0 | AA36: 0 | AB36: 0 | AC36: 0 | AD36: 0 | AE36: 0 | AG36: 503 | AH36: 416.25 | AI36: 393.25 | AJ36: 376.25 | AK36: 343.25 | AM36: 487.5 | AN36: 401.75 | AO36: 373.25 | AP36: 328.75 | AQ36: 258.75
B37: AD HOC | C37: AURICULARES AD HOC BT01 | D37: 71 | E37: 0 | F37: OC_AURICULARES | I37: 71 | J37: 71 | K37: 71 | L37: 71 | M37: 71 | O37: 71 | P37: 71 | Q37: 71 | R37: 71 | S37: 71 | U37: 0 | V37: 0 | W37: 0 | X37: 0 | Y37: 0 | AA37: 0 | AB37: 0 | AC37: 0 | AD37: 0 | AE37: 0 | AG37: 0 | AH37: 0 | AI37: 0 | AJ37: 0 | AK37: 0 | AM37: 0 | AN37: 0 | AO37: 0 | AP37: 0 | AQ37: 0
B38: AD HOC | C38: AURICULARES AD HOC HC01 | D38: 49 | E38: 0 | F38: OC_AURICULARES | I38: 49 | J38: 49 | K38: 49 | L38: 49 | M38: 49 | O38: 49 | P38: 49 | Q38: 49 | R38: 49 | S38: 49 | U38: 0 | V38: 0 | W38: 0 | X38: 0 | Y38: 0 | AA38: 0 | AB38: 0 | AC38: 0 | AD38: 0 | AE38: 0 | AG38: 0 | AH38: 0 | AI38: 0 | AJ38: 0 | AK38: 0 | AM38: 0 | AN38: 0 | AO38: 0 | AP38: 0 | AQ38: 0
B39: SAMSUNG | C39: AURICULARES SAMSUNG GALAXY BUDS 3 | D39: 172 | E39: 0 | F39: OC_AURICULARES | I39: 82 | J39: 102 | K39: 125 | L39: 142 | M39: 175 | O39: 98 | P39: 117 | Q39: 145 | R39: 190 | S39: 260 | U39: 0 | V39: 0 | W39: 0 | X39: 0 | Y39: 0 | AA39: 0 | AB39: 0 | AC39: 0 | AD39: 0 | AE39: 0 | AG39: 90 | AH39: 70 | AI39: 47 | AJ39: 30 | AK39: -3 | AM39: 74.5 | AN39: 55.5 | AO39: 27 | AP39: -17.5 | AQ39: -87.5
B40: SAMSUNG | C40: AURICULARES SAMSUNG GALAXY BUDS 3 PRO | D40: 240 | E40: 0 | F40: OC_AURICULARES | I40: 103 | J40: 123 | K40: 146 | L40: 163 | M40: 196 | O40: 119 | P40: 138 | Q40: 166 | R40: 211 | S40: 281 | U40: 0 | V40: 0 | W40: 0 | X40: 0 | Y40: 0 | AA40: 0 | AB40: 0 | AC40: 0 | AD40: 0 | AE40: 0 | AG40: 137 | AH40: 117 | AI40: 94 | AJ40: 77 | AK40: 44 | AM40: 121.5 | AN40: 102.5 | AO40: 74 | AP40: 29.5 | AQ40: -40.5
B41: SPC | C41: AURICULARES SPC BRAVE PRO | D41: 44 | E41: 0 | F41: OC_AURICULARES | I41: 44 | J41: 44 | K41: 44 | L41: 44 | M41: 44 | O41: 44 | P41: 44 | Q41: 44 | R41: 44 | S41: 44 | U41: 0 | V41: 0 | W41: 0 | X41: 0 | Y41: 0 | AA41: 0 | AB41: 0 | AC41: 0 | AD41: 0 | AE41: 0 | AG41: 0 | AH41: 0 | AI41: 0 | AJ41: 0 | AK41: 0 | AM41: 0 | AN41: 0 | AO41: 0 | AP41: 0 | AQ41: 0
B42: SPC | C42: AURICULARES SPC DREAMER PRO | D42: 77 | E42: 0 | F42: OC_AURICULARES | I42: 77 | J42: 77 | K42: 77 | L42: 77 | M42: 77 | O42: 77 | P42: 77 | Q42: 77 | R42: 77 | S42: 77 | U42: 0 | V42: 0 | W42: 0 | X42: 0 | Y42: 0 | AA42: 0 | AB42: 0 | AC42: 0 | AD42: 0 | AE42: 0 | AG42: 0 | AH42: 0 | AI42: 0 | AJ42: 0 | AK42: 0 | AM42: 0 | AN42: 0 | AO42: 0 | AP42: 0 | AQ42: 0
... B74: LENOVO | C74: LENOVO IDEAPAD 1 15ADA7 4120 8+256GB | D74: 462 | E74: 5.33 | F74: PC | I74: 169 | J74: 189 | K74: 212 | L74: 229 | M74: 262 | O74: 184 | P74: 203 | Q74: 232 | R74: 276 | S74: 346 | U74: -30 | V74: -30 | W74: -30 | X74: -30 | Y74: -30 | AA74: -30 | AB74: -30 | AC74: -30 | AD74: -30 | AE74: -30 | AG74: 293.33 | AH74: 273.33 | AI74: 250.33 | AJ74: 233.33 | AK74: 200.33 | AM74: 277.83 | AN74: 258.83 | AO74: 230.33 | AP74: 185.83 | AQ74: 115.83
B75: LENOVO | C75: LENOVO IDEAPAD 3 15IAH8 CI5 8+512GB | D75: 620 | E75: 5.33 | F75: PC | I75: 52 | J75: 138 | K75: 161 | L75: 178 | M75: 211 | O75: 68 | P75: 153 | Q75: 181 | R75: 226 | S75: 296 | U75: =NA() -> #N/A | V75: =NA() -> #N/A | W75: =NA() -> #N/A | X75: =NA() -> #N/A | Y75: =NA() -> #N/A | AA75: =NA() -> #N/A | AB75: =NA() -> #N/A | AC75: =NA() -> #N/A | AD75: =NA() -> #N/A | AE75: =NA() -> #N/A | AG75: 568 | AH75: 481.59 | AI75: 458.59 | AJ75: 441.59 | AK75: 408.59 | AM75: 552.5 | AN75: 467.09 | AO75: 438.59 | AP75: 394.09 | AQ75: 324.09
B76: LENOVO | C76: LENOVO IDEAPAD 3 15IAH8 CI5 8+512GB + TAB M11 WIFI | D76: 620 | E76: 5.33 | F76: PC | I76: 52 | J76: 138 | K76: 161 | L76: 178 | M76: 211 | O76: 68 | P76: 153 | Q76: 181 | R76: 226 | S76: 296 | U76: =NA() -> #N/A | V76: =NA() -> #N/A | W76: =NA() -> #N/A | X76: =NA() -> #N/A | Y76: =NA() -> #N/A | AA76: =NA() -> #N/A | AB76: =NA() -> #N/A | AC76: =NA() -> #N/A | AD76: =NA() -> #N/A | AE76: =NA() -> #N/A | AG76: 568 | AH76: 481.59 | AI76: 458.59 | AJ76: 441.59 | AK76: 408.59 | AM76: 552.5 | AN76: 467.09 | AO76: 438.59 | AP76: 394.09 | AQ76: 324.09
B77: LENOVO | C77: LENOVO IDEAPAD 3 15ITL6 CI5 | D77: 638 | E77: 5.33 | F77: PC | I77: 52 | J77: 156 | K77: 179 | L77: 196 | M77: 229 | O77: 68 | P77: 171 | Q77: 199 | R77: 244 | S77: 314 | U77: 0 | V77: 50 | W77: 50 | X77: 50 | Y77: 50 | AA77: 0 | AB77: 50 | AC77: 50 | AD77: 50 | AE77: 50 | AG77: 586 | AH77: 481.59 | AI77: 458.59 | AJ77: 441.59 | AK77: 408.59 | AM77: 570.5 | AN77: 467.09 | AO77: 438.59 | AP77: 394.09 | AQ77: 324.09
B78: LENOVO | C78: LENOVO IDEAPAD 5 16IRL8 I7 13GEN 16GB+1TB | D78: 915 | E78: 5.33 | F78: PC | I78: 52 | J78: 243 | K78: 266 | L78: 283 | M78: 316 | O78: 68 | P78: 257 | Q78: 286 | R78: 330 | S78: 400 | U78: 0 | V78: 0 | W78: 0 | X78: 0 | Y78: 0 | AA78: 0 | AB78: 0 | AC78: 0 | AD78: 0 | AE78: 0 | AG78: 863 | AH78: 672.33 | AI78: 649.33 | AJ78: 632.33 | AK78: 599.33 | AM78: 847.5 | AN78: 657.83 | AO78: 629.33 | AP78: 584.83 | AQ78: 514.83
B79: LENOVO | C79: LENOVO LOQ 3 15IRH8 i5 RTX 2050 | D79: 948 | E79: 5.33 | F79: PC | I79: 52 | J79: 220 | K79: 243 | L79: 260 | M79: 293 | O79: 68 | P79: 234 | Q79: 263 | R79: 307 | S79: 377 | U79: 0 | V79: 0 | W79: 0 | X79: 0 | Y79: 0 | AA79: 0 | AB79: 0 | AC79: 0 | AD79: 0 | AE79: 0 | AG79: 896 | AH79: 728.33 | AI79: 705.33 | AJ79: 688.33 | AK79: 655.33 | AM79: 880.5 | AN79: 713.83 | AO79: 685.33 | AP79: 640.83 | AQ79: 570.83
B80: LENOVO | C80: LENOVO P3 CHROMEBOOK PLUS 14" i3 8+256GB | D80: 525 | E80: 5.33 | F80: PC | I80: 218 | J80: 238 | K80: 261 | L80: 278 | M80: 311 | O80: 234 | P80: 253 | Q80: 281 | R80: 326 | S80: 396 | U80: 0 | V80: 0 | W80: 0 | X80: 0 | Y80: 0 | AA80: 0 | AB80: 0 | AC80: 0 | AD80: 0 | AE80: 0 | AG80: 306.59 | AH80: 286.59 | AI80: 263.59 | AJ80: 246.59 | AK80: 213.59 | AM80: 291.09 | AN80: 272.09 | AO80: 243.59 | AP80: 199.09 | AQ80: 129.09
B81: LG | C81: LG SMART TV 32" LQ | D81: 215 | E81: 0 | F81: SMART TV | I81: 84 | J81: 104 | K81: 127 | L81: 144 | M81: 177 | O81: 100 | P81: 119 | Q81: 147 | R81: 192 | S81: 156 | U81: 0 | V81: 0 | W81: 0 | X81: 0 | Y81: 0 | AA81: 0 | AB81: 0 | AC81: 0 | AD81: 0 | AE81: 0 | AG81: 131 | AH81: 111 | AI81: 88 | AJ81: 71 | AK81: 38 | AM81: 115.5 | AN81: 96.5 | AO81: 68 | AP81: 23.5 | AQ81: 59
B82: LG | C82: LG SMART TV 43" UR78 4K | D82: 396 | E82: 0 | F82: SMART TV | I82: 161 | J82: 181 | K82: 204 | L82: 221 | M82: 254 | O82: 177 | P82: 196 | Q82: 224 | R82: 269 | S82: 339 | U82: 0 | V82: 0 | W82: 0 | X82: 0 | Y82: 0 | AA82: 0 | AB82: 0 | AC82: 0 | AD82: 0 | AE82: 0 | AG82: 235 | AH82: 215 | AI82: 192 | AJ82: 175 | AK82: 142 | AM82: 219.5 | AN82: 200.5 | AO82: 172 | AP82: 127.5 | AQ82: 57.5
B83: LG | C83: LG SMART TV 50" UR78 4K | D83: 479 | E83: 0 | F83: SMART TV | I83: 191 | J83: 211 | K83: 234 | L83: 251 | M83: 284 | O83: 207 | P83: 226 | Q83: 254 | R83: 299 | S83: 369 | U83: 0 | V83: 0 | W83: 0 | X83: 0 | Y83: 0 | AA83: 0 | AB83: 0 | AC83: 0 | AD83: 0 | AE83: 0 | AG83: 288 | AH83: 268 | AI83: 245 | AJ83: 228 | AK83: 195 | AM83: 272.5 | AN83: 253.5 | AO83: 225 | AP83: 180.5 | AQ83: 110.5
B84: LG | C84: LG SMART TV 55" OLED C46 4K | D84: 1735 | E84: 0 | F84: SMART TV | I84: 52 | J84: 72 | K84: 875 | L84: 892 | M84: 925 | O84: 68 | P84: 87 | Q84: 895 | R84: 940 | S84: 1010 | U84: 0 | V84: 0 | W84: 0 | X84: 0 | Y84: 0 | AA84: 0 | AB84: 0 | AC84: 0 | AD84: 0 | AE84: 0 | AG84: 1683 | AH84: 1663 | AI84: 859.8 | AJ84: 842.8 | AK84: 809.8 | AM84: 1667.5 | AN84: 1648.5 | AO84: 839.8 | AP84: 795.3 | AQ84: 725.3
B85: LG | C85: LG SMART TV 55" UR78 4K | D85: 537 | E85: 0 | F85: SMART TV | I85: 204 | J85: 224 | K85: 247 | L85: 264 | M85: 297 | O85: 220 | P85: 239 | Q85: 267 | R85: 312 | S85: 382 | U85: 0 | V85: 0 | W85: 0 | X85: 0 | Y85: 0 | AA85: 0 | AB85: 0 | AC85: 0 | AD85: 0 | AE85: 0 | AG85: 332.8 | AH85: 312.8 | AI85: 289.8 | AJ85: 272.8 | AK85: 239.8 | AM85: 317.3 | AN85: 298.3 | AO85: 269.8 | AP85: 225.3 | AQ85: 155.3
B86: LG | C86: LG SMART TV 65" OLED C46 4K | D86: 2396 | E86: 0 | F86: SMART TV | I86: 52 | J86: 72 | K86: 1211 | L86: 1228 | M86: 1261 | O86: 68 | P86: 87 | Q86: 1231 | R86: 1276 | S86: 1346 | U86: 0 | V86: 0 | W86: 0 | X86: 0 | Y86: 0 | AA86: 0 | AB86: 0 | AC86: 0 | AD86: 0 | AE86: 0 | AG86: 2344 | AH86: 2324 | AI86: 1184.8 | AJ86: 1167.8 | AK86: 1134.8 | AM86: 2328.5 | AN86: 2309.5 | AO86: 1164.8 | AP86: 1120.3 | AQ86: 1050.3
B87: LG | C87: LG SMART TV 65" UR78 4K | D87: 686 | E87: 0 | F87: SMART TV | I87: 52 | J87: 72 | K87: 316 | L87: 333 | M87: 366 | O87: 68 | P87: 87 | Q87: 336 | R87: 381 | S87: 451 | U87: 0 | V87: 0 | W87: 0 | X87: 0 | Y87: 0 | AA87: 0 | AB87: 0 | AC87: 0 | AD87: 0 | AE87: 0 | AG87: 634 | AH87: 614 | AI87: 369.8 | AJ87: 352.8 | AK87: 319.8 | AM87: 618.5 | AN87: 599.5 | AO87: 349.8 | AP87: 305.3 | AQ87: 235.3
B88: LG | C88: LG SMART TV 75" UT80 4K | D88: 1157 | E88: 0 | F88: SMART TV | I88: 52 | J88: 72 | K88: 498 | L88: 515 | M88: 548 | O88: 68 | P88: 87 | Q88: 518 | R88: 563 | S88: 633 | U88: 0 | V88: 0 | W88: 0 | X88: 0 | Y88: 0 | AA88: 0 | AB88: 0 | AC88: 0 | AD88: 0 | AE88: 0 | AG88: 1105 | AH88: 1085 | AI88: 658.85 | AJ88: 641.85 | AK88: 608.85 | AM88: 1089.5 | AN88: 1070.5 | AO88: 638.85 | AP88: 594.35 | AQ88: 524.35
... B94: MOTOROLA | C94: MOTOROLA MOTO G54 256GB 5G | D94: 199 | E94: 3.25 | F94: SMARTPHONE | I94: 106 | J94: 126 | K94: 149 | L94: 166 | M94: 199 | O94: 121 | P94: 140 | Q94: 169 | R94: 213 | S94: 283 | U94: 0 | V94: 0 | W94: 0 | X94: 0 | Y94: 0 | AA94: 0 | AB94: 0 | AC94: 0 | AD94: 0 | AE94: 0 | AG94: 93.49 | AH94: 73.49 | AI94: 50.49 | AJ94: 33.49 | AK94: 0.49 | AM94: 77.99 | AN94: 58.99 | AO94: 30.49 | AP94: -14.01 | AQ94: -84.01
B95: MOTOROLA | C95: MOTOROLA MOTO G55 256GB 5G | D95: 255 | E95: 3.25 | F95: SMARTPHONE | I95: 108 | J95: 128 | K95: 151 | L95: 168 | M95: 201 | O95: 124 | P95: 143 | Q95: 171 | R95: 216 | S95: 286 | U95: =NA() -> #N/A | V95: =NA() -> #N/A | W95: =NA() -> #N/A | X95: =NA() -> #N/A | Y95: =NA() -> #N/A | AA95: =NA() -> #N/A | AB95: =NA() -> #N/A | AC95: =NA() -> #N/A | AD95: =NA() -> #N/A | AE95: =NA() -> #N/A | AG95: 146.75 | AH95: 126.75 | AI95: 103.75 | AJ95: 86.75 | AK95: 53.75 | AM95: 131.25 | AN95: 112.25 | AO95: 83.75 | AP95: 39.25 | AQ95: -30.75
B96: MOTOROLA | C96: MOTOROLA MOTO G85 256GB 5G | D96: 353 | E96: 3.25 | F96: SMARTPHONE | I96: 128 | J96: 148 | K96: 171 | L96: 188 | M96: 221 | O96: 143 | P96: 162 | Q96: 191 | R96: 235 | S96: 305 | U96: 0 | V96: 0 | W96: 0 | X96: 0 | Y96: 0 | AA96: 0 | AB96: 0 | AC96: 0 | AD96: 0 | AE96: 0 | AG96: 225.26 | AH96: 205.26 | AI96: 182.26 | AJ96: 165.26 | AK96: 132.26 | AM96: 209.76 | AN96: 190.76 | AO96: 162.26 | AP96: 117.76 | AQ96: 47.76
B97: MOTOROLA | C97: MOTOROLA MOTO THINKPHONE 25 256GB 5G | D97: 481 | E97: 3.25 | F97: SMARTPHONE | I97: 178 | J97: 198 | K97: 221 | L97: 238 | M97: 271 | O97: 193 | P97: 212 | Q97: 241 | R97: 285 | S97: 355 | U97: =NA() -> #N/A | V97: =NA() -> #N/A | W97: =NA() -> #N/A | X97: =NA() -> #N/A | Y97: =NA() -> #N/A | AA97: =NA() -> #N/A | AB97: =NA() -> #N/A | AC97: =NA() -> #N/A | AD97: =NA() -> #N/A | AE97: =NA() -> #N/A | AG97: 303.03 | AH97: 283.03 | AI97: 260.03 | AJ97: 243.03 | AK97: 210.03 | AM97: 287.53 | AN97: 268.53 | AO97: 240.03 | AP97: 195.53 | AQ97: 125.53
B98: MOTOROLA | C98: MOTOROLA RAZR 50 256GB 5G | D98: 869 | E98: 3.25 | F98: SMARTPHONE | I98: 52 | J98: 301 | K98: 324 | L98: 341 | M98: 374 | O98: 68 | P98: 316 | Q98: 344 | R98: 389 | S98: 459 | U98: 0 | V98: 0 | W98: 0 | X98: 0 | Y98: 0 | AA98: 0 | AB98: 0 | AC98: 0 | AD98: 0 | AE98: 0 | AG98: 817 | AH98: 567.78 | AI98: 544.78 | AJ98: 527.78 | AK98: 494.78 | AM98: 801.5 | AN98: 553.28 | AO98: 524.78 | AP98: 480.28 | AQ98: 410.28
B99: OPPO | C99: OPPO A38 | D99: 191 | E99: 3.25 | F99: SMARTPHONE | I99: 131 | J99: 151 | K99: 174 | L99: 191 | M99: 224 | O99: 146 | P99: 165 | Q99: 194 | R99: 238 | S99: 308 | U99: 0 | V99: 0 | W99: 0 | X99: 0 | Y99: 0 | AA99: 0 | AB99: 0 | AC99: 0 | AD99: 0 | AE99: 0 | AG99: 60.29 | AH99: 40.29 | AI99: 17.29 | AJ99: 0.29 | AK99: -32.71 | AM99: 44.79 | AN99: 25.79 | AO99: -2.71 | AP99: -47.21 | AQ99: -117.21
B100: OPPO | C100: OPPO A40 128GB | D100: 160 | E100: 3.25 | F100: SMARTPHONE | I100: 102 | J100: 122 | K100: 145 | L100: 162 | M100: 195 | O100: 118 | P100: 137 | Q100: 165 | R100: 210 | S100: 280 | U100: 0 | V100: 0 | W100: 0 | X100: 0 | Y100: 0 | AA100: 0 | AB100: 0 | AC100: 0 | AD100: 0 | AE100: 0 | AG100: 57.98 | AH100: 37.98 | AI100: 14.98 | AJ100: -2.02 | AK100: -35.02 | AM100: 42.48 | AN100: 23.48 | AO100: -5.02 | AP100: -49.52 | AQ100: -119.52
B101: OPPO | C101: OPPO A60 128GB 5G | D101: 176 | E101: 3.25 | F101: SMARTPHONE | I101: 103 | J101: 123 | K101: 146 | L101: 163 | M101: 196 | O101: 118 | P101: 137 | Q101: 166 | R101: 210 | S101: 280 | U101: 0 | V101: 0 | W101: 0 | X101: 0 | Y101: 0 | AA101: 0 | AB101: 0 | AC101: 0 | AD101: 0 | AE101: 0 | AG101: 73.18 | AH101: 53.18 | AI101: 30.18 | AJ101: 13.18 | AK101: -19.82 | AM101: 57.68 | AN101: 38.68 | AO101: 10.18 | AP101: -34.32 | AQ101: -104.32
B102: OPPO | C102: OPPO A80 256GB 5G | D102: 245 | E102: 3.25 | F102: SMARTPHONE | I102: 132 | J102: 152 | K102: 175 | L102: 192 | M102: 225 | O102: 147 | P102: 166 | Q102: 195 | R102: 239 | S102: 309 | U102: 0 | V102: 0 | W102: 0 | X102: 0 | Y102: 0 | AA102: 0 | AB102: 0 | AC102: 0 | AD102: 0 | AE102: 0 | AG102: 113.32 | AH102: 93.32 | AI102: 70.32 | AJ102: 53.32 | AK102: 20.32 | AM102: 97.82 | AN102: 78.82 | AO102: 50.32 | AP102: 5.82 | AQ102: -64.18
B103: OPPO | C103: OPPO FIND X8 PRO 512GB 5G | D103: 1072 | E103: 3.25 | F103: SMARTPHONE | I103: 52 | J103: 313 | K103: 336 | L103: 353 | M103: 386 | O103: 68 | P103: 327 | Q103: 356 | R103: 400 | S103: 470 | U103: =NA() -> #N/A | V103: =NA() -> #N/A | W103: =NA() -> #N/A | X103: =NA() -> #N/A | Y103: =NA() -> #N/A | AA103: =NA() -> #N/A | AB103: =NA() -> #N/A | AC103: =NA() -> #N/A | AD103: =NA() -> #N/A | AE103: =NA() -> #N/A | AG103: 1020 | AH103: 759.45 | AI103: 736.45 | AJ103: 719.45 | AK103: 686.45 | AM103: 1004.5 | AN103: 744.95 | AO103: 716.45 | AP103: 671.95 | AQ103: 601.95
B104: OPPO | C104: OPPO RENO12 256GB 5G | D104: 428 | E104: 3.25 | F104: SMARTPHONE | I104: 209 | J104: 229 | K104: 252 | L104: 269 | M104: 302 | O104: 224 | P104: 243 | Q104: 272 | R104: 316 | S104: 386 | U104: 0 | V104: 0 | W104: 0 | X104: 0 | Y104: 0 | AA104: 0 | AB104: 0 | AC104: 0 | AD104: 0 | AE104: 0 | AG104: 219.39 | AH104: 199.39 | AI104: 176.39 | AJ104: 159.39 | AK104: 126.39 | AM104: 203.89 | AN104: 184.89 | AO104: 156.39 | AP104: 111.89 | AQ104: 41.89
B105: OPPO | C105: OPPO RENO12 FS 512GB 5G | D105: 364 | E105: 3.25 | F105: SMARTPHONE | I105: 168 | J105: 188 | K105: 211 | L105: 228 | M105: 261 | O105: 183 | P105: 202 | Q105: 231 | R105: 275 | S105: 345 | U105: 0 | V105: 0 | W105: 0 | X105: 0 | Y105: 0 | AA105: 0 | AB105: 0 | AC105: 0 | AD105: 0 | AE105: 0 | AG105: 196.2 | AH105: 176.2 | AI105: 153.2 | AJ105: 136.2 | AK105: 103.2 | AM105: 180.7 | AN105: 161.7 | AO105: 133.2 | AP105: 88.7 | AQ105: 18.7
B106: OPPO | C106: OPPO RENO12 PRO 512GB 5G | D106: 524 | E106: 3.25 | F106: SMARTPHONE | I106: 214 | J106: 234 | K106: 257 | L106: 274 | M106: 307 | O106: 229 | P106: 248 | Q106: 277 | R106: 321 | S106: 391 | U106: 0 | V106: 0 | W106: 0 | X106: 0 | Y106: 0 | AA106: 0 | AB106: 0 | AC106: 0 | AD106: 0 | AE106: 0 | AG106: 310.42 | AH106: 290.42 | AI106: 267.42 | AJ106: 250.42 | AK106: 217.42 | AM106: 294.92 | AN106: 275.92 | AO106: 247.42 | AP106: 202.92 | AQ106: 132.92
B107: ORANGE | C107: ORANGE GAMA 120 4G | D107: 74 | E107: 1.1 | F107: FIXED STYLE | I107: 74 | J107: 74 | K107: 74 | L107: 74 | M107: 74 | O107: 74 | P107: 74 | Q107: 74 | R107: 74 | S107: 74 | U107: 0 | V107: -74 | W107: -74 | X107: -74 | Y107: -74 | AA107: 0 | AB107: -74 | AC107: -74 | AD107: -74 | AE107: -74 | AG107: 0 | AH107: 0 | AI107: 0 | AJ107: 0 | AK107: 0 | AM107: 0 | AN107: 0 | AO107: 0 | AP107: 0 | AQ107: 0
B108: ORANGE | C108: ORANGE GAMA 401 CESIÓN | D108: 0 | E108: 1.1 | F108: FIXED STYLE | I108: 0 | J108: 0 | K108: 0 | L108: 0 | M108: 0 | O108: 0 | P108: 0 | Q108: 0 | R108: 0 | S108: 0 | U108: 0 | V108: 0 | W108: 0 | X108: 0 | Y108: 0 | AA108: 0 | AB108: 0 | AC108: 0 | AD108: 0 | AE108: 0 | AG108: - | AH108: - | AI108: - | AJ108: - | AK108: - | AM108: - | AN108: - | AO108: - | AP108: - | AQ108: -
B109: ORANGE | C109: ORANGE GAMA 402 | D109: 70 | E109: 1.1 | F109: FIXED STYLE | I109: 70 | J109: 0 | K109: 0 | L109: 0 | M109: 0 | O109: 70 | P109: 0 | Q109: 0 | R109: 0 | S109: 0 | U109: 0 | V109: 0 | W109: 0 | X109: 0 | Y109: 0 | AA109: 0 | AB109: 0 | AC109: 0 | AD109: 0 | AE109: 0 | AG109: 0 | AH109: - | AI109: - | AJ109: - | AK109: - | AM109: 0 | AN109: - | AO109: - | AP109: - | AQ109: -
B110: ORANGE | C110: ORANGE GAMA 402 CESIÓN | D110: 0 | E110: 1.1 | F110: FIXED STYLE | I110: 0 | J110: 0 | K110: 0 | L110: 0 | M110: 0 | O110: 0 | P110: 0 | Q110: 0 | R110: 0 | S110: 0 | U110: 0 | V110: 0 | W110: 0 | X110: 0 | Y110: 0 | AA110: 0 | AB110: 0 | AC110: 0 | AD110: 0 | AE110: 0 | AG110: - | AH110: - | AI110: - | AJ110: - | AK110: - | AM110: - | AN110: - | AO110: - | AP110: - | AQ110: -
B111: ORANGE | C111: ORANGE GAMA 704 | D111: 104 | E111: 1.1 | F111: FIXED STYLE | I111: 80 | J111: 0 | K111: 0 | L111: 0 | M111: 0 | O111: 80 | P111: 0 | Q111: 0 | R111: 0 | S111: 0 | U111: 0 | V111: 0 | W111: 0 | X111: 0 | Y111: 0 | AA111: 0 | AB111: 0 | AC111: 0 | AD111: 0 | AE111: 0 | AG111: 24 | AH111: - | AI111: - | AJ111: - | AK111: - | AM111: 24 | AN111: - | AO111: - | AP111: - | AQ111: -
B112: ORANGE | C112: ORANGE GAMA 704 CESIÓN | D112: 0 | E112: 1.1 | F112: FIXED STYLE | I112: 0 | J112: 0 | K112: 0 | L112: 0 | M112: 0 | O112: 0 | P112: 0 | Q112: 0 | R112: 0 | S112: 0 | U112: 0 | V112: 0 | W112: 0 | X112: 0 | Y112: 0 | AA112: 0 | AB112: 0 | AC112: 0 | AD112: 0 | AE112: 0 | AG112: - | AH112: - | AI112: - | AJ112: - | AK112: - | AM112: - | AN112: - | AO112: - | AP112: - | AQ112: -
B113: ORANGE | C113: ORANGE GAMA 803 CESIÓN | D113: 0 | E113: 1.1 | F113: FIXED STYLE | I113: 0 | J113: 0 | K113: 0 | L113: 0 | M113: 0 | O113: 0 | P113: 0 | Q113: 0 | R113: 0 | S113: 0 | U113: 0 | V113: 0 | W113: 0 | X113: 0 | Y113: 0 | AA113: 0 | AB113: 0 | AC113: 0 | AD113: 0 | AE113: 0 | AG113: - | AH113: - | AI113: - | AJ113: - | AK113: - | AM113: - | AN113: - | AO113: - | AP113: - | AQ113: -
B114: DEF | C114: PACK BALIZA CONECTADA DGT 2 UNIDADES | D114: 96 | E114: 0 | F114: OC_OTROS DISPOSITIVOS | I114: 91 | J114: 96 | K114: 96 | L114: 96 | M114: 96 | O114: 96 | P114: 96 | Q114: 96 | R114: 96 | S114: 96 | U114: 0 | V114: 0 | W114: 0 | X114: 0 | Y114: 0 | AA114: 0 | AB114: 0 | AC114: 0 | AD114: 0 | AE114: 0 | AG114: 5 | AH114: 0 | AI114: 0 | AJ114: 0 | AK114: 0 | AM114: 0 | AN114: 0 | AO114: 0 | AP114: 0 | AQ114: 0
B115: NEXTIVITY | C115: REPETIDOR NEXTIVITY CELFI CONNECT C41 | D115: 547 | E115: 0 | F115: OC_OTROS DISPOSITIVOS | I115: 352 | J115: 352 | K115: 352 | L115: 352 | M115: 352 | O115: 352 | P115: 352 | Q115: 352 | R115: 352 | S115: 352 | U115: 0 | V115: 0 | W115: 0 | X115: 0 | Y115: 0 | AA115: 0 | AB115: 0 | AC115: 0 | AD115: 0 | AE115: 0 | AG115: 195 | AH115: 195 | AI115: 195 | AJ115: 195 | AK115: 195 | AM115: 195 | AN115: 195 | AO115: 195 | AP115: 195 | AQ115: 195
B116: SAMSUNG | C116: SAMSUNG GALAXY A15 | D116: 186 | E116: 3.25 | F116: SMARTPHONE | I116: 52 | J116: 72 | K116: 95 | L116: 112 | M116: 145 | O116: 68 | P116: 87 | Q116: 115 | R116: 160 | S116: 230 | U116: 13 | V116: 13 | W116: 13 | X116: 13 | Y116: 13 | AA116: 18 | AB116: 18 | AC116: 19 | AD116: 18 | AE116: 18 | AG116: 134 | AH116: 114 | AI116: 91 | AJ116: 74 | AK116: 41 | AM116: 118.5 | AN116: 99.5 | AO116: 71 | AP116: 26.5 | AQ116: -43.5
B117: SAMSUNG | C117: SAMSUNG GALAXY A15 5G | D117: 215 | E117: 3.25 | F117: SMARTPHONE | I117: 52 | J117: 72 | K117: 95 | L117: 112 | M117: 145 | O117: 68 | P117: 87 | Q117: 115 | R117: 160 | S117: 230 | U117: 23 | V117: 23 | W117: 23 | X117: 23 | Y117: 23 | AA117: 22 | AB117: 22 | AC117: 23 | AD117: 22 | AE117: 22 | AG117: 163 | AH117: 143 | AI117: 120 | AJ117: 103 | AK117: 70 | AM117: 147.5 | AN117: 128.5 | AO117: 100 | AP117: 55.5 | AQ117: -14.5
B118: SAMSUNG | C118: SAMSUNG GALAXY A16 128GB | D118: 186 | E118: 3.25 | F118: SMARTPHONE | I118: 101 | J118: 121 | K118: 144 | L118: 161 | M118: 194 | O118: 116 | P118: 135 | Q118: 164 | R118: 208 | S118: 278 | U118: 0 | V118: 0 | W118: 0 | X118: 0 | Y118: 0 | AA118: 0 | AB118: 0 | AC118: 0 | AD118: 0 | AE118: 0 | AG118: 85.25 | AH118: 65.25 | AI118: 42.25 | AJ118: 25.25 | AK118: -7.75 | AM118: 69.75 | AN118: 50.75 | AO118: 22.25 | AP118: -22.25 | AQ118: -92.25
B119: SAMSUNG | C119: SAMSUNG GALAXY A16 128GB 5G | D119: 248 | E119: 3.25 | F119: SMARTPHONE | I119: 150 | J119: 170 | K119: 193 | L119: 210 | M119: 243 | O119: 166 | P119: 185 | Q119: 213 | R119: 258 | S119: 328 | U119: 0 | V119: 0 | W119: 0 | X119: 0 | Y119: 0 | AA119: 0 | AB119: 0 | AC119: 0 | AD119: 0 | AE119: 0 | AG119: 98 | AH119: 78 | AI119: 55 | AJ119: 38 | AK119: 5 | AM119: 82.5 | AN119: 63.5 | AO119: 35 | AP119: -9.5 | AQ119: -79.5
B120: SAMSUNG | C120: SAMSUNG GALAXY A25 5G | D120: 299 | E120: 3.25 | F120: SMARTPHONE | I120: 108 | J120: 128 | K120: 151 | L120: 168 | M120: 201 | O120: 123 | P120: 142 | Q120: 171 | R120: 215 | S120: 285 | U120: 30 | V120: 30 | W120: 30 | X120: 30 | Y120: 30 | AA120: 30 | AB120: 30 | AC120: 30 | AD120: 30 | AE120: 30 | AG120: 191.25 | AH120: 171.25 | AI120: 148.25 | AJ120: 131.25 | AK120: 98.25 | AM120: 175.75 | AN120: 156.75 | AO120: 128.25 | AP120: 83.75 | AQ120: 13.75
B121: SAMSUNG | C121: SAMSUNG GALAXY A35 5G | D121: 358 | E121: 3.25 | F121: SMARTPHONE | I121: 124 | J121: 144 | K121: 167 | L121: 184 | M121: 217 | O121: 139 | P121: 158 | Q121: 187 | R121: 231 | S121: 301 | U121: 35 | V121: 35 | W121: 35 | X121: 35 | Y121: 35 | AA121: 35 | AB121: 35 | AC121: 35 | AD121: 35 | AE121: 35 | AG121: 234.25 | AH121: 214.25 | AI121: 191.25 | AJ121: 174.25 | AK121: 141.25 | AM121: 218.75 | AN121: 199.75 | AO121: 171.25 | AP121: 126.75 | AQ121: 56.75
B122: SAMSUNG | C122: SAMSUNG GALAXY A55 5G | D122: 442 | E122: 3.25 | F122: SMARTPHONE | I122: 179 | J122: 199 | K122: 222 | L122: 239 | M122: 272 | O122: 194 | P122: 213 | Q122: 242 | R122: 286 | S122: 356 | U122: 0 | V122: 0 | W122: 0 | X122: 0 | Y122: 0 | AA122: 0 | AB122: 0 | AC122: 0 | AD122: 0 | AE122: 0 | AG122: 263.25 | AH122: 243.25 | AI122: 220.25 | AJ122: 203.25 | AK122: 170.25 | AM122: 247.75 | AN122: 228.75 | AO122: 200.25 | AP122: 155.75 | AQ122: 85.75
B123: SAMSUNG | C123: SAMSUNG GALAXY BOOK2 GO 14" | D123: 533 | E123: 5.33 | F123: PC | I123: 209 | J123: 229 | K123: 252 | L123: 269 | M123: 302 | O123: 224 | P123: 243 | Q123: 272 | R123: 316 | S123: 386 | U123: 0 | V123: 0 | W123: 0 | X123: 0 | Y123: 0 | AA123: 0 | AB123: 0 | AC123: 0 | AD123: 0 | AE123: 0 | AG123: 324.12 | AH123: 304.12 | AI123: 281.12 | AJ123: 264.12 | AK123: 231.12 | AM123: 308.62 | AN123: 289.62 | AO123: 261.12 | AP123: 216.62 | AQ123: 146.62
B124: SAMSUNG | C124: SAMSUNG GALAXY BOOK4 EDGE15 16+256GB | D124: 801 | E124: 5.33 | F124: PC | I124: 52 | J124: 268 | K124: 291 | L124: 308 | M124: 341 | O124: 68 | P124: 282 | Q124: 311 | R124: 355 | S124: 425 | U124: 0 | V124: 71 | W124: 71 | X124: 71 | Y124: 71 | AA124: 0 | AB124: 72 | AC124: 71 | AD124: 72 | AE124: 72 | AG124: 749 | AH124: 533.09 | AI124: 510.09 | AJ124: 493.09 | AK124: 460.09 | AM124: 733.5 | AN124: 518.59 | AO124: 490.09 | AP124: 445.59 | AQ124: 375.59
B125: SAMSUNG | C125: SAMSUNG GALAXY BOOK4 PRO 16" i5 | D125: 1487 | E125: 5.33 | F125: PC | I125: 52 | J125: 450 | K125: 473 | L125: 490 | M125: 523 | O125: 68 | P125: 464 | Q125: 493 | R125: 537 | S125: 607 | U125: 0 | V125: 0 | W125: 0 | X125: 0 | Y125: 0 | AA125: 0 | AB125: 0 | AC125: 0 | AD125: 0 | AE125: 0 | AG125: 1435 | AH125: 1037.33 | AI125: 1014.33 | AJ125: 997.33 | AK125: 964.33 | AM125: 1419.5 | AN125: 1022.83 | AO125: 994.33 | AP125: 949.83 | AQ125: 879.83
... B160: TCL | C160: TCL ANDROID TV 32" S5400A | D160: 159 | E160: 0 | F160: SMART TV | I160: 52 | J160: 72 | K160: 95 | L160: 112 | M160: 145 | O160: 68 | P160: 87 | Q160: 115 | R160: 160 | S160: 118 | U160: 0 | V160: 0 | W160: 0 | X160: 0 | Y160: 0 | AA160: 0 | AB160: 0 | AC160: 0 | AD160: 0 | AE160: 0 | AG160: 107 | AH160: 87 | AI160: 64 | AJ160: 47 | AK160: 14 | AM160: 91.5 | AN160: 72.5 | AO160: 44 | AP160: -0.5 | AQ160: 41.5
B161: TCL | C161: TCL ONETOUCH 4042s | D161: 49 | E161: 1.1 | F161: VOZ | I161: 49 | J161: 49 | K161: 0 | L161: 0 | M161: 0 | O161: 49 | P161: 0 | Q161: 0 | R161: 0 | S161: 0 | U161: 0 | V161: 0 | W161: 0 | X161: 0 | Y161: 0 | AA161: 0 | AB161: 0 | AC161: 0 | AD161: 0 | AE161: 0 | AG161: 0 | AH161: 0 | AI161: - | AJ161: - | AK161: - | AM161: 0 | AN161: - | AO161: - | AP161: - | AQ161: -
B162: TCL | C162: TCL ONETOUCH 4043 | D162: 60 | E162: 1.1 | F162: VOZ | I162: 60 | J162: 60 | K162: 0 | L162: 0 | M162: 0 | O162: 60 | P162: 0 | Q162: 0 | R162: 0 | S162: 0 | U162: 0 | V162: 0 | W162: 0 | X162: 0 | Y162: 0 | AA162: 0 | AB162: 0 | AC162: 0 | AD162: 0 | AE162: 0 | AG162: 0 | AH162: 0 | AI162: - | AJ162: - | AK162: - | AM162: 0 | AN162: - | AO162: - | AP162: - | AQ162: -
B163: TCL | C163: TCL TAB 10 2a GEN WIFI | D163: 132 | E163: 3.75 | F163: TABLET | I163: 52 | J163: 72 | K163: 95 | L163: 112 | M163: 145 | O163: 68 | P163: 87 | Q163: 115 | R163: 160 | S163: 230 | U163: 0 | V163: 0 | W163: 0 | X163: 0 | Y163: 0 | AA163: 0 | AB163: 0 | AC163: 0 | AD163: 0 | AE163: 0 | AG163: 80 | AH163: 60 | AI163: 37 | AJ163: 20 | AK163: -13 | AM163: 64.5 | AN163: 45.5 | AO163: 17 | AP163: -27.5 | AQ163: -97.5
B164: XACOM | C164: Xacom EasyGate | D164: 159 | E164: 0 | F164: VOZ | I164: 85 | J164: 0 | K164: 0 | L164: 0 | M164: 0 | O164: 85 | P164: 0 | Q164: 0 | R164: 0 | S164: 0 | U164: 0 | V164: 0 | W164: 0 | X164: 0 | Y164: 0 | AA164: 0 | AB164: 0 | AC164: 0 | AD164: 0 | AE164: 0 | AG164: 74 | AH164: - | AI164: - | AJ164: - | AK164: - | AM164: 74 | AN164: - | AO164: - | AP164: - | AQ164: -
B165: XACOM | C165: Xacom Track Digital RDSI | D165: 301 | E165: 0 | F165: VOZ | I165: 62 | J165: 0 | K165: 0 | L165: 0 | M165: 0 | O165: 62 | P165: 0 | Q165: 0 | R165: 0 | S165: 0 | U165: 0 | V165: 0 | W165: 0 | X165: 0 | Y165: 0 | AA165: 0 | AB165: 0 | AC165: 0 | AD165: 0 | AE165: 0 | AG165: 239 | AH165: - | AI165: - | AJ165: - | AK165: - | AM165: 239 | AN165: - | AO165: - | AP165: - | AQ165: -
B166: XIAOMI | C166: XIAOMI 14 5G | D166: 1072 | E166: 3.25 | F166: SMARTPHONE | I166: 52 | J166: 522 | K166: 545 | L166: 562 | M166: 595 | O166: 68 | P166: 537 | Q166: 565 | R166: 610 | S166: 680 | U166: 0 | V166: 0 | W166: 0 | X166: 0 | Y166: 0 | AA166: 0 | AB166: 0 | AC166: 0 | AD166: 0 | AE166: 0 | AG166: 1020 | AH166: 549.51 | AI166: 526.51 | AJ166: 509.51 | AK166: 476.51 | AM166: 1004.5 | AN166: 535.01 | AO166: 506.51 | AP166: 462.01 | AQ166: 392.01
B167: XIAOMI | C167: XIAOMI 14 ULTRA 5G | D167: 1402 | E167: 3.25 | F167: SMARTPHONE | I167: 52 | J167: 592 | K167: 615 | L167: 632 | M167: 665 | O167: 68 | P167: 606 | Q167: 635 | R167: 679 | S167: 749 | U167: 0 | V167: 0 | W167: 0 | X167: 0 | Y167: 0 | AA167: 0 | AB167: 0 | AC167: 0 | AD167: 0 | AE167: 0 | AG167: 1350 | AH167: 810.09 | AI167: 787.09 | AJ167: 770.09 | AK167: 737.09 | AM167: 1334.5 | AN167: 795.59 | AO167: 767.09 | AP167: 722.59 | AQ167: 652.59
B168: XIAOMI | C168: XIAOMI 14C 128GB | D168: 174 | E168: 3.25 | F168: SMARTPHONE | I168: 116 | J168: 136 | K168: 159 | L168: 176 | M168: 209 | O168: 132 | P168: 151 | Q168: 179 | R168: 224 | S168: 294 | U168: 0 | V168: 0 | W168: 0 | X168: 0 | Y168: 0 | AA168: 0 | AB168: 0 | AC168: 0 | AD168: 0 | AE168: 0 | AG168: 57.68 | AH168: 37.68 | AI168: 14.68 | AJ168: -2.32 | AK168: -35.32 | AM168: 42.18 | AN168: 23.18 | AO168: -5.32 | AP168: -49.82 | AQ168: -119.82
B169: XIAOMI | C169: XIAOMI 14T 256GB 5G | D169: 638 | E169: 3.25 | F169: SMARTPHONE | I169: 52 | J169: 268 | K169: 291 | L169: 308 | M169: 341 | O169: 68 | P169: 283 | Q169: 311 | R169: 356 | S169: 426 | U169: 0 | V169: 0 | W169: 0 | X169: 0 | Y169: 0 | AA169: 0 | AB169: 0 | AC169: 0 | AD169: 0 | AE169: 0 | AG169: 586 | AH169: 369.57 | AI169: 346.57 | AJ169: 329.57 | AK169: 296.57 | AM169: 570.5 | AN169: 355.07 | AO169: 326.57 | AP169: 282.07 | AQ169: 212.07
B170: XIAOMI | C170: XIAOMI 14T PRO 256GB 5G | D170: 801 | E170: 3.25 | F170: SMARTPHONE | I170: 52 | J170: 324 | K170: 347 | L170: 364 | M170: 397 | O170: 68 | P170: 339 | Q170: 367 | R170: 412 | S170: 482 | U170: 0 | V170: 0 | W170: 0 | X170: 0 | Y170: 0 | AA170: 0 | AB170: 0 | AC170: 0 | AD170: 0 | AE170: 0 | AG170: 749 | AH170: 476.68 | AI170: 453.68 | AJ170: 436.68 | AK170: 403.68 | AM170: 733.5 | AN170: 462.18 | AO170: 433.68 | AP170: 389.18 | AQ170: 319.18
B171: XIAOMI | C171: XIAOMI 14T PRO 512GB 5G | D171: 895 | E171: 3.25 | F171: SMARTPHONE | I171: 52 | J171: 412 | K171: 435 | L171: 452 | M171: 485 | O171: 68 | P171: 426 | Q171: 455 | R171: 499 | S171: 569 | U171: 0 | V171: 0 | W171: 0 | X171: 0 | Y171: 0 | AA171: 0 | AB171: 0 | AC171: 0 | AD171: 0 | AE171: 0 | AG171: 843 | AH171: 483.08 | AI171: 460.08 | AJ171: 443.08 | AK171: 410.08 | AM171: 827.5 | AN171: 468.58 | AO171: 440.08 | AP171: 395.58 | AQ171: 325.58
B172: XIAOMI | C172: XIAOMI GOOGLE TV 43" QLED A PRO | D172: 298 | E172: 0 | F172: SMART TV | I172: 103 | J172: 123 | K172: 146 | L172: 163 | M172: 196 | O172: 118 | P172: 137 | Q172: 166 | R172: 210 | S172: 271 | U172: 0 | V172: 0 | W172: 0 | X172: 0 | Y172: 0 | AA172: 0 | AB172: 0 | AC172: 0 | AD172: 0 | AE172: 0 | AG172: 195.4 | AH172: 175.4 | AI172: 152.4 | AJ172: 135.4 | AK172: 102.4 | AM172: 179.9 | AN172: 160.9 | AO172: 132.4 | AP172: 87.9 | AQ172: 26.8
B173: XIAOMI | C173: XIAOMI GOOGLE TV 55" QLED A PRO | D173: 445 | E173: 0 | F173: SMART TV | I173: 98 | J173: 118 | K173: 141 | L173: 158 | M173: 191 | O173: 114 | P173: 133 | Q173: 161 | R173: 206 | S173: 276 | U173: 0 | V173: 0 | W173: 0 | X173: 0 | Y173: 0 | AA173: 0 | AB173: 0 | AC173: 0 | AD173: 0 | AE173: 0 | AG173: 346.77 | AH173: 326.77 | AI173: 303.77 | AJ173: 286.77 | AK173: 253.77 | AM173: 331.27 | AN173: 312.27 | AO173: 283.77 | AP173: 239.27 | AQ173: 169.27
B174: XIAOMI | C174: XIAOMI GOOGLE TV 65" QLED A PRO | D174: 577 | E174: 0 | F174: SMART TV | I174: 52 | J174: 72 | K174: 212 | L174: 229 | M174: 262 | O174: 68 | P174: 87 | Q174: 232 | R174: 276 | S174: 346 | U174: 0 | V174: 0 | W174: 0 | X174: 0 | Y174: 0 | AA174: 0 | AB174: 0 | AC174: 0 | AD174: 0 | AE174: 0 | AG174: 525 | AH174: 505 | AI174: 365.34 | AJ174: 348.34 | AK174: 315.34 | AM174: 509.5 | AN174: 490.5 | AO174: 345.34 | AP174: 300.84 | AQ174: 230.84
B175: XIAOMI | C175: XIAOMI MI ELECTRIC SCOOTER 4 | D175: 459 | E175: 0 | F175: OC_TIEMPO LIBRE | I175: 243 | J175: 263 | K175: 286 | L175: 303 | M175: 336 | O175: 258 | P175: 277 | Q175: 306 | R175: 350 | S175: 420 | U175: 0 | V175: 0 | W175: 0 | X175: 0 | Y175: 0 | AA175: 0 | AB175: 0 | AC175: 0 | AD175: 0 | AE175: 0 | AG175: 216.11 | AH175: 196.11 | AI175: 173.11 | AJ175: 156.11 | AK175: 123.11 | AM175: 200.61 | AN175: 181.61 | AO175: 153.11 | AP175: 108.61 | AQ175: 38.61
B176: XIAOMI | C176: XIAOMI MI ELECTRIC SCOOTER 4 PRO 2a GEN | D176: 516 | E176: 0 | F176: OC_TIEMPO LIBRE | I176: 218 | J176: 238 | K176: 261 | L176: 278 | M176: 311 | O176: 234 | P176: 253 | Q176: 281 | R176: 326 | S176: 396 | U176: 0 | V176: 0 | W176: 0 | X176: 0 | Y176: 0 | AA176: 0 | AB176: 0 | AC176: 0 | AD176: 0 | AE176: 0 | AG176: 297.9 | AH176: 277.9 | AI176: 254.9 | AJ176: 237.9 | AK176: 204.9 | AM176: 282.4 | AN176: 263.4 | AO176: 234.9 | AP176: 190.4 | AQ176: 120.4
B177: XIAOMI | C177: XIAOMI PAD 6S PRO WIFI | D177: 647 | E177: 3.75 | F177: TABLET | I177: 52 | J177: 299 | K177: 322 | L177: 339 | M177: 372 | O177: 68 | P177: 313 | Q177: 342 | R177: 386 | S177: 456 | U177: 0 | V177: 0 | W177: 0 | X177: 0 | Y177: 0 | AA177: 0 | AB177: 0 | AC177: 0 | AD177: 0 | AE177: 0 | AG177: 595 | AH177: 348.11 | AI177: 325.11 | AJ177: 308.11 | AK177: 275.11 | AM177: 579.5 | AN177: 333.61 | AO177: 305.11 | AP177: 260.61 | AQ177: 190.61
... B183: XIAOMI | C183: XIAOMI REDMI NOTE 13 PRO+ 5G | D183: 522 | E183: 3.25 | F183: SMARTPHONE | I183: 238 | J183: 258 | K183: 281 | L183: 298 | M183: 331 | O183: 254 | P183: 273 | Q183: 301 | R183: 346 | S183: 416 | U183: 0 | V183: 0 | W183: 0 | X183: 0 | Y183: 0 | AA183: 0 | AB183: 0 | AC183: 0 | AD183: 0 | AE183: 0 | AG183: 283.65 | AH183: 263.65 | AI183: 240.65 | AJ183: 223.65 | AK183: 190.65 | AM183: 268.15 | AN183: 249.15 | AO183: 220.65 | AP183: 176.15 | AQ183: 106.15
B184: XIAOMI | C184: XIAOMI REDMI NOTE 14 PRO 256GB 5G | D184: 415 | E184: 3.25 | F184: SMARTPHONE | I184: 169 | J184: 189 | K184: 212 | L184: 229 | M184: 262 | O184: 184 | P184: 203 | Q184: 232 | R184: 276 | S184: 346 | U184: =NA() -> #N/A | V184: =NA() -> #N/A | W184: =NA() -> #N/A | X184: =NA() -> #N/A | Y184: =NA() -> #N/A | AA184: =NA() -> #N/A | AB184: =NA() -> #N/A | AC184: =NA() -> #N/A | AD184: =NA() -> #N/A | AE184: =NA() -> #N/A | AG184: 246.06 | AH184: 226.06 | AI184: 203.06 | AJ184: 186.06 | AK184: 153.06 | AM184: 230.56 | AN184: 211.56 | AO184: 183.06 | AP184: 138.56 | AQ184: 68.56
B185: XIAOMI | C185: XIAOMI REDMI NOTE 14 PRO+ 256GB 5G | D185: 516 | E185: 3.25 | F185: SMARTPHONE | I185: 189 | J185: 209 | K185: 232 | L185: 249 | M185: 282 | O185: 204 | P185: 223 | Q185: 252 | R185: 296 | S185: 366 | U185: =NA() -> #N/A | V185: =NA() -> #N/A | W185: =NA() -> #N/A | X185: =NA() -> #N/A | Y185: =NA() -> #N/A | AA185: =NA() -> #N/A | AB185: =NA() -> #N/A | AC185: =NA() -> #N/A | AD185: =NA() -> #N/A | AE185: =NA() -> #N/A | AG185: 327.46 | AH185: 307.46 | AI185: 284.46 | AJ185: 267.46 | AK185: 234.46 | AM185: 311.96 | AN185: 292.96 | AO185: 264.46 | AP185: 219.96 | AQ185: 149.96
B186: XIAOMI | C186: XIAOMI REDMI PAD PRO WIFI | D186: 327 | E186: 3.75 | F186: TABLET | I186: 138 | J186: 158 | K186: 181 | L186: 198 | M186: 231 | O186: 154 | P186: 173 | Q186: 201 | R186: 246 | S186: 316 | U186: -15 | V186: -15 | W186: -15 | X186: -15 | Y186: -15 | AA186: -15 | AB186: -15 | AC186: -15 | AD186: -15 | AE186: -15 | AG186: 188.86 | AH186: 168.86 | AI186: 145.86 | AJ186: 128.86 | AK186: 95.86 | AM186: 173.36 | AN186: 154.36 | AO186: 125.86 | AP186: 81.36 | AQ186: 11.36
B187: XIAOMI | C187: XIAOMI REDMI PAD SE 8.7" WIFI 4+128GB | D187: 167 | E187: 3.75 | F187: TABLET | I187: 82 | J187: 102 | K187: 125 | L187: 142 | M187: 175 | O187: 103 | P187: 122 | Q187: 150 | R187: 195 | S187: 265 | U187: 5 | V187: 5 | W187: 5 | X187: 5 | Y187: 5 | AA187: 0 | AB187: 0 | AC187: 0 | AD187: 0 | AE187: 0 | AG187: 85.25 | AH187: 65.25 | AI187: 42.25 | AJ187: 25.25 | AK187: -7.75 | AM187: 64.39 | AN187: 45.39 | AO187: 16.89 | AP187: -27.61 | AQ187: -97.61
B188: XIAOMI | C188: XIAOMI SMART TV A 32" | D188: 165 | E188: 0 | F188: SMART TV | I188: 52 | J188: 72 | K188: 95 | L188: 112 | M188: 145 | O188: 68 | P188: 87 | Q188: 115 | R188: 159 | S188: 117 | U188: 0 | V188: 0 | W188: 0 | X188: 0 | Y188: 0 | AA188: 0 | AB188: 0 | AC188: 0 | AD188: 0 | AE188: 0 | AG188: 113 | AH188: 93 | AI188: 70 | AJ188: 53 | AK188: 20 | AM188: 97.5 | AN188: 78.5 | AO188: 50 | AP188: 5.95 | AQ188: 47.95
...

Sheet PVP Subv IEW - Pyme
B2: OFERTA TÁCTICA EMPRESAS | I2: CAPTA / PORTABILIDAD
B4: ='PVP VaP - Pyme'!B4 -> 45627 | C4: ='PVP VaP - Pyme'!C4 -> 01/12 al 31/12 | I4: ENTRADA PRO | J4: NORMAL PRO | K4: VALOR PRO | L4: PREMIUM PRO
B5: 1. CONDICIONES DE LA OFERTA SUBVENCIONADA (según tarifa y situación del cliente) | D5: Tarifas | I5: Internet Movil 3GB Empresa | J5: Internet Movil 10GB Empresa | K5: Internet Movil 25GB Empresa | L5: Internet Movil 90GB Empresa Internet 4G en tu Negocio Internet Empresa Ilimitado
D12: Ampliaciones (meses antigüedad) | I12: - | J12: - | K12: - | L12: -
D13: Origen (Portabilidad / Migración) | I13: Captación Pos / Pre Migración | J13: Captación Pos / Pre Migración | K13: Captación Pos / Pre Migración | L13: Captación Pos / Pre Migración
D14: CP Tarifa | I14: 12 M / 24 M (Tablet) | J14: 12 M / 24 M (Tablet) | K14: 12 M / 24 M (Tablet) | L14: 12 M / 24 M (Tablet)
D15: CP Terminal | I15: 12 M / 24 M (Tablet) | J15: 12 M / 24 M (Tablet) | K15: 12 M / 24 M (Tablet) | L15: 12 M / 24 M (Tablet)
B18: 2. PRECIO DEL TERMINAL POR GRUPO DE TARIFAS | I18: PVPR CAPTA / PORTABILIDAD | N18: DxC CAPTA / PORTABILIDAD
I20: GRUPOS DE TARIFAS IEW Pro | N20: GRUPOS DE TARIFAS IEW Pro
I22: ENTRADA PRO | J22: NORMAL PRO | K22: VALOR PRO | L22: PREMIUM PRO | N22: ENTRADA PRO | O22: NORMAL PRO | P22: VALOR PRO | Q22: PREMIUM PRO
B24: MARCA | C24: Modelo (Novedades) | D24: Precio Cesión | E24: Canon Digital | F24: Gama | I24: PVP (sin IVA) | J24: PVP (sin IVA) | K24: PVP (sin IVA) | L24: PVP (sin IVA) | N24: DxC | O24: DxC | P24: DxC | Q24: DxC
B25: ALCATEL | C25: ALCATEL AIRBOX 4G MW45 | D25: 49 | E25: 0 | F25: MBB | I25: 9 | J25: 0 | K25: 0 | L25: 0 | N25: 40 | O25: 49 | P25: 49 | Q25: 49
B26: ALCATEL | C26: ALCATEL AIRBOX 4G MW70 | D26: 59 | E26: 0 | F26: MBB | I26: 29 | J26: 19 | K26: 9 | L26: 0 | N26: 30 | O26: 40 | P26: 50 | Q26: 59
B27: HUAWEI | C27: FLYBOX HUAWEI B535 232A 4G | D27: 132 | E27: 0 | F27: MBB | I27: 29 | J27: 19 | K27: 9 | L27: 0 | N27: 103 | O27: 113 | P27: 123 | Q27: 132
B28: HUAWEI | C28: HUAWEI AIRBOX E5576-320 IEW 4G | D28: 66 | E28: 0 | F28: MBB | I28: 19 | J28: 0 | K28: 0 | L28: 0 | N28: 47 | O28: 66 | P28: 66 | Q28: 66
B29: TP-LINK | C29: ROUTER TPLINK MR200 IEW 4G | D29: 58 | E29: 0 | F29: MBB | I29: 19 | J29: 9 | K29: 0 | L29: 0 | N29: 39 | O29: 49 | P29: 58 | Q29: 58
B30: ZTE | C30: ZTE AIRBOX MF920U 4G | D30: 66 | E30: 0 | F30: MBB | I30: 9 | J30: 0 | K30: 0 | L30: 0 | N30: 57 | O30: 66 | P30: 66 | Q30: 66
B31: ZTE | C31: ZTE AIRBOX MU5001 5G | D31: 244 | E31: 0 | F31: MBB | I31: 169 | J31: 159 | K31: 149 | L31: 129 | N31: 75 | O31: 85 | P31: 95 | Q31: 115
B32: ZTE | C32: ZTE FLYBOX MC801A 5G | D32: 200 | E32: 0 | F32: MBB | I32: 149 | J32: 139 | K32: 129 | L32: 109 | N32: 51 | O32: 61 | P32: 71 | Q32: 91
B33: NOKIA | C33: FLYBOX NOKIA FASTMILE 5G | D33: 207 | E33: 0 | F33: MBB | I33: 129 | J33: 119 | K33: 109 | L33: 79 | N33: 78 | O33: 88 | P33: 98 | Q33: 128
B34: HUAWEI | C34: FLYBOX HUAWEI H153-381 5G | D34: 248 | E34: 0 | F34: MBB | I34: 79 | J34: 69 | K34: 59 | L34: 39 | N34: 169 | O34: 179 | P34: 189 | Q34: 209
B35: SAMSUNG | C35: SAMSUNG GALAXY TAB A9 8,7" WIFI | D35: 182 | E35: 3.75 | F35: TABLET | I35: 109 | J35: 99 | K35: 89 | L35: 69 | N35: 73 | O35: 83 | P35: 93 | Q35: 113
B36: XIAOMI | C36: XIAOMI REDMI PAD SE 8.7" WIFI 4+128GB | D36: 167 | E36: 3.75 | F36: TABLET | I36: 79 | J36: 69 | K36: 59 | L36: 39 | N36: 88 | O36: 98 | P36: 108 | Q36: 128

Sheet PVP VaP 2º Dispo Pyme
B2: OFERTA TÁCTICA EMPRESAS | H2: Pago Único | J2: CAPTA / PORTA
B4: ='PVP VaP - Pyme'!B4 -> 45627 | C4: ='PVP VaP - Pyme'!C4 -> 01/12 al 31/12 | J4: 2º DISPOSITIVO
B5: 1. CONDICIONES DE LA OFERTA VENTA A PLAZOS (según tarifa y situación del cliente) | D5: Tarifas | H5: Todas Tarifas | J5: T. Optima Plus Empresas T. Optima Plus Empresas Big
D13: Ampliaciones (meses antigüedad) | H13: - | J13: Todos
D14: Origen (Portabilidad / Migración) | H14: Capta Pos/Pre Migra | J14: Capta Pos / Pre Migracion
D15: CP Terminal | H15: - | J15: 24 M
B18: 2. PRECIO DEL TERMINAL POR GRUPO DE TARIFAS | H18: Pago Único | J18: PVPR CAPTA / PORTA | M18: DxC Pago Único | O18: DxC CAPTA / PORTA
J22: 2º DISPOSITIVO | O22: 2º DISPOSITIVO
B24: MARCA | C24: Modelo (Novedades) | D24: Precio Cesión | E24: Canon Digital | F24: Gama | G24: Meses Cuota | H24: Pago Unico (sin IVA) | J24: Pago Inicial (sin IVA) | K24: Cuota Mes (sin IVA) | M24: DxC Pago Unico | O24: DxC Precio | P24: DxC VaP
B25: ORANGE | C25: AD HOC H3 CESIÓN | D25: 0 | E25: 1.1 | F25: FIXED STYLE | G25: - | H25: - | J25: - | K25: - | M25: 0 | O25: 0 | P25: 0
B26: ORANGE | C26: ADOC D30 | D26: 239 | E26: 3.75 | F26: FIXED STYLE | G26: 24 | H26: 280 | J26: 29 | K26: 7.4 | M26: -41 | O26: 32 | P26: 177.6
B27: ORANGE | C27: ADOC D30 CESIÓN | D27: 0 | E27: 3.75 | F27: FIXED STYLE | G27: - | H27: - | J27: - | K27: - | M27: 0 | O27: 0 | P27: 0
B28: AD HOC | C28: ADOC SC01 | D28: 64 | E28: 1.1 | F28: VOZ | G28: - | H28: - | J28: - | K28: - | M28: 0 | O28: 0 | P28: 0
B29: ADOC | C29: ADOC SC04 | D29: 77 | E29: 1.1 | F29: VOZ | G29: 24 | H29: 93 | J29: 0 | K29: 0 | M29: -16 | O29: 77 | P29: 0
B30: APPLE | C30: APPLE AIRPODS 4 | D30: 137 | E30: 0 | F30: OC_AURICULARES | G30: 24 | H30: 165 | J30: 19 | K30: 4.5 | M30: -28 | O30: 10 | P30: 108
B31: APPLE | C31: APPLE AIRPODS 4 CON CANCELACION ACTIVA RUIDO | D31: 184 | E31: 0 | F31: OC_AURICULARES | G31: 24 | H31: 222 | J31: 29 | K31: 5.7 | M31: -38 | O31: 18 | P31: 136.8
B32: APPLE | C32: APPLE AIRPODS PRO 2a GENERACION MAGSAFE USBC | D32: 279 | E32: 0 | F32: OC_AURICULARES | G32: 24 | H32: 336 | J32: 39 | K32: 7.8 | M32: -57 | O32: 53 | P32: 187.2
B33: APPLE | C33: APPLE WATCH S10 CELLULAR 42MM | D33: 532 | E33: 2.5 | F33: OC_SMART WATCH | G33: 24 | H33: 643 | J33: 69 | K33: 16.2 | M33: -111 | O33: 74 | P33: 388.8
B34: APPLE | C34: APPLE WATCH S10 CELLULAR 46MM | D34: 555 | E34: 2.5 | F34: OC_SMART WATCH | G34: 24 | H34: 671 | J34: 69 | K34: 17.1 | M34: -116 | O34: 76 | P34: 410.4
B35: APPLE | C35: APPLE WATCH S9 CELLULAR 45MM | D35: 555 | E35: 2.5 | F35: OC_SMART WATCH | G35: 24 | H35: 671 | J35: 69 | K35: 17.1 | M35: -116 | O35: 76 | P35: 410.4
B36: AD HOC | C36: AURICULARES AD HOC BT01 | D36: 71 | E36: 0 | F36: OC_AURICULARES | G36: 24 | H36: 57.024793 | J36: 0 | K36: 0.6 | M36: 14 | O36: 57 | P36: 14.4
B37: AD HOC | C37: AURICULARES AD HOC HC01 | D37: 49 | E37: 0 | F37: OC_AURICULARES | G37: 24 | H37: 35.53719 | J37: 0 | K37: 0.4 | M37: 13 | O37: 39 | P37: 9.6
B38: SAMSUNG | C38: AURICULARES SAMSUNG GALAXY BUDS 3 | D38: 172 | E38: 0 | F38: OC_AURICULARES | G38: 24 | H38: 158 | J38: 19 | K38: 4.3 | M38: 14 | O38: 50 | P38: 103.2
B39: SAMSUNG | C39: AURICULARES SAMSUNG GALAXY BUDS 3 PRO | D39: 240 | E39: 0 | F39: OC_AURICULARES | G39: 24 | H39: 227 | J39: 29 | K39: 5.9 | M39: 13 | O39: 69 | P39: 141.6
B40: SPC | C40: AURICULARES SPC BRAVE PRO | D40: 44 | E40: 0 | F40: OC_AURICULARES | G40: 24 | H40: 47.933884 | J40: 0 | K40: 0.7 | M40: -4 | O40: 27 | P40: 16.8
... B105: OPPO | C105: OPPO RENO12 PRO 512GB 5G | D105: 524 | E105: 3.25 | F105: SMARTPHONE | G105: 24 | H105: 518 | J105: 49 | K105: 12.5 | M105: 6 | O105: 175 | P105: 300
B106: ORANGE | C106: ORANGE GAMA 120 4G | D106: 74 | E106: 1.1 | F106: FIXED STYLE | G106: - | H106: - | J106: - | K106: - | M106: 0 | O106: 0 | P106: 0
B107: ORANGE | C107: ORANGE GAMA 401 CESIÓN | D107: 0 | E107: 1.1 | F107: FIXED STYLE | G107: - | H107: - | J107: - | K107: - | M107: 0 | O107: 0 | P107: 0
B108: ORANGE | C108: ORANGE GAMA 402 | D108: 70 | E108: 1.1 | F108: FIXED STYLE | G108: - | H108: - | J108: - | K108: - | M108: 0 | O108: 0 | P108: 0
B109: ORANGE | C109: ORANGE GAMA 402 CESIÓN | D109: 0 | E109: 1.1 | F109: FIXED STYLE | G109: - | H109: - | J109: - | K109: - | M109: 0 | O109: 0 | P109: 0
B110: ORANGE | C110: ORANGE GAMA 704 | D110: 104 | E110: 1.1 | F110: FIXED STYLE | G110: - | H110: - | J110: - | K110: - | M110: 0 | O110: 0 | P110: 0
B111: ORANGE | C111: ORANGE GAMA 704 CESIÓN | D111: 0 | E111: 1.1 | F111: FIXED STYLE | G111: - | H111: - | J111: - | K111: - | M111: 0 | O111: 0 | P111: 0
B112: ORANGE | C112: ORANGE GAMA 803 CESIÓN | D112: 0 | E112: 1.1 | F112: FIXED STYLE | G112: - | H112: - | J112: - | K112: - | M112: 0 | O112: 0 | P112: 0
B113: DEF | C113: PACK BALIZA CONECTADA DGT 2 UNIDADES | D113: 96 | E113: 0 | F113: OC_OTROS DISPOSITIVOS | G113: 24 | H113: 92 | J113: 0 | K113: 1.4 | M113: 4 | O113: 62 | P113: 33.6
B114: NEXTIVITY | C114: REPETIDOR NEXTIVITY CELFI CONNECT C41 | D114: 547 | E114: 0 | F114: OC_OTROS DISPOSITIVOS | G114: 24 | H114: 499 | J114: 69 | K114: 16.8 | M114: 48 | O114: 75 | P114: 403.2
B115: SAMSUNG | C115: SAMSUNG GALAXY A15 | D115: 186 | E115: 3.25 | F115: SMARTPHONE | G115: 24 | H115: 201 | J115: 29 | K115: 5.8 | M115: -15 | O115: 18 | P115: 139.2
B116: SAMSUNG | C116: SAMSUNG GALAXY A15 5G | D116: 215 | E116: 3.25 | F116: SMARTPHONE | G116: 24 | H116: 231 | J116: 29 | K116: 6.9 | M116: -16 | O116: 20 | P116: 165.6
B117: SAMSUNG | C117: SAMSUNG GALAXY A16 128GB | D117: 186 | E117: 3.25 | F117: SMARTPHONE | G117: 24 | H117: 201 | J117: 19 | K117: 4.1 | M117: -15 | O117: 69 | P117: 98.4
B118: SAMSUNG | C118: SAMSUNG GALAXY A16 128GB 5G | D118: 248 | E118: 3.25 | F118: SMARTPHONE | G118: 24 | H118: 299 | J118: 19 | K118: 4.6 | M118: -51 | O118: 119 | P118: 110.4
B119: SAMSUNG | C119: SAMSUNG GALAXY A25 5G | D119: 299 | E119: 3.25 | F119: SMARTPHONE | G119: 24 | H119: 337 | J119: 39 | K119: 7.8 | M119: -38 | O119: 73 | P119: 187.2
B120: SAMSUNG | C120: SAMSUNG GALAXY A35 5G | D120: 358 | E120: 3.25 | F120: SMARTPHONE | G120: 24 | H120: 389 | J120: 39 | K120: 9.7 | M120: -31 | O120: 86 | P120: 232.8
B121: SAMSUNG | C121: SAMSUNG GALAXY A55 5G | D121: 442 | E121: 3.25 | F121: SMARTPHONE | G121: 24 | H121: 510 | J121: 49 | K121: 10.5 | M121: -68 | O121: 141 | P121: 252
B122: SAMSUNG | C122: SAMSUNG GALAXY BOOK2 GO 14" | D122: 533 | E122: 5.33 | F122: PC | G122: 24 | H122: 511 | J122: 59 | K122: 12.7 | M122: 22 | O122: 169 | P122: 304.8
B123: SAMSUNG | C123: SAMSUNG GALAXY BOOK4 EDGE15 16+256GB | D123: 801 | E123: 5.33 | F123: PC | G123: 24 | H123: 812 | J123: 89 | K123: 21.4 | M123: -11 | O123: 198 | P123: 513.6
B124: SAMSUNG | C124: SAMSUNG GALAXY BOOK4 PRO 16" i5 | D124: 1487 | E124: 5.33 | F124: PC | G124: 24 | H124: 1487 | J124: 169 | K124: 39.8 | M124: 0 | O124: 363 | P124: 955.2
... B159: TCL | C159: TCL ANDROID TV 32" S5400A | D159: 159 | E159: 0 | F159: SMART TV | G159: 24 | H159: 192 | J159: 19 | K159: 5 | M159: -33 | O159: 20 | P159: 120
B160: TCL | C160: TCL ONETOUCH 4042s | D160: 49 | E160: 1.1 | F160: VOZ | G160: - | H160: - | J160: - | K160: - | M160: 0 | O160: 0 | P160: 0
B161: TCL | C161: TCL ONETOUCH 4043 | D161: 60 | E161: 1.1 | F161: VOZ | G161: - | H161: - | J161: - | K161: - | M161: 0 | O161: 0 | P161: 0
B162: TCL | C162: TCL TAB 10 2a GEN WIFI | D162: 132 | E162: 3.75 | F162: TABLET | G162: 24 | H162: 122 | J162: 19 | K162: 3.4 | M162: 10 | O162: 31 | P162: 81.6
B163: XACOM | C163: Xacom EasyGate | D163: 159 | E163: 0 | F163: VOZ | G163: - | H163: - | J163: - | K163: - | M163: 0 | O163: 0 | P163: 0
B164: XACOM | C164: Xacom Track Digital RDSI | D164: 301 | E164: 0 | F164: VOZ | G164: - | H164: - | J164: - | K164: - | M164: 0 | O164: 0 | P164: 0
B165: XIAOMI | C165: XIAOMI 14 5G | D165: 1072 | E165: 3.25 | F165: SMARTPHONE | G165: 24 | H165: 832 | J165: 89 | K165: 22.1 | M165: 240 | O165: 453 | P165: 530.4
B166: XIAOMI | C166: XIAOMI 14 ULTRA 5G | D166: 1402 | E166: 3.25 | F166: SMARTPHONE | G166: 24 | H166: 1212 | J166: 129 | K166: 31.7 | M166: 190 | O166: 512 | P166: 760.8
B167: XIAOMI | C167: XIAOMI 14C 128GB | D167: 174 | E167: 3.25 | F167: SMARTPHONE | G167: 24 | H167: 107 | J167: 19 | K167: 2.9 | M167: 67 | O167: 85 | P167: 69.6
B168: XIAOMI | C168: XIAOMI 14T 256GB 5G | D168: 638 | E168: 3.25 | F168: SMARTPHONE | G168: 24 | H168: 614 | J168: 69 | K168: 15.1 | M168: 24 | O168: 207 | P168: 362.4
B169: XIAOMI | C169: XIAOMI 14T PRO 256GB 5G | D169: 801 | E169: 3.25 | F169: SMARTPHONE | G169: 24 | H169: 744 | J169: 79 | K169: 19.3 | M169: 57 | O169: 259 | P169: 463.2
B170: XIAOMI | C170: XIAOMI 14T PRO 512GB 5G | D170: 895 | E170: 3.25 | F170: SMARTPHONE | G170: 24 | H170: 921 | J170: 79 | K170: 19.6 | M170: -26 | O170: 346 | P170: 470.4
B171: XIAOMI | C171: XIAOMI GOOGLE TV 43" QLED A PRO | D171: 298 | E171: 0 | F171: SMART TV | G171: 24 | H171: 342 | J171: 39 | K171: 8 | M171: -44 | O171: 67 | P171: 192
B172: XIAOMI | C172: XIAOMI GOOGLE TV 55" QLED A PRO | D172: 445 | E172: 0 | F172: SMART TV | G172: 24 | H172: 538 | J172: 59 | K172: 13.7 | M172: -93 | O172: 57 | P172: 328.8
B173: XIAOMI | C173: XIAOMI GOOGLE TV 65" QLED A PRO | D173: 577 | E173: 0 | F173: SMART TV | G173: 24 | H173: 637 | J173: 69 | K173: 15.9 | M173: -60 | O173: 126 | P173: 381.6
B174: XIAOMI | C174: XIAOMI MI ELECTRIC SCOOTER 4 | D174: 459 | E174: 0 | F174: OC_TIEMPO LIBRE | G174: 24 | H174: 367 | J174: 39 | K174: 8.9 | M174: 92 | O174: 206 | P174: 213.6
B175: XIAOMI | C175: XIAOMI MI ELECTRIC SCOOTER 4 PRO 2a GEN | D175: 516 | E175: 0 | F175: OC_TIEMPO LIBRE | G175: 24 | H175: 466 | J175: 49 | K175: 12 | M175: 50 | O175: 179 | P175: 288
B176: XIAOMI | C176: XIAOMI PAD 6S PRO WIFI | D176: 647 | E176: 3.75 | F176: TABLET | G176: 24 | H176: 564 | J176: 59 | K176: 14.6 | M176: 83 | O176: 238 | P176: 350.4
... B188: ZTE | C188: ZTE A75 128GB 5G | D188: 148 | E188: 3.25 | F188: SMARTPHONE | G188: 24 | H188: 117 | J188: 19 | K188: 3.2 | M188: 31 | O188: 52 | P188: 76.8
